Workbook

Sheet Relatório de Mudanças
A1: RELATÓRIO DE MUDANÇAS: PLANILHA DE FIDELIDADE VULTO+
A2: Limpeza feita em 19/10/2026. Arquivo original: clientes_fidelidade_FINAL_v3. Base de comparação: clientes atualizado.xlsx (enviado pelo usuário).
A4: 1. RESUMO
A5: Antes | B5: 5 abas (Clientes, clientes antigos (NAO APAGAR), Resgates, LEIA ISSO, Plan1), com 2.535 linhas de clientes, formatos misturados, duplicados e contagens desatualizadas.
A6: Depois | B6: 6 abas com função clara: Clientes (cadastro), Resgates (movimentação), Pendências (o que falta resolver), Regras e Parâmetros (regras e faixas), Faltam no outro arquivo (correções para o clientes atualizado) e este relatório.
A7: Clientes | B7: 2.535 linhas → 2.395 clientes únicos (1 linha por CPF).
A8: Resgates sem cliente | B8: 45 casos (R$ 2.350) → 21 casos (R$ 980), todos listados na aba Pendências.
A9: Desconto acima da regra | B9: 420 resgates, R$ 17.795 a mais (identificados, não alterados).
A11: 2. ABA CLIENTES
A12: Colunas | B12: Padronizadas e renomeadas: Nome, CPF, CPF válido, E-mail, Telefone, Data Cadastro, Loja Cadastro, Pontos (até 01/01/2025), Categoria, Aceita Msg, Obs, Pendências.
A13: CPF | B13: Todos no formato 000.000.000-00, guardados como texto. Os CPFs que tinham perdido o zero da frente (9 ou 10 dígitos) foram completados com zeros. Nova coluna 'CPF válido' confere os dígitos verificadores (23 continuam inválidos e estão marcados).
A14: Duplicados | B14: 131 CPFs apareciam em 2 ou 3 linhas (271 linhas). DECISÃO DO USUÁRIO: juntar em 1 linha, SOMANDO os pontos, mantendo a data de cadastro mais antiga e o contato mais recente. As linhas de origem ficaram anotadas na coluna Obs.
A15: Nomes e e-mails | B15: Espaços sobrando removidos, nomes com inicial maiúscula, e-mails em minúsculas. E-mails vazios, '-' ou 'nao tem' viraram vazio e foram marcados 'Sem e-mail' (18).
A16: Telefone | B16: Padronizado como (DD) 99999-9999 (o +55 foi tirado). 66 DDDs foram completados com a planilha de atendimentos (WhatsApp/Insta), só quando os 9 dígitos finais eram idênticos; 10 deles ficaram marcados para conferir porque só o telefone bateu. 319 continuam sem DDD (não completei pela loja, porque seria um chute).
A17: Data Cadastro | B17: Convertida para data (dd/mm/aaaa). As datas vinham em vários formatos (dd/mm/aaaa, aaaa-mm-dd, número de série, 'jun/21'). As que só tinham mês e ano (198) ficaram no dia 1 do mês e foram marcadas 'Data aproximada'.
A18: Loja Cadastro | B18: Nomes unificados: Site (site, ecommerce), App, Pinheiros, Eldorado (eldorado shop), Savassi (bh), Batel (CWB).
A19: Pontos | B19: Convertidos para número ('2.203', '1389 pts', '15000 pts'). Valores como '2,7k' viraram 2700 e foram marcados 'Pontos aproximados' (96).
A20: Pontos pós-2025 | B20: DECISÃO DO USUÁRIO: a coluna de pontos foi congelada em 01/01/2025 (regra do LEIA ISSO). Quem se cadastrou depois tem 0 pontos aqui e está marcado 'Pontos no sistema' (894), porque o saldo real está no vulto.db. 26 recadastros pós-2025 também tiveram os pontos zerados.
A21: Categoria | B21: DECISÃO DO USUÁRIO: usar a regra do arquivo 'clientes atualizado' (Bronze 1–1500, Prata 1501–5000, Ouro 5001–9999, Vip 10000+, vazio para 0 pontos), em vez da regra antiga do LEIA ISSO. Virou uma FÓRMULA ligada à tabela de faixas (muda sozinha se a faixa mudar). Antes era digitada à mão (bronze, BRONZE, brz, Silver, Gold, ouro ★, vip?...).
A22: Aceita Msg | B22: 8 formas diferentes (sim, S, 1, x, nao, N, 0, vazio) viraram Sim / Não / Não informado. Não informado deve ser tratado como NÃO (LGPD).
A23: Pendências | B23: Nova coluna que lista o que precisa conferir em cada cliente. Use o filtro dela.
A25: 3. ABA RESGATES
A26: Colunas | B26: Data, CPF, Nome do cliente (fórmula que busca pelo CPF), Pontos usados, Desconto lançado, Desconto pela regra (fórmula), Diferença, Loja, Atendente, Cliente (como anotado), Pendências.
A27: Datas e valores | B27: Datas em 5 formatos foram convertidas para data. Pontos ('1.000') e descontos ('R$ 50,0') que estavam como texto viraram número.
A28: Cliente | B28: Antes a coluna misturava CPF e nome (às vezes só o primeiro nome). Agora tem uma coluna CPF (padronizada) e a anotação original foi mantida em 'Cliente (como anotado)', para ninguém perder a informação.
A29: Identificação | B29: Dos 45 resgates sem cliente identificado, 24 foram resolvidos: nome completo único no cadastro, CPF com erro de digitação corrigido e cruzamento com a planilha de atendimentos (ex.: Luan, linha 413, pelo telefone).
A30: Sem cliente | B30: DECISÃO: os 21 restantes NÃO foram apagados. O desconto foi dado de verdade, e apagar só esconderia o problema (e o saldo de algum cliente pode estar errado). Ficam em amarelo, e 12 deles têm sugestão de cliente para a loja confirmar.
A31: Atendentes | B31: Nomes unificados (ex.: Thiago/tiago/THIAGO → Thiago; carlos.savassi → Carlos; jess.eldorado/jessica → Jéssica).
A32: Taxa de resgate | B32: Nova coluna 'Desconto pela regra' calcula pela taxa da data: R$ 10 por 100 pontos até fev/2025 e R$ 5 desde mar/2025. A coluna Diferença fica em VERMELHO quando o desconto lançado é maior que o da regra.
A34: 4. ACHADO IMPORTANTE: DESCONTO EM DOBRO
A35: O quê | B35: 420 resgates feitos desde mar/2025 foram calculados com a taxa antiga (R$ 10 em vez de R$ 5): R$ 17.795 de desconto a mais.
A36: Padrão | B36: TODOS os 420 são resgates sem atendente anotado, e todos com exatamente o dobro do valor. Nenhum resgate com atendente está errado. No Site, 100% estão errados; nas lojas, de 62% a 75%. O erro acontece todo mês até hoje.
A37: Conclusão | B37: Provável lançamento automático ou em lote (Site/integração) com a taxa antiga configurada. Não é erro das atendentes.
A38: DECISÃO | B38: Os valores NÃO foram alterados (o desconto já saiu). Fica para a empresa conferir no sistema e corrigir a configuração. O resumo por loja e por atendente está na aba Pendências (coluna Q em diante).
A40: 5. ABAS APAGADAS OU JUNTADAS (com autorização do usuário)
A41: Plan1 | B41: Apagada. Tinha contagens de categoria digitadas e desatualizadas (Bronze 300, Prata 140...). Foi substituída pelo resumo automático na aba Regras e Parâmetros.
A42: LEIA ISSO | B42: O texto foi levado para a aba Regras e Parâmetros (coluna E) e atualizado com as novas regras (taxa, categoria, LGPD, como usar a planilha).
A43: clientes antigos | B43: Apagada (programa de 2023, já migrado em jan/24). Antes, aproveitei o que importava: 31 clientes 'Ativo' que não foram migrados estão na aba Pendências (coluna K), e 29 clientes atuais que estavam 'Bloqueado' no programa antigo ganharam esse aviso na coluna Obs.
A44: Backups | B44: As cópias de segurança criadas durante a limpeza foram apagadas no fim. ⚠ Não dá para desfazer pela planilha: guarde o arquivo original se precisar consultar.
A46: 6. ABAS NOVAS
A47: Pendências | B47: Lista automática dos resgates sem cliente (sai da lista quando o CPF é preenchido), os clientes antigos não migrados e o resumo dos descontos acima da regra.
A48: Regras e Parâmetros | B48: Tabela de faixas de categoria, taxa de resgate por data, resumo de clientes por categoria (por fórmula) e as regras do programa.
A49: Faltam no outro arquivo | B49: 81 clientes: 80 que faltam no 'clientes atualizado' e 1 CPF errado lá (Alice Nogueira: 212.976.285-78 → 012.976.285-78).
A51: 7. COMPARAÇÃO COM 'clientes atualizado' (2.315 × 2.395)
A52: Resultado | B52: Todos os 2.315 clientes de lá estão aqui. Os 80 a mais aqui são clientes reais, todos com CPF começando com 0, que o outro arquivo perdeu (provavelmente porque o zero da frente sumiu e o CPF ficou com menos de 11 dígitos). 2.395 é o número correto.
A53: Também | B53: O outro arquivo marca 'Dados válidos = Sim' para todos, mas 28 CPFs de lá são inválidos.
A55: 8. O QUE AINDA DEPENDE DE ALGUÉM (não dá para resolver só com os dados)
A56: Resgates | B56: 11 sem cliente (R$ 500): 9 na aba Pendências + 2 não identificáveis. 4 têm sugestão.
A57: Desconto em dobro | B57: R$ 17.795: conferir no sistema e corrigir a taxa do Site/integração.
A58: Cadastro | B58: 319 telefones sem DDD, 18 sem e-mail, 23 CPFs inválidos, 198 datas aproximadas, 96 pontos aproximados: completar direto com o cliente.
A59: Saldos pós-2025 | B59: 894 clientes têm o saldo só no sistema (vulto.db).
A60: Regra Ouro 18 meses | B60: Combinada (segundo o LEIA ISSO) mas ainda não está no sistema.
A61: Outro arquivo | B61: Incluir os 80 clientes e corrigir o CPF da Alice no 'clientes atualizado', usando a aba Faltam no outro arquivo.
A63: 9. VARREDURA DOS RESGATES SÓ COM O PRIMEIRO NOME (feita em 19/10/2026)
A64: Como | B64: Script migracao/varredura_resgates.py (repo copy.vulto-legado-back), seguindo a aba Varredura: venda da mesma loja no dia do resgate (±1 dia) de cliente cujo nome começa com o anotado. O CPF só foi preenchido quando sobrou 1 cliente E o desconto da venda era igual ao desconto do resgate.
A65: Resolvidos | B65: 10 resgates (linhas 104, 144, 159, 249, 251, 265, 324, 394, 442 e 523 da aba Resgates): CPF na coluna B e a venda que comprova na coluna Pendências.
A66: Sugestões antigas | B66: 3 se confirmaram (Melissa 144, Carolina 251, Ícaro 324). 3 não: a venda do dia é de outro cliente (João 159 = João Oliveira Cardoso; Hugo 249 = Hugo Peixoto; Giovanna 265 = Giovanna Oliveira).
A67: Sugestão | B67: Linha 554 (Júlia, Savassi): a única venda do dia é da Julia Fernandes, mas com desconto de R$ 33,00 (o resgate é de R$ 25,00). Fica como sugestão, junto com a anterior (Júlia Peixoto Ferreira).
A68: Sem candidato | B68: Linha 582 (João, Eldorado, 16/09/2026): nenhuma venda de cliente com esse nome de 15 a 17/09.
A69: Sem fonte | B69: 6 resgates de 2023 e 2024 (linhas 15, 17, 53, 56, 58 e 59): o vulto.db só tem vendas a partir de 01/01/2025. Continuam para a loja confirmar.
A70: Resultado | B70: Pendências: de 19 para 9 casos (13.800 → 4.200 pontos; R$ 850 → R$ 370). No passivo de pontos, só 2 deles (1.000 pontos, de 2025 em diante) ainda podem mexer.

Sheet Clientes
A1: Nome | B1: CPF | C1: CPF válido | D1: E-mail | E1: Telefone | F1: Data Cadastro | G1: Loja Cadastro | H1: Pontos (até 01/01/2025) | I1: Categoria | J1: Aceita Msg | K1: Obs | L1: Pendências
A2: Alexandre Almeida Ribeiro | B2: 166.438.408-13 | C2: Sim | D2: alexandre.ribeiro28@yahoo.com.br | E2: 94371-6949 | F2: 44590 | G2: App | H2: 3638 | I2: =IF(H2<=0,"",LOOKUP(H2,'Regras e Parâmetros'!$B$4:$B$7,'Regras e Parâmetros'!$A$4:$A$7)) -> Prata | J2: Não informado | K2: Estava BLOQUEADO no programa antigo | L2: Telefone sem DDD
A3: Alexandre Batista | B3: 874.391.558-23 | C3: Sim | D3: alexandre.batista70@hotmail.com | E3: (41) 90723-3343 | F3: 44967 | G3: Batel | H3: 3321 | I3: =IF(H3<=0,"",LOOKUP(H3,'Regras e Parâmetros'!$B$4:$B$7,'Regras e Parâmetros'!$A$4:$A$7)) -> Prata | J3: Não informado
A4: Alexandre C. Alves | B4: 162.219.500-07 | C4: Sim | D4: alexandre.alves36@outlook.com | E4: 93581-6538 | F4: 45601 | G4: Pinheiros | H4: 75 | I4: =IF(H4<=0,"",LOOKUP(H4,'Regras e Parâmetros'!$B$4:$B$7,'Regras e Parâmetros'!$A$4:$A$7)) -> Bronze | J4: Não | L4: Telefone sem DDD
A5: Alexandre Cardoso | B5: 090.516.597-76 | C5: Sim | D5: alexandre504@gmail.com | E5: (41) 93307-2553 | F5: 45585 | G5: Batel | H5: 294 | I5: =IF(H5<=0,"",LOOKUP(H5,'Regras e Parâmetros'!$B$4:$B$7,'Regras e Parâmetros'!$A$4:$A$7)) -> Bronze | J5: Não informado | K5: Cadastro unificado (2 linhas: 1460, 2427) | Outros e-mails: alexandre.cardoso32@gmial.com | L5: Pontos de recadastro pós-2025 zerados
A6: Alexandre Correia | B6: 503.752.048-73 | C6: Sim | D6: alexandre.correia27@hotmail.com | E6: (85) 91904-3605 | F6: 45682 | G6: Site | H6: 0 | I6: =IF(H6<=0,"",LOOKUP(H6,'Regras e Parâmetros'!$B$4:$B$7,'Regras e Parâmetros'!$A$4:$A$7)) | J6: Sim | K6: aniversario em maio | L6: Pontos no sistema (cadastro após 01/01/2025)
A7: Alexandre Costa | B7: 615.278.307-05 | C7: Sim | D7: alexandre.costa92@icloud.com | E7: (11) 96608-7877 | F7: 46059 | G7: Pinheiros | H7: 0 | I7: =IF(H7<=0,"",LOOKUP(H7,'Regras e Parâmetros'!$B$4:$B$7,'Regras e Parâmetros'!$A$4:$A$7)) | J7: Sim | K7: cliente reclamou | L7: Pontos no sistema (cadastro após 01/01/2025)
A8: Alexandre Fernandes | B8: 140.620.046-82 | C8: Sim | D8: alexandre.fernandes83@icloud.com | E8: (11) 94054-8828 | F8: 45558 | G8: Eldorado | H8: 785 | I8: =IF(H8<=0,"",LOOKUP(H8,'Regras e Parâmetros'!$B$4:$B$7,'Regras e Parâmetros'!$A$4:$A$7)) -> Bronze | J8: Sim
A9: Alexandre Ferreira Araújo | B9: 605.917.487-62 | C9: Sim | D9: alexandre.araujo26@gmail.com | E9: (41) 95110-2094 | F9: 44510 | G9: Batel | H9: 508 | I9: =IF(H9<=0,"",LOOKUP(H9,'Regras e Parâmetros'!$B$4:$B$7,'Regras e Parâmetros'!$A$4:$A$7)) -> Bronze | J9: Não informado | K9: ver com gerente
A10: Alexandre Ferreira Pereira | B10: 785.912.707-54 | C10: Sim | D10: alexandre.pereira62@yahoo.com.br | E10: (11) 98465-0023 | F10: 45379 | G10: Pinheiros | H10: 305 | I10: =IF(H10<=0,"",LOOKUP(H10,'Regras e Parâmetros'!$B$4:$B$7,'Regras e Parâmetros'!$A$4:$A$7)) -> Bronze | J10: Sim
A11: Alexandre Freitas Ramos | B11: 826.620.339-32 | C11: Sim | D11: alexandre.ramos3@hotmail.com | E11: (11) 97561-9899 | F11: 45752 | G11: Pinheiros | H11: 0 | I11: =IF(H11<=0,"",LOOKUP(H11,'Regras e Parâmetros'!$B$4:$B$7,'Regras e Parâmetros'!$A$4:$A$7)) | J11: Não | L11: Pontos no sistema (cadastro após 01/01/2025)
A12: Alexandre Gomes | B12: 256.768.897-80 | C12: Sim | D12: alexandre.gomes37@icloud.com | E12: 94673-6967 | F12: 44937 | G12: Site | H12: 3042 | I12: =IF(H12<=0,"",LOOKUP(H12,'Regras e Parâmetros'!$B$4:$B$7,'Regras e Parâmetros'!$A$4:$A$7)) -> Prata | J12: Não informado | L12: Telefone sem DDD
A13: Alexandre Lopes Martins | B13: 420.881.664-32 | C13: Sim | D13: alexandre.martins92@hotmail.com | E13: (85) 99521-0580 | F13: 44624 | G13: App | H13: 884 | I13: =IF(H13<=0,"",LOOKUP(H13,'Regras e Parâmetros'!$B$4:$B$7,'Regras e Parâmetros'!$A$4:$A$7)) -> Bronze | J13: Não informado
A14: Alexandre Machado Almeida | B14: 406.037.566-70 | C14: Sim | D14: alexandre.almeida3@hotmail.com | E14: (41) 90244-7822 | F14: 46051 | G14: Site | H14: 0 | I14: =IF(H14<=0,"",LOOKUP(H14,'Regras e Parâmetros'!$B$4:$B$7,'Regras e Parâmetros'!$A$4:$A$7)) | J14: Não informado | L14: Pontos no sistema (cadastro após 01/01/2025)
A15: Alexandre Machado Cavalcanti | B15: 569.416.793-79 | C15: Sim | D15: alexandre.cavalcanti5@outlook.com | E15: (11) 90279-6820 | F15: 45614 | G15: Eldorado | H15: 135 | I15: =IF(H15<=0,"",LOOKUP(H15,'Regras e Parâmetros'!$B$4:$B$7,'Regras e Parâmetros'!$A$4:$A$7)) -> Bronze | J15: Não informado | K15: ver com gerente
A16: Alexandre Moreira Fonseca | B16: 250.088.560-73 | C16: Sim | E16: (11) 95372-9822 | F16: 45444 | G16: Eldorado | H16: 0 | I16: =IF(H16<=0,"",LOOKUP(H16,'Regras e Parâmetros'!$B$4:$B$7,'Regras e Parâmetros'!$A$4:$A$7)) | J16: Não informado | L16: Sem e-mail
A17: Alexandre Oliveira | B17: 291.910.183-82 | C17: Sim | D17: alexandre.oliveira15@gmial.com | E17: (31) 99866-0683 | F17: 44746 | G17: Savassi | H17: 1423 | I17: =IF(H17<=0,"",LOOKUP(H17,'Regras e Parâmetros'!$B$4:$B$7,'Regras e Parâmetros'!$A$4:$A$7)) -> Bronze | J17: Não informado | K17: aniversario em maio
A18: Alexandre Ribeiro | B18: 002.747.357-09 | C18: Sim | D18: alexandre.ribeiro51@hotmail.com | E18: (11) 94003-6688 | F18: 45121 | G18: Eldorado | H18: 1000 | I18: =IF(H18<=0,"",LOOKUP(H18,'Regras e Parâmetros'!$B$4:$B$7,'Regras e Parâmetros'!$A$4:$A$7)) -> Bronze | J18: Não | L18: Pontos aproximados (ex.: 2,7k)
A19: Alexandre Rocha Mendes | B19: 140.521.881-95 | C19: Sim | D19: alexandre.mendes92@hotmail.com | E19: (31) 97970-9642 | F19: 45425 | G19: Site | H19: 972 | I19: =IF(H19<=0,"",LOOKUP(H19,'Regras e Parâmetros'!$B$4:$B$7,'Regras e Parâmetros'!$A$4:$A$7)) -> Bronze | J19: Não informado | K19: cliente reclamou
A20: Alexandre Tavares | B20: 105.288.691-40 | C20: Sim | D20: alexandre.tavares50@outlook.com | E20: 96783-6339 | F20: 45428 | G20: Site | H20: 0 | I20: =IF(H20<=0,"",LOOKUP(H20,'Regras e Parâmetros'!$B$4:$B$7,'Regras e Parâmetros'!$A$4:$A$7)) | J20: Sim | L20: Telefone sem DDD
A21: Alice Andrade | B21: 850.663.524-14 | C21: Sim | D21: alice.andrade63@bol.com.br | E21: (11) 92623-8139 | F21: 45834 | G21: Eldorado | H21: 0 | I21: =IF(H21<=0,"",LOOKUP(H21,'Regras e Parâmetros'!$B$4:$B$7,'Regras e Parâmetros'!$A$4:$A$7)) | J21: Não | L21: Pontos no sistema (cadastro após 01/01/2025)
A22: Alice Andrade Dias | B22: 925.262.202-03 | C22: Sim | D22: alice.dias2@bol.com.br | E22: (41) 99085-6913 | F22: 45834 | G22: Site | H22: 0 | I22: =IF(H22<=0,"",LOOKUP(H22,'Regras e Parâmetros'!$B$4:$B$7,'Regras e Parâmetros'!$A$4:$A$7)) | J22: Não informado | K22: cliente reclamou | L22: Pontos no sistema (cadastro após 01/01/2025)
A23: Alice Batista Farias | B23: 677.217.774-61 | C23: Sim | D23: alice.farias36@gmail.com | E23: (11) 99997-9423 | F23: 45548 | G23: Site | H23: 88 | I23: =IF(H23<=0,"",LOOKUP(H23,'Regras e Parâmetros'!$B$4:$B$7,'Regras e Parâmetros'!$A$4:$A$7)) -> Bronze | J23: Não | K23: não ligar
A24: Alice C. Machado | B24: 447.502.186-34 | C24: Sim | D24: alice.machado83@uol.com.br | E24: (41) 98741-0686 | F24: 45413 | G24: Batel | H24: 200 | I24: =IF(H24<=0,"",LOOKUP(H24,'Regras e Parâmetros'!$B$4:$B$7,'Regras e Parâmetros'!$A$4:$A$7)) -> Bronze | J24: Não informado | L24: Data aproximada (só mês/ano)
A25: Alice Cardoso Alves | B25: 105.916.969-08 | C25: Sim | D25: alice.alves72@gmail.com | E25: (21) 96526-5164 | F25: 45191 | G25: App | H25: 97 | I25: =IF(H25<=0,"",LOOKUP(H25,'Regras e Parâmetros'!$B$4:$B$7,'Regras e Parâmetros'!$A$4:$A$7)) -> Bronze | J25: Sim
A26: Alice Correia | B26: 485.479.084-98 | C26: Sim | D26: alice.correia3@hotmail.com | E26: (41) 99478-3236 | F26: 44926 | G26: App | H26: 1823 | I26: =IF(H26<=0,"",LOOKUP(H26,'Regras e Parâmetros'!$B$4:$B$7,'Regras e Parâmetros'!$A$4:$A$7)) -> Prata | J26: Não
A27: Alice Correia | B27: 783.626.843-80 | C27: Sim | D27: alice.correia105@hotmail.com | E27: (31) 97092-2008 | F27: 45261 | G27: Savassi | H27: 1414 | I27: =IF(H27<=0,"",LOOKUP(H27,'Regras e Parâmetros'!$B$4:$B$7,'Regras e Parâmetros'!$A$4:$A$7)) -> Bronze | J27: Sim | K27: Cadastro unificado (2 linhas: 1135, 1435) | Outros e-mails: alice.correia10@hotmail.com | L27: Data aproximada (só mês/ano)
A28: Alice D. Rodrigues | B28: 893.877.273-00 | C28: Sim | D28: alice.rodrigues25@gmail.com | E28: (31) 96413-5345 | F28: 44800 | G28: Savassi | H28: 5717 | I28: =IF(H28<=0,"",LOOKUP(H28,'Regras e Parâmetros'!$B$4:$B$7,'Regras e Parâmetros'!$A$4:$A$7)) -> Ouro | J28: Não informado
A29: Alice Dias Ferreira | B29: 397.719.945-57 | C29: Sim | D29: alice.ferreira76@gmail.com | E29: 91490-7638 | F29: 45865 | G29: App | H29: 0 | I29: =IF(H29<=0,"",LOOKUP(H29,'Regras e Parâmetros'!$B$4:$B$7,'Regras e Parâmetros'!$A$4:$A$7)) | J29: Sim | L29: Pontos no sistema (cadastro após 01/01/2025) | Telefone sem DDD
A30: Alice Ferreira Ribeiro | B30: 001.973.032-26 | C30: Sim | D30: alice.ribeiro87@outlook.com | E30: (11) 97259-2263 | F30: 45444 | G30: App | H30: 5596 | I30: =IF(H30<=0,"",LOOKUP(H30,'Regras e Parâmetros'!$B$4:$B$7,'Regras e Parâmetros'!$A$4:$A$7)) -> Ouro | J30: Não
A31: Alice Fonseca | B31: 941.377.422-60 | C31: Sim | D31: alice.fonseca86@icloud.com | E31: (62) 91890-9061 | F31: 44845 | G31: Site | H31: 1123 | I31: =IF(H31<=0,"",LOOKUP(H31,'Regras e Parâmetros'!$B$4:$B$7,'Regras e Parâmetros'!$A$4:$A$7)) -> Bronze | J31: Sim | K31: não ligar
A32: Alice Gomes | B32: 627.532.074-53 | C32: Sim | D32: alice.gomes14@uol.com.br | E32: (31) 92897-6385 | F32: 45382 | G32: Savassi | H32: 2700 | I32: =IF(H32<=0,"",LOOKUP(H32,'Regras e Parâmetros'!$B$4:$B$7,'Regras e Parâmetros'!$A$4:$A$7)) -> Prata | J32: Não | K32: aniversario em maio | L32: Pontos aproximados (ex.: 2,7k)
A33: Alice Marques Correia | B33: 713.929.904-83 | C33: Sim | D33: alice.correia64@gmail.com | E33: (11) 91527-3444 | F33: 45444 | G33: Pinheiros | H33: 1298 | I33: =IF(H33<=0,"",LOOKUP(H33,'Regras e Parâmetros'!$B$4:$B$7,'Regras e Parâmetros'!$A$4:$A$7)) -> Bronze | J33: Não informado | L33: Data aproximada (só mês/ano)
A34: Alice Marques Teixeira | B34: 868.471.190-47 | C34: Sim | D34: alice.teixeira9@gmail.com | E34: (11) 98823-7237 | F34: 44367 | G34: Pinheiros | H34: 2373 | I34: =IF(H34<=0,"",LOOKUP(H34,'Regras e Parâmetros'!$B$4:$B$7,'Regras e Parâmetros'!$A$4:$A$7)) -> Prata | J34: Sim
A35: Alice Monteiro Moreira | B35: 920.354.730-47 | C35: Sim | D35: alice.moreira16@uol.com.br | E35: (31) 98825-2395 | F35: 44632 | G35: Savassi | H35: 3100 | I35: =IF(H35<=0,"",LOOKUP(H35,'Regras e Parâmetros'!$B$4:$B$7,'Regras e Parâmetros'!$A$4:$A$7)) -> Prata | J35: Sim | L35: Pontos aproximados (ex.: 2,7k)
A36: Alice Moreira Lima | B36: 085.763.295-73 | C36: Sim | D36: alice.lima85@hotmail.com | E36: (11) 94421-2062 | F36: 44621 | G36: Eldorado | H36: 658 | I36: =IF(H36<=0,"",LOOKUP(H36,'Regras e Parâmetros'!$B$4:$B$7,'Regras e Parâmetros'!$A$4:$A$7)) -> Bronze | J36: Não | L36: Data aproximada (só mês/ano)
A37: Alice Moura | B37: 705.054.626-72 | C37: Sim | D37: alice.moura71@yahoo.com.br | E37: (51) 92821-5195 | F37: 45217 | G37: App | H37: 771 | I37: =IF(H37<=0,"",LOOKUP(H37,'Regras e Parâmetros'!$B$4:$B$7,'Regras e Parâmetros'!$A$4:$A$7)) -> Bronze | J37: Não
A38: Alice Nogueira | B38: 888.288.629-80 | C38: Sim | D38: alice.nogueira97@outlook.com | E38: 95302-9297 | F38: 45397 | G38: App | H38: 2712 | I38: =IF(H38<=0,"",LOOKUP(H38,'Regras e Parâmetros'!$B$4:$B$7,'Regras e Parâmetros'!$A$4:$A$7)) -> Prata | J38: Não | L38: Telefone sem DDD
A39: Alice Nogueira | B39: 012.976.285-78 | C39: Sim | D39: alice.nogueira43@outlook.com | E39: 95722-2852 | F39: 45872 | G39: Pinheiros | H39: 0 | I39: =IF(H39<=0,"",LOOKUP(H39,'Regras e Parâmetros'!$B$4:$B$7,'Regras e Parâmetros'!$A$4:$A$7)) | J39: Não informado | K39: CPF corrigido em 19/10/2026 (era 212.976.285-78, inválido; o correto veio dos resgates) | L39: Pontos no sistema (cadastro após 01/01/2025) | Telefone sem DDD
A40: Alice Oliveira Machado | B40: 316.389.963-34 | C40: Sim | D40: alice.machado13@icloud.com | E40: (11) 93748-4445 | F40: 44927 | G40: Eldorado | H40: 1105 | I40: =IF(H40<=0,"",LOOKUP(H40,'Regras e Parâmetros'!$B$4:$B$7,'Regras e Parâmetros'!$A$4:$A$7)) -> Bronze | J40: Não informado | L40: Data aproximada (só mês/ano)
A41: Alice Ribeiro Alves | B41: 575.810.313-65 | C41: Sim | D41: alice.alves18@yahoo.com.br | E41: (11) 93277-8121 | F41: 44452 | G41: Site | H41: 3196 | I41: =IF(H41<=0,"",LOOKUP(H41,'Regras e Parâmetros'!$B$4:$B$7,'Regras e Parâmetros'!$A$4:$A$7)) -> Prata | J41: Sim
A42: Alice Rocha Pereira | B42: 374.254.923-50 | C42: Sim | D42: alice.pereira32@uol.com.br | E42: 91817-6487 | F42: 44484 | G42: Eldorado | H42: 692 | I42: =IF(H42<=0,"",LOOKUP(H42,'Regras e Parâmetros'!$B$4:$B$7,'Regras e Parâmetros'!$A$4:$A$7)) -> Bronze | J42: Sim | L42: Telefone sem DDD
A43: Alice Santana Rodrigues | B43: 418.229.060-75 | C43: Sim | D43: alice.rodrigues37@gmail.com | E43: (21) 91831-9725 | F43: 46025 | G43: Site | H43: 0 | I43: =IF(H43<=0,"",LOOKUP(H43,'Regras e Parâmetros'!$B$4:$B$7,'Regras e Parâmetros'!$A$4:$A$7)) | J43: Não informado | L43: Pontos no sistema (cadastro após 01/01/2025)
A44: Aline Almeida | B44: 189.839.983-26 | C44: Sim | D44: aline.almeida78@gmail.com | E44: (11) 95176-9022 | F44: 44547 | G44: Pinheiros | H44: 0 | I44: =IF(H44<=0,"",LOOKUP(H44,'Regras e Parâmetros'!$B$4:$B$7,'Regras e Parâmetros'!$A$4:$A$7)) | J44: Não informado | K44: ver com gerente
A45: Aline Alves Cardoso | B45: 193.118.618-98 | C45: Sim | D45: aline.cardoso53@bol.com.br | E45: (11) 92405-9703 | F45: 45856 | G45: Pinheiros | H45: 0 | I45: =IF(H45<=0,"",LOOKUP(H45,'Regras e Parâmetros'!$B$4:$B$7,'Regras e Parâmetros'!$A$4:$A$7)) | J45: Não | K45: trocou de cpf? | L45: Pontos no sistema (cadastro após 01/01/2025)
A46: Aline Alves Carvalho | B46: 581.935.772-80 | C46: Sim | D46: aline.carvalho24@outlook.com | E46: (11) 97140-6709 | F46: 45665 | G46: Site | H46: 0 | I46: =IF(H46<=0,"",LOOKUP(H46,'Regras e Parâmetros'!$B$4:$B$7,'Regras e Parâmetros'!$A$4:$A$7)) | J46: Não | K46: VIP | L46: Pontos no sistema (cadastro após 01/01/2025)
A47: Aline Araújo | B47: 108.143.902-50 | C47: Sim | D47: aline.araujo85@yahoo.com.br | E47: (11) 90580-3144 | F47: 44634 | G47: App | H47: 290 | I47: =IF(H47<=0,"",LOOKUP(H47,'Regras e Parâmetros'!$B$4:$B$7,'Regras e Parâmetros'!$A$4:$A$7)) -> Bronze | J47: Sim
A48: Aline Araújo | B48: 219.385.130-10 | C48: Sim | D48: aline.araujo29@hotmail.com | E48: (11) 90397-8437 | F48: 45528 | G48: Eldorado | H48: 3041 | I48: =IF(H48<=0,"",LOOKUP(H48,'Regras e Parâmetros'!$B$4:$B$7,'Regras e Parâmetros'!$A$4:$A$7)) -> Prata | J48: Não informado
A49: Aline Barbosa Barros | B49: 883.620.557-20 | C49: Não | D49: aline.barros9@hotmail.com | E49: (11) 92805-4214 | F49: 45142 | G49: Pinheiros | H49: 1477 | I49: =IF(H49<=0,"",LOOKUP(H49,'Regras e Parâmetros'!$B$4:$B$7,'Regras e Parâmetros'!$A$4:$A$7)) -> Bronze | J49: Não informado | K49: VIP | L49: CPF inválido – no próximo login o cliente precisa atualizar os dados para continuar usando os benefícios do programa
A50: Aline Barbosa Pereira | B50: 022.119.698-60 | C50: Sim | D50: aline.pereira36@bol.com.br | E50: (41) 96280-7938 | F50: 45383 | G50: App | H50: 0 | I50: =IF(H50<=0,"",LOOKUP(H50,'Regras e Parâmetros'!$B$4:$B$7,'Regras e Parâmetros'!$A$4:$A$7)) | J50: Não informado
A51: Aline Barros | B51: 752.099.584-42 | C51: Sim | D51: aline.barros64@uol.com.br | E51: (11) 95102-1527 | F51: 44349 | G51: Site | H51: 2203 | I51: =IF(H51<=0,"",LOOKUP(H51,'Regras e Parâmetros'!$B$4:$B$7,'Regras e Parâmetros'!$A$4:$A$7)) -> Prata | J51: Não informado | K51: aniversario em maio
A52: Aline C. Gomes | B52: 838.178.990-76 | C52: Sim | D52: aline.gomes5@gmail.com | E52: (11) 90402-2367 | F52: 46163 | G52: App | H52: 0 | I52: =IF(H52<=0,"",LOOKUP(H52,'Regras e Parâmetros'!$B$4:$B$7,'Regras e Parâmetros'!$A$4:$A$7)) | J52: Sim | L52: Pontos no sistema (cadastro após 01/01/2025)
A53: Aline Cardoso | B53: 633.098.355-02 | C53: Sim | D53: aline.cardoso52@outlook.com | E53: (11) 96511-7591 | F53: 45608 | G53: Site | H53: 519 | I53: =IF(H53<=0,"",LOOKUP(H53,'Regras e Parâmetros'!$B$4:$B$7,'Regras e Parâmetros'!$A$4:$A$7)) -> Bronze | J53: Não
A54: Aline Cardoso Costa | B54: 120.465.661-49 | C54: Sim | D54: aline.costa45@hotmail.com | E54: (11) 92538-7729 | F54: 45399 | G54: Eldorado | H54: 639 | I54: =IF(H54<=0,"",LOOKUP(H54,'Regras e Parâmetros'!$B$4:$B$7,'Regras e Parâmetros'!$A$4:$A$7)) -> Bronze | J54: Não informado
A55: Aline Carvalho Costa | B55: 393.427.106-54 | C55: Sim | D55: aline.costa344@hotmail.com | E55: (41) 94825-3542 | F55: 45954 | G55: Batel | H55: 0 | I55: =IF(H55<=0,"",LOOKUP(H55,'Regras e Parâmetros'!$B$4:$B$7,'Regras e Parâmetros'!$A$4:$A$7)) | J55: Não | K55: ver com gerente | cadastro refeito | Cadastro unificado (2 linhas: 1997, 2510) | Outros e-mails: aline.costa34@hotmail.com | L55: Pontos no sistema (cadastro após 01/01/2025)
A56: Aline Farias | B56: 084.388.703-68 | C56: Sim | D56: aline.farias71@gmail.com | E56: (11) 96487-5191 | F56: 44971 | G56: Eldorado | H56: 381 | I56: =IF(H56<=0,"",LOOKUP(H56,'Regras e Parâmetros'!$B$4:$B$7,'Regras e Parâmetros'!$A$4:$A$7)) -> Bronze | J56: Não informado
A57: Aline Fernandes | B57: 458.740.530-26 | C57: Sim | D57: aline.fernandes40@outlook.com | E57: (51) 92155-2771 | F57: 45633 | G57: App | H57: 6982 | I57: =IF(H57<=0,"",LOOKUP(H57,'Regras e Parâmetros'!$B$4:$B$7,'Regras e Parâmetros'!$A$4:$A$7)) -> Ouro | J57: Não informado
A58: Aline Goncalves Campos | B58: 133.528.890-23 | C58: Sim | D58: aline.campos67@bol.com.br | E58: (11) 95296-8800 | F58: 45091 | G58: Pinheiros | H58: 3672 | I58: =IF(H58<=0,"",LOOKUP(H58,'Regras e Parâmetros'!$B$4:$B$7,'Regras e Parâmetros'!$A$4:$A$7)) -> Prata | J58: Não informado
A59: Aline Gonçalves Costa | B59: 136.811.304-42 | C59: Sim | D59: aline.costa272@hotmail.com | E59: (11) 97873-0697 | F59: 45747 | G59: App | H59: 0 | I59: =IF(H59<=0,"",LOOKUP(H59,'Regras e Parâmetros'!$B$4:$B$7,'Regras e Parâmetros'!$A$4:$A$7)) | J59: Sim | K59: cadastro refeito | Cadastro unificado (2 linhas: 1698, 2056) | Outros e-mails: aline.costa27@hotmail.com | L59: Pontos no sistema (cadastro após 01/01/2025)
A60: Aline Lima Costa | B60: 311.161.674-68 | C60: Sim | D60: aline.costa96@gmail.com | E60: (11) 95649-3621 | F60: 45113 | G60: Eldorado | H60: 1123 | I60: =IF(H60<=0,"",LOOKUP(H60,'Regras e Parâmetros'!$B$4:$B$7,'Regras e Parâmetros'!$A$4:$A$7)) -> Bronze | J60: Não | K60: trocou de cpf?
A61: Aline Machado | B61: 428.889.549-90 | C61: Sim | D61: aline.machado83@icloud.com | E61: (47) 97780-6779 | F61: 44385 | G61: Site | H61: 531 | I61: =IF(H61<=0,"",LOOKUP(H61,'Regras e Parâmetros'!$B$4:$B$7,'Regras e Parâmetros'!$A$4:$A$7)) -> Bronze | J61: Não informado | K61: aniversario em maio
A62: Aline Machado Rodrigues | B62: 031.621.647-02 | C62: Sim | D62: aline.rodrigues92@hotmail.com | E62: 92451-7672 | F62: 45799 | G62: Eldorado | H62: 0 | I62: =IF(H62<=0,"",LOOKUP(H62,'Regras e Parâmetros'!$B$4:$B$7,'Regras e Parâmetros'!$A$4:$A$7)) | J62: Sim | K62: cadastro refeito | L62: Pontos no sistema (cadastro após 01/01/2025) | Telefone sem DDD
A63: Aline Marques Barros | B63: 138.252.763-25 | C63: Sim | D63: aline.barros23@bol.com.br | E63: (11) 90703-6452 | F63: 45689 | G63: Eldorado | H63: 0 | I63: =IF(H63<=0,"",LOOKUP(H63,'Regras e Parâmetros'!$B$4:$B$7,'Regras e Parâmetros'!$A$4:$A$7)) | J63: Não | L63: Pontos no sistema (cadastro após 01/01/2025) | Data aproximada (só mês/ano)
A64: Aline Mendes | B64: 174.326.530-11 | C64: Sim | D64: aline.mendes34@gmail.com | E64: (48) 97834-1122 | F64: 46155 | G64: App | H64: 0 | I64: =IF(H64<=0,"",LOOKUP(H64,'Regras e Parâmetros'!$B$4:$B$7,'Regras e Parâmetros'!$A$4:$A$7)) | J64: Não | L64: Pontos no sistema (cadastro após 01/01/2025)
A65: Aline Nascimento Freitas | B65: 394.003.178-08 | C65: Sim | D65: aline.freitas5@outlook.com | E65: (41) 93913-9396 | F65: 45528 | G65: Batel | H65: 402 | I65: =IF(H65<=0,"",LOOKUP(H65,'Regras e Parâmetros'!$B$4:$B$7,'Regras e Parâmetros'!$A$4:$A$7)) -> Bronze | J65: Sim | K65: ver com gerente
A66: Aline Ramos | B66: 951.575.739-87 | C66: Sim | D66: aline.ramos86@gmail.com | E66: (51) 91671-0891 | F66: 44502 | G66: App | H66: 9981 | I66: =IF(H66<=0,"",LOOKUP(H66,'Regras e Parâmetros'!$B$4:$B$7,'Regras e Parâmetros'!$A$4:$A$7)) -> Ouro | J66: Não
A67: Aline Rezende Soares | B67: 747.385.815-70 | C67: Sim | D67: aline.soares14@bol.com.br | E67: (11) 91946-0692 | F67: 45510 | G67: App | H67: 769 | I67: =IF(H67<=0,"",LOOKUP(H67,'Regras e Parâmetros'!$B$4:$B$7,'Regras e Parâmetros'!$A$4:$A$7)) -> Bronze | J67: Sim
A68: Aline Rocha | B68: 454.819.837-70 | C68: Sim | D68: aline.rocha44@gmail.com | E68: (71) 97333-2854 | F68: 44371 | G68: App | H68: 0 | I68: =IF(H68<=0,"",LOOKUP(H68,'Regras e Parâmetros'!$B$4:$B$7,'Regras e Parâmetros'!$A$4:$A$7)) | J68: Sim | K68: Estava BLOQUEADO no programa antigo
A69: Aline Santana | B69: 344.462.665-78 | C69: Sim | D69: aline.santana13@gmail.com | E69: (11) 91743-5771 | F69: 45910 | G69: Site | H69: 0 | I69: =IF(H69<=0,"",LOOKUP(H69,'Regras e Parâmetros'!$B$4:$B$7,'Regras e Parâmetros'!$A$4:$A$7)) | J69: Não informado | L69: Pontos no sistema (cadastro após 01/01/2025)
A70: Aline Silva Freitas | B70: 879.981.910-40 | C70: Sim | D70: aline.freitas92@gmail.com | E70: (31) 97714-2234 | F70: 45139 | G70: Site | H70: 218 | I70: =IF(H70<=0,"",LOOKUP(H70,'Regras e Parâmetros'!$B$4:$B$7,'Regras e Parâmetros'!$A$4:$A$7)) -> Bronze | J70: Sim | L70: Data aproximada (só mês/ano)
A71: Aline Soares | B71: 832.682.561-12 | C71: Sim | D71: aline.soares26@gmail.com | E71: 91258-7201 | F71: 44379 | G71: Savassi | H71: 0 | I71: =IF(H71<=0,"",LOOKUP(H71,'Regras e Parâmetros'!$B$4:$B$7,'Regras e Parâmetros'!$A$4:$A$7)) | J71: Não | L71: Telefone sem DDD
A72: Aline Teixeira | B72: 733.071.206-03 | C72: Sim | D72: aline.teixeira8@hotmail.com | E72: (11) 99049-9104 | F72: 44563 | G72: Eldorado | H72: 318 | I72: =IF(H72<=0,"",LOOKUP(H72,'Regras e Parâmetros'!$B$4:$B$7,'Regras e Parâmetros'!$A$4:$A$7)) -> Bronze | J72: Não
A73: Aline Teixeira Nascimento | B73: 383.154.106-01 | C73: Sim | D73: aline.nascimento8@gmail.com | E73: (85) 95251-7632 | F73: 44755 | G73: App | H73: 0 | I73: =IF(H73<=0,"",LOOKUP(H73,'Regras e Parâmetros'!$B$4:$B$7,'Regras e Parâmetros'!$A$4:$A$7)) | J73: Não
A74: Aline Teixeira Peixoto | B74: 829.813.272-67 | C74: Sim | D74: aline.peixoto62@icloud.com | E74: (11) 98577-3025 | F74: 45913 | G74: Pinheiros | H74: 0 | I74: =IF(H74<=0,"",LOOKUP(H74,'Regras e Parâmetros'!$B$4:$B$7,'Regras e Parâmetros'!$A$4:$A$7)) | J74: Não informado | L74: Pontos no sistema (cadastro após 01/01/2025)
A75: Ana Barbosa Moura | B75: 781.460.955-00 | C75: Sim | D75: ana.moura4@gmail.com | E75: (31) 92132-1004 | F75: 46274 | G75: Site | H75: 0 | I75: =IF(H75<=0,"",LOOKUP(H75,'Regras e Parâmetros'!$B$4:$B$7,'Regras e Parâmetros'!$A$4:$A$7)) | J75: Não | K75: cadastro refeito | L75: Pontos no sistema (cadastro após 01/01/2025)
A76: Ana Cavalcanti | B76: 359.687.364-96 | C76: Sim | D76: ana.cavalcanti18@gmail.com | E76: (31) 99324-2948 | F76: 44517 | G76: App | H76: 1485 | I76: =IF(H76<=0,"",LOOKUP(H76,'Regras e Parâmetros'!$B$4:$B$7,'Regras e Parâmetros'!$A$4:$A$7)) -> Bronze | J76: Não informado
A77: Ana Costa Martins | B77: 536.631.279-58 | C77: Sim | D77: ana.martins3@bol.com.br | E77: (62) 97501-7584 | F77: 45534 | G77: App | H77: 1582 | I77: =IF(H77<=0,"",LOOKUP(H77,'Regras e Parâmetros'!$B$4:$B$7,'Regras e Parâmetros'!$A$4:$A$7)) -> Prata | J77: Sim
A78: Ana Farias | B78: 780.930.930-79 | C78: Sim | D78: ana.farias68@hotmail.com | E78: (11) 95467-3989 | F78: 44704 | G78: Pinheiros | H78: 11667 | I78: =IF(H78<=0,"",LOOKUP(H78,'Regras e Parâmetros'!$B$4:$B$7,'Regras e Parâmetros'!$A$4:$A$7)) -> Vip | J78: Não informado
A79: Ana Farias | B79: 825.290.263-43 | C79: Sim | D79: ana.farias196@outlook.com | E79: (31) 93154-1441 | F79: 45255 | G79: Savassi | H79: 0 | I79: =IF(H79<=0,"",LOOKUP(H79,'Regras e Parâmetros'!$B$4:$B$7,'Regras e Parâmetros'!$A$4:$A$7)) | J79: Sim | K79: Cadastro unificado (2 linhas: 1110, 1884) | Outros e-mails: ana.farias19@outlook.com
A80: Ana Fernandes Silva | B80: 979.901.638-02 | C80: Sim | D80: ana.silva96@gmail.com | E80: (11) 97694-4214 | F80: 45735 | G80: Eldorado | H80: 0 | I80: =IF(H80<=0,"",LOOKUP(H80,'Regras e Parâmetros'!$B$4:$B$7,'Regras e Parâmetros'!$A$4:$A$7)) | J80: Sim | K80: não ligar | L80: Pontos no sistema (cadastro após 01/01/2025)
A81: Ana Fonseca | B81: 546.876.878-06 | C81: Sim | D81: ana.fonseca70@gmail.com | E81: (11) 98386-0517 | F81: 45342 | G81: Eldorado | H81: 15000 | I81: =IF(H81<=0,"",LOOKUP(H81,'Regras e Parâmetros'!$B$4:$B$7,'Regras e Parâmetros'!$A$4:$A$7)) -> Vip | J81: Sim
A82: Ana Fonseca | B82: 736.497.716-32 | C82: Sim | D82: ana.fonseca76@gmail.com | E82: (61) 98820-1942 | F82: 45596 | G82: Site | H82: 404 | I82: =IF(H82<=0,"",LOOKUP(H82,'Regras e Parâmetros'!$B$4:$B$7,'Regras e Parâmetros'!$A$4:$A$7)) -> Bronze | J82: Não informado
A83: Ana Gomes | B83: 954.768.436-12 | C83: Sim | D83: ana.gomes49@gmail.com | E83: (11) 93032-6406 | F83: 46232 | G83: Pinheiros | H83: 0 | I83: =IF(H83<=0,"",LOOKUP(H83,'Regras e Parâmetros'!$B$4:$B$7,'Regras e Parâmetros'!$A$4:$A$7)) | J83: Não informado | L83: Pontos no sistema (cadastro após 01/01/2025)
A84: Ana Gomes | B84: 013.651.224-09 | C84: Sim | D84: ana.gomes90@gmail.com | E84: (11) 93439-5506 | F84: 46260 | G84: Pinheiros | H84: 0 | I84: =IF(H84<=0,"",LOOKUP(H84,'Regras e Parâmetros'!$B$4:$B$7,'Regras e Parâmetros'!$A$4:$A$7)) | J84: Não | L84: Pontos no sistema (cadastro após 01/01/2025)
A85: Ana Gomes Marques | B85: 673.814.856-99 | C85: Sim | D85: ana.marques43@gmail.com | E85: (11) 90884-5208 | F85: 44845 | G85: Pinheiros | H85: 3928 | I85: =IF(H85<=0,"",LOOKUP(H85,'Regras e Parâmetros'!$B$4:$B$7,'Regras e Parâmetros'!$A$4:$A$7)) -> Prata | J85: Não | K85: aniversario em maio
A86: Ana Gonçalves | B86: 104.286.394-61 | C86: Sim | D86: ana.goncalves963@hotmail.com | E86: (31) 95278-3799 | F86: 45445 | G86: Savassi | H86: 236 | I86: =IF(H86<=0,"",LOOKUP(H86,'Regras e Parâmetros'!$B$4:$B$7,'Regras e Parâmetros'!$A$4:$A$7)) -> Bronze | J86: Não informado | K86: cliente reclamou | Cadastro unificado (2 linhas: 1292, 2100) | Outros e-mails: ana.goncalves96@hotmail.com | L86: Pontos de recadastro pós-2025 zerados
A87: Ana Machado | B87: 462.709.601-18 | C87: Sim | D87: ana.machado19@yahoo.com.br | E87: (19) 96152-7912 | F87: 44531 | G87: Site | H87: 3370 | I87: =IF(H87<=0,"",LOOKUP(H87,'Regras e Parâmetros'!$B$4:$B$7,'Regras e Parâmetros'!$A$4:$A$7)) -> Prata | J87: Sim
A88: Ana Mendes | B88: 971.794.885-26 | C88: Sim | D88: ana.mendes21@gmail.com | E88: (11) 90364-7965 | F88: 45238 | G88: Site | H88: 5018 | I88: =IF(H88<=0,"",LOOKUP(H88,'Regras e Parâmetros'!$B$4:$B$7,'Regras e Parâmetros'!$A$4:$A$7)) -> Ouro | J88: Sim
A89: Ana Nascimento | B89: 071.412.802-35 | C89: Sim | D89: ana.nascimento22@bol.com.br | E89: 93625-8743 | F89: 44534 | G89: Savassi | H89: 946 | I89: =IF(H89<=0,"",LOOKUP(H89,'Regras e Parâmetros'!$B$4:$B$7,'Regras e Parâmetros'!$A$4:$A$7)) -> Bronze | J89: Sim | K89: VIP | L89: Telefone sem DDD
A90: Ana Nogueira | B90: 345.786.103-06 | C90: Sim | D90: ana.nogueira91@outlook.com | E90: (11) 91604-8494 | F90: 46235 | G90: Site | H90: 0 | I90: =IF(H90<=0,"",LOOKUP(H90,'Regras e Parâmetros'!$B$4:$B$7,'Regras e Parâmetros'!$A$4:$A$7)) | J90: Não informado | L90: Pontos no sistema (cadastro após 01/01/2025) | Data aproximada (só mês/ano)
A91: Ana Nogueira Nunes | B91: 984.711.503-60 | C91: Sim | D91: ana.nunes38@uol.com.br | E91: (41) 92834-4812 | F91: 44649 | G91: Batel | H91: 906 | I91: =IF(H91<=0,"",LOOKUP(H91,'Regras e Parâmetros'!$B$4:$B$7,'Regras e Parâmetros'!$A$4:$A$7)) -> Bronze | J91: Não
A92: Ana Peixoto | B92: 982.395.665-02 | C92: Sim | D92: ana.peixoto94@bol.com.br | E92: (47) 96365-4291 | F92: 44949 | G92: Site | H92: 800 | I92: =IF(H92<=0,"",LOOKUP(H92,'Regras e Parâmetros'!$B$4:$B$7,'Regras e Parâmetros'!$A$4:$A$7)) -> Bronze | J92: Não
A93: Ana Pereira | B93: 192.379.275-09 | C93: Sim | D93: ana.pereira37@hotmail.com | E93: (41) 95448-9178 | F93: 44376 | G93: Batel | H93: 1207 | I93: =IF(H93<=0,"",LOOKUP(H93,'Regras e Parâmetros'!$B$4:$B$7,'Regras e Parâmetros'!$A$4:$A$7)) -> Bronze | J93: Não
A94: Ana Pereira | B94: 941.720.716-43 | C94: Sim | D94: ana.pereira24@gmail.com | E94: 96836-9315 | F94: 44438 | G94: App | H94: 177 | I94: =IF(H94<=0,"",LOOKUP(H94,'Regras e Parâmetros'!$B$4:$B$7,'Regras e Parâmetros'!$A$4:$A$7)) -> Bronze | J94: Sim | L94: Telefone sem DDD
A95: Ana Pinto | B95: 077.824.827-55 | C95: Sim | D95: ana.pinto99@outlook.com | E95: 97365-6883 | F95: 44565 | G95: App | H95: 5232 | I95: =IF(H95<=0,"",LOOKUP(H95,'Regras e Parâmetros'!$B$4:$B$7,'Regras e Parâmetros'!$A$4:$A$7)) -> Ouro | J95: Não informado | L95: Telefone sem DDD
A96: Ana Pinto Nogueira | B96: 572.178.736-81 | C96: Sim | D96: ana.nogueira136@gmail.com | E96: (31) 94013-2998 | F96: 44378 | G96: Savassi | H96: 13019 | I96: =IF(H96<=0,"",LOOKUP(H96,'Regras e Parâmetros'!$B$4:$B$7,'Regras e Parâmetros'!$A$4:$A$7)) -> Vip | J96: Sim | K96: Cadastro unificado (2 linhas: 52, 562) | Outros e-mails: ana.nogueira13@gmail.com | L96: Data aproximada (só mês/ano)
A97: Ana Rezende Dias | B97: 757.596.457-65 | C97: Sim | D97: ana.dias60@gmail.com | E97: (41) 91982-3844 | F97: 46145 | G97: Batel | H97: 0 | I97: =IF(H97<=0,"",LOOKUP(H97,'Regras e Parâmetros'!$B$4:$B$7,'Regras e Parâmetros'!$A$4:$A$7)) | J97: Sim | L97: Pontos no sistema (cadastro após 01/01/2025)
A98: Ana Rocha Gomes | B98: 568.915.115-77 | C98: Sim | D98: ana.gomes38@hotmail.com | E98: (48) 99897-3525 | F98: 44962 | G98: Site | H98: 1893 | I98: =IF(H98<=0,"",LOOKUP(H98,'Regras e Parâmetros'!$B$4:$B$7,'Regras e Parâmetros'!$A$4:$A$7)) -> Prata | J98: Sim
A99: Ana Santana | B99: 561.988.452-06 | C99: Sim | D99: ana.santana40@outlook.com | E99: (48) 90558-1936 | F99: 45185 | G99: App | H99: 2330 | I99: =IF(H99<=0,"",LOOKUP(H99,'Regras e Parâmetros'!$B$4:$B$7,'Regras e Parâmetros'!$A$4:$A$7)) -> Prata | J99: Não informado
A100: Ana Santana | B100: 337.321.463-75 | C100: Sim | D100: ana.santana83@hotmail.com | E100: (31) 98013-3706 | F100: 46001 | G100: Savassi | H100: 0 | I100: =IF(H100<=0,"",LOOKUP(H100,'Regras e Parâmetros'!$B$4:$B$7,'Regras e Parâmetros'!$A$4:$A$7)) | J100: Não informado | L100: Pontos no sistema (cadastro após 01/01/2025)
...

Sheet Resgates
A1: Data | B1: CPF | C1: Nome do cliente | D1: Pontos usados | E1: Desconto lançado (R$) | F1: Desconto pela regra (R$) | G1: Diferença (R$) | H1: Loja | I1: Atendente | J1: Cliente (como anotado) | K1: Pendências
A2: 44927 | B2: 908.579.218-51 | C2: =IF(B2="","",IFERROR(INDEX(Clientes!$A:$A,MATCH(B2,Clientes!$B:$B,0)),"(CPF não cadastrado)")) -> Heloísa Nascimento | D2: 1000 | E2: 100 | F2: =D2/100*LOOKUP(A2,'Regras e Parâmetros'!$A$11:$A$12,'Regras e Parâmetros'!$B$11:$B$12) -> 100 | G2: =E2-F2 -> 0 | H2: Eldorado | I2: Carlos | J2: 908.579.218-51 | K2: Data aproximada (só mês/ano)
A3: 44927 | B3: 638.765.788-17 | C3: =IF(B3="","",IFERROR(INDEX(Clientes!$A:$A,MATCH(B3,Clientes!$B:$B,0)),"(CPF não cadastrado)")) -> Sabrina Fonseca Nascimento | D3: 1000 | E3: 100 | F3: =D3/100*LOOKUP(A3,'Regras e Parâmetros'!$A$11:$A$12,'Regras e Parâmetros'!$B$11:$B$12) -> 100 | G3: =E3-F3 -> 0 | H3: Batel | I3: Carlos | J3: 63876578817
A4: 44939 | B4: 638.765.788-17 | C4: =IF(B4="","",IFERROR(INDEX(Clientes!$A:$A,MATCH(B4,Clientes!$B:$B,0)),"(CPF não cadastrado)")) -> Sabrina Fonseca Nascimento | D4: 1000 | E4: 100 | F4: =D4/100*LOOKUP(A4,'Regras e Parâmetros'!$A$11:$A$12,'Regras e Parâmetros'!$B$11:$B$12) -> 100 | G4: =E4-F4 -> 0 | H4: Batel | I4: Carlos | J4: 638.765.788-17
A5: 44947 | B5: 434.741.978-35 | C5: =IF(B5="","",IFERROR(INDEX(Clientes!$A:$A,MATCH(B5,Clientes!$B:$B,0)),"(CPF não cadastrado)")) -> Guilherme Peixoto | D5: 300 | E5: 30 | F5: =D5/100*LOOKUP(A5,'Regras e Parâmetros'!$A$11:$A$12,'Regras e Parâmetros'!$B$11:$B$12) -> 30 | G5: =E5-F5 -> 0 | H5: Batel | I5: Carlos | J5: 43474197835
A6: 44973 | B6: 952.987.358-19 | C6: =IF(B6="","",IFERROR(INDEX(Clientes!$A:$A,MATCH(B6,Clientes!$B:$B,0)),"(CPF não cadastrado)")) -> Eduarda Ramos Cardoso | D6: 1000 | E6: 100 | F6: =D6/100*LOOKUP(A6,'Regras e Parâmetros'!$A$11:$A$12,'Regras e Parâmetros'!$B$11:$B$12) -> 100 | G6: =E6-F6 -> 0 | H6: Eldorado | I6: Carlos | J6: Eduarda Ramos Cardoso | K6: CPF localizado pelo nome
A7: 44982 | B7: 147.527.113-11 | C7: =IF(B7="","",IFERROR(INDEX(Clientes!$A:$A,MATCH(B7,Clientes!$B:$B,0)),"(CPF não cadastrado)")) -> Sofia Freitas | D7: 1000 | E7: 100 | F7: =D7/100*LOOKUP(A7,'Regras e Parâmetros'!$A$11:$A$12,'Regras e Parâmetros'!$B$11:$B$12) -> 100 | G7: =E7-F7 -> 0 | H7: Batel | I7: Carlos | J7: Sofia Freitas | K7: CPF localizado pelo nome
A8: 44986 | B8: 139.616.512-64 | C8: =IF(B8="","",IFERROR(INDEX(Clientes!$A:$A,MATCH(B8,Clientes!$B:$B,0)),"(CPF não cadastrado)")) -> Lívia Araújo Tavares | D8: 200 | E8: 20 | F8: =D8/100*LOOKUP(A8,'Regras e Parâmetros'!$A$11:$A$12,'Regras e Parâmetros'!$B$11:$B$12) -> 20 | G8: =E8-F8 -> 0 | H8: Eldorado | I8: Rafa | J8: 139.616.512-64 | K8: CPF estava certo; o erro era no cadastro (corrigido).
A9: 44989 | B9: 826.562.154-04 | C9: =IF(B9="","",IFERROR(INDEX(Clientes!$A:$A,MATCH(B9,Clientes!$B:$B,0)),"(CPF não cadastrado)")) -> Mariana Rezende | D9: 100 | E9: 10 | F9: =D9/100*LOOKUP(A9,'Regras e Parâmetros'!$A$11:$A$12,'Regras e Parâmetros'!$B$11:$B$12) -> 10 | G9: =E9-F9 -> 0 | H9: Savassi | I9: Bia | J9: 82656215404
A10: 44989 | B10: 428.928.423-01 | C10: =IF(B10="","",IFERROR(INDEX(Clientes!$A:$A,MATCH(B10,Clientes!$B:$B,0)),"(CPF não cadastrado)")) -> Thaís Moura | D10: 200 | E10: 20 | F10: =D10/100*LOOKUP(A10,'Regras e Parâmetros'!$A$11:$A$12,'Regras e Parâmetros'!$B$11:$B$12) -> 20 | G10: =E10-F10 -> 0 | H10: Pinheiros | I10: Carlos | J10: 428.928.423-01
A11: 45000 | B11: 285.089.997-63 | C11: =IF(B11="","",IFERROR(INDEX(Clientes!$A:$A,MATCH(B11,Clientes!$B:$B,0)),"(CPF não cadastrado)")) -> Débora Almeida | D11: 500 | E11: 50 | F11: =D11/100*LOOKUP(A11,'Regras e Parâmetros'!$A$11:$A$12,'Regras e Parâmetros'!$B$11:$B$12) -> 50 | G11: =E11-F11 -> 0 | H11: Savassi | I11: Rafa | J11: 285.089.997-63
A12: 45002 | B12: 036.750.517-73 | C12: =IF(B12="","",IFERROR(INDEX(Clientes!$A:$A,MATCH(B12,Clientes!$B:$B,0)),"(CPF não cadastrado)")) -> Luana Ribeiro Nogueira | D12: 1000 | E12: 100 | F12: =D12/100*LOOKUP(A12,'Regras e Parâmetros'!$A$11:$A$12,'Regras e Parâmetros'!$B$11:$B$12) -> 100 | G12: =E12-F12 -> 0 | H12: Eldorado | J12: Luana Ribeiro Nogueira | K12: CPF localizado pelo nome
A13: 45009 | B13: 151.911.217-32 | C13: =IF(B13="","",IFERROR(INDEX(Clientes!$A:$A,MATCH(B13,Clientes!$B:$B,0)),"(CPF não cadastrado)")) -> Cecília Batista Barros | D13: 500 | E13: 50 | F13: =D13/100*LOOKUP(A13,'Regras e Parâmetros'!$A$11:$A$12,'Regras e Parâmetros'!$B$11:$B$12) -> 50 | G13: =E13-F13 -> 0 | H13: Pinheiros | I13: Rafa | J13: 15191121732
A14: 45016 | C14: =IF(B14="","",IFERROR(INDEX(Clientes!$A:$A,MATCH(B14,Clientes!$B:$B,0)),"(CPF não cadastrado)")) | D14: 300 | E14: 30 | F14: =D14/100*LOOKUP(A14,'Regras e Parâmetros'!$A$11:$A$12,'Regras e Parâmetros'!$B$11:$B$12) -> 30 | G14: =E14-F14 -> 0 | H14: Savassi | I14: Carlos | J14: Nicole Campos Barbosa | K14: Não identificável: nome igual a 2 clientes com CPFs diferentes (830.908.872-82 / 444.089.668-51) – resgate fica sem cliente e fora das pendências
A15: 45019 | C15: =IF(B15="","",IFERROR(INDEX(Clientes!$A:$A,MATCH(B15,Clientes!$B:$B,0)),"(CPF não cadastrado)")) | D15: 300 | E15: 30 | F15: =D15/100*LOOKUP(A15,'Regras e Parâmetros'!$A$11:$A$12,'Regras e Parâmetros'!$B$11:$B$12) -> 30 | G15: =E15-F15 -> 0 | H15: Eldorado | I15: Bia | J15: Rodrigo | K15: Cliente não identificado (só primeiro nome) | Varredura 19/10/2026: sem vendas antes de 2025 no vulto.db para cruzar
A16: 45020 | B16: 445.248.146-98 | C16: =IF(B16="","",IFERROR(INDEX(Clientes!$A:$A,MATCH(B16,Clientes!$B:$B,0)),"(CPF não cadastrado)")) -> Sofia Ferreira | D16: 200 | E16: 20 | F16: =D16/100*LOOKUP(A16,'Regras e Parâmetros'!$A$11:$A$12,'Regras e Parâmetros'!$B$11:$B$12) -> 20 | G16: =E16-F16 -> 0 | H16: Batel | I16: Jéssica | J16: Sofia Ferreira | K16: CPF localizado pelo nome
A17: 45049 | C17: =IF(B17="","",IFERROR(INDEX(Clientes!$A:$A,MATCH(B17,Clientes!$B:$B,0)),"(CPF não cadastrado)")) | D17: 500 | E17: 50 | F17: =D17/100*LOOKUP(A17,'Regras e Parâmetros'!$A$11:$A$12,'Regras e Parâmetros'!$B$11:$B$12) -> 50 | G17: =E17-F17 -> 0 | H17: Eldorado | J17: Luan | K17: Sugestão: Luan Oliveira Gomes 740.762.313-92 (único da loja com DDD; confiança média) | Varredura 19/10/2026: sem vendas antes de 2025 no vulto.db para cruzar
A18: 45056 | B18: 822.480.015-68 | C18: =IF(B18="","",IFERROR(INDEX(Clientes!$A:$A,MATCH(B18,Clientes!$B:$B,0)),"(CPF não cadastrado)")) -> Priscila T. Martins | D18: 100 | E18: 10 | F18: =D18/100*LOOKUP(A18,'Regras e Parâmetros'!$A$11:$A$12,'Regras e Parâmetros'!$B$11:$B$12) -> 10 | G18: =E18-F18 -> 0 | H18: Savassi | I18: Gerente | J18: 82248001568
A19: 45059 | B19: 585.935.177-14 | C19: =IF(B19="","",IFERROR(INDEX(Clientes!$A:$A,MATCH(B19,Clientes!$B:$B,0)),"(CPF não cadastrado)")) -> Davi Ferreira | D19: 300 | E19: 30 | F19: =D19/100*LOOKUP(A19,'Regras e Parâmetros'!$A$11:$A$12,'Regras e Parâmetros'!$B$11:$B$12) -> 30 | G19: =E19-F19 -> 0 | H19: Pinheiros | I19: Carlos | J19: Davi Ferreira | K19: CPF atribuído pela análise (nome repetido: só esta cliente já era cadastrada na data). Confiança alta.
A20: 45075 | B20: 554.320.410-81 | C20: =IF(B20="","",IFERROR(INDEX(Clientes!$A:$A,MATCH(B20,Clientes!$B:$B,0)),"(CPF não cadastrado)")) -> Camila Lima | D20: 100 | E20: 10 | F20: =D20/100*LOOKUP(A20,'Regras e Parâmetros'!$A$11:$A$12,'Regras e Parâmetros'!$B$11:$B$12) -> 10 | G20: =E20-F20 -> 0 | H20: Pinheiros | I20: Gerente | J20: Camila | K20: CPF atribuído pela análise (1º nome: mesma loja, já resgatou lá e DDD). Confiança alta.
A21: 45084 | B21: 383.154.106-01 | C21: =IF(B21="","",IFERROR(INDEX(Clientes!$A:$A,MATCH(B21,Clientes!$B:$B,0)),"(CPF não cadastrado)")) -> Aline Teixeira Nascimento | D21: 200 | E21: 20 | F21: =D21/100*LOOKUP(A21,'Regras e Parâmetros'!$A$11:$A$12,'Regras e Parâmetros'!$B$11:$B$12) -> 20 | G21: =E21-F21 -> 0 | H21: Eldorado | J21: 383.154.106-01
A22: 45109 | B22: 766.120.436-36 | C22: =IF(B22="","",IFERROR(INDEX(Clientes!$A:$A,MATCH(B22,Clientes!$B:$B,0)),"(CPF não cadastrado)")) -> Rafaela Lopes Ramos | D22: 500 | E22: 50 | F22: =D22/100*LOOKUP(A22,'Regras e Parâmetros'!$A$11:$A$12,'Regras e Parâmetros'!$B$11:$B$12) -> 50 | G22: =E22-F22 -> 0 | H22: Batel | I22: Bia | J22: 766.120.436-36
A23: 45118 | B23: 652.493.544-67 | C23: =IF(B23="","",IFERROR(INDEX(Clientes!$A:$A,MATCH(B23,Clientes!$B:$B,0)),"(CPF não cadastrado)")) -> Manuela Ferreira | D23: 500 | E23: 50 | F23: =D23/100*LOOKUP(A23,'Regras e Parâmetros'!$A$11:$A$12,'Regras e Parâmetros'!$B$11:$B$12) -> 50 | G23: =E23-F23 -> 0 | H23: Savassi | I23: Rafa | J23: 652.493.544-67
A24: 45129 | B24: 683.077.020-38 | C24: =IF(B24="","",IFERROR(INDEX(Clientes!$A:$A,MATCH(B24,Clientes!$B:$B,0)),"(CPF não cadastrado)")) -> Paula Rezende | D24: 500 | E24: 50 | F24: =D24/100*LOOKUP(A24,'Regras e Parâmetros'!$A$11:$A$12,'Regras e Parâmetros'!$B$11:$B$12) -> 50 | G24: =E24-F24 -> 0 | H24: Batel | I24: Jéssica | J24: 683.077.020-38
A25: 45133 | B25: 649.567.046-07 | C25: =IF(B25="","",IFERROR(INDEX(Clientes!$A:$A,MATCH(B25,Clientes!$B:$B,0)),"(CPF não cadastrado)")) -> Felipe Monteiro | D25: 1000 | E25: 100 | F25: =D25/100*LOOKUP(A25,'Regras e Parâmetros'!$A$11:$A$12,'Regras e Parâmetros'!$B$11:$B$12) -> 100 | G25: =E25-F25 -> 0 | H25: Batel | I25: Gerente | J25: Felipe | K25: CPF atribuído pela análise (1º nome: mesma loja, já resgatou lá e DDD). Confiança alta.
A26: 45170 | B26: 852.250.131-98 | C26: =IF(B26="","",IFERROR(INDEX(Clientes!$A:$A,MATCH(B26,Clientes!$B:$B,0)),"(CPF não cadastrado)")) -> Juliana Ribeiro Farias | D26: 1000 | E26: 100 | F26: =D26/100*LOOKUP(A26,'Regras e Parâmetros'!$A$11:$A$12,'Regras e Parâmetros'!$B$11:$B$12) -> 100 | G26: =E26-F26 -> 0 | H26: Pinheiros | I26: Gerente | J26: 852.250.131-98 | K26: Data aproximada (só mês/ano)
A27: 45170 | B27: 116.606.891-98 | C27: =IF(B27="","",IFERROR(INDEX(Clientes!$A:$A,MATCH(B27,Clientes!$B:$B,0)),"(CPF não cadastrado)")) -> Emanuelly Pereira Ribeiro | D27: 300 | E27: 30 | F27: =D27/100*LOOKUP(A27,'Regras e Parâmetros'!$A$11:$A$12,'Regras e Parâmetros'!$B$11:$B$12) -> 30 | G27: =E27-F27 -> 0 | H27: Pinheiros | I27: Rafa | J27: Emanuelly Pereira Ribeiro | K27: CPF localizado pelo nome | Data aproximada (só mês/ano)
A28: 45170 | B28: 274.651.585-75 | C28: =IF(B28="","",IFERROR(INDEX(Clientes!$A:$A,MATCH(B28,Clientes!$B:$B,0)),"(CPF não cadastrado)")) -> Daniela Rocha | D28: 200 | E28: 20 | F28: =D28/100*LOOKUP(A28,'Regras e Parâmetros'!$A$11:$A$12,'Regras e Parâmetros'!$B$11:$B$12) -> 20 | G28: =E28-F28 -> 0 | H28: Savassi | I28: Jéssica | J28: Daniela | K28: CPF atribuído pela análise (1º nome: mesma loja, já resgatou lá e DDD). Confiança alta.
A29: 45170 | B29: 409.415.763-88 | C29: =IF(B29="","",IFERROR(INDEX(Clientes!$A:$A,MATCH(B29,Clientes!$B:$B,0)),"(CPF não cadastrado)")) -> Fernanda Campos | D29: 1000 | E29: 100 | F29: =D29/100*LOOKUP(A29,'Regras e Parâmetros'!$A$11:$A$12,'Regras e Parâmetros'!$B$11:$B$12) -> 100 | G29: =E29-F29 -> 0 | H29: Eldorado | I29: Carlos | J29: 40941576388 | K29: Data aproximada (só mês/ano)
A30: 45180 | B30: 110.441.742-18 | C30: =IF(B30="","",IFERROR(INDEX(Clientes!$A:$A,MATCH(B30,Clientes!$B:$B,0)),"(CPF não cadastrado)")) -> Eduarda Ramos | D30: 100 | E30: 10 | F30: =D30/100*LOOKUP(A30,'Regras e Parâmetros'!$A$11:$A$12,'Regras e Parâmetros'!$B$11:$B$12) -> 10 | G30: =E30-F30 -> 0 | H30: Savassi | J30: Eduarda Ramos | K30: CPF localizado pelo nome
A31: 45200 | B31: 588.828.059-30 | C31: =IF(B31="","",IFERROR(INDEX(Clientes!$A:$A,MATCH(B31,Clientes!$B:$B,0)),"(CPF não cadastrado)")) -> Sabrina Campos | D31: 200 | E31: 20 | F31: =D31/100*LOOKUP(A31,'Regras e Parâmetros'!$A$11:$A$12,'Regras e Parâmetros'!$B$11:$B$12) -> 20 | G31: =E31-F31 -> 0 | H31: Eldorado | J31: Sabrina | K31: CPF atribuído pela análise (1º nome: mesma loja, já resgatou lá e DDD). Confiança alta.
A32: 45209 | B32: 103.631.755-20 | C32: =IF(B32="","",IFERROR(INDEX(Clientes!$A:$A,MATCH(B32,Clientes!$B:$B,0)),"(CPF não cadastrado)")) -> Heloísa Campos Nascimento | D32: 1000 | E32: 100 | F32: =D32/100*LOOKUP(A32,'Regras e Parâmetros'!$A$11:$A$12,'Regras e Parâmetros'!$B$11:$B$12) -> 100 | G32: =E32-F32 -> 0 | H32: Savassi | I32: Carlos | J32: 103.631.755-20
A33: 45218 | B33: 339.338.681-65 | C33: =IF(B33="","",IFERROR(INDEX(Clientes!$A:$A,MATCH(B33,Clientes!$B:$B,0)),"(CPF não cadastrado)")) -> Marcelo Rocha | D33: 300 | E33: 30 | F33: =D33/100*LOOKUP(A33,'Regras e Parâmetros'!$A$11:$A$12,'Regras e Parâmetros'!$B$11:$B$12) -> 30 | G33: =E33-F33 -> 0 | H33: Pinheiros | I33: Jéssica | J33: 33933868165
A34: 45239 | B34: 470.492.413-00 | C34: =IF(B34="","",IFERROR(INDEX(Clientes!$A:$A,MATCH(B34,Clientes!$B:$B,0)),"(CPF não cadastrado)")) -> Luana Pinto | D34: 500 | E34: 50 | F34: =D34/100*LOOKUP(A34,'Regras e Parâmetros'!$A$11:$A$12,'Regras e Parâmetros'!$B$11:$B$12) -> 50 | G34: =E34-F34 -> 0 | H34: Eldorado | I34: Jéssica | J34: 47049241300
A35: 45239 | B35: 936.966.479-34 | C35: =IF(B35="","",IFERROR(INDEX(Clientes!$A:$A,MATCH(B35,Clientes!$B:$B,0)),"(CPF não cadastrado)")) -> Juliana Soares | D35: 200 | E35: 20 | F35: =D35/100*LOOKUP(A35,'Regras e Parâmetros'!$A$11:$A$12,'Regras e Parâmetros'!$B$11:$B$12) -> 20 | G35: =E35-F35 -> 0 | H35: Eldorado | I35: Carlos | J35: 93696647934
A36: 45253 | B36: 411.634.979-83 | C36: =IF(B36="","",IFERROR(INDEX(Clientes!$A:$A,MATCH(B36,Clientes!$B:$B,0)),"(CPF não cadastrado)")) -> Henrique Santana | D36: 300 | E36: 30 | F36: =D36/100*LOOKUP(A36,'Regras e Parâmetros'!$A$11:$A$12,'Regras e Parâmetros'!$B$11:$B$12) -> 30 | G36: =E36-F36 -> 0 | H36: Savassi | I36: Bia | J36: Henrique Santana | K36: CPF localizado pelo nome
A37: 45285 | B37: 106.710.169-11 | C37: =IF(B37="","",IFERROR(INDEX(Clientes!$A:$A,MATCH(B37,Clientes!$B:$B,0)),"(CPF não cadastrado)")) -> Rebeca Martins | D37: 200 | E37: 20 | F37: =D37/100*LOOKUP(A37,'Regras e Parâmetros'!$A$11:$A$12,'Regras e Parâmetros'!$B$11:$B$12) -> 20 | G37: =E37-F37 -> 0 | H37: Savassi | J37: 10671016911
A38: 45295 | B38: 572.245.905-41 | C38: =IF(B38="","",IFERROR(INDEX(Clientes!$A:$A,MATCH(B38,Clientes!$B:$B,0)),"(CPF não cadastrado)")) -> Lorena Rodrigues | D38: 500 | E38: 50 | F38: =D38/100*LOOKUP(A38,'Regras e Parâmetros'!$A$11:$A$12,'Regras e Parâmetros'!$B$11:$B$12) -> 50 | G38: =E38-F38 -> 0 | H38: Savassi | I38: Gerente | J38: 57224590541
A39: 45299 | B39: 110.867.188-87 | C39: =IF(B39="","",IFERROR(INDEX(Clientes!$A:$A,MATCH(B39,Clientes!$B:$B,0)),"(CPF não cadastrado)")) -> Rodrigo Nunes | D39: 300 | E39: 30 | F39: =D39/100*LOOKUP(A39,'Regras e Parâmetros'!$A$11:$A$12,'Regras e Parâmetros'!$B$11:$B$12) -> 30 | G39: =E39-F39 -> 0 | H39: Batel | J39: 11086718887
A40: 45305 | B40: 092.742.848-29 | C40: =IF(B40="","",IFERROR(INDEX(Clientes!$A:$A,MATCH(B40,Clientes!$B:$B,0)),"(CPF não cadastrado)")) -> (CPF não cadastrado) | D40: 500 | E40: 50 | F40: =D40/100*LOOKUP(A40,'Regras e Parâmetros'!$A$11:$A$12,'Regras e Parâmetros'!$B$11:$B$12) -> 50 | G40: =E40-F40 -> 0 | H40: Batel | I40: Carlos | J40: 9274284829 | K40: CPF não está no cadastro
A41: 45325 | B41: 606.799.266-31 | C41: =IF(B41="","",IFERROR(INDEX(Clientes!$A:$A,MATCH(B41,Clientes!$B:$B,0)),"(CPF não cadastrado)")) -> Isabela Gonçalves | D41: 300 | E41: 30 | F41: =D41/100*LOOKUP(A41,'Regras e Parâmetros'!$A$11:$A$12,'Regras e Parâmetros'!$B$11:$B$12) -> 30 | G41: =E41-F41 -> 0 | H41: Eldorado | I41: Bia | J41: 606.799.266-31
A42: 45344 | B42: 272.617.924-03 | C42: =IF(B42="","",IFERROR(INDEX(Clientes!$A:$A,MATCH(B42,Clientes!$B:$B,0)),"(CPF não cadastrado)")) -> Renata Barbosa Pinto | D42: 100 | E42: 10 | F42: =D42/100*LOOKUP(A42,'Regras e Parâmetros'!$A$11:$A$12,'Regras e Parâmetros'!$B$11:$B$12) -> 10 | G42: =E42-F42 -> 0 | H42: Savassi | I42: Gerente | J42: Renata Barbosa Pinto | K42: CPF localizado pelo nome
A43: 45386 | B43: 097.383.043-34 | C43: =IF(B43="","",IFERROR(INDEX(Clientes!$A:$A,MATCH(B43,Clientes!$B:$B,0)),"(CPF não cadastrado)")) -> Emanuelly A. Cardoso | D43: 300 | E43: 30 | F43: =D43/100*LOOKUP(A43,'Regras e Parâmetros'!$A$11:$A$12,'Regras e Parâmetros'!$B$11:$B$12) -> 30 | G43: =E43-F43 -> 0 | H43: Pinheiros | J43: 9738304334
A44: 45443 | C44: =IF(B44="","",IFERROR(INDEX(Clientes!$A:$A,MATCH(B44,Clientes!$B:$B,0)),"(CPF não cadastrado)")) | D44: 1000 | E44: 100 | F44: =D44/100*LOOKUP(A44,'Regras e Parâmetros'!$A$11:$A$12,'Regras e Parâmetros'!$B$11:$B$12) -> 100 | G44: =E44-F44 -> 0 | H44: Savassi | J44: Paulo Teixeira | K44: Não identificável: nome igual a 2 clientes com CPFs diferentes (589.386.957-51 / 815.973.832-36) – resgate fica sem cliente e fora das pendências
A45: 45474 | B45: 896.348.156-50 | C45: =IF(B45="","",IFERROR(INDEX(Clientes!$A:$A,MATCH(B45,Clientes!$B:$B,0)),"(CPF não cadastrado)")) -> Jaqueline Vieira Lima | D45: 300 | E45: 30 | F45: =D45/100*LOOKUP(A45,'Regras e Parâmetros'!$A$11:$A$12,'Regras e Parâmetros'!$B$11:$B$12) -> 30 | G45: =E45-F45 -> 0 | H45: Batel | J45: 896.348.156-50
A46: 45515 | B46: 524.230.614-98 | C46: =IF(B46="","",IFERROR(INDEX(Clientes!$A:$A,MATCH(B46,Clientes!$B:$B,0)),"(CPF não cadastrado)")) -> Arthur Nogueira | D46: 200 | E46: 20 | F46: =D46/100*LOOKUP(A46,'Regras e Parâmetros'!$A$11:$A$12,'Regras e Parâmetros'!$B$11:$B$12) -> 20 | G46: =E46-F46 -> 0 | H46: Eldorado | I46: Carlos | J46: Arthur Nogueira | K46: CPF localizado pelo nome
A47: 45515 | B47: 461.517.743-70 | C47: =IF(B47="","",IFERROR(INDEX(Clientes!$A:$A,MATCH(B47,Clientes!$B:$B,0)),"(CPF não cadastrado)")) -> Caio Santana Pinto | D47: 200 | E47: 20 | F47: =D47/100*LOOKUP(A47,'Regras e Parâmetros'!$A$11:$A$12,'Regras e Parâmetros'!$B$11:$B$12) -> 20 | G47: =E47-F47 -> 0 | H47: Batel | I47: Carlos | J47: 461.517.743-70
A48: 45545 | B48: 409.532.729-40 | C48: =IF(B48="","",IFERROR(INDEX(Clientes!$A:$A,MATCH(B48,Clientes!$B:$B,0)),"(CPF não cadastrado)")) -> Lívia Moreira | D48: 200 | E48: 20 | F48: =D48/100*LOOKUP(A48,'Regras e Parâmetros'!$A$11:$A$12,'Regras e Parâmetros'!$B$11:$B$12) -> 20 | G48: =E48-F48 -> 0 | H48: Eldorado | I48: Jéssica | J48: 40953272940
A49: 45553 | B49: 888.288.629-80 | C49: =IF(B49="","",IFERROR(INDEX(Clientes!$A:$A,MATCH(B49,Clientes!$B:$B,0)),"(CPF não cadastrado)")) -> Alice Nogueira | D49: 500 | E49: 50 | F49: =D49/100*LOOKUP(A49,'Regras e Parâmetros'!$A$11:$A$12,'Regras e Parâmetros'!$B$11:$B$12) -> 50 | G49: =E49-F49 -> 0 | H49: Pinheiros | I49: Rafa | J49: Alice Nogueira | K49: CPF atribuído pela análise (nome repetido: só esta cliente já era cadastrada na data). Confiança alta.
A50: 45556 | B50: 093.344.476-13 | C50: =IF(B50="","",IFERROR(INDEX(Clientes!$A:$A,MATCH(B50,Clientes!$B:$B,0)),"(CPF não cadastrado)")) -> André Araújo Gonçalves | D50: 1000 | E50: 100 | F50: =D50/100*LOOKUP(A50,'Regras e Parâmetros'!$A$11:$A$12,'Regras e Parâmetros'!$B$11:$B$12) -> 100 | G50: =E50-F50 -> 0 | H50: Batel | I50: Bia | J50: André Araújo Gonçalves | K50: CPF localizado pelo nome
A51: 45565 | B51: 816.866.754-96 | C51: =IF(B51="","",IFERROR(INDEX(Clientes!$A:$A,MATCH(B51,Clientes!$B:$B,0)),"(CPF não cadastrado)")) -> Sabrina Marques | D51: 1000 | E51: 100 | F51: =D51/100*LOOKUP(A51,'Regras e Parâmetros'!$A$11:$A$12,'Regras e Parâmetros'!$B$11:$B$12) -> 100 | G51: =E51-F51 -> 0 | H51: Eldorado | I51: Gerente | J51: 816.866.754-96
A52: 45566 | B52: 357.668.414-00 | C52: =IF(B52="","",IFERROR(INDEX(Clientes!$A:$A,MATCH(B52,Clientes!$B:$B,0)),"(CPF não cadastrado)")) -> Natália Rocha Freitas | D52: 200 | E52: 20 | F52: =D52/100*LOOKUP(A52,'Regras e Parâmetros'!$A$11:$A$12,'Regras e Parâmetros'!$B$11:$B$12) -> 20 | G52: =E52-F52 -> 0 | H52: Savassi | I52: Carlos | J52: 35766841400 | K52: Data aproximada (só mês/ano)
A53: 45567 | C53: =IF(B53="","",IFERROR(INDEX(Clientes!$A:$A,MATCH(B53,Clientes!$B:$B,0)),"(CPF não cadastrado)")) | D53: 1000 | E53: 100 | F53: =D53/100*LOOKUP(A53,'Regras e Parâmetros'!$A$11:$A$12,'Regras e Parâmetros'!$B$11:$B$12) -> 100 | G53: =E53-F53 -> 0 | H53: Savassi | J53: Juliana | K53: Cliente não identificado (só primeiro nome) | Varredura 19/10/2026: sem vendas antes de 2025 no vulto.db para cruzar
A54: 45588 | B54: 822.101.992-55 | C54: =IF(B54="","",IFERROR(INDEX(Clientes!$A:$A,MATCH(B54,Clientes!$B:$B,0)),"(CPF não cadastrado)")) -> Valentina Santana | D54: 500 | E54: 50 | F54: =D54/100*LOOKUP(A54,'Regras e Parâmetros'!$A$11:$A$12,'Regras e Parâmetros'!$B$11:$B$12) -> 50 | G54: =E54-F54 -> 0 | H54: Savassi | I54: Gerente | J54: Valentina Santana | K54: CPF localizado pelo nome
A55: 45597 | B55: 572.245.905-41 | C55: =IF(B55="","",IFERROR(INDEX(Clientes!$A:$A,MATCH(B55,Clientes!$B:$B,0)),"(CPF não cadastrado)")) -> Lorena Rodrigues | D55: 300 | E55: 30 | F55: =D55/100*LOOKUP(A55,'Regras e Parâmetros'!$A$11:$A$12,'Regras e Parâmetros'!$B$11:$B$12) -> 30 | G55: =E55-F55 -> 0 | H55: Savassi | J55: Lorena Rodrigues | K55: CPF localizado pelo nome | Data aproximada (só mês/ano)
A56: 45597 | C56: =IF(B56="","",IFERROR(INDEX(Clientes!$A:$A,MATCH(B56,Clientes!$B:$B,0)),"(CPF não cadastrado)")) | D56: 300 | E56: 30 | F56: =D56/100*LOOKUP(A56,'Regras e Parâmetros'!$A$11:$A$12,'Regras e Parâmetros'!$B$11:$B$12) -> 30 | G56: =E56-F56 -> 0 | H56: Batel | I56: Carlos | J56: Alexandre | K56: Cliente não identificado (só primeiro nome) | Data aproximada (só mês/ano) | Varredura 19/10/2026: sem vendas antes de 2025 no vulto.db para cruzar
A57: 45600 | B57: 277.233.139-34 | C57: =IF(B57="","",IFERROR(INDEX(Clientes!$A:$A,MATCH(B57,Clientes!$B:$B,0)),"(CPF não cadastrado)")) -> Eduarda Monteiro Teixeira | D57: 500 | E57: 50 | F57: =D57/100*LOOKUP(A57,'Regras e Parâmetros'!$A$11:$A$12,'Regras e Parâmetros'!$B$11:$B$12) -> 50 | G57: =E57-F57 -> 0 | H57: Savassi | I57: Jéssica | J57: Eduarda Monteiro Teixeira | K57: CPF localizado pelo nome
A58: 45604 | C58: =IF(B58="","",IFERROR(INDEX(Clientes!$A:$A,MATCH(B58,Clientes!$B:$B,0)),"(CPF não cadastrado)")) | D58: 100 | E58: 10 | F58: =D58/100*LOOKUP(A58,'Regras e Parâmetros'!$A$11:$A$12,'Regras e Parâmetros'!$B$11:$B$12) -> 10 | G58: =E58-F58 -> 0 | H58: Eldorado | I58: Rafa | J58: Leonardo | K58: Cliente não identificado (só primeiro nome) | Varredura 19/10/2026: sem vendas antes de 2025 no vulto.db para cruzar
A59: 45610 | C59: =IF(B59="","",IFERROR(INDEX(Clientes!$A:$A,MATCH(B59,Clientes!$B:$B,0)),"(CPF não cadastrado)")) | D59: 500 | E59: 50 | F59: =D59/100*LOOKUP(A59,'Regras e Parâmetros'!$A$11:$A$12,'Regras e Parâmetros'!$B$11:$B$12) -> 50 | G59: =E59-F59 -> 0 | H59: Batel | J59: Mariana | K59: Sugestão: Mariana Marques 142.255.830-40 (única da loja com DDD; confiança média) | Varredura 19/10/2026: sem vendas antes de 2025 no vulto.db para cruzar
A60: 45622 | B60: 750.968.674-12 | C60: =IF(B60="","",IFERROR(INDEX(Clientes!$A:$A,MATCH(B60,Clientes!$B:$B,0)),"(CPF não cadastrado)")) -> Heloísa Ribeiro | D60: 500 | E60: 50 | F60: =D60/100*LOOKUP(A60,'Regras e Parâmetros'!$A$11:$A$12,'Regras e Parâmetros'!$B$11:$B$12) -> 50 | G60: =E60-F60 -> 0 | H60: Batel | J60: Heloísa | K60: CPF atribuído pela análise (1º nome: mesma loja, já resgatou lá e DDD). Confiança alta.
A61: 45623 | B61: 602.419.677-67 | C61: =IF(B61="","",IFERROR(INDEX(Clientes!$A:$A,MATCH(B61,Clientes!$B:$B,0)),"(CPF não cadastrado)")) -> Henrique Almeida | D61: 1000 | E61: 100 | F61: =D61/100*LOOKUP(A61,'Regras e Parâmetros'!$A$11:$A$12,'Regras e Parâmetros'!$B$11:$B$12) -> 100 | G61: =E61-F61 -> 0 | H61: Savassi | I61: Jéssica | J61: Henrique Almeida | K61: CPF localizado pelo nome
A62: 45659 | B62: 639.229.499-67 | C62: =IF(B62="","",IFERROR(INDEX(Clientes!$A:$A,MATCH(B62,Clientes!$B:$B,0)),"(CPF não cadastrado)")) -> Priscila M. Cardoso | D62: 500 | E62: 50 | F62: =D62/100*LOOKUP(A62,'Regras e Parâmetros'!$A$11:$A$12,'Regras e Parâmetros'!$B$11:$B$12) -> 50 | G62: =E62-F62 -> 0 | H62: Site | J62: 63922949967 | K62: Após 01/01/2025: conferir lançamento no sistema
A63: 45661 | B63: 859.410.216-07 | C63: =IF(B63="","",IFERROR(INDEX(Clientes!$A:$A,MATCH(B63,Clientes!$B:$B,0)),"(CPF não cadastrado)")) -> Breno Silva Farias | D63: 2000 | E63: 200 | F63: =D63/100*LOOKUP(A63,'Regras e Parâmetros'!$A$11:$A$12,'Regras e Parâmetros'!$B$11:$B$12) -> 200 | G63: =E63-F63 -> 0 | H63: Site | J63: 85941021607 | K63: Após 01/01/2025: conferir lançamento no sistema
A64: 45662 | B64: 173.072.622-40 | C64: =IF(B64="","",IFERROR(INDEX(Clientes!$A:$A,MATCH(B64,Clientes!$B:$B,0)),"(CPF não cadastrado)")) -> Lucas Pereira Tavares | D64: 500 | E64: 50 | F64: =D64/100*LOOKUP(A64,'Regras e Parâmetros'!$A$11:$A$12,'Regras e Parâmetros'!$B$11:$B$12) -> 50 | G64: =E64-F64 -> 0 | H64: Pinheiros | J64: 17307262240 | K64: Após 01/01/2025: conferir lançamento no sistema
A65: 45662 | B65: 627.725.103-10 | C65: =IF(B65="","",IFERROR(INDEX(Clientes!$A:$A,MATCH(B65,Clientes!$B:$B,0)),"(CPF não cadastrado)")) -> Arthur Goncalves | D65: 1700 | E65: 170 | F65: =D65/100*LOOKUP(A65,'Regras e Parâmetros'!$A$11:$A$12,'Regras e Parâmetros'!$B$11:$B$12) -> 170 | G65: =E65-F65 -> 0 | H65: Pinheiros | J65: 62772510310 | K65: Após 01/01/2025: conferir lançamento no sistema
A66: 45668 | B66: 029.691.685-45 | C66: =IF(B66="","",IFERROR(INDEX(Clientes!$A:$A,MATCH(B66,Clientes!$B:$B,0)),"(CPF não cadastrado)")) -> Nicole Nunes Vieira | D66: 300 | E66: 30 | F66: =D66/100*LOOKUP(A66,'Regras e Parâmetros'!$A$11:$A$12,'Regras e Parâmetros'!$B$11:$B$12) -> 30 | G66: =E66-F66 -> 0 | H66: Eldorado | I66: Thiago | J66: Nicole Nunes Vieira | K66: CPF localizado pelo nome | Após 01/01/2025: conferir lançamento no sistema
A67: 45668 | B67: 280.265.310-51 | C67: =IF(B67="","",IFERROR(INDEX(Clientes!$A:$A,MATCH(B67,Clientes!$B:$B,0)),"(CPF não cadastrado)")) -> Rafaela Peixoto Farias | D67: 500 | E67: 50 | F67: =D67/100*LOOKUP(A67,'Regras e Parâmetros'!$A$11:$A$12,'Regras e Parâmetros'!$B$11:$B$12) -> 50 | G67: =E67-F67 -> 0 | H67: Site | J67: 28026531051 | K67: Após 01/01/2025: conferir lançamento no sistema
A68: 45673 | B68: 699.747.500-08 | C68: =IF(B68="","",IFERROR(INDEX(Clientes!$A:$A,MATCH(B68,Clientes!$B:$B,0)),"(CPF não cadastrado)")) -> Leonardo Carvalho Marques | D68: 600 | E68: 60 | F68: =D68/100*LOOKUP(A68,'Regras e Parâmetros'!$A$11:$A$12,'Regras e Parâmetros'!$B$11:$B$12) -> 60 | G68: =E68-F68 -> 0 | H68: Eldorado | J68: 69974750008 | K68: Após 01/01/2025: conferir lançamento no sistema
A69: 45673 | B69: 807.133.820-66 | C69: =IF(B69="","",IFERROR(INDEX(Clientes!$A:$A,MATCH(B69,Clientes!$B:$B,0)),"(CPF não cadastrado)")) -> Rodrigo Nunes Dias | D69: 500 | E69: 50 | F69: =D69/100*LOOKUP(A69,'Regras e Parâmetros'!$A$11:$A$12,'Regras e Parâmetros'!$B$11:$B$12) -> 50 | G69: =E69-F69 -> 0 | H69: Savassi | I69: Carlos | J69: Rodrigo Nunes Dias | K69: CPF localizado pelo nome | Após 01/01/2025: conferir lançamento no sistema
A70: 45673 | B70: 602.419.677-67 | C70: =IF(B70="","",IFERROR(INDEX(Clientes!$A:$A,MATCH(B70,Clientes!$B:$B,0)),"(CPF não cadastrado)")) -> Henrique Almeida | D70: 700 | E70: 70 | F70: =D70/100*LOOKUP(A70,'Regras e Parâmetros'!$A$11:$A$12,'Regras e Parâmetros'!$B$11:$B$12) -> 70 | G70: =E70-F70 -> 0 | H70: Savassi | J70: 60241967767 | K70: Após 01/01/2025: conferir lançamento no sistema
A71: 45674 | B71: 341.994.132-35 | C71: =IF(B71="","",IFERROR(INDEX(Clientes!$A:$A,MATCH(B71,Clientes!$B:$B,0)),"(CPF não cadastrado)")) -> Vinícius Mendes | D71: 1000 | E71: 100 | F71: =D71/100*LOOKUP(A71,'Regras e Parâmetros'!$A$11:$A$12,'Regras e Parâmetros'!$B$11:$B$12) -> 100 | G71: =E71-F71 -> 0 | H71: Eldorado | J71: 34199413235 | K71: Após 01/01/2025: conferir lançamento no sistema
A72: 45674 | B72: 689.838.363-93 | C72: =IF(B72="","",IFERROR(INDEX(Clientes!$A:$A,MATCH(B72,Clientes!$B:$B,0)),"(CPF não cadastrado)")) -> Thaís Monteiro Costa | D72: 1000 | E72: 100 | F72: =D72/100*LOOKUP(A72,'Regras e Parâmetros'!$A$11:$A$12,'Regras e Parâmetros'!$B$11:$B$12) -> 100 | G72: =E72-F72 -> 0 | H72: Eldorado | I72: Jéssica | J72: Thaís Monteiro Costa | K72: CPF localizado pelo nome | Após 01/01/2025: conferir lançamento no sistema
A73: 45683 | B73: 177.282.376-75 | C73: =IF(B73="","",IFERROR(INDEX(Clientes!$A:$A,MATCH(B73,Clientes!$B:$B,0)),"(CPF não cadastrado)")) -> Gabriel Alves Teixeira | D73: 500 | E73: 50 | F73: =D73/100*LOOKUP(A73,'Regras e Parâmetros'!$A$11:$A$12,'Regras e Parâmetros'!$B$11:$B$12) -> 50 | G73: =E73-F73 -> 0 | H73: Eldorado | I73: Thiago | J73: Gabriel Alves Teixeira | K73: CPF localizado pelo nome | Após 01/01/2025: conferir lançamento no sistema
A74: 45684 | B74: 791.984.724-96 | C74: =IF(B74="","",IFERROR(INDEX(Clientes!$A:$A,MATCH(B74,Clientes!$B:$B,0)),"(CPF não cadastrado)")) -> Marina Ramos Lopes | D74: 500 | E74: 50 | F74: =D74/100*LOOKUP(A74,'Regras e Parâmetros'!$A$11:$A$12,'Regras e Parâmetros'!$B$11:$B$12) -> 50 | G74: =E74-F74 -> 0 | H74: Eldorado | I74: Jéssica | J74: 79198472496 | K74: Após 01/01/2025: conferir lançamento no sistema
A75: 45684 | B75: 558.887.980-53 | C75: =IF(B75="","",IFERROR(INDEX(Clientes!$A:$A,MATCH(B75,Clientes!$B:$B,0)),"(CPF não cadastrado)")) -> Tainá Monteiro Nascimento | D75: 500 | E75: 50 | F75: =D75/100*LOOKUP(A75,'Regras e Parâmetros'!$A$11:$A$12,'Regras e Parâmetros'!$B$11:$B$12) -> 50 | G75: =E75-F75 -> 0 | H75: Site | J75: 55888798053 | K75: Após 01/01/2025: conferir lançamento no sistema
A76: 45684 | B76: 055.606.209-47 | C76: =IF(B76="","",IFERROR(INDEX(Clientes!$A:$A,MATCH(B76,Clientes!$B:$B,0)),"(CPF não cadastrado)")) -> Caetano Fonseca Lima | D76: 500 | E76: 50 | F76: =D76/100*LOOKUP(A76,'Regras e Parâmetros'!$A$11:$A$12,'Regras e Parâmetros'!$B$11:$B$12) -> 50 | G76: =E76-F76 -> 0 | H76: Site | J76: 05560620947 | K76: Após 01/01/2025: conferir lançamento no sistema
A77: 45685 | B77: 146.779.420-13 | C77: =IF(B77="","",IFERROR(INDEX(Clientes!$A:$A,MATCH(B77,Clientes!$B:$B,0)),"(CPF não cadastrado)")) -> Yasmin Cardoso Nascimento | D77: 1000 | E77: 100 | F77: =D77/100*LOOKUP(A77,'Regras e Parâmetros'!$A$11:$A$12,'Regras e Parâmetros'!$B$11:$B$12) -> 100 | G77: =E77-F77 -> 0 | H77: Site | J77: 14677942013 | K77: Após 01/01/2025: conferir lançamento no sistema
A78: 45693 | B78: 429.948.714-16 | C78: =IF(B78="","",IFERROR(INDEX(Clientes!$A:$A,MATCH(B78,Clientes!$B:$B,0)),"(CPF não cadastrado)")) -> Pedro Rodrigues Pinto | D78: 300 | E78: 30 | F78: =D78/100*LOOKUP(A78,'Regras e Parâmetros'!$A$11:$A$12,'Regras e Parâmetros'!$B$11:$B$12) -> 30 | G78: =E78-F78 -> 0 | H78: Pinheiros | J78: 42994871416 | K78: Após 01/01/2025: conferir lançamento no sistema
A79: 45693 | B79: 602.419.677-67 | C79: =IF(B79="","",IFERROR(INDEX(Clientes!$A:$A,MATCH(B79,Clientes!$B:$B,0)),"(CPF não cadastrado)")) -> Henrique Almeida | D79: 500 | E79: 50 | F79: =D79/100*LOOKUP(A79,'Regras e Parâmetros'!$A$11:$A$12,'Regras e Parâmetros'!$B$11:$B$12) -> 50 | G79: =E79-F79 -> 0 | H79: Savassi | J79: 60241967767 | K79: Após 01/01/2025: conferir lançamento no sistema
A80: 45694 | B80: 834.497.354-62 | C80: =IF(B80="","",IFERROR(INDEX(Clientes!$A:$A,MATCH(B80,Clientes!$B:$B,0)),"(CPF não cadastrado)")) -> Caetano Farias | D80: 500 | E80: 50 | F80: =D80/100*LOOKUP(A80,'Regras e Parâmetros'!$A$11:$A$12,'Regras e Parâmetros'!$B$11:$B$12) -> 50 | G80: =E80-F80 -> 0 | H80: Site | J80: 83449735462 | K80: Após 01/01/2025: conferir lançamento no sistema
A81: 45696 | B81: 906.184.934-92 | C81: =IF(B81="","",IFERROR(INDEX(Clientes!$A:$A,MATCH(B81,Clientes!$B:$B,0)),"(CPF não cadastrado)")) -> Nicolas Souza | D81: 2000 | E81: 200 | F81: =D81/100*LOOKUP(A81,'Regras e Parâmetros'!$A$11:$A$12,'Regras e Parâmetros'!$B$11:$B$12) -> 200 | G81: =E81-F81 -> 0 | H81: Pinheiros | J81: 90618493492 | K81: CPF estava certo; o erro era no cadastro (corrigido).
A82: 45698 | B82: 393.072.518-51 | C82: =IF(B82="","",IFERROR(INDEX(Clientes!$A:$A,MATCH(B82,Clientes!$B:$B,0)),"(CPF não cadastrado)")) -> Fernanda Campos Peixoto | D82: 700 | E82: 70 | F82: =D82/100*LOOKUP(A82,'Regras e Parâmetros'!$A$11:$A$12,'Regras e Parâmetros'!$B$11:$B$12) -> 70 | G82: =E82-F82 -> 0 | H82: Batel | J82: 39307251851 | K82: Após 01/01/2025: conferir lançamento no sistema
A83: 45700 | B83: 839.485.382-04 | C83: =IF(B83="","",IFERROR(INDEX(Clientes!$A:$A,MATCH(B83,Clientes!$B:$B,0)),"(CPF não cadastrado)")) -> Wesley Nogueira Barbosa | D83: 1400 | E83: 140 | F83: =D83/100*LOOKUP(A83,'Regras e Parâmetros'!$A$11:$A$12,'Regras e Parâmetros'!$B$11:$B$12) -> 140 | G83: =E83-F83 -> 0 | H83: Eldorado | J83: 83948538204 | K83: Após 01/01/2025: conferir lançamento no sistema
A84: 45700 | B84: 804.398.212-07 | C84: =IF(B84="","",IFERROR(INDEX(Clientes!$A:$A,MATCH(B84,Clientes!$B:$B,0)),"(CPF não cadastrado)")) -> Daniela Pinto Peixoto | D84: 500 | E84: 50 | F84: =D84/100*LOOKUP(A84,'Regras e Parâmetros'!$A$11:$A$12,'Regras e Parâmetros'!$B$11:$B$12) -> 50 | G84: =E84-F84 -> 0 | H84: Site | J84: 80439821207 | K84: Após 01/01/2025: conferir lançamento no sistema
A85: 45702 | B85: 851.054.001-27 | C85: =IF(B85="","",IFERROR(INDEX(Clientes!$A:$A,MATCH(B85,Clientes!$B:$B,0)),"(CPF não cadastrado)")) -> Melissa Mendes Moreira | D85: 300 | E85: 30 | F85: =D85/100*LOOKUP(A85,'Regras e Parâmetros'!$A$11:$A$12,'Regras e Parâmetros'!$B$11:$B$12) -> 30 | G85: =E85-F85 -> 0 | H85: Site | J85: 85105400127 | K85: Após 01/01/2025: conferir lançamento no sistema
A86: 45703 | B86: 249.948.661-98 | C86: =IF(B86="","",IFERROR(INDEX(Clientes!$A:$A,MATCH(B86,Clientes!$B:$B,0)),"(CPF não cadastrado)")) -> Enzo Lima Costa | D86: 500 | E86: 50 | F86: =D86/100*LOOKUP(A86,'Regras e Parâmetros'!$A$11:$A$12,'Regras e Parâmetros'!$B$11:$B$12) -> 50 | G86: =E86-F86 -> 0 | H86: Savassi | I86: Carlos | J86: ENZO LIMA COSTA | K86: CPF localizado pelo nome | Após 01/01/2025: conferir lançamento no sistema
A87: 45704 | B87: 884.903.975-11 | C87: =IF(B87="","",IFERROR(INDEX(Clientes!$A:$A,MATCH(B87,Clientes!$B:$B,0)),"(CPF não cadastrado)")) -> Carolina Oliveira | D87: 1000 | E87: 100 | F87: =D87/100*LOOKUP(A87,'Regras e Parâmetros'!$A$11:$A$12,'Regras e Parâmetros'!$B$11:$B$12) -> 100 | G87: =E87-F87 -> 0 | H87: Site | J87: 88490397511 | K87: Após 01/01/2025: conferir lançamento no sistema
A88: 45706 | B88: 713.220.125-55 | C88: =IF(B88="","",IFERROR(INDEX(Clientes!$A:$A,MATCH(B88,Clientes!$B:$B,0)),"(CPF não cadastrado)")) -> Camila Alves | D88: 300 | E88: 30 | F88: =D88/100*LOOKUP(A88,'Regras e Parâmetros'!$A$11:$A$12,'Regras e Parâmetros'!$B$11:$B$12) -> 30 | G88: =E88-F88 -> 0 | H88: Eldorado | J88: 71322012555 | K88: Após 01/01/2025: conferir lançamento no sistema
A89: 45707 | B89: 754.997.868-95 | C89: =IF(B89="","",IFERROR(INDEX(Clientes!$A:$A,MATCH(B89,Clientes!$B:$B,0)),"(CPF não cadastrado)")) -> Miguel Fonseca Tavares | D89: 2000 | E89: 200 | F89: =D89/100*LOOKUP(A89,'Regras e Parâmetros'!$A$11:$A$12,'Regras e Parâmetros'!$B$11:$B$12) -> 200 | G89: =E89-F89 -> 0 | H89: Eldorado | I89: Thiago | J89: 75499786895 | K89: Após 01/01/2025: conferir lançamento no sistema
A90: 45711 | B90: 204.914.541-12 | C90: =IF(B90="","",IFERROR(INDEX(Clientes!$A:$A,MATCH(B90,Clientes!$B:$B,0)),"(CPF não cadastrado)")) -> Caua Moura | D90: 300 | E90: 30 | F90: =D90/100*LOOKUP(A90,'Regras e Parâmetros'!$A$11:$A$12,'Regras e Parâmetros'!$B$11:$B$12) -> 30 | G90: =E90-F90 -> 0 | H90: Savassi | J90: 20491454112 | K90: Após 01/01/2025: conferir lançamento no sistema
A91: 45715 | B91: 495.147.810-23 | C91: =IF(B91="","",IFERROR(INDEX(Clientes!$A:$A,MATCH(B91,Clientes!$B:$B,0)),"(CPF não cadastrado)")) -> Gustavo Barbosa | D91: 300 | E91: 30 | F91: =D91/100*LOOKUP(A91,'Regras e Parâmetros'!$A$11:$A$12,'Regras e Parâmetros'!$B$11:$B$12) -> 30 | G91: =E91-F91 -> 0 | H91: Pinheiros | J91: 49514781023 | K91: Após 01/01/2025: conferir lançamento no sistema
A92: 45718 | B92: 893.877.273-00 | C92: =IF(B92="","",IFERROR(INDEX(Clientes!$A:$A,MATCH(B92,Clientes!$B:$B,0)),"(CPF não cadastrado)")) -> Alice D. Rodrigues | D92: 500 | E92: 50 | F92: =D92/100*LOOKUP(A92,'Regras e Parâmetros'!$A$11:$A$12,'Regras e Parâmetros'!$B$11:$B$12) -> 25 | G92: =E92-F92 -> 25 | H92: Savassi | J92: 89387727300 | K92: Após 01/01/2025: conferir lançamento no sistema
A93: 45719 | B93: 696.028.328-00 | C93: =IF(B93="","",IFERROR(INDEX(Clientes!$A:$A,MATCH(B93,Clientes!$B:$B,0)),"(CPF não cadastrado)")) -> Enzo Ferreira Batista | D93: 2000 | E93: 200 | F93: =D93/100*LOOKUP(A93,'Regras e Parâmetros'!$A$11:$A$12,'Regras e Parâmetros'!$B$11:$B$12) -> 100 | G93: =E93-F93 -> 100 | H93: Eldorado | J93: 69602832800 | K93: Após 01/01/2025: conferir lançamento no sistema
A94: 45721 | B94: 001.973.032-26 | C94: =IF(B94="","",IFERROR(INDEX(Clientes!$A:$A,MATCH(B94,Clientes!$B:$B,0)),"(CPF não cadastrado)")) -> Alice Ferreira Ribeiro | D94: 1000 | E94: 100 | F94: =D94/100*LOOKUP(A94,'Regras e Parâmetros'!$A$11:$A$12,'Regras e Parâmetros'!$B$11:$B$12) -> 50 | G94: =E94-F94 -> 50 | H94: Pinheiros | J94: 00197303226 | K94: Após 01/01/2025: conferir lançamento no sistema
A95: 45721 | B95: 620.512.841-13 | C95: =IF(B95="","",IFERROR(INDEX(Clientes!$A:$A,MATCH(B95,Clientes!$B:$B,0)),"(CPF não cadastrado)")) -> Sabrina Peixoto | D95: 300 | E95: 30 | F95: =D95/100*LOOKUP(A95,'Regras e Parâmetros'!$A$11:$A$12,'Regras e Parâmetros'!$B$11:$B$12) -> 15 | G95: =E95-F95 -> 15 | H95: Site | J95: 62051284113 | K95: Após 01/01/2025: conferir lançamento no sistema
A96: 45723 | B96: 280.265.310-51 | C96: =IF(B96="","",IFERROR(INDEX(Clientes!$A:$A,MATCH(B96,Clientes!$B:$B,0)),"(CPF não cadastrado)")) -> Rafaela Peixoto Farias | D96: 500 | E96: 50 | F96: =D96/100*LOOKUP(A96,'Regras e Parâmetros'!$A$11:$A$12,'Regras e Parâmetros'!$B$11:$B$12) -> 25 | G96: =E96-F96 -> 25 | H96: Site | J96: 28026531051 | K96: Após 01/01/2025: conferir lançamento no sistema
A97: 45724 | B97: 887.303.394-64 | C97: =IF(B97="","",IFERROR(INDEX(Clientes!$A:$A,MATCH(B97,Clientes!$B:$B,0)),"(CPF não cadastrado)")) -> Melissa Moreira | D97: 1000 | E97: 100 | F97: =D97/100*LOOKUP(A97,'Regras e Parâmetros'!$A$11:$A$12,'Regras e Parâmetros'!$B$11:$B$12) -> 50 | G97: =E97-F97 -> 50 | H97: Savassi | J97: 88730339464 | K97: Após 01/01/2025: conferir lançamento no sistema
A98: 45725 | B98: 834.497.354-62 | C98: =IF(B98="","",IFERROR(INDEX(Clientes!$A:$A,MATCH(B98,Clientes!$B:$B,0)),"(CPF não cadastrado)")) -> Caetano Farias | D98: 300 | E98: 30 | F98: =D98/100*LOOKUP(A98,'Regras e Parâmetros'!$A$11:$A$12,'Regras e Parâmetros'!$B$11:$B$12) -> 15 | G98: =E98-F98 -> 15 | H98: Site | J98: 83449735462 | K98: Após 01/01/2025: conferir lançamento no sistema
A99: 45726 | B99: 545.657.636-80 | C99: =IF(B99="","",IFERROR(INDEX(Clientes!$A:$A,MATCH(B99,Clientes!$B:$B,0)),"(CPF não cadastrado)")) -> Daniela Mendes Freitas | D99: 1500 | E99: 150 | F99: =D99/100*LOOKUP(A99,'Regras e Parâmetros'!$A$11:$A$12,'Regras e Parâmetros'!$B$11:$B$12) -> 75 | G99: =E99-F99 -> 75 | H99: Batel | J99: 54565763680 | K99: Após 01/01/2025: conferir lançamento no sistema
A100: 45727 | B100: 147.457.023-29 | C100: =IF(B100="","",IFERROR(INDEX(Clientes!$A:$A,MATCH(B100,Clientes!$B:$B,0)),"(CPF não cadastrado)")) -> Manuela Cardoso | D100: 1000 | E100: 100 | F100: =D100/100*LOOKUP(A100,'Regras e Parâmetros'!$A$11:$A$12,'Regras e Parâmetros'!$B$11:$B$12) -> 50 | G100: =E100-F100 -> 50 | H100: Batel | J100: 14745702329 | K100: Após 01/01/2025: conferir lançamento no sistema
...

Sheet Pendências
A1: PENDÊNCIAS PARA CONFERIR
A2: Como resolver: descubra o CPF (com a loja/atendente ou pela venda do dia) e digite na coluna CPF da aba Resgates, na linha indicada. O caso sai desta lista automaticamente.
A3: 1) Resgates sem cliente identificado | K3: 2) Clientes ATIVOS do programa antigo fora da aba Clientes – apenas registro (nada a devolver) | Q3: 3) Descontos dados ACIMA da regra (taxa antiga de R$10 usada depois de mar/2025)
A4: Casos pendentes | B4: =COUNT(INDEX(_xlfn.ANCHORARRAY(A10),0,1)) -> 9 | K4: Clientes | L4: =COUNTA(L10:L40) -> 31 | Q4: Resgates com erro | R4: =COUNTIF(Resgates!$G$2:$G$597,">0") -> 420
A5: Pontos usados | B5: =SUM(INDEX(_xlfn.ANCHORARRAY(A10),0,4)) -> 4200 | K5: Pontos em 2023 | L5: =SUM(M10:M40) -> 112103 | Q5: Desconto a mais (R$) | R5: =SUMIF(Resgates!$G$2:$G$597,">0") -> 17795
A6: Desconto dado (R$) | B6: =SUM(INDEX(_xlfn.ANCHORARRAY(A10),0,5)) -> 370 | Q6: Padrão: TODOS os 420 erros são resgates sem atendente anotado, e todos têm exatamente o dobro do valor. Nenhum resgate com atendente anotado está errado. Provável origem: lançamento automático ou em lote (o Site está 100% errado), ainda calculado com a taxa antiga. Conferir no sistema se o desconto foi realmente dado em dobro ou se só o registro está errado.
A9: Linha na aba Resgates | B9: Data | C9: Cliente (como anotado) | D9: Pontos usados | E9: Desconto lançado (R$) | F9: Loja | G9: Atendente | H9: Motivo | I9: Sugestão / clientes possíveis | J9: Próximo passo (varredura automática) | K9: Nome | L9: CPF | M9: Pontos 2023 | N9: Última compra | O9: Situação | Q9: Loja | R9: Resgates desde mar/25 | S9: Com erro | T9: % com erro | U9: Desconto a mais (R$)
A10: {=_xlfn._xlws.FILTER(_xlfn.HSTACK(ROW(Resgates!A2:A597),Resgates!A2:A597,IF(Resgates!J2:J597="","",Resgates!J2:J597),Resgates!D2:D597,Resgates!E2:E597,Resgates!H2:H597,IF(Resgates!I2:I597="","",Resgates!I2:I597)),((Resgates!C2:C597="")+(Resgates!C2:C597="(CPF não cadastrado)"))*(LEFT(Resgates!K2:K597,17)<>"Não identificável"),"Nenhum caso pendente")} -> 15 | B10: 45019 | C10: Rodrigo | D10: 300 | E10: 30 | F10: Eldorado | G10: Bia | H10: {=IF(NOT(ISNUMBER(A10)),"",IF(INDEX(Resgates!$B:$B,A10)<>"","CPF não está no cadastro",IF(ISNUMBER(SEARCH(" ",TRIM(C10))),IF(COUNTIF(Clientes!$A$2:$A$2396,TRIM(C10))>1,"Nome repetido no cadastro","Nome não encontrado no cadastro"),"Só o primeiro nome")))} -> Só o primeiro nome | I10: {=IF(H10="","",IF(LEFT(INDEX(Resgates!$K:$K,A10),9)="Sugestão:",INDEX(Resgates!$K:$K,A10),IF(H10="Nome repetido no cadastro",_xlfn.TEXTJOIN(" / ",TRUE,_xlfn._xlws.FILTER(Clientes!$A$2:$A$2396&" – "&Clientes!$B$2:$B$2396&" (cadastro "&Clientes!$G$2:$G$2396&")",Clientes!$A$2:$A$2396=TRIM(C10))),IF(H10="Só o primeiro nome",COUNTIF(Clientes!$A$2:$A$2396,TRIM(C10)&" *")&" clientes com esse primeiro nome – confirmar com a loja/atendente",IF(H10="CPF não está no cadastro","Conferir se o CPF foi digitado errado ou se o cliente não foi cadastrado","Confirmar com a loja")))))} -> 30 clientes com esse primeiro nome – confirmar com a loja/atendente | J10: =IF(H10="Só o primeiro nome","Buscar em vendas e atendimentos: primeiro nome """&TRIM(C10)&""" + loja "&F10&" + dia "&TEXT(DAY(B10),"00")&"/"&TEXT(MONTH(B10),"00")&"/"&YEAR(B10)&" (ver aba Varredura)","") -> Buscar em vendas e atendimentos: primeiro nome "Rodrigo" + loja Eldorado + dia 03/04/2023 (ver aba Varredura) | K10: Eduarda Nunes | L10: 366.019.093-43 | M10: 4669 | N10: 45025 | O10: Encerrado: pontos de 2023 já teriam vencido (regra de 12 meses) | Q10: Site | R10: =COUNTIFS(Resgates!$H$2:$H$597,Q10,Resgates!$A$2:$A$597,">="&'Regras e Parâmetros'!$A$12) -> 229 | S10: =COUNTIFS(Resgates!$H$2:$H$597,Q10,Resgates!$G$2:$G$597,">0") -> 229 | T10: =IF(R10=0,0,S10/R10) -> 1 | U10: =SUMIFS(Resgates!$G$2:$G$597,Resgates!$H$2:$H$597,Q10,Resgates!$G$2:$G$597,">0") -> 8555
A11: 17 | B11: 45049 | C11: Luan | D11: 500 | E11: 50 | F11: Eldorado | H11: {=IF(NOT(ISNUMBER(A11)),"",IF(INDEX(Resgates!$B:$B,A11)<>"","CPF não está no cadastro",IF(ISNUMBER(SEARCH(" ",TRIM(C11))),IF(COUNTIF(Clientes!$A$2:$A$2396,TRIM(C11))>1,"Nome repetido no cadastro","Nome não encontrado no cadastro"),"Só o primeiro nome")))} -> Só o primeiro nome | I11: {=IF(H11="","",IF(LEFT(INDEX(Resgates!$K:$K,A11),9)="Sugestão:",INDEX(Resgates!$K:$K,A11),IF(H11="Nome repetido no cadastro",_xlfn.TEXTJOIN(" / ",TRUE,_xlfn._xlws.FILTER(Clientes!$A$2:$A$2396&" – "&Clientes!$B$2:$B$2396&" (cadastro "&Clientes!$G$2:$G$2396&")",Clientes!$A$2:$A$2396=TRIM(C11))),IF(H11="Só o primeiro nome",COUNTIF(Clientes!$A$2:$A$2396,TRIM(C11)&" *")&" clientes com esse primeiro nome – confirmar com a loja/atendente",IF(H11="CPF não está no cadastro","Conferir se o CPF foi digitado errado ou se o cliente não foi cadastrado","Confirmar com a loja")))))} -> Sugestão: Luan Oliveira Gomes 740.762.313-92 (único da loja com DDD; confiança média) | Varredura 19/10/2026: sem vendas antes de 2025 no vulto.db para cruzar | J11: =IF(H11="Só o primeiro nome","Buscar em vendas e atendimentos: primeiro nome """&TRIM(C11)&""" + loja "&F11&" + dia "&TEXT(DAY(B11),"00")&"/"&TEXT(MONTH(B11),"00")&"/"&YEAR(B11)&" (ver aba Varredura)","") -> Buscar em vendas e atendimentos: primeiro nome "Luan" + loja Eldorado + dia 03/05/2023 (ver aba Varredura) | K11: Valentina Correia | L11: 231.639.906-14 | M11: 7659 | N11: 45122 | O11: Encerrado: pontos de 2023 já teriam vencido (regra de 12 meses) | Q11: Eldorado | R11: =COUNTIFS(Resgates!$H$2:$H$597,Q11,Resgates!$A$2:$A$597,">="&'Regras e Parâmetros'!$A$12) -> 72 | S11: =COUNTIFS(Resgates!$H$2:$H$597,Q11,Resgates!$G$2:$G$597,">0") -> 50 | T11: =IF(R11=0,0,S11/R11) -> 0.69444444 | U11: =SUMIFS(Resgates!$G$2:$G$597,Resgates!$H$2:$H$597,Q11,Resgates!$G$2:$G$597,">0") -> 2515
A12: 40 | B12: 45305 | C12: 9274284829 | D12: 500 | E12: 50 | F12: Batel | G12: Carlos | H12: {=IF(NOT(ISNUMBER(A12)),"",IF(INDEX(Resgates!$B:$B,A12)<>"","CPF não está no cadastro",IF(ISNUMBER(SEARCH(" ",TRIM(C12))),IF(COUNTIF(Clientes!$A$2:$A$2396,TRIM(C12))>1,"Nome repetido no cadastro","Nome não encontrado no cadastro"),"Só o primeiro nome")))} -> CPF não está no cadastro | I12: {=IF(H12="","",IF(LEFT(INDEX(Resgates!$K:$K,A12),9)="Sugestão:",INDEX(Resgates!$K:$K,A12),IF(H12="Nome repetido no cadastro",_xlfn.TEXTJOIN(" / ",TRUE,_xlfn._xlws.FILTER(Clientes!$A$2:$A$2396&" – "&Clientes!$B$2:$B$2396&" (cadastro "&Clientes!$G$2:$G$2396&")",Clientes!$A$2:$A$2396=TRIM(C12))),IF(H12="Só o primeiro nome",COUNTIF(Clientes!$A$2:$A$2396,TRIM(C12)&" *")&" clientes com esse primeiro nome – confirmar com a loja/atendente",IF(H12="CPF não está no cadastro","Conferir se o CPF foi digitado errado ou se o cliente não foi cadastrado","Confirmar com a loja")))))} -> Conferir se o CPF foi digitado errado ou se o cliente não foi cadastrado | J12: =IF(H12="Só o primeiro nome","Buscar em vendas e atendimentos: primeiro nome """&TRIM(C12)&""" + loja "&F12&" + dia "&TEXT(DAY(B12),"00")&"/"&TEXT(MONTH(B12),"00")&"/"&YEAR(B12)&" (ver aba Varredura)","") | K12: Manuela Monteiro | L12: 169.217.378-29 | M12: 1778 | N12: 45032 | O12: Encerrado: pontos de 2023 já teriam vencido (regra de 12 meses) | Q12: Pinheiros | R12: =COUNTIFS(Resgates!$H$2:$H$597,Q12,Resgates!$A$2:$A$597,">="&'Regras e Parâmetros'!$A$12) -> 74 | S12: =COUNTIFS(Resgates!$H$2:$H$597,Q12,Resgates!$G$2:$G$597,">0") -> 46 | T12: =IF(R12=0,0,S12/R12) -> 0.62162162 | U12: =SUMIFS(Resgates!$G$2:$G$597,Resgates!$H$2:$H$597,Q12,Resgates!$G$2:$G$597,">0") -> 2410
A13: 53 | B13: 45567 | C13: Juliana | D13: 1000 | E13: 100 | F13: Savassi | H13: {=IF(NOT(ISNUMBER(A13)),"",IF(INDEX(Resgates!$B:$B,A13)<>"","CPF não está no cadastro",IF(ISNUMBER(SEARCH(" ",TRIM(C13))),IF(COUNTIF(Clientes!$A$2:$A$2396,TRIM(C13))>1,"Nome repetido no cadastro","Nome não encontrado no cadastro"),"Só o primeiro nome")))} -> Só o primeiro nome | I13: {=IF(H13="","",IF(LEFT(INDEX(Resgates!$K:$K,A13),9)="Sugestão:",INDEX(Resgates!$K:$K,A13),IF(H13="Nome repetido no cadastro",_xlfn.TEXTJOIN(" / ",TRUE,_xlfn._xlws.FILTER(Clientes!$A$2:$A$2396&" – "&Clientes!$B$2:$B$2396&" (cadastro "&Clientes!$G$2:$G$2396&")",Clientes!$A$2:$A$2396=TRIM(C13))),IF(H13="Só o primeiro nome",COUNTIF(Clientes!$A$2:$A$2396,TRIM(C13)&" *")&" clientes com esse primeiro nome – confirmar com a loja/atendente",IF(H13="CPF não está no cadastro","Conferir se o CPF foi digitado errado ou se o cliente não foi cadastrado","Confirmar com a loja")))))} -> 39 clientes com esse primeiro nome – confirmar com a loja/atendente | J13: =IF(H13="Só o primeiro nome","Buscar em vendas e atendimentos: primeiro nome """&TRIM(C13)&""" + loja "&F13&" + dia "&TEXT(DAY(B13),"00")&"/"&TEXT(MONTH(B13),"00")&"/"&YEAR(B13)&" (ver aba Varredura)","") -> Buscar em vendas e atendimentos: primeiro nome "Juliana" + loja Savassi + dia 02/10/2024 (ver aba Varredura) | K13: Breno Ferreira | L13: 220.402.682-43 | M13: 960 | N13: 45232 | O13: Encerrado: pontos de 2023 já teriam vencido (regra de 12 meses) | Q13: Batel | R13: =COUNTIFS(Resgates!$H$2:$H$597,Q13,Resgates!$A$2:$A$597,">="&'Regras e Parâmetros'!$A$12) -> 71 | S13: =COUNTIFS(Resgates!$H$2:$H$597,Q13,Resgates!$G$2:$G$597,">0") -> 50 | T13: =IF(R13=0,0,S13/R13) -> 0.70422535 | U13: =SUMIFS(Resgates!$G$2:$G$597,Resgates!$H$2:$H$597,Q13,Resgates!$G$2:$G$597,">0") -> 2270
A14: 56 | B14: 45597 | C14: Alexandre | D14: 300 | E14: 30 | F14: Batel | G14: Carlos | H14: {=IF(NOT(ISNUMBER(A14)),"",IF(INDEX(Resgates!$B:$B,A14)<>"","CPF não está no cadastro",IF(ISNUMBER(SEARCH(" ",TRIM(C14))),IF(COUNTIF(Clientes!$A$2:$A$2396,TRIM(C14))>1,"Nome repetido no cadastro","Nome não encontrado no cadastro"),"Só o primeiro nome")))} -> Só o primeiro nome | I14: {=IF(H14="","",IF(LEFT(INDEX(Resgates!$K:$K,A14),9)="Sugestão:",INDEX(Resgates!$K:$K,A14),IF(H14="Nome repetido no cadastro",_xlfn.TEXTJOIN(" / ",TRUE,_xlfn._xlws.FILTER(Clientes!$A$2:$A$2396&" – "&Clientes!$B$2:$B$2396&" (cadastro "&Clientes!$G$2:$G$2396&")",Clientes!$A$2:$A$2396=TRIM(C14))),IF(H14="Só o primeiro nome",COUNTIF(Clientes!$A$2:$A$2396,TRIM(C14)&" *")&" clientes com esse primeiro nome – confirmar com a loja/atendente",IF(H14="CPF não está no cadastro","Conferir se o CPF foi digitado errado ou se o cliente não foi cadastrado","Confirmar com a loja")))))} -> 19 clientes com esse primeiro nome – confirmar com a loja/atendente | J14: =IF(H14="Só o primeiro nome","Buscar em vendas e atendimentos: primeiro nome """&TRIM(C14)&""" + loja "&F14&" + dia "&TEXT(DAY(B14),"00")&"/"&TEXT(MONTH(B14),"00")&"/"&YEAR(B14)&" (ver aba Varredura)","") -> Buscar em vendas e atendimentos: primeiro nome "Alexandre" + loja Batel + dia 01/11/2024 (ver aba Varredura) | K14: Rafaela Soares Barros | L14: 651.539.252-42 | M14: 1542 | N14: 45190 | O14: Encerrado: pontos de 2023 já teriam vencido (regra de 12 meses) | Q14: Savassi | R14: =COUNTIFS(Resgates!$H$2:$H$597,Q14,Resgates!$A$2:$A$597,">="&'Regras e Parâmetros'!$A$12) -> 60 | S14: =COUNTIFS(Resgates!$H$2:$H$597,Q14,Resgates!$G$2:$G$597,">0") -> 45 | T14: =IF(R14=0,0,S14/R14) -> 0.75 | U14: =SUMIFS(Resgates!$G$2:$G$597,Resgates!$H$2:$H$597,Q14,Resgates!$G$2:$G$597,">0") -> 2045
A15: 58 | B15: 45604 | C15: Leonardo | D15: 100 | E15: 10 | F15: Eldorado | G15: Rafa | H15: {=IF(NOT(ISNUMBER(A15)),"",IF(INDEX(Resgates!$B:$B,A15)<>"","CPF não está no cadastro",IF(ISNUMBER(SEARCH(" ",TRIM(C15))),IF(COUNTIF(Clientes!$A$2:$A$2396,TRIM(C15))>1,"Nome repetido no cadastro","Nome não encontrado no cadastro"),"Só o primeiro nome")))} -> Só o primeiro nome | I15: {=IF(H15="","",IF(LEFT(INDEX(Resgates!$K:$K,A15),9)="Sugestão:",INDEX(Resgates!$K:$K,A15),IF(H15="Nome repetido no cadastro",_xlfn.TEXTJOIN(" / ",TRUE,_xlfn._xlws.FILTER(Clientes!$A$2:$A$2396&" – "&Clientes!$B$2:$B$2396&" (cadastro "&Clientes!$G$2:$G$2396&")",Clientes!$A$2:$A$2396=TRIM(C15))),IF(H15="Só o primeiro nome",COUNTIF(Clientes!$A$2:$A$2396,TRIM(C15)&" *")&" clientes com esse primeiro nome – confirmar com a loja/atendente",IF(H15="CPF não está no cadastro","Conferir se o CPF foi digitado errado ou se o cliente não foi cadastrado","Confirmar com a loja")))))} -> 13 clientes com esse primeiro nome – confirmar com a loja/atendente | J15: =IF(H15="Só o primeiro nome","Buscar em vendas e atendimentos: primeiro nome """&TRIM(C15)&""" + loja "&F15&" + dia "&TEXT(DAY(B15),"00")&"/"&TEXT(MONTH(B15),"00")&"/"&YEAR(B15)&" (ver aba Varredura)","") -> Buscar em vendas e atendimentos: primeiro nome "Leonardo" + loja Eldorado + dia 08/11/2024 (ver aba Varredura) | K15: Davi Alves | L15: 983.293.371-46 | M15: 3107 | N15: 45093 | O15: Encerrado: pontos de 2023 já teriam vencido (regra de 12 meses) | Q15: Total | R15: =SUM(R10:R14) -> 506 | S15: =SUM(S10:S14) -> 420 | T15: =IF(R15=0,0,S15/R15) -> 0.83003953 | U15: =SUM(U10:U14) -> 17795
A16: 59 | B16: 45610 | C16: Mariana | D16: 500 | E16: 50 | F16: Batel | H16: {=IF(NOT(ISNUMBER(A16)),"",IF(INDEX(Resgates!$B:$B,A16)<>"","CPF não está no cadastro",IF(ISNUMBER(SEARCH(" ",TRIM(C16))),IF(COUNTIF(Clientes!$A$2:$A$2396,TRIM(C16))>1,"Nome repetido no cadastro","Nome não encontrado no cadastro"),"Só o primeiro nome")))} -> Só o primeiro nome | I16: {=IF(H16="","",IF(LEFT(INDEX(Resgates!$K:$K,A16),9)="Sugestão:",INDEX(Resgates!$K:$K,A16),IF(H16="Nome repetido no cadastro",_xlfn.TEXTJOIN(" / ",TRUE,_xlfn._xlws.FILTER(Clientes!$A$2:$A$2396&" – "&Clientes!$B$2:$B$2396&" (cadastro "&Clientes!$G$2:$G$2396&")",Clientes!$A$2:$A$2396=TRIM(C16))),IF(H16="Só o primeiro nome",COUNTIF(Clientes!$A$2:$A$2396,TRIM(C16)&" *")&" clientes com esse primeiro nome – confirmar com a loja/atendente",IF(H16="CPF não está no cadastro","Conferir se o CPF foi digitado errado ou se o cliente não foi cadastrado","Confirmar com a loja")))))} -> Sugestão: Mariana Marques 142.255.830-40 (única da loja com DDD; confiança média) | Varredura 19/10/2026: sem vendas antes de 2025 no vulto.db para cruzar | J16: =IF(H16="Só o primeiro nome","Buscar em vendas e atendimentos: primeiro nome """&TRIM(C16)&""" + loja "&F16&" + dia "&TEXT(DAY(B16),"00")&"/"&TEXT(MONTH(B16),"00")&"/"&YEAR(B16)&" (ver aba Varredura)","") -> Buscar em vendas e atendimentos: primeiro nome "Mariana" + loja Batel + dia 14/11/2024 (ver aba Varredura) | K16: Giovanna Almeida Pinto | L16: 300.105.589-85 | M16: 5526 | N16: 45001 | O16: Encerrado: pontos de 2023 já teriam vencido (regra de 12 meses)
A17: 554 | B17: 46245 | C17: Júlia | D17: 500 | E17: 25 | F17: Savassi | G17: Ana Paula | H17: {=IF(NOT(ISNUMBER(A17)),"",IF(INDEX(Resgates!$B:$B,A17)<>"","CPF não está no cadastro",IF(ISNUMBER(SEARCH(" ",TRIM(C17))),IF(COUNTIF(Clientes!$A$2:$A$2396,TRIM(C17))>1,"Nome repetido no cadastro","Nome não encontrado no cadastro"),"Só o primeiro nome")))} -> Só o primeiro nome | I17: {=IF(H17="","",IF(LEFT(INDEX(Resgates!$K:$K,A17),9)="Sugestão:",INDEX(Resgates!$K:$K,A17),IF(H17="Nome repetido no cadastro",_xlfn.TEXTJOIN(" / ",TRUE,_xlfn._xlws.FILTER(Clientes!$A$2:$A$2396&" – "&Clientes!$B$2:$B$2396&" (cadastro "&Clientes!$G$2:$G$2396&")",Clientes!$A$2:$A$2396=TRIM(C17))),IF(H17="Só o primeiro nome",COUNTIF(Clientes!$A$2:$A$2396,TRIM(C17)&" *")&" clientes com esse primeiro nome – confirmar com a loja/atendente",IF(H17="CPF não está no cadastro","Conferir se o CPF foi digitado errado ou se o cliente não foi cadastrado","Confirmar com a loja")))))} -> Sugestão: Julia Fernandes 558.971.099-58 (única venda do dia na loja com esse nome, venda 17215, mas o desconto foi R$ 33,00 e o resgate anotado é R$ 25,00) ou Júlia Peixoto Ferreira 123.214.834-23 (cadastro na Savassi + atendimento de 16/08/2026 com o mesmo nome; confiança média-alta); confirmar com a loja | J17: =IF(H17="Só o primeiro nome","Buscar em vendas e atendimentos: primeiro nome """&TRIM(C17)&""" + loja "&F17&" + dia "&TEXT(DAY(B17),"00")&"/"&TEXT(MONTH(B17),"00")&"/"&YEAR(B17)&" (ver aba Varredura)","") -> Buscar em vendas e atendimentos: primeiro nome "Júlia" + loja Savassi + dia 11/08/2026 (ver aba Varredura) | K17: Rebeca Soares | L17: 507.766.382-38 | M17: 7240 | N17: 44949 | O17: Encerrado: pontos de 2023 já teriam vencido (regra de 12 meses)
A18: 582 | B18: 46281 | C18: João | D18: 500 | E18: 25 | F18: Eldorado | G18: Thiago | H18: {=IF(NOT(ISNUMBER(A18)),"",IF(INDEX(Resgates!$B:$B,A18)<>"","CPF não está no cadastro",IF(ISNUMBER(SEARCH(" ",TRIM(C18))),IF(COUNTIF(Clientes!$A$2:$A$2396,TRIM(C18))>1,"Nome repetido no cadastro","Nome não encontrado no cadastro"),"Só o primeiro nome")))} -> Só o primeiro nome | I18: {=IF(H18="","",IF(LEFT(INDEX(Resgates!$K:$K,A18),9)="Sugestão:",INDEX(Resgates!$K:$K,A18),IF(H18="Nome repetido no cadastro",_xlfn.TEXTJOIN(" / ",TRUE,_xlfn._xlws.FILTER(Clientes!$A$2:$A$2396&" – "&Clientes!$B$2:$B$2396&" (cadastro "&Clientes!$G$2:$G$2396&")",Clientes!$A$2:$A$2396=TRIM(C18))),IF(H18="Só o primeiro nome",COUNTIF(Clientes!$A$2:$A$2396,TRIM(C18)&" *")&" clientes com esse primeiro nome – confirmar com a loja/atendente",IF(H18="CPF não está no cadastro","Conferir se o CPF foi digitado errado ou se o cliente não foi cadastrado","Confirmar com a loja")))))} -> Sugestão: João Pereira Mendes 249.952.721-86 (único da loja; confiança média) | Varredura 19/10/2026: nenhuma venda de cliente com esse nome na loja de 15 a 17/09/2026 | J18: =IF(H18="Só o primeiro nome","Buscar em vendas e atendimentos: primeiro nome """&TRIM(C18)&""" + loja "&F18&" + dia "&TEXT(DAY(B18),"00")&"/"&TEXT(MONTH(B18),"00")&"/"&YEAR(B18)&" (ver aba Varredura)","") -> Buscar em vendas e atendimentos: primeiro nome "João" + loja Eldorado + dia 16/09/2026 (ver aba Varredura) | K18: Cecília Fernandes | L18: 799.921.299-72 | M18: 4483 | N18: 45222 | O18: Provavelmente migrou com outro CPF: 934.365.449-90 | Q18: Atendente | R18: Resgates desde mar/25 | S18: Com erro | T18: % com erro | U18: Desconto a mais (R$)
H19: {=IF(NOT(ISNUMBER(A19)),"",IF(INDEX(Resgates!$B:$B,A19)<>"","CPF não está no cadastro",IF(ISNUMBER(SEARCH(" ",TRIM(C19))),IF(COUNTIF(Clientes!$A$2:$A$2396,TRIM(C19))>1,"Nome repetido no cadastro","Nome não encontrado no cadastro"),"Só o primeiro nome")))} | I19: {=IF(H19="","",IF(LEFT(INDEX(Resgates!$K:$K,A19),9)="Sugestão:",INDEX(Resgates!$K:$K,A19),IF(H19="Nome repetido no cadastro",_xlfn.TEXTJOIN(" / ",TRUE,_xlfn._xlws.FILTER(Clientes!$A$2:$A$2396&" – "&Clientes!$B$2:$B$2396&" (cadastro "&Clientes!$G$2:$G$2396&")",Clientes!$A$2:$A$2396=TRIM(C19))),IF(H19="Só o primeiro nome",COUNTIF(Clientes!$A$2:$A$2396,TRIM(C19)&" *")&" clientes com esse primeiro nome – confirmar com a loja/atendente",IF(H19="CPF não está no cadastro","Conferir se o CPF foi digitado errado ou se o cliente não foi cadastrado","Confirmar com a loja")))))} | J19: =IF(H19="Só o primeiro nome","Buscar em vendas e atendimentos: primeiro nome """&TRIM(C19)&""" + loja "&F19&" + dia "&TEXT(DAY(B19),"00")&"/"&TEXT(MONTH(B19),"00")&"/"&YEAR(B19)&" (ver aba Varredura)","") | K19: Renata Soares | L19: 731.675.299-89 | M19: 6167 | N19: 44944 | O19: Encerrado: pontos de 2023 já teriam vencido (regra de 12 meses) | Q19: {=_xlfn._xlws.SORT(_xlfn.UNIQUE(_xlfn._xlws.FILTER(Resgates!$I$2:$I$597,(Resgates!$A$2:$A$597>='Regras e Parâmetros'!$A$12)*(Resgates!$I$2:$I$597<>""))))} -> Ana Paula | R19: =IF(Q19="","",COUNTIFS(Resgates!$I$2:$I$597,Q19,Resgates!$A$2:$A$597,">="&'Regras e Parâmetros'!$A$12)) -> 8 | S19: =IF(Q19="","",COUNTIFS(Resgates!$I$2:$I$597,Q19,Resgates!$G$2:$G$597,">0")) -> 0 | T19: =IF(Q19="","",IF(R19=0,0,S19/R19)) -> 0 | U19: =IF(Q19="","",SUMIFS(Resgates!$G$2:$G$597,Resgates!$I$2:$I$597,Q19,Resgates!$G$2:$G$597,">0")) -> 0
H20: {=IF(NOT(ISNUMBER(A20)),"",IF(INDEX(Resgates!$B:$B,A20)<>"","CPF não está no cadastro",IF(ISNUMBER(SEARCH(" ",TRIM(C20))),IF(COUNTIF(Clientes!$A$2:$A$2396,TRIM(C20))>1,"Nome repetido no cadastro","Nome não encontrado no cadastro"),"Só o primeiro nome")))} | I20: {=IF(H20="","",IF(LEFT(INDEX(Resgates!$K:$K,A20),9)="Sugestão:",INDEX(Resgates!$K:$K,A20),IF(H20="Nome repetido no cadastro",_xlfn.TEXTJOIN(" / ",TRUE,_xlfn._xlws.FILTER(Clientes!$A$2:$A$2396&" – "&Clientes!$B$2:$B$2396&" (cadastro "&Clientes!$G$2:$G$2396&")",Clientes!$A$2:$A$2396=TRIM(C20))),IF(H20="Só o primeiro nome",COUNTIF(Clientes!$A$2:$A$2396,TRIM(C20)&" *")&" clientes com esse primeiro nome – confirmar com a loja/atendente",IF(H20="CPF não está no cadastro","Conferir se o CPF foi digitado errado ou se o cliente não foi cadastrado","Confirmar com a loja")))))} | J20: =IF(H20="Só o primeiro nome","Buscar em vendas e atendimentos: primeiro nome """&TRIM(C20)&""" + loja "&F20&" + dia "&TEXT(DAY(B20),"00")&"/"&TEXT(MONTH(B20),"00")&"/"&YEAR(B20)&" (ver aba Varredura)","") | K20: Camila Nogueira | L20: 890.646.714-19 | M20: 1793 | N20: 44945 | O20: Encerrado: pontos de 2023 já teriam vencido (regra de 12 meses) | Q20: Beatriz | R20: =IF(Q20="","",COUNTIFS(Resgates!$I$2:$I$597,Q20,Resgates!$A$2:$A$597,">="&'Regras e Parâmetros'!$A$12)) -> 5 | S20: =IF(Q20="","",COUNTIFS(Resgates!$I$2:$I$597,Q20,Resgates!$G$2:$G$597,">0")) -> 0 | T20: =IF(Q20="","",IF(R20=0,0,S20/R20)) -> 0 | U20: =IF(Q20="","",SUMIFS(Resgates!$G$2:$G$597,Resgates!$I$2:$I$597,Q20,Resgates!$G$2:$G$597,">0")) -> 0
H21: {=IF(NOT(ISNUMBER(A21)),"",IF(INDEX(Resgates!$B:$B,A21)<>"","CPF não está no cadastro",IF(ISNUMBER(SEARCH(" ",TRIM(C21))),IF(COUNTIF(Clientes!$A$2:$A$2396,TRIM(C21))>1,"Nome repetido no cadastro","Nome não encontrado no cadastro"),"Só o primeiro nome")))} | I21: {=IF(H21="","",IF(LEFT(INDEX(Resgates!$K:$K,A21),9)="Sugestão:",INDEX(Resgates!$K:$K,A21),IF(H21="Nome repetido no cadastro",_xlfn.TEXTJOIN(" / ",TRUE,_xlfn._xlws.FILTER(Clientes!$A$2:$A$2396&" – "&Clientes!$B$2:$B$2396&" (cadastro "&Clientes!$G$2:$G$2396&")",Clientes!$A$2:$A$2396=TRIM(C21))),IF(H21="Só o primeiro nome",COUNTIF(Clientes!$A$2:$A$2396,TRIM(C21)&" *")&" clientes com esse primeiro nome – confirmar com a loja/atendente",IF(H21="CPF não está no cadastro","Conferir se o CPF foi digitado errado ou se o cliente não foi cadastrado","Confirmar com a loja")))))} | J21: =IF(H21="Só o primeiro nome","Buscar em vendas e atendimentos: primeiro nome """&TRIM(C21)&""" + loja "&F21&" + dia "&TEXT(DAY(B21),"00")&"/"&TEXT(MONTH(B21),"00")&"/"&YEAR(B21)&" (ver aba Varredura)","") | K21: Rebeca Fernandes Moura | L21: 610.429.147-37 | M21: 3600 | N21: 45187 | O21: Encerrado: pontos de 2023 já teriam vencido (regra de 12 meses) | Q21: Bia | R21: =IF(Q21="","",COUNTIFS(Resgates!$I$2:$I$597,Q21,Resgates!$A$2:$A$597,">="&'Regras e Parâmetros'!$A$12)) -> 10 | S21: =IF(Q21="","",COUNTIFS(Resgates!$I$2:$I$597,Q21,Resgates!$G$2:$G$597,">0")) -> 0 | T21: =IF(Q21="","",IF(R21=0,0,S21/R21)) -> 0 | U21: =IF(Q21="","",SUMIFS(Resgates!$G$2:$G$597,Resgates!$I$2:$I$597,Q21,Resgates!$G$2:$G$597,">0")) -> 0
H22: {=IF(NOT(ISNUMBER(A22)),"",IF(INDEX(Resgates!$B:$B,A22)<>"","CPF não está no cadastro",IF(ISNUMBER(SEARCH(" ",TRIM(C22))),IF(COUNTIF(Clientes!$A$2:$A$2396,TRIM(C22))>1,"Nome repetido no cadastro","Nome não encontrado no cadastro"),"Só o primeiro nome")))} | I22: {=IF(H22="","",IF(LEFT(INDEX(Resgates!$K:$K,A22),9)="Sugestão:",INDEX(Resgates!$K:$K,A22),IF(H22="Nome repetido no cadastro",_xlfn.TEXTJOIN(" / ",TRUE,_xlfn._xlws.FILTER(Clientes!$A$2:$A$2396&" – "&Clientes!$B$2:$B$2396&" (cadastro "&Clientes!$G$2:$G$2396&")",Clientes!$A$2:$A$2396=TRIM(C22))),IF(H22="Só o primeiro nome",COUNTIF(Clientes!$A$2:$A$2396,TRIM(C22)&" *")&" clientes com esse primeiro nome – confirmar com a loja/atendente",IF(H22="CPF não está no cadastro","Conferir se o CPF foi digitado errado ou se o cliente não foi cadastrado","Confirmar com a loja")))))} | J22: =IF(H22="Só o primeiro nome","Buscar em vendas e atendimentos: primeiro nome """&TRIM(C22)&""" + loja "&F22&" + dia "&TEXT(DAY(B22),"00")&"/"&TEXT(MONTH(B22),"00")&"/"&YEAR(B22)&" (ver aba Varredura)","") | K22: Priscila Barbosa | L22: 349.803.647-56 | M22: 2705 | N22: 45112 | O22: Encerrado: pontos de 2023 já teriam vencido (regra de 12 meses) | Q22: Bianca | R22: =IF(Q22="","",COUNTIFS(Resgates!$I$2:$I$597,Q22,Resgates!$A$2:$A$597,">="&'Regras e Parâmetros'!$A$12)) -> 2 | S22: =IF(Q22="","",COUNTIFS(Resgates!$I$2:$I$597,Q22,Resgates!$G$2:$G$597,">0")) -> 0 | T22: =IF(Q22="","",IF(R22=0,0,S22/R22)) -> 0 | U22: =IF(Q22="","",SUMIFS(Resgates!$G$2:$G$597,Resgates!$I$2:$I$597,Q22,Resgates!$G$2:$G$597,">0")) -> 0
H23: {=IF(NOT(ISNUMBER(A23)),"",IF(INDEX(Resgates!$B:$B,A23)<>"","CPF não está no cadastro",IF(ISNUMBER(SEARCH(" ",TRIM(C23))),IF(COUNTIF(Clientes!$A$2:$A$2396,TRIM(C23))>1,"Nome repetido no cadastro","Nome não encontrado no cadastro"),"Só o primeiro nome")))} | I23: {=IF(H23="","",IF(LEFT(INDEX(Resgates!$K:$K,A23),9)="Sugestão:",INDEX(Resgates!$K:$K,A23),IF(H23="Nome repetido no cadastro",_xlfn.TEXTJOIN(" / ",TRUE,_xlfn._xlws.FILTER(Clientes!$A$2:$A$2396&" – "&Clientes!$B$2:$B$2396&" (cadastro "&Clientes!$G$2:$G$2396&")",Clientes!$A$2:$A$2396=TRIM(C23))),IF(H23="Só o primeiro nome",COUNTIF(Clientes!$A$2:$A$2396,TRIM(C23)&" *")&" clientes com esse primeiro nome – confirmar com a loja/atendente",IF(H23="CPF não está no cadastro","Conferir se o CPF foi digitado errado ou se o cliente não foi cadastrado","Confirmar com a loja")))))} | J23: =IF(H23="Só o primeiro nome","Buscar em vendas e atendimentos: primeiro nome """&TRIM(C23)&""" + loja "&F23&" + dia "&TEXT(DAY(B23),"00")&"/"&TEXT(MONTH(B23),"00")&"/"&YEAR(B23)&" (ver aba Varredura)","") | K23: Vitória Mendes | L23: 921.341.835-35 | M23: 3930 | N23: 45042 | O23: Encerrado: pontos de 2023 já teriam vencido (regra de 12 meses) | Q23: Camila | R23: =IF(Q23="","",COUNTIFS(Resgates!$I$2:$I$597,Q23,Resgates!$A$2:$A$597,">="&'Regras e Parâmetros'!$A$12)) -> 5 | S23: =IF(Q23="","",COUNTIFS(Resgates!$I$2:$I$597,Q23,Resgates!$G$2:$G$597,">0")) -> 0 | T23: =IF(Q23="","",IF(R23=0,0,S23/R23)) -> 0 | U23: =IF(Q23="","",SUMIFS(Resgates!$G$2:$G$597,Resgates!$I$2:$I$597,Q23,Resgates!$G$2:$G$597,">0")) -> 0
H24: {=IF(NOT(ISNUMBER(A24)),"",IF(INDEX(Resgates!$B:$B,A24)<>"","CPF não está no cadastro",IF(ISNUMBER(SEARCH(" ",TRIM(C24))),IF(COUNTIF(Clientes!$A$2:$A$2396,TRIM(C24))>1,"Nome repetido no cadastro","Nome não encontrado no cadastro"),"Só o primeiro nome")))} | I24: {=IF(H24="","",IF(LEFT(INDEX(Resgates!$K:$K,A24),9)="Sugestão:",INDEX(Resgates!$K:$K,A24),IF(H24="Nome repetido no cadastro",_xlfn.TEXTJOIN(" / ",TRUE,_xlfn._xlws.FILTER(Clientes!$A$2:$A$2396&" – "&Clientes!$B$2:$B$2396&" (cadastro "&Clientes!$G$2:$G$2396&")",Clientes!$A$2:$A$2396=TRIM(C24))),IF(H24="Só o primeiro nome",COUNTIF(Clientes!$A$2:$A$2396,TRIM(C24)&" *")&" clientes com esse primeiro nome – confirmar com a loja/atendente",IF(H24="CPF não está no cadastro","Conferir se o CPF foi digitado errado ou se o cliente não foi cadastrado","Confirmar com a loja")))))} | J24: =IF(H24="Só o primeiro nome","Buscar em vendas e atendimentos: primeiro nome """&TRIM(C24)&""" + loja "&F24&" + dia "&TEXT(DAY(B24),"00")&"/"&TEXT(MONTH(B24),"00")&"/"&YEAR(B24)&" (ver aba Varredura)","") | K24: Davi Vieira | L24: 182.008.073-04 | M24: 1285 | N24: 44964 | O24: Encerrado: pontos de 2023 já teriam vencido (regra de 12 meses) | Q24: Carlos | R24: =IF(Q24="","",COUNTIFS(Resgates!$I$2:$I$597,Q24,Resgates!$A$2:$A$597,">="&'Regras e Parâmetros'!$A$12)) -> 3 | S24: =IF(Q24="","",COUNTIFS(Resgates!$I$2:$I$597,Q24,Resgates!$G$2:$G$597,">0")) -> 0 | T24: =IF(Q24="","",IF(R24=0,0,S24/R24)) -> 0 | U24: =IF(Q24="","",SUMIFS(Resgates!$G$2:$G$597,Resgates!$I$2:$I$597,Q24,Resgates!$G$2:$G$597,">0")) -> 0
H25: {=IF(NOT(ISNUMBER(A25)),"",IF(INDEX(Resgates!$B:$B,A25)<>"","CPF não está no cadastro",IF(ISNUMBER(SEARCH(" ",TRIM(C25))),IF(COUNTIF(Clientes!$A$2:$A$2396,TRIM(C25))>1,"Nome repetido no cadastro","Nome não encontrado no cadastro"),"Só o primeiro nome")))} | I25: {=IF(H25="","",IF(LEFT(INDEX(Resgates!$K:$K,A25),9)="Sugestão:",INDEX(Resgates!$K:$K,A25),IF(H25="Nome repetido no cadastro",_xlfn.TEXTJOIN(" / ",TRUE,_xlfn._xlws.FILTER(Clientes!$A$2:$A$2396&" – "&Clientes!$B$2:$B$2396&" (cadastro "&Clientes!$G$2:$G$2396&")",Clientes!$A$2:$A$2396=TRIM(C25))),IF(H25="Só o primeiro nome",COUNTIF(Clientes!$A$2:$A$2396,TRIM(C25)&" *")&" clientes com esse primeiro nome – confirmar com a loja/atendente",IF(H25="CPF não está no cadastro","Conferir se o CPF foi digitado errado ou se o cliente não foi cadastrado","Confirmar com a loja")))))} | J25: =IF(H25="Só o primeiro nome","Buscar em vendas e atendimentos: primeiro nome """&TRIM(C25)&""" + loja "&F25&" + dia "&TEXT(DAY(B25),"00")&"/"&TEXT(MONTH(B25),"00")&"/"&YEAR(B25)&" (ver aba Varredura)","") | K25: Priscila Vieira | L25: 711.805.999-42 | M25: 7211 | N25: 45129 | O25: Encerrado: pontos de 2023 já teriam vencido (regra de 12 meses) | Q25: Fernanda | R25: =IF(Q25="","",COUNTIFS(Resgates!$I$2:$I$597,Q25,Resgates!$A$2:$A$597,">="&'Regras e Parâmetros'!$A$12)) -> 8 | S25: =IF(Q25="","",COUNTIFS(Resgates!$I$2:$I$597,Q25,Resgates!$G$2:$G$597,">0")) -> 0 | T25: =IF(Q25="","",IF(R25=0,0,S25/R25)) -> 0 | U25: =IF(Q25="","",SUMIFS(Resgates!$G$2:$G$597,Resgates!$I$2:$I$597,Q25,Resgates!$G$2:$G$597,">0")) -> 0
H26: {=IF(NOT(ISNUMBER(A26)),"",IF(INDEX(Resgates!$B:$B,A26)<>"","CPF não está no cadastro",IF(ISNUMBER(SEARCH(" ",TRIM(C26))),IF(COUNTIF(Clientes!$A$2:$A$2396,TRIM(C26))>1,"Nome repetido no cadastro","Nome não encontrado no cadastro"),"Só o primeiro nome")))} | I26: {=IF(H26="","",IF(LEFT(INDEX(Resgates!$K:$K,A26),9)="Sugestão:",INDEX(Resgates!$K:$K,A26),IF(H26="Nome repetido no cadastro",_xlfn.TEXTJOIN(" / ",TRUE,_xlfn._xlws.FILTER(Clientes!$A$2:$A$2396&" – "&Clientes!$B$2:$B$2396&" (cadastro "&Clientes!$G$2:$G$2396&")",Clientes!$A$2:$A$2396=TRIM(C26))),IF(H26="Só o primeiro nome",COUNTIF(Clientes!$A$2:$A$2396,TRIM(C26)&" *")&" clientes com esse primeiro nome – confirmar com a loja/atendente",IF(H26="CPF não está no cadastro","Conferir se o CPF foi digitado errado ou se o cliente não foi cadastrado","Confirmar com a loja")))))} | J26: =IF(H26="Só o primeiro nome","Buscar em vendas e atendimentos: primeiro nome """&TRIM(C26)&""" + loja "&F26&" + dia "&TEXT(DAY(B26),"00")&"/"&TEXT(MONTH(B26),"00")&"/"&YEAR(B26)&" (ver aba Varredura)","") | K26: Marina Peixoto | L26: 696.583.178-20 | M26: 2632 | N26: 45242 | O26: Provavelmente migrou com outro CPF: 170.196.150-40 ou 545.192.880-02 | Q26: Gustavo | R26: =IF(Q26="","",COUNTIFS(Resgates!$I$2:$I$597,Q26,Resgates!$A$2:$A$597,">="&'Regras e Parâmetros'!$A$12)) -> 4 | S26: =IF(Q26="","",COUNTIFS(Resgates!$I$2:$I$597,Q26,Resgates!$G$2:$G$597,">0")) -> 0 | T26: =IF(Q26="","",IF(R26=0,0,S26/R26)) -> 0 | U26: =IF(Q26="","",SUMIFS(Resgates!$G$2:$G$597,Resgates!$I$2:$I$597,Q26,Resgates!$G$2:$G$597,">0")) -> 0
H27: {=IF(NOT(ISNUMBER(A27)),"",IF(INDEX(Resgates!$B:$B,A27)<>"","CPF não está no cadastro",IF(ISNUMBER(SEARCH(" ",TRIM(C27))),IF(COUNTIF(Clientes!$A$2:$A$2396,TRIM(C27))>1,"Nome repetido no cadastro","Nome não encontrado no cadastro"),"Só o primeiro nome")))} | I27: {=IF(H27="","",IF(LEFT(INDEX(Resgates!$K:$K,A27),9)="Sugestão:",INDEX(Resgates!$K:$K,A27),IF(H27="Nome repetido no cadastro",_xlfn.TEXTJOIN(" / ",TRUE,_xlfn._xlws.FILTER(Clientes!$A$2:$A$2396&" – "&Clientes!$B$2:$B$2396&" (cadastro "&Clientes!$G$2:$G$2396&")",Clientes!$A$2:$A$2396=TRIM(C27))),IF(H27="Só o primeiro nome",COUNTIF(Clientes!$A$2:$A$2396,TRIM(C27)&" *")&" clientes com esse primeiro nome – confirmar com a loja/atendente",IF(H27="CPF não está no cadastro","Conferir se o CPF foi digitado errado ou se o cliente não foi cadastrado","Confirmar com a loja")))))} | J27: =IF(H27="Só o primeiro nome","Buscar em vendas e atendimentos: primeiro nome """&TRIM(C27)&""" + loja "&F27&" + dia "&TEXT(DAY(B27),"00")&"/"&TEXT(MONTH(B27),"00")&"/"&YEAR(B27)&" (ver aba Varredura)","") | K27: Priscila Correia Almeida | L27: 689.794.108-59 | M27: 335 | N27: 45134 | O27: Encerrado: pontos de 2023 já teriam vencido (regra de 12 meses) | Q27: Jéssica | R27: =IF(Q27="","",COUNTIFS(Resgates!$I$2:$I$597,Q27,Resgates!$A$2:$A$597,">="&'Regras e Parâmetros'!$A$12)) -> 7 | S27: =IF(Q27="","",COUNTIFS(Resgates!$I$2:$I$597,Q27,Resgates!$G$2:$G$597,">0")) -> 0 | T27: =IF(Q27="","",IF(R27=0,0,S27/R27)) -> 0 | U27: =IF(Q27="","",SUMIFS(Resgates!$G$2:$G$597,Resgates!$I$2:$I$597,Q27,Resgates!$G$2:$G$597,">0")) -> 0
H28: {=IF(NOT(ISNUMBER(A28)),"",IF(INDEX(Resgates!$B:$B,A28)<>"","CPF não está no cadastro",IF(ISNUMBER(SEARCH(" ",TRIM(C28))),IF(COUNTIF(Clientes!$A$2:$A$2396,TRIM(C28))>1,"Nome repetido no cadastro","Nome não encontrado no cadastro"),"Só o primeiro nome")))} | I28: {=IF(H28="","",IF(LEFT(INDEX(Resgates!$K:$K,A28),9)="Sugestão:",INDEX(Resgates!$K:$K,A28),IF(H28="Nome repetido no cadastro",_xlfn.TEXTJOIN(" / ",TRUE,_xlfn._xlws.FILTER(Clientes!$A$2:$A$2396&" – "&Clientes!$B$2:$B$2396&" (cadastro "&Clientes!$G$2:$G$2396&")",Clientes!$A$2:$A$2396=TRIM(C28))),IF(H28="Só o primeiro nome",COUNTIF(Clientes!$A$2:$A$2396,TRIM(C28)&" *")&" clientes com esse primeiro nome – confirmar com a loja/atendente",IF(H28="CPF não está no cadastro","Conferir se o CPF foi digitado errado ou se o cliente não foi cadastrado","Confirmar com a loja")))))} | J28: =IF(H28="Só o primeiro nome","Buscar em vendas e atendimentos: primeiro nome """&TRIM(C28)&""" + loja "&F28&" + dia "&TEXT(DAY(B28),"00")&"/"&TEXT(MONTH(B28),"00")&"/"&YEAR(B28)&" (ver aba Varredura)","") | K28: Yasmin Barros Marques | L28: 408.083.222-22 | M28: 5530 | N28: 45224 | O28: Encerrado: pontos de 2023 já teriam vencido (regra de 12 meses) | Q28: Larissa | R28: =IF(Q28="","",COUNTIFS(Resgates!$I$2:$I$597,Q28,Resgates!$A$2:$A$597,">="&'Regras e Parâmetros'!$A$12)) -> 5 | S28: =IF(Q28="","",COUNTIFS(Resgates!$I$2:$I$597,Q28,Resgates!$G$2:$G$597,">0")) -> 0 | T28: =IF(Q28="","",IF(R28=0,0,S28/R28)) -> 0 | U28: =IF(Q28="","",SUMIFS(Resgates!$G$2:$G$597,Resgates!$I$2:$I$597,Q28,Resgates!$G$2:$G$597,">0")) -> 0
H29: {=IF(NOT(ISNUMBER(A29)),"",IF(INDEX(Resgates!$B:$B,A29)<>"","CPF não está no cadastro",IF(ISNUMBER(SEARCH(" ",TRIM(C29))),IF(COUNTIF(Clientes!$A$2:$A$2396,TRIM(C29))>1,"Nome repetido no cadastro","Nome não encontrado no cadastro"),"Só o primeiro nome")))} | I29: {=IF(H29="","",IF(LEFT(INDEX(Resgates!$K:$K,A29),9)="Sugestão:",INDEX(Resgates!$K:$K,A29),IF(H29="Nome repetido no cadastro",_xlfn.TEXTJOIN(" / ",TRUE,_xlfn._xlws.FILTER(Clientes!$A$2:$A$2396&" – "&Clientes!$B$2:$B$2396&" (cadastro "&Clientes!$G$2:$G$2396&")",Clientes!$A$2:$A$2396=TRIM(C29))),IF(H29="Só o primeiro nome",COUNTIF(Clientes!$A$2:$A$2396,TRIM(C29)&" *")&" clientes com esse primeiro nome – confirmar com a loja/atendente",IF(H29="CPF não está no cadastro","Conferir se o CPF foi digitado errado ou se o cliente não foi cadastrado","Confirmar com a loja")))))} | J29: =IF(H29="Só o primeiro nome","Buscar em vendas e atendimentos: primeiro nome """&TRIM(C29)&""" + loja "&F29&" + dia "&TEXT(DAY(B29),"00")&"/"&TEXT(MONTH(B29),"00")&"/"&YEAR(B29)&" (ver aba Varredura)","") | K29: Felipe Barbosa Machado | L29: 476.728.859-28 | M29: 6798 | N29: 45019 | O29: Provavelmente migrou com outro CPF: 476.728.859-26 | Q29: Patrícia | R29: =IF(Q29="","",COUNTIFS(Resgates!$I$2:$I$597,Q29,Resgates!$A$2:$A$597,">="&'Regras e Parâmetros'!$A$12)) -> 9 | S29: =IF(Q29="","",COUNTIFS(Resgates!$I$2:$I$597,Q29,Resgates!$G$2:$G$597,">0")) -> 0 | T29: =IF(Q29="","",IF(R29=0,0,S29/R29)) -> 0 | U29: =IF(Q29="","",SUMIFS(Resgates!$G$2:$G$597,Resgates!$I$2:$I$597,Q29,Resgates!$G$2:$G$597,">0")) -> 0
H30: {=IF(NOT(ISNUMBER(A30)),"",IF(INDEX(Resgates!$B:$B,A30)<>"","CPF não está no cadastro",IF(ISNUMBER(SEARCH(" ",TRIM(C30))),IF(COUNTIF(Clientes!$A$2:$A$2396,TRIM(C30))>1,"Nome repetido no cadastro","Nome não encontrado no cadastro"),"Só o primeiro nome")))} | I30: {=IF(H30="","",IF(LEFT(INDEX(Resgates!$K:$K,A30),9)="Sugestão:",INDEX(Resgates!$K:$K,A30),IF(H30="Nome repetido no cadastro",_xlfn.TEXTJOIN(" / ",TRUE,_xlfn._xlws.FILTER(Clientes!$A$2:$A$2396&" – "&Clientes!$B$2:$B$2396&" (cadastro "&Clientes!$G$2:$G$2396&")",Clientes!$A$2:$A$2396=TRIM(C30))),IF(H30="Só o primeiro nome",COUNTIF(Clientes!$A$2:$A$2396,TRIM(C30)&" *")&" clientes com esse primeiro nome – confirmar com a loja/atendente",IF(H30="CPF não está no cadastro","Conferir se o CPF foi digitado errado ou se o cliente não foi cadastrado","Confirmar com a loja")))))} | J30: =IF(H30="Só o primeiro nome","Buscar em vendas e atendimentos: primeiro nome """&TRIM(C30)&""" + loja "&F30&" + dia "&TEXT(DAY(B30),"00")&"/"&TEXT(MONTH(B30),"00")&"/"&YEAR(B30)&" (ver aba Varredura)","") | K30: Larissa Araújo | L30: 141.638.864-86 | M30: 665 | N30: 45143 | O30: Encerrado: pontos de 2023 já teriam vencido (regra de 12 meses) | Q30: Rafa | R30: =IF(Q30="","",COUNTIFS(Resgates!$I$2:$I$597,Q30,Resgates!$A$2:$A$597,">="&'Regras e Parâmetros'!$A$12)) -> 5 | S30: =IF(Q30="","",COUNTIFS(Resgates!$I$2:$I$597,Q30,Resgates!$G$2:$G$597,">0")) -> 0 | T30: =IF(Q30="","",IF(R30=0,0,S30/R30)) -> 0 | U30: =IF(Q30="","",SUMIFS(Resgates!$G$2:$G$597,Resgates!$I$2:$I$597,Q30,Resgates!$G$2:$G$597,">0")) -> 0
H31: {=IF(NOT(ISNUMBER(A31)),"",IF(INDEX(Resgates!$B:$B,A31)<>"","CPF não está no cadastro",IF(ISNUMBER(SEARCH(" ",TRIM(C31))),IF(COUNTIF(Clientes!$A$2:$A$2396,TRIM(C31))>1,"Nome repetido no cadastro","Nome não encontrado no cadastro"),"Só o primeiro nome")))} | I31: {=IF(H31="","",IF(LEFT(INDEX(Resgates!$K:$K,A31),9)="Sugestão:",INDEX(Resgates!$K:$K,A31),IF(H31="Nome repetido no cadastro",_xlfn.TEXTJOIN(" / ",TRUE,_xlfn._xlws.FILTER(Clientes!$A$2:$A$2396&" – "&Clientes!$B$2:$B$2396&" (cadastro "&Clientes!$G$2:$G$2396&")",Clientes!$A$2:$A$2396=TRIM(C31))),IF(H31="Só o primeiro nome",COUNTIF(Clientes!$A$2:$A$2396,TRIM(C31)&" *")&" clientes com esse primeiro nome – confirmar com a loja/atendente",IF(H31="CPF não está no cadastro","Conferir se o CPF foi digitado errado ou se o cliente não foi cadastrado","Confirmar com a loja")))))} | J31: =IF(H31="Só o primeiro nome","Buscar em vendas e atendimentos: primeiro nome """&TRIM(C31)&""" + loja "&F31&" + dia "&TEXT(DAY(B31),"00")&"/"&TEXT(MONTH(B31),"00")&"/"&YEAR(B31)&" (ver aba Varredura)","") | K31: Eduarda Silva | L31: 733.569.983-58 | M31: 1968 | N31: 45285 | O31: Encerrado: pontos de 2023 já teriam vencido (regra de 12 meses) | Q31: Rafael | R31: =IF(Q31="","",COUNTIFS(Resgates!$I$2:$I$597,Q31,Resgates!$A$2:$A$597,">="&'Regras e Parâmetros'!$A$12)) -> 1 | S31: =IF(Q31="","",COUNTIFS(Resgates!$I$2:$I$597,Q31,Resgates!$G$2:$G$597,">0")) -> 0 | T31: =IF(Q31="","",IF(R31=0,0,S31/R31)) -> 0 | U31: =IF(Q31="","",SUMIFS(Resgates!$G$2:$G$597,Resgates!$I$2:$I$597,Q31,Resgates!$G$2:$G$597,">0")) -> 0
... H33: {=IF(NOT(ISNUMBER(A33)),"",IF(INDEX(Resgates!$B:$B,A33)<>"","CPF não está no cadastro",IF(ISNUMBER(SEARCH(" ",TRIM(C33))),IF(COUNTIF(Clientes!$A$2:$A$2396,TRIM(C33))>1,"Nome repetido no cadastro","Nome não encontrado no cadastro"),"Só o primeiro nome")))} | I33: {=IF(H33="","",IF(LEFT(INDEX(Resgates!$K:$K,A33),9)="Sugestão:",INDEX(Resgates!$K:$K,A33),IF(H33="Nome repetido no cadastro",_xlfn.TEXTJOIN(" / ",TRUE,_xlfn._xlws.FILTER(Clientes!$A$2:$A$2396&" – "&Clientes!$B$2:$B$2396&" (cadastro "&Clientes!$G$2:$G$2396&")",Clientes!$A$2:$A$2396=TRIM(C33))),IF(H33="Só o primeiro nome",COUNTIF(Clientes!$A$2:$A$2396,TRIM(C33)&" *")&" clientes com esse primeiro nome – confirmar com a loja/atendente",IF(H33="CPF não está no cadastro","Conferir se o CPF foi digitado errado ou se o cliente não foi cadastrado","Confirmar com a loja")))))} | J33: =IF(H33="Só o primeiro nome","Buscar em vendas e atendimentos: primeiro nome """&TRIM(C33)&""" + loja "&F33&" + dia "&TEXT(DAY(B33),"00")&"/"&TEXT(MONTH(B33),"00")&"/"&YEAR(B33)&" (ver aba Varredura)","") | K33: Eduardo Nunes | L33: 548.079.520-13 | M33: 3618 | N33: 45022 | O33: Encerrado: pontos de 2023 já teriam vencido (regra de 12 meses) | Q33: Thiago | R33: =IF(Q33="","",COUNTIFS(Resgates!$I$2:$I$597,Q33,Resgates!$A$2:$A$597,">="&'Regras e Parâmetros'!$A$12)) -> 10 | S33: =IF(Q33="","",COUNTIFS(Resgates!$I$2:$I$597,Q33,Resgates!$G$2:$G$597,">0")) -> 0 | T33: =IF(Q33="","",IF(R33=0,0,S33/R33)) -> 0 | U33: =IF(Q33="","",SUMIFS(Resgates!$G$2:$G$597,Resgates!$I$2:$I$597,Q33,Resgates!$G$2:$G$597,">0")) -> 0
H34: {=IF(NOT(ISNUMBER(A34)),"",IF(INDEX(Resgates!$B:$B,A34)<>"","CPF não está no cadastro",IF(ISNUMBER(SEARCH(" ",TRIM(C34))),IF(COUNTIF(Clientes!$A$2:$A$2396,TRIM(C34))>1,"Nome repetido no cadastro","Nome não encontrado no cadastro"),"Só o primeiro nome")))} | I34: {=IF(H34="","",IF(LEFT(INDEX(Resgates!$K:$K,A34),9)="Sugestão:",INDEX(Resgates!$K:$K,A34),IF(H34="Nome repetido no cadastro",_xlfn.TEXTJOIN(" / ",TRUE,_xlfn._xlws.FILTER(Clientes!$A$2:$A$2396&" – "&Clientes!$B$2:$B$2396&" (cadastro "&Clientes!$G$2:$G$2396&")",Clientes!$A$2:$A$2396=TRIM(C34))),IF(H34="Só o primeiro nome",COUNTIF(Clientes!$A$2:$A$2396,TRIM(C34)&" *")&" clientes com esse primeiro nome – confirmar com a loja/atendente",IF(H34="CPF não está no cadastro","Conferir se o CPF foi digitado errado ou se o cliente não foi cadastrado","Confirmar com a loja")))))} | J34: =IF(H34="Só o primeiro nome","Buscar em vendas e atendimentos: primeiro nome """&TRIM(C34)&""" + loja "&F34&" + dia "&TEXT(DAY(B34),"00")&"/"&TEXT(MONTH(B34),"00")&"/"&YEAR(B34)&" (ver aba Varredura)","") | K34: Rebeca Campos Marques | L34: 456.182.168-68 | M34: 5810 | N34: 45152 | O34: Encerrado: pontos de 2023 já teriam vencido (regra de 12 meses) | R34: =IF(Q34="","",COUNTIFS(Resgates!$I$2:$I$597,Q34,Resgates!$A$2:$A$597,">="&'Regras e Parâmetros'!$A$12)) | S34: =IF(Q34="","",COUNTIFS(Resgates!$I$2:$I$597,Q34,Resgates!$G$2:$G$597,">0")) | T34: =IF(Q34="","",IF(R34=0,0,S34/R34)) | U34: =IF(Q34="","",SUMIFS(Resgates!$G$2:$G$597,Resgates!$I$2:$I$597,Q34,Resgates!$G$2:$G$597,">0"))
H35: {=IF(NOT(ISNUMBER(A35)),"",IF(INDEX(Resgates!$B:$B,A35)<>"","CPF não está no cadastro",IF(ISNUMBER(SEARCH(" ",TRIM(C35))),IF(COUNTIF(Clientes!$A$2:$A$2396,TRIM(C35))>1,"Nome repetido no cadastro","Nome não encontrado no cadastro"),"Só o primeiro nome")))} | I35: {=IF(H35="","",IF(LEFT(INDEX(Resgates!$K:$K,A35),9)="Sugestão:",INDEX(Resgates!$K:$K,A35),IF(H35="Nome repetido no cadastro",_xlfn.TEXTJOIN(" / ",TRUE,_xlfn._xlws.FILTER(Clientes!$A$2:$A$2396&" – "&Clientes!$B$2:$B$2396&" (cadastro "&Clientes!$G$2:$G$2396&")",Clientes!$A$2:$A$2396=TRIM(C35))),IF(H35="Só o primeiro nome",COUNTIF(Clientes!$A$2:$A$2396,TRIM(C35)&" *")&" clientes com esse primeiro nome – confirmar com a loja/atendente",IF(H35="CPF não está no cadastro","Conferir se o CPF foi digitado errado ou se o cliente não foi cadastrado","Confirmar com a loja")))))} | J35: =IF(H35="Só o primeiro nome","Buscar em vendas e atendimentos: primeiro nome """&TRIM(C35)&""" + loja "&F35&" + dia "&TEXT(DAY(B35),"00")&"/"&TEXT(MONTH(B35),"00")&"/"&YEAR(B35)&" (ver aba Varredura)","") | K35: Wesley Vieira Dias | L35: 790.119.061-28 | M35: 3264 | N35: 45219 | O35: Encerrado: pontos de 2023 já teriam vencido (regra de 12 meses) | R35: =IF(Q35="","",COUNTIFS(Resgates!$I$2:$I$597,Q35,Resgates!$A$2:$A$597,">="&'Regras e Parâmetros'!$A$12)) | S35: =IF(Q35="","",COUNTIFS(Resgates!$I$2:$I$597,Q35,Resgates!$G$2:$G$597,">0")) | T35: =IF(Q35="","",IF(R35=0,0,S35/R35)) | U35: =IF(Q35="","",SUMIFS(Resgates!$G$2:$G$597,Resgates!$I$2:$I$597,Q35,Resgates!$G$2:$G$597,">0"))
H36: {=IF(NOT(ISNUMBER(A36)),"",IF(INDEX(Resgates!$B:$B,A36)<>"","CPF não está no cadastro",IF(ISNUMBER(SEARCH(" ",TRIM(C36))),IF(COUNTIF(Clientes!$A$2:$A$2396,TRIM(C36))>1,"Nome repetido no cadastro","Nome não encontrado no cadastro"),"Só o primeiro nome")))} | I36: {=IF(H36="","",IF(LEFT(INDEX(Resgates!$K:$K,A36),9)="Sugestão:",INDEX(Resgates!$K:$K,A36),IF(H36="Nome repetido no cadastro",_xlfn.TEXTJOIN(" / ",TRUE,_xlfn._xlws.FILTER(Clientes!$A$2:$A$2396&" – "&Clientes!$B$2:$B$2396&" (cadastro "&Clientes!$G$2:$G$2396&")",Clientes!$A$2:$A$2396=TRIM(C36))),IF(H36="Só o primeiro nome",COUNTIF(Clientes!$A$2:$A$2396,TRIM(C36)&" *")&" clientes com esse primeiro nome – confirmar com a loja/atendente",IF(H36="CPF não está no cadastro","Conferir se o CPF foi digitado errado ou se o cliente não foi cadastrado","Confirmar com a loja")))))} | J36: =IF(H36="Só o primeiro nome","Buscar em vendas e atendimentos: primeiro nome """&TRIM(C36)&""" + loja "&F36&" + dia "&TEXT(DAY(B36),"00")&"/"&TEXT(MONTH(B36),"00")&"/"&YEAR(B36)&" (ver aba Varredura)","") | K36: Tainá Vieira | L36: 927.677.348-76 | M36: 6519 | N36: 45185 | O36: Encerrado: pontos de 2023 já teriam vencido (regra de 12 meses) | R36: =IF(Q36="","",COUNTIFS(Resgates!$I$2:$I$597,Q36,Resgates!$A$2:$A$597,">="&'Regras e Parâmetros'!$A$12)) | S36: =IF(Q36="","",COUNTIFS(Resgates!$I$2:$I$597,Q36,Resgates!$G$2:$G$597,">0")) | T36: =IF(Q36="","",IF(R36=0,0,S36/R36)) | U36: =IF(Q36="","",SUMIFS(Resgates!$G$2:$G$597,Resgates!$I$2:$I$597,Q36,Resgates!$G$2:$G$597,">0"))
H37: {=IF(NOT(ISNUMBER(A37)),"",IF(INDEX(Resgates!$B:$B,A37)<>"","CPF não está no cadastro",IF(ISNUMBER(SEARCH(" ",TRIM(C37))),IF(COUNTIF(Clientes!$A$2:$A$2396,TRIM(C37))>1,"Nome repetido no cadastro","Nome não encontrado no cadastro"),"Só o primeiro nome")))} | I37: {=IF(H37="","",IF(LEFT(INDEX(Resgates!$K:$K,A37),9)="Sugestão:",INDEX(Resgates!$K:$K,A37),IF(H37="Nome repetido no cadastro",_xlfn.TEXTJOIN(" / ",TRUE,_xlfn._xlws.FILTER(Clientes!$A$2:$A$2396&" – "&Clientes!$B$2:$B$2396&" (cadastro "&Clientes!$G$2:$G$2396&")",Clientes!$A$2:$A$2396=TRIM(C37))),IF(H37="Só o primeiro nome",COUNTIF(Clientes!$A$2:$A$2396,TRIM(C37)&" *")&" clientes com esse primeiro nome – confirmar com a loja/atendente",IF(H37="CPF não está no cadastro","Conferir se o CPF foi digitado errado ou se o cliente não foi cadastrado","Confirmar com a loja")))))} | J37: =IF(H37="Só o primeiro nome","Buscar em vendas e atendimentos: primeiro nome """&TRIM(C37)&""" + loja "&F37&" + dia "&TEXT(DAY(B37),"00")&"/"&TEXT(MONTH(B37),"00")&"/"&YEAR(B37)&" (ver aba Varredura)","") | K37: Luana Nogueira | L37: 952.280.885-71 | M37: 1551 | N37: 45055 | O37: Encerrado: pontos de 2023 já teriam vencido (regra de 12 meses) | R37: =IF(Q37="","",COUNTIFS(Resgates!$I$2:$I$597,Q37,Resgates!$A$2:$A$597,">="&'Regras e Parâmetros'!$A$12)) | S37: =IF(Q37="","",COUNTIFS(Resgates!$I$2:$I$597,Q37,Resgates!$G$2:$G$597,">0")) | T37: =IF(Q37="","",IF(R37=0,0,S37/R37)) | U37: =IF(Q37="","",SUMIFS(Resgates!$G$2:$G$597,Resgates!$I$2:$I$597,Q37,Resgates!$G$2:$G$597,">0"))
H38: {=IF(NOT(ISNUMBER(A38)),"",IF(INDEX(Resgates!$B:$B,A38)<>"","CPF não está no cadastro",IF(ISNUMBER(SEARCH(" ",TRIM(C38))),IF(COUNTIF(Clientes!$A$2:$A$2396,TRIM(C38))>1,"Nome repetido no cadastro","Nome não encontrado no cadastro"),"Só o primeiro nome")))} | I38: {=IF(H38="","",IF(LEFT(INDEX(Resgates!$K:$K,A38),9)="Sugestão:",INDEX(Resgates!$K:$K,A38),IF(H38="Nome repetido no cadastro",_xlfn.TEXTJOIN(" / ",TRUE,_xlfn._xlws.FILTER(Clientes!$A$2:$A$2396&" – "&Clientes!$B$2:$B$2396&" (cadastro "&Clientes!$G$2:$G$2396&")",Clientes!$A$2:$A$2396=TRIM(C38))),IF(H38="Só o primeiro nome",COUNTIF(Clientes!$A$2:$A$2396,TRIM(C38)&" *")&" clientes com esse primeiro nome – confirmar com a loja/atendente",IF(H38="CPF não está no cadastro","Conferir se o CPF foi digitado errado ou se o cliente não foi cadastrado","Confirmar com a loja")))))} | J38: =IF(H38="Só o primeiro nome","Buscar em vendas e atendimentos: primeiro nome """&TRIM(C38)&""" + loja "&F38&" + dia "&TEXT(DAY(B38),"00")&"/"&TEXT(MONTH(B38),"00")&"/"&YEAR(B38)&" (ver aba Varredura)","") | K38: Heloísa Carvalho | L38: 079.844.488-68 | M38: 2289 | N38: 45271 | O38: Provavelmente migrou com outro CPF: 085.153.849-57 | R38: =IF(Q38="","",COUNTIFS(Resgates!$I$2:$I$597,Q38,Resgates!$A$2:$A$597,">="&'Regras e Parâmetros'!$A$12)) | S38: =IF(Q38="","",COUNTIFS(Resgates!$I$2:$I$597,Q38,Resgates!$G$2:$G$597,">0")) | T38: =IF(Q38="","",IF(R38=0,0,S38/R38)) | U38: =IF(Q38="","",SUMIFS(Resgates!$G$2:$G$597,Resgates!$I$2:$I$597,Q38,Resgates!$G$2:$G$597,">0"))
H39: {=IF(NOT(ISNUMBER(A39)),"",IF(INDEX(Resgates!$B:$B,A39)<>"","CPF não está no cadastro",IF(ISNUMBER(SEARCH(" ",TRIM(C39))),IF(COUNTIF(Clientes!$A$2:$A$2396,TRIM(C39))>1,"Nome repetido no cadastro","Nome não encontrado no cadastro"),"Só o primeiro nome")))} | I39: {=IF(H39="","",IF(LEFT(INDEX(Resgates!$K:$K,A39),9)="Sugestão:",INDEX(Resgates!$K:$K,A39),IF(H39="Nome repetido no cadastro",_xlfn.TEXTJOIN(" / ",TRUE,_xlfn._xlws.FILTER(Clientes!$A$2:$A$2396&" – "&Clientes!$B$2:$B$2396&" (cadastro "&Clientes!$G$2:$G$2396&")",Clientes!$A$2:$A$2396=TRIM(C39))),IF(H39="Só o primeiro nome",COUNTIF(Clientes!$A$2:$A$2396,TRIM(C39)&" *")&" clientes com esse primeiro nome – confirmar com a loja/atendente",IF(H39="CPF não está no cadastro","Conferir se o CPF foi digitado errado ou se o cliente não foi cadastrado","Confirmar com a loja")))))} | J39: =IF(H39="Só o primeiro nome","Buscar em vendas e atendimentos: primeiro nome """&TRIM(C39)&""" + loja "&F39&" + dia "&TEXT(DAY(B39),"00")&"/"&TEXT(MONTH(B39),"00")&"/"&YEAR(B39)&" (ver aba Varredura)","") | K39: Miguel Moreira | L39: 287.389.015-01 | M39: 5909 | N39: 45139 | O39: Encerrado: pontos de 2023 já teriam vencido (regra de 12 meses) | R39: =IF(Q39="","",COUNTIFS(Resgates!$I$2:$I$597,Q39,Resgates!$A$2:$A$597,">="&'Regras e Parâmetros'!$A$12)) | S39: =IF(Q39="","",COUNTIFS(Resgates!$I$2:$I$597,Q39,Resgates!$G$2:$G$597,">0")) | T39: =IF(Q39="","",IF(R39=0,0,S39/R39)) | U39: =IF(Q39="","",SUMIFS(Resgates!$G$2:$G$597,Resgates!$I$2:$I$597,Q39,Resgates!$G$2:$G$597,">0"))
H40: {=IF(NOT(ISNUMBER(A40)),"",IF(INDEX(Resgates!$B:$B,A40)<>"","CPF não está no cadastro",IF(ISNUMBER(SEARCH(" ",TRIM(C40))),IF(COUNTIF(Clientes!$A$2:$A$2396,TRIM(C40))>1,"Nome repetido no cadastro","Nome não encontrado no cadastro"),"Só o primeiro nome")))} | I40: {=IF(H40="","",IF(LEFT(INDEX(Resgates!$K:$K,A40),9)="Sugestão:",INDEX(Resgates!$K:$K,A40),IF(H40="Nome repetido no cadastro",_xlfn.TEXTJOIN(" / ",TRUE,_xlfn._xlws.FILTER(Clientes!$A$2:$A$2396&" – "&Clientes!$B$2:$B$2396&" (cadastro "&Clientes!$G$2:$G$2396&")",Clientes!$A$2:$A$2396=TRIM(C40))),IF(H40="Só o primeiro nome",COUNTIF(Clientes!$A$2:$A$2396,TRIM(C40)&" *")&" clientes com esse primeiro nome – confirmar com a loja/atendente",IF(H40="CPF não está no cadastro","Conferir se o CPF foi digitado errado ou se o cliente não foi cadastrado","Confirmar com a loja")))))} | J40: =IF(H40="Só o primeiro nome","Buscar em vendas e atendimentos: primeiro nome """&TRIM(C40)&""" + loja "&F40&" + dia "&TEXT(DAY(B40),"00")&"/"&TEXT(MONTH(B40),"00")&"/"&YEAR(B40)&" (ver aba Varredura)","") | K40: Murilo Santana | L40: 054.483.028-82 | M40: 660 | N40: 45249 | O40: Encerrado: pontos de 2023 já teriam vencido (regra de 12 meses) | R40: =IF(Q40="","",COUNTIFS(Resgates!$I$2:$I$597,Q40,Resgates!$A$2:$A$597,">="&'Regras e Parâmetros'!$A$12)) | S40: =IF(Q40="","",COUNTIFS(Resgates!$I$2:$I$597,Q40,Resgates!$G$2:$G$597,">0")) | T40: =IF(Q40="","",IF(R40=0,0,S40/R40)) | U40: =IF(Q40="","",SUMIFS(Resgates!$G$2:$G$597,Resgates!$I$2:$I$597,Q40,Resgates!$G$2:$G$597,">0"))
H41: {=IF(NOT(ISNUMBER(A41)),"",IF(INDEX(Resgates!$B:$B,A41)<>"","CPF não está no cadastro",IF(ISNUMBER(SEARCH(" ",TRIM(C41))),IF(COUNTIF(Clientes!$A$2:$A$2396,TRIM(C41))>1,"Nome repetido no cadastro","Nome não encontrado no cadastro"),"Só o primeiro nome")))} | I41: {=IF(H41="","",IF(LEFT(INDEX(Resgates!$K:$K,A41),9)="Sugestão:",INDEX(Resgates!$K:$K,A41),IF(H41="Nome repetido no cadastro",_xlfn.TEXTJOIN(" / ",TRUE,_xlfn._xlws.FILTER(Clientes!$A$2:$A$2396&" – "&Clientes!$B$2:$B$2396&" (cadastro "&Clientes!$G$2:$G$2396&")",Clientes!$A$2:$A$2396=TRIM(C41))),IF(H41="Só o primeiro nome",COUNTIF(Clientes!$A$2:$A$2396,TRIM(C41)&" *")&" clientes com esse primeiro nome – confirmar com a loja/atendente",IF(H41="CPF não está no cadastro","Conferir se o CPF foi digitado errado ou se o cliente não foi cadastrado","Confirmar com a loja")))))} | J41: =IF(H41="Só o primeiro nome","Buscar em vendas e atendimentos: primeiro nome """&TRIM(C41)&""" + loja "&F41&" + dia "&TEXT(DAY(B41),"00")&"/"&TEXT(MONTH(B41),"00")&"/"&YEAR(B41)&" (ver aba Varredura)","") | R41: =IF(Q41="","",COUNTIFS(Resgates!$I$2:$I$597,Q41,Resgates!$A$2:$A$597,">="&'Regras e Parâmetros'!$A$12)) | S41: =IF(Q41="","",COUNTIFS(Resgates!$I$2:$I$597,Q41,Resgates!$G$2:$G$597,">0")) | T41: =IF(Q41="","",IF(R41=0,0,S41/R41)) | U41: =IF(Q41="","",SUMIFS(Resgates!$G$2:$G$597,Resgates!$I$2:$I$597,Q41,Resgates!$G$2:$G$597,">0"))
H42: {=IF(NOT(ISNUMBER(A42)),"",IF(INDEX(Resgates!$B:$B,A42)<>"","CPF não está no cadastro",IF(ISNUMBER(SEARCH(" ",TRIM(C42))),IF(COUNTIF(Clientes!$A$2:$A$2396,TRIM(C42))>1,"Nome repetido no cadastro","Nome não encontrado no cadastro"),"Só o primeiro nome")))} | I42: {=IF(H42="","",IF(LEFT(INDEX(Resgates!$K:$K,A42),9)="Sugestão:",INDEX(Resgates!$K:$K,A42),IF(H42="Nome repetido no cadastro",_xlfn.TEXTJOIN(" / ",TRUE,_xlfn._xlws.FILTER(Clientes!$A$2:$A$2396&" – "&Clientes!$B$2:$B$2396&" (cadastro "&Clientes!$G$2:$G$2396&")",Clientes!$A$2:$A$2396=TRIM(C42))),IF(H42="Só o primeiro nome",COUNTIF(Clientes!$A$2:$A$2396,TRIM(C42)&" *")&" clientes com esse primeiro nome – confirmar com a loja/atendente",IF(H42="CPF não está no cadastro","Conferir se o CPF foi digitado errado ou se o cliente não foi cadastrado","Confirmar com a loja")))))} | J42: =IF(H42="Só o primeiro nome","Buscar em vendas e atendimentos: primeiro nome """&TRIM(C42)&""" + loja "&F42&" + dia "&TEXT(DAY(B42),"00")&"/"&TEXT(MONTH(B42),"00")&"/"&YEAR(B42)&" (ver aba Varredura)","") | R42: =IF(Q42="","",COUNTIFS(Resgates!$I$2:$I$597,Q42,Resgates!$A$2:$A$597,">="&'Regras e Parâmetros'!$A$12)) | S42: =IF(Q42="","",COUNTIFS(Resgates!$I$2:$I$597,Q42,Resgates!$G$2:$G$597,">0")) | T42: =IF(Q42="","",IF(R42=0,0,S42/R42)) | U42: =IF(Q42="","",SUMIFS(Resgates!$G$2:$G$597,Resgates!$I$2:$I$597,Q42,Resgates!$G$2:$G$597,">0"))
H43: {=IF(NOT(ISNUMBER(A43)),"",IF(INDEX(Resgates!$B:$B,A43)<>"","CPF não está no cadastro",IF(ISNUMBER(SEARCH(" ",TRIM(C43))),IF(COUNTIF(Clientes!$A$2:$A$2396,TRIM(C43))>1,"Nome repetido no cadastro","Nome não encontrado no cadastro"),"Só o primeiro nome")))} | I43: {=IF(H43="","",IF(LEFT(INDEX(Resgates!$K:$K,A43),9)="Sugestão:",INDEX(Resgates!$K:$K,A43),IF(H43="Nome repetido no cadastro",_xlfn.TEXTJOIN(" / ",TRUE,_xlfn._xlws.FILTER(Clientes!$A$2:$A$2396&" – "&Clientes!$B$2:$B$2396&" (cadastro "&Clientes!$G$2:$G$2396&")",Clientes!$A$2:$A$2396=TRIM(C43))),IF(H43="Só o primeiro nome",COUNTIF(Clientes!$A$2:$A$2396,TRIM(C43)&" *")&" clientes com esse primeiro nome – confirmar com a loja/atendente",IF(H43="CPF não está no cadastro","Conferir se o CPF foi digitado errado ou se o cliente não foi cadastrado","Confirmar com a loja")))))} | J43: =IF(H43="Só o primeiro nome","Buscar em vendas e atendimentos: primeiro nome """&TRIM(C43)&""" + loja "&F43&" + dia "&TEXT(DAY(B43),"00")&"/"&TEXT(MONTH(B43),"00")&"/"&YEAR(B43)&" (ver aba Varredura)","") | R43: =IF(Q43="","",COUNTIFS(Resgates!$I$2:$I$597,Q43,Resgates!$A$2:$A$597,">="&'Regras e Parâmetros'!$A$12)) | S43: =IF(Q43="","",COUNTIFS(Resgates!$I$2:$I$597,Q43,Resgates!$G$2:$G$597,">0")) | T43: =IF(Q43="","",IF(R43=0,0,S43/R43)) | U43: =IF(Q43="","",SUMIFS(Resgates!$G$2:$G$597,Resgates!$I$2:$I$597,Q43,Resgates!$G$2:$G$597,">0"))
H44: {=IF(NOT(ISNUMBER(A44)),"",IF(INDEX(Resgates!$B:$B,A44)<>"","CPF não está no cadastro",IF(ISNUMBER(SEARCH(" ",TRIM(C44))),IF(COUNTIF(Clientes!$A$2:$A$2396,TRIM(C44))>1,"Nome repetido no cadastro","Nome não encontrado no cadastro"),"Só o primeiro nome")))} | I44: {=IF(H44="","",IF(LEFT(INDEX(Resgates!$K:$K,A44),9)="Sugestão:",INDEX(Resgates!$K:$K,A44),IF(H44="Nome repetido no cadastro",_xlfn.TEXTJOIN(" / ",TRUE,_xlfn._xlws.FILTER(Clientes!$A$2:$A$2396&" – "&Clientes!$B$2:$B$2396&" (cadastro "&Clientes!$G$2:$G$2396&")",Clientes!$A$2:$A$2396=TRIM(C44))),IF(H44="Só o primeiro nome",COUNTIF(Clientes!$A$2:$A$2396,TRIM(C44)&" *")&" clientes com esse primeiro nome – confirmar com a loja/atendente",IF(H44="CPF não está no cadastro","Conferir se o CPF foi digitado errado ou se o cliente não foi cadastrado","Confirmar com a loja")))))} | J44: =IF(H44="Só o primeiro nome","Buscar em vendas e atendimentos: primeiro nome """&TRIM(C44)&""" + loja "&F44&" + dia "&TEXT(DAY(B44),"00")&"/"&TEXT(MONTH(B44),"00")&"/"&YEAR(B44)&" (ver aba Varredura)","") | R44: =IF(Q44="","",COUNTIFS(Resgates!$I$2:$I$597,Q44,Resgates!$A$2:$A$597,">="&'Regras e Parâmetros'!$A$12)) | S44: =IF(Q44="","",COUNTIFS(Resgates!$I$2:$I$597,Q44,Resgates!$G$2:$G$597,">0")) | T44: =IF(Q44="","",IF(R44=0,0,S44/R44)) | U44: =IF(Q44="","",SUMIFS(Resgates!$G$2:$G$597,Resgates!$I$2:$I$597,Q44,Resgates!$G$2:$G$597,">0"))
H45: {=IF(NOT(ISNUMBER(A45)),"",IF(INDEX(Resgates!$B:$B,A45)<>"","CPF não está no cadastro",IF(ISNUMBER(SEARCH(" ",TRIM(C45))),IF(COUNTIF(Clientes!$A$2:$A$2396,TRIM(C45))>1,"Nome repetido no cadastro","Nome não encontrado no cadastro"),"Só o primeiro nome")))} | I45: {=IF(H45="","",IF(LEFT(INDEX(Resgates!$K:$K,A45),9)="Sugestão:",INDEX(Resgates!$K:$K,A45),IF(H45="Nome repetido no cadastro",_xlfn.TEXTJOIN(" / ",TRUE,_xlfn._xlws.FILTER(Clientes!$A$2:$A$2396&" – "&Clientes!$B$2:$B$2396&" (cadastro "&Clientes!$G$2:$G$2396&")",Clientes!$A$2:$A$2396=TRIM(C45))),IF(H45="Só o primeiro nome",COUNTIF(Clientes!$A$2:$A$2396,TRIM(C45)&" *")&" clientes com esse primeiro nome – confirmar com a loja/atendente",IF(H45="CPF não está no cadastro","Conferir se o CPF foi digitado errado ou se o cliente não foi cadastrado","Confirmar com a loja")))))} | J45: =IF(H45="Só o primeiro nome","Buscar em vendas e atendimentos: primeiro nome """&TRIM(C45)&""" + loja "&F45&" + dia "&TEXT(DAY(B45),"00")&"/"&TEXT(MONTH(B45),"00")&"/"&YEAR(B45)&" (ver aba Varredura)","") | R45: =IF(Q45="","",COUNTIFS(Resgates!$I$2:$I$597,Q45,Resgates!$A$2:$A$597,">="&'Regras e Parâmetros'!$A$12)) | S45: =IF(Q45="","",COUNTIFS(Resgates!$I$2:$I$597,Q45,Resgates!$G$2:$G$597,">0")) | T45: =IF(Q45="","",IF(R45=0,0,S45/R45)) | U45: =IF(Q45="","",SUMIFS(Resgates!$G$2:$G$597,Resgates!$I$2:$I$597,Q45,Resgates!$G$2:$G$597,">0"))
H46: {=IF(NOT(ISNUMBER(A46)),"",IF(INDEX(Resgates!$B:$B,A46)<>"","CPF não está no cadastro",IF(ISNUMBER(SEARCH(" ",TRIM(C46))),IF(COUNTIF(Clientes!$A$2:$A$2396,TRIM(C46))>1,"Nome repetido no cadastro","Nome não encontrado no cadastro"),"Só o primeiro nome")))} | I46: {=IF(H46="","",IF(LEFT(INDEX(Resgates!$K:$K,A46),9)="Sugestão:",INDEX(Resgates!$K:$K,A46),IF(H46="Nome repetido no cadastro",_xlfn.TEXTJOIN(" / ",TRUE,_xlfn._xlws.FILTER(Clientes!$A$2:$A$2396&" – "&Clientes!$B$2:$B$2396&" (cadastro "&Clientes!$G$2:$G$2396&")",Clientes!$A$2:$A$2396=TRIM(C46))),IF(H46="Só o primeiro nome",COUNTIF(Clientes!$A$2:$A$2396,TRIM(C46)&" *")&" clientes com esse primeiro nome – confirmar com a loja/atendente",IF(H46="CPF não está no cadastro","Conferir se o CPF foi digitado errado ou se o cliente não foi cadastrado","Confirmar com a loja")))))} | J46: =IF(H46="Só o primeiro nome","Buscar em vendas e atendimentos: primeiro nome """&TRIM(C46)&""" + loja "&F46&" + dia "&TEXT(DAY(B46),"00")&"/"&TEXT(MONTH(B46),"00")&"/"&YEAR(B46)&" (ver aba Varredura)","") | Q46: (atendente não anotado) | R46: =COUNTIFS(Resgates!$I$2:$I$597,"",Resgates!$A$2:$A$597,">="&'Regras e Parâmetros'!$A$12) -> 420 | S46: =COUNTIFS(Resgates!$I$2:$I$597,"",Resgates!$G$2:$G$597,">0") -> 420 | T46: =IF(R46=0,0,S46/R46) -> 1 | U46: =SUMIFS(Resgates!$G$2:$G$597,Resgates!$I$2:$I$597,"",Resgates!$G$2:$G$597,">0") -> 17795
H47: {=IF(NOT(ISNUMBER(A47)),"",IF(INDEX(Resgates!$B:$B,A47)<>"","CPF não está no cadastro",IF(ISNUMBER(SEARCH(" ",TRIM(C47))),IF(COUNTIF(Clientes!$A$2:$A$2396,TRIM(C47))>1,"Nome repetido no cadastro","Nome não encontrado no cadastro"),"Só o primeiro nome")))} | I47: {=IF(H47="","",IF(LEFT(INDEX(Resgates!$K:$K,A47),9)="Sugestão:",INDEX(Resgates!$K:$K,A47),IF(H47="Nome repetido no cadastro",_xlfn.TEXTJOIN(" / ",TRUE,_xlfn._xlws.FILTER(Clientes!$A$2:$A$2396&" – "&Clientes!$B$2:$B$2396&" (cadastro "&Clientes!$G$2:$G$2396&")",Clientes!$A$2:$A$2396=TRIM(C47))),IF(H47="Só o primeiro nome",COUNTIF(Clientes!$A$2:$A$2396,TRIM(C47)&" *")&" clientes com esse primeiro nome – confirmar com a loja/atendente",IF(H47="CPF não está no cadastro","Conferir se o CPF foi digitado errado ou se o cliente não foi cadastrado","Confirmar com a loja")))))} | J47: =IF(H47="Só o primeiro nome","Buscar em vendas e atendimentos: primeiro nome """&TRIM(C47)&""" + loja "&F47&" + dia "&TEXT(DAY(B47),"00")&"/"&TEXT(MONTH(B47),"00")&"/"&YEAR(B47)&" (ver aba Varredura)","")
H48: {=IF(NOT(ISNUMBER(A48)),"",IF(INDEX(Resgates!$B:$B,A48)<>"","CPF não está no cadastro",IF(ISNUMBER(SEARCH(" ",TRIM(C48))),IF(COUNTIF(Clientes!$A$2:$A$2396,TRIM(C48))>1,"Nome repetido no cadastro","Nome não encontrado no cadastro"),"Só o primeiro nome")))} | I48: {=IF(H48="","",IF(LEFT(INDEX(Resgates!$K:$K,A48),9)="Sugestão:",INDEX(Resgates!$K:$K,A48),IF(H48="Nome repetido no cadastro",_xlfn.TEXTJOIN(" / ",TRUE,_xlfn._xlws.FILTER(Clientes!$A$2:$A$2396&" – "&Clientes!$B$2:$B$2396&" (cadastro "&Clientes!$G$2:$G$2396&")",Clientes!$A$2:$A$2396=TRIM(C48))),IF(H48="Só o primeiro nome",COUNTIF(Clientes!$A$2:$A$2396,TRIM(C48)&" *")&" clientes com esse primeiro nome – confirmar com a loja/atendente",IF(H48="CPF não está no cadastro","Conferir se o CPF foi digitado errado ou se o cliente não foi cadastrado","Confirmar com a loja")))))} | J48: =IF(H48="Só o primeiro nome","Buscar em vendas e atendimentos: primeiro nome """&TRIM(C48)&""" + loja "&F48&" + dia "&TEXT(DAY(B48),"00")&"/"&TEXT(MONTH(B48),"00")&"/"&YEAR(B48)&" (ver aba Varredura)","")
H49: {=IF(NOT(ISNUMBER(A49)),"",IF(INDEX(Resgates!$B:$B,A49)<>"","CPF não está no cadastro",IF(ISNUMBER(SEARCH(" ",TRIM(C49))),IF(COUNTIF(Clientes!$A$2:$A$2396,TRIM(C49))>1,"Nome repetido no cadastro","Nome não encontrado no cadastro"),"Só o primeiro nome")))} | I49: {=IF(H49="","",IF(LEFT(INDEX(Resgates!$K:$K,A49),9)="Sugestão:",INDEX(Resgates!$K:$K,A49),IF(H49="Nome repetido no cadastro",_xlfn.TEXTJOIN(" / ",TRUE,_xlfn._xlws.FILTER(Clientes!$A$2:$A$2396&" – "&Clientes!$B$2:$B$2396&" (cadastro "&Clientes!$G$2:$G$2396&")",Clientes!$A$2:$A$2396=TRIM(C49))),IF(H49="Só o primeiro nome",COUNTIF(Clientes!$A$2:$A$2396,TRIM(C49)&" *")&" clientes com esse primeiro nome – confirmar com a loja/atendente",IF(H49="CPF não está no cadastro","Conferir se o CPF foi digitado errado ou se o cliente não foi cadastrado","Confirmar com a loja")))))} | J49: =IF(H49="Só o primeiro nome","Buscar em vendas e atendimentos: primeiro nome """&TRIM(C49)&""" + loja "&F49&" + dia "&TEXT(DAY(B49),"00")&"/"&TEXT(MONTH(B49),"00")&"/"&YEAR(B49)&" (ver aba Varredura)","")
H50: {=IF(NOT(ISNUMBER(A50)),"",IF(INDEX(Resgates!$B:$B,A50)<>"","CPF não está no cadastro",IF(ISNUMBER(SEARCH(" ",TRIM(C50))),IF(COUNTIF(Clientes!$A$2:$A$2396,TRIM(C50))>1,"Nome repetido no cadastro","Nome não encontrado no cadastro"),"Só o primeiro nome")))} | I50: {=IF(H50="","",IF(LEFT(INDEX(Resgates!$K:$K,A50),9)="Sugestão:",INDEX(Resgates!$K:$K,A50),IF(H50="Nome repetido no cadastro",_xlfn.TEXTJOIN(" / ",TRUE,_xlfn._xlws.FILTER(Clientes!$A$2:$A$2396&" – "&Clientes!$B$2:$B$2396&" (cadastro "&Clientes!$G$2:$G$2396&")",Clientes!$A$2:$A$2396=TRIM(C50))),IF(H50="Só o primeiro nome",COUNTIF(Clientes!$A$2:$A$2396,TRIM(C50)&" *")&" clientes com esse primeiro nome – confirmar com a loja/atendente",IF(H50="CPF não está no cadastro","Conferir se o CPF foi digitado errado ou se o cliente não foi cadastrado","Confirmar com a loja")))))} | J50: =IF(H50="Só o primeiro nome","Buscar em vendas e atendimentos: primeiro nome """&TRIM(C50)&""" + loja "&F50&" + dia "&TEXT(DAY(B50),"00")&"/"&TEXT(MONTH(B50),"00")&"/"&YEAR(B50)&" (ver aba Varredura)","")
H51: {=IF(NOT(ISNUMBER(A51)),"",IF(INDEX(Resgates!$B:$B,A51)<>"","CPF não está no cadastro",IF(ISNUMBER(SEARCH(" ",TRIM(C51))),IF(COUNTIF(Clientes!$A$2:$A$2396,TRIM(C51))>1,"Nome repetido no cadastro","Nome não encontrado no cadastro"),"Só o primeiro nome")))} | I51: {=IF(H51="","",IF(LEFT(INDEX(Resgates!$K:$K,A51),9)="Sugestão:",INDEX(Resgates!$K:$K,A51),IF(H51="Nome repetido no cadastro",_xlfn.TEXTJOIN(" / ",TRUE,_xlfn._xlws.FILTER(Clientes!$A$2:$A$2396&" – "&Clientes!$B$2:$B$2396&" (cadastro "&Clientes!$G$2:$G$2396&")",Clientes!$A$2:$A$2396=TRIM(C51))),IF(H51="Só o primeiro nome",COUNTIF(Clientes!$A$2:$A$2396,TRIM(C51)&" *")&" clientes com esse primeiro nome – confirmar com a loja/atendente",IF(H51="CPF não está no cadastro","Conferir se o CPF foi digitado errado ou se o cliente não foi cadastrado","Confirmar com a loja")))))} | J51: =IF(H51="Só o primeiro nome","Buscar em vendas e atendimentos: primeiro nome """&TRIM(C51)&""" + loja "&F51&" + dia "&TEXT(DAY(B51),"00")&"/"&TEXT(MONTH(B51),"00")&"/"&YEAR(B51)&" (ver aba Varredura)","")
H52: {=IF(NOT(ISNUMBER(A52)),"",IF(INDEX(Resgates!$B:$B,A52)<>"","CPF não está no cadastro",IF(ISNUMBER(SEARCH(" ",TRIM(C52))),IF(COUNTIF(Clientes!$A$2:$A$2396,TRIM(C52))>1,"Nome repetido no cadastro","Nome não encontrado no cadastro"),"Só o primeiro nome")))} | I52: {=IF(H52="","",IF(LEFT(INDEX(Resgates!$K:$K,A52),9)="Sugestão:",INDEX(Resgates!$K:$K,A52),IF(H52="Nome repetido no cadastro",_xlfn.TEXTJOIN(" / ",TRUE,_xlfn._xlws.FILTER(Clientes!$A$2:$A$2396&" – "&Clientes!$B$2:$B$2396&" (cadastro "&Clientes!$G$2:$G$2396&")",Clientes!$A$2:$A$2396=TRIM(C52))),IF(H52="Só o primeiro nome",COUNTIF(Clientes!$A$2:$A$2396,TRIM(C52)&" *")&" clientes com esse primeiro nome – confirmar com a loja/atendente",IF(H52="CPF não está no cadastro","Conferir se o CPF foi digitado errado ou se o cliente não foi cadastrado","Confirmar com a loja")))))} | J52: =IF(H52="Só o primeiro nome","Buscar em vendas e atendimentos: primeiro nome """&TRIM(C52)&""" + loja "&F52&" + dia "&TEXT(DAY(B52),"00")&"/"&TEXT(MONTH(B52),"00")&"/"&YEAR(B52)&" (ver aba Varredura)","")
H53: {=IF(NOT(ISNUMBER(A53)),"",IF(INDEX(Resgates!$B:$B,A53)<>"","CPF não está no cadastro",IF(ISNUMBER(SEARCH(" ",TRIM(C53))),IF(COUNTIF(Clientes!$A$2:$A$2396,TRIM(C53))>1,"Nome repetido no cadastro","Nome não encontrado no cadastro"),"Só o primeiro nome")))} | I53: {=IF(H53="","",IF(LEFT(INDEX(Resgates!$K:$K,A53),9)="Sugestão:",INDEX(Resgates!$K:$K,A53),IF(H53="Nome repetido no cadastro",_xlfn.TEXTJOIN(" / ",TRUE,_xlfn._xlws.FILTER(Clientes!$A$2:$A$2396&" – "&Clientes!$B$2:$B$2396&" (cadastro "&Clientes!$G$2:$G$2396&")",Clientes!$A$2:$A$2396=TRIM(C53))),IF(H53="Só o primeiro nome",COUNTIF(Clientes!$A$2:$A$2396,TRIM(C53)&" *")&" clientes com esse primeiro nome – confirmar com a loja/atendente",IF(H53="CPF não está no cadastro","Conferir se o CPF foi digitado errado ou se o cliente não foi cadastrado","Confirmar com a loja")))))} | J53: =IF(H53="Só o primeiro nome","Buscar em vendas e atendimentos: primeiro nome """&TRIM(C53)&""" + loja "&F53&" + dia "&TEXT(DAY(B53),"00")&"/"&TEXT(MONTH(B53),"00")&"/"&YEAR(B53)&" (ver aba Varredura)","")
H54: {=IF(NOT(ISNUMBER(A54)),"",IF(INDEX(Resgates!$B:$B,A54)<>"","CPF não está no cadastro",IF(ISNUMBER(SEARCH(" ",TRIM(C54))),IF(COUNTIF(Clientes!$A$2:$A$2396,TRIM(C54))>1,"Nome repetido no cadastro","Nome não encontrado no cadastro"),"Só o primeiro nome")))} | I54: {=IF(H54="","",IF(LEFT(INDEX(Resgates!$K:$K,A54),9)="Sugestão:",INDEX(Resgates!$K:$K,A54),IF(H54="Nome repetido no cadastro",_xlfn.TEXTJOIN(" / ",TRUE,_xlfn._xlws.FILTER(Clientes!$A$2:$A$2396&" – "&Clientes!$B$2:$B$2396&" (cadastro "&Clientes!$G$2:$G$2396&")",Clientes!$A$2:$A$2396=TRIM(C54))),IF(H54="Só o primeiro nome",COUNTIF(Clientes!$A$2:$A$2396,TRIM(C54)&" *")&" clientes com esse primeiro nome – confirmar com a loja/atendente",IF(H54="CPF não está no cadastro","Conferir se o CPF foi digitado errado ou se o cliente não foi cadastrado","Confirmar com a loja")))))} | J54: =IF(H54="Só o primeiro nome","Buscar em vendas e atendimentos: primeiro nome """&TRIM(C54)&""" + loja "&F54&" + dia "&TEXT(DAY(B54),"00")&"/"&TEXT(MONTH(B54),"00")&"/"&YEAR(B54)&" (ver aba Varredura)","")
H55: {=IF(NOT(ISNUMBER(A55)),"",IF(INDEX(Resgates!$B:$B,A55)<>"","CPF não está no cadastro",IF(ISNUMBER(SEARCH(" ",TRIM(C55))),IF(COUNTIF(Clientes!$A$2:$A$2396,TRIM(C55))>1,"Nome repetido no cadastro","Nome não encontrado no cadastro"),"Só o primeiro nome")))} | I55: {=IF(H55="","",IF(LEFT(INDEX(Resgates!$K:$K,A55),9)="Sugestão:",INDEX(Resgates!$K:$K,A55),IF(H55="Nome repetido no cadastro",_xlfn.TEXTJOIN(" / ",TRUE,_xlfn._xlws.FILTER(Clientes!$A$2:$A$2396&" – "&Clientes!$B$2:$B$2396&" (cadastro "&Clientes!$G$2:$G$2396&")",Clientes!$A$2:$A$2396=TRIM(C55))),IF(H55="Só o primeiro nome",COUNTIF(Clientes!$A$2:$A$2396,TRIM(C55)&" *")&" clientes com esse primeiro nome – confirmar com a loja/atendente",IF(H55="CPF não está no cadastro","Conferir se o CPF foi digitado errado ou se o cliente não foi cadastrado","Confirmar com a loja")))))} | J55: =IF(H55="Só o primeiro nome","Buscar em vendas e atendimentos: primeiro nome """&TRIM(C55)&""" + loja "&F55&" + dia "&TEXT(DAY(B55),"00")&"/"&TEXT(MONTH(B55),"00")&"/"&YEAR(B55)&" (ver aba Varredura)","")
H56: {=IF(NOT(ISNUMBER(A56)),"",IF(INDEX(Resgates!$B:$B,A56)<>"","CPF não está no cadastro",IF(ISNUMBER(SEARCH(" ",TRIM(C56))),IF(COUNTIF(Clientes!$A$2:$A$2396,TRIM(C56))>1,"Nome repetido no cadastro","Nome não encontrado no cadastro"),"Só o primeiro nome")))} | I56: {=IF(H56="","",IF(LEFT(INDEX(Resgates!$K:$K,A56),9)="Sugestão:",INDEX(Resgates!$K:$K,A56),IF(H56="Nome repetido no cadastro",_xlfn.TEXTJOIN(" / ",TRUE,_xlfn._xlws.FILTER(Clientes!$A$2:$A$2396&" – "&Clientes!$B$2:$B$2396&" (cadastro "&Clientes!$G$2:$G$2396&")",Clientes!$A$2:$A$2396=TRIM(C56))),IF(H56="Só o primeiro nome",COUNTIF(Clientes!$A$2:$A$2396,TRIM(C56)&" *")&" clientes com esse primeiro nome – confirmar com a loja/atendente",IF(H56="CPF não está no cadastro","Conferir se o CPF foi digitado errado ou se o cliente não foi cadastrado","Confirmar com a loja")))))} | J56: =IF(H56="Só o primeiro nome","Buscar em vendas e atendimentos: primeiro nome """&TRIM(C56)&""" + loja "&F56&" + dia "&TEXT(DAY(B56),"00")&"/"&TEXT(MONTH(B56),"00")&"/"&YEAR(B56)&" (ver aba Varredura)","")
H57: {=IF(NOT(ISNUMBER(A57)),"",IF(INDEX(Resgates!$B:$B,A57)<>"","CPF não está no cadastro",IF(ISNUMBER(SEARCH(" ",TRIM(C57))),IF(COUNTIF(Clientes!$A$2:$A$2396,TRIM(C57))>1,"Nome repetido no cadastro","Nome não encontrado no cadastro"),"Só o primeiro nome")))} | I57: {=IF(H57="","",IF(LEFT(INDEX(Resgates!$K:$K,A57),9)="Sugestão:",INDEX(Resgates!$K:$K,A57),IF(H57="Nome repetido no cadastro",_xlfn.TEXTJOIN(" / ",TRUE,_xlfn._xlws.FILTER(Clientes!$A$2:$A$2396&" – "&Clientes!$B$2:$B$2396&" (cadastro "&Clientes!$G$2:$G$2396&")",Clientes!$A$2:$A$2396=TRIM(C57))),IF(H57="Só o primeiro nome",COUNTIF(Clientes!$A$2:$A$2396,TRIM(C57)&" *")&" clientes com esse primeiro nome – confirmar com a loja/atendente",IF(H57="CPF não está no cadastro","Conferir se o CPF foi digitado errado ou se o cliente não foi cadastrado","Confirmar com a loja")))))} | J57: =IF(H57="Só o primeiro nome","Buscar em vendas e atendimentos: primeiro nome """&TRIM(C57)&""" + loja "&F57&" + dia "&TEXT(DAY(B57),"00")&"/"&TEXT(MONTH(B57),"00")&"/"&YEAR(B57)&" (ver aba Varredura)","")
H58: {=IF(NOT(ISNUMBER(A58)),"",IF(INDEX(Resgates!$B:$B,A58)<>"","CPF não está no cadastro",IF(ISNUMBER(SEARCH(" ",TRIM(C58))),IF(COUNTIF(Clientes!$A$2:$A$2396,TRIM(C58))>1,"Nome repetido no cadastro","Nome não encontrado no cadastro"),"Só o primeiro nome")))} | I58: {=IF(H58="","",IF(LEFT(INDEX(Resgates!$K:$K,A58),9)="Sugestão:",INDEX(Resgates!$K:$K,A58),IF(H58="Nome repetido no cadastro",_xlfn.TEXTJOIN(" / ",TRUE,_xlfn._xlws.FILTER(Clientes!$A$2:$A$2396&" – "&Clientes!$B$2:$B$2396&" (cadastro "&Clientes!$G$2:$G$2396&")",Clientes!$A$2:$A$2396=TRIM(C58))),IF(H58="Só o primeiro nome",COUNTIF(Clientes!$A$2:$A$2396,TRIM(C58)&" *")&" clientes com esse primeiro nome – confirmar com a loja/atendente",IF(H58="CPF não está no cadastro","Conferir se o CPF foi digitado errado ou se o cliente não foi cadastrado","Confirmar com a loja")))))} | J58: =IF(H58="Só o primeiro nome","Buscar em vendas e atendimentos: primeiro nome """&TRIM(C58)&""" + loja "&F58&" + dia "&TEXT(DAY(B58),"00")&"/"&TEXT(MONTH(B58),"00")&"/"&YEAR(B58)&" (ver aba Varredura)","")
... H100: {=IF(NOT(ISNUMBER(A100)),"",IF(INDEX(Resgates!$B:$B,A100)<>"","CPF não está no cadastro",IF(ISNUMBER(SEARCH(" ",TRIM(C100))),IF(COUNTIF(Clientes!$A$2:$A$2396,TRIM(C100))>1,"Nome repetido no cadastro","Nome não encontrado no cadastro"),"Só o primeiro nome")))} | I100: {=IF(H100="","",IF(LEFT(INDEX(Resgates!$K:$K,A100),9)="Sugestão:",INDEX(Resgates!$K:$K,A100),IF(H100="Nome repetido no cadastro",_xlfn.TEXTJOIN(" / ",TRUE,_xlfn._xlws.FILTER(Clientes!$A$2:$A$2396&" – "&Clientes!$B$2:$B$2396&" (cadastro "&Clientes!$G$2:$G$2396&")",Clientes!$A$2:$A$2396=TRIM(C100))),IF(H100="Só o primeiro nome",COUNTIF(Clientes!$A$2:$A$2396,TRIM(C100)&" *")&" clientes com esse primeiro nome – confirmar com a loja/atendente",IF(H100="CPF não está no cadastro","Conferir se o CPF foi digitado errado ou se o cliente não foi cadastrado","Confirmar com a loja")))))} | J100: =IF(H100="Só o primeiro nome","Buscar em vendas e atendimentos: primeiro nome """&TRIM(C100)&""" + loja "&F100&" + dia "&TEXT(DAY(B100),"00")&"/"&TEXT(MONTH(B100),"00")&"/"&YEAR(B100)&" (ver aba Varredura)","")

Sheet Regras e Parâmetros
A1: PARÂMETROS DO PROGRAMA VULTO+ | E1: REGRAS DO PROGRAMA VULTO+
A3: Categoria | B3: Pontos mínimos | C3: Pontos máximos | E3: - Cada R$ 1 em loja física = 1 ponto. Compras no site/app valem pontos em dobro.
A4: Bronze | B4: 1 | C4: 1500 | E4: - Clientes Ouro ganham 50% a mais (em cima de tudo).
A5: Prata | B5: 1501 | C5: 5000 | E5: - Resgate: 100 pontos = R$ 5,00 (era R$ 10,00 até fev/2025). Mínimo 100 pontos, só múltiplos de 100.
A6: Ouro | B6: 5001 | C6: 9999 | E6: - Os pontos vencem em 12 meses. Ouro: 18 meses (combinado com o Diego, ainda não está no sistema).
A7: Vip | B7: 10000 | E7: - O saldo NÃO pode ficar negativo (o sistema deixa, cuidado).
E8: - Pontos só com CPF. Telefone/e-mail não vale (a loja pode lançar depois na tela de fidelidade).
A9: Conversão de resgate | E9: - Categoria: calculada pelos pontos, com as faixas da tabela ao lado.
A10: Vigente a partir de | B10: R$ por 100 pontos | E10: - Aceita Msg = Não ou Não informado: NÃO enviar mensagem (LGPD).
A11: =DATE(2000,1,1) -> 36526 | B11: 10
A12: =DATE(2025,3,1) -> 45717 | B12: 5 | E12: SOBRE ESTA PLANILHA
E13: - A coluna de pontos da aba Clientes foi congelada em 01/01/2025. Depois disso os pontos ficam no sistema (vulto.db); quem se cadastrou depois dessa data tem 0 aqui.
A14: Resumo (atualiza sozinho) | B14: Qtd clientes | E14: - Cada CPF aparece uma vez só (os cadastros duplicados foram juntados e os pontos somados; as linhas de origem estão em Obs).
A15: Bronze | B15: =COUNTIF(Clientes!$I:$I,A15) -> 763 | E15: - Use o filtro da coluna Pendências (Clientes e Resgates) para ver o que precisa conferir.
A16: Prata | B16: =COUNTIF(Clientes!$I:$I,A16) -> 403 | E16: - Na aba Resgates: vermelho = desconto acima da regra; amarelo = cliente não identificado.
A17: Ouro | B17: =COUNTIF(Clientes!$I:$I,A17) -> 107 | E17: - A aba Pendências se atualiza sozinha quando o CPF é preenchido na aba Resgates.
A18: Vip | B18: =COUNTIF(Clientes!$I:$I,A18) -> 91 | E18: - Limpeza feita em 19/10/2026. O programa antigo e as versões originais foram apagados; o que ainda importava foi levado para Clientes (Obs) e Pendências.
A19: Sem categoria (0 pts) | B19: =COUNTA(Clientes!$B:$B)-1-SUM(B15:B18) -> 1031 | E19: - CPF inválido: no próximo login o cliente é obrigado a atualizar os dados (CPF) para continuar usando os benefícios. Até lá, os pontos ficam guardados.
A20: Total | B20: =SUM(B15:B19) -> 2395 | E20: - Login (decidido em 19/10/2026): o cliente entra com CPF ou e-mail. E-mail usado por mais de um cliente não serve para entrar (entra pelo CPF). Com CPF inválido, entra pelo e-mail e atualiza o CPF; sem e-mail próprio, a loja ou o atendimento corrige.

Sheet Varredura (automação)
A1: VARREDURA AUTOMÁTICA – RESGATES ANOTADOS SÓ COM O PRIMEIRO NOME
A2: Esta aba é um roteiro para quem for rodar a varredura (ex.: Claude Code). Os passos abaixo não foram feitos aqui. Esta planilha só não tem acesso às vendas completas de todas as lojas.
A4: OBJETIVO
A5: Descobrir o CPF de cada resgate anotado só com o primeiro nome. A ideia é cruzar o nome com quem comprou NA MESMA LOJA e NO MESMO DIA do resgate. Isso reduz muito a lista de candidatos (hoje são de 13 a 39 clientes por nome).
A7: ENTRADA
A8: - Casos: aba Pendências, linhas em que o Motivo (col. H) = "Só o primeiro nome". A coluna A traz a linha da aba Resgates; as colunas B, C e F trazem data, nome e loja.
A9: - Cadastro: aba Clientes (Nome, CPF, Telefone, Loja Cadastro).
A10: - Fontes externas para cruzar: arquivos de vendas de cada loja (ex.: vendas_batel_MANUAL_marco.xlsx, que só cobre o Batel em março), exportação de atendimentos (atendimentos_export_whatsapp_insta.xlsx) e o sistema vulto.db (pontos e resgates depois de 01/01/2025).
A12: PASSO A PASSO
A13: 1. Para cada caso, pegue: primeiro nome, loja e data do resgate.
A14: 2. Nas vendas, filtre: mesma loja + mesma data (aceitar até 1 dia de diferença, caso o lançamento tenha sido feito no dia seguinte) + nome do comprador começando com o primeiro nome (ignorar maiúsculas e acentos).
A15: 3. Para cada venda encontrada, ache o CPF dela: pelo próprio CPF da venda, ou pelo telefone ou e-mail batendo com a aba Clientes.
... A32: FEITO EM 19/10/2026: ver a seção 9 da aba Relatório de Mudanças (10 resolvidos, 1 sugestão, 1 sem candidato, 6 sem vendas para cruzar).
