Workbook

Sheet PINHEIROS
A1: SKU | B1: CÓDIGO CD | C1: QTD | D1: STATUS CATÁLOGO | E1: OBS | F1: AVARIA (real) | H1: RESUMO AVARIA – PINHEIROS
A2: VLT-MOL-002-OLI-GG | B2: =_xlfn.XLOOKUP(A2,CATÁLOGO!$A$2:$A$846,CATÁLOGO!$B$2:$B$846,"FORA DO CATÁLOGO") -> MOL002VGG | C2: 0 | D2: =_xlfn.XLOOKUP(A2,CATÁLOGO!$A$2:$A$846,CATÁLOGO!$E$2:$E$846,"FORA DO CATÁLOGO") -> Fora do catálogo 2026 | F2: =SUMIFS('AVARIA PINHEIROS'!$C$2:$C$24,'AVARIA PINHEIROS'!$A$2:$A$24,A2) -> 0 | H2: Tipo de avaria | I2: Real (contada)
A3: VLT-CAL-001-VIN-G | B3: =_xlfn.XLOOKUP(A3,CATÁLOGO!$A$2:$A$846,CATÁLOGO!$B$2:$B$846,"FORA DO CATÁLOGO") -> CAL001H42 | C3: 1 | D3: =_xlfn.XLOOKUP(A3,CATÁLOGO!$A$2:$A$846,CATÁLOGO!$E$2:$E$846,"FORA DO CATÁLOGO") -> Fora do catálogo 2026 | F3: =SUMIFS('AVARIA PINHEIROS'!$C$2:$C$24,'AVARIA PINHEIROS'!$A$2:$A$24,A3) -> 0 | H3: Estoque contado (inclui avaria) | I3: =SUM(C2:C725)+I4 -> 2438
A4: VLT-ACE-001-PRE-U | B4: =_xlfn.XLOOKUP(A4,CATÁLOGO!$A$2:$A$846,CATÁLOGO!$B$2:$B$846,"FORA DO CATÁLOGO") -> ACE001PU | C4: 0 | D4: =_xlfn.XLOOKUP(A4,CATÁLOGO!$A$2:$A$846,CATÁLOGO!$E$2:$E$846,"FORA DO CATÁLOGO") -> Fora do catálogo 2026 | E4: avaria? | 1 peça(s) transferida(s) p/ aba AVARIA PINHEIROS (decisão 15/10) | F4: =SUMIFS('AVARIA PINHEIROS'!$C$2:$C$24,'AVARIA PINHEIROS'!$A$2:$A$24,A4) -> 1 | H4: Peças com avaria | I4: =SUM(F2:F725) -> 80
A5: VLT-TRI-003-BEG-M | B5: =_xlfn.XLOOKUP(A5,CATÁLOGO!$A$2:$A$846,CATÁLOGO!$B$2:$B$846,"FORA DO CATÁLOGO") -> TRI003GM | C5: 1 | D5: =_xlfn.XLOOKUP(A5,CATÁLOGO!$A$2:$A$846,CATÁLOGO!$E$2:$E$846,"FORA DO CATÁLOGO") -> Fora do catálogo 2026 | F5: =SUMIFS('AVARIA PINHEIROS'!$C$2:$C$24,'AVARIA PINHEIROS'!$A$2:$A$24,A5) -> 0 | H5: Estoque vendável | I5: =I3-I4 -> 2358
A6: VLT-TRI-003-BEG-GG | B6: =_xlfn.XLOOKUP(A6,CATÁLOGO!$A$2:$A$846,CATÁLOGO!$B$2:$B$846,"FORA DO CATÁLOGO") -> TRI003GGG | C6: 1 | D6: =_xlfn.XLOOKUP(A6,CATÁLOGO!$A$2:$A$846,CATÁLOGO!$E$2:$E$846,"FORA DO CATÁLOGO") -> Fora do catálogo 2026 | F6: =SUMIFS('AVARIA PINHEIROS'!$C$2:$C$24,'AVARIA PINHEIROS'!$A$2:$A$24,A6) -> 0 | H6: % avaria | I6: =I4/I3 -> 0.032813782
A7: VLT-TRI-003-MRR-P | B7: =_xlfn.XLOOKUP(A7,CATÁLOGO!$A$2:$A$846,CATÁLOGO!$B$2:$B$846,"FORA DO CATÁLOGO") -> TRI003MP | C7: 1 | D7: =_xlfn.XLOOKUP(A7,CATÁLOGO!$A$2:$A$846,CATÁLOGO!$E$2:$E$846,"FORA DO CATÁLOGO") -> Fora do catálogo 2026 | F7: =SUMIFS('AVARIA PINHEIROS'!$C$2:$C$24,'AVARIA PINHEIROS'!$A$2:$A$24,A7) -> 0 | H7: SKUs afetados | I7: =COUNTIF(F2:F725,">0") -> 23
A8: VLT-TRI-003-MRR-M | B8: =_xlfn.XLOOKUP(A8,CATÁLOGO!$A$2:$A$846,CATÁLOGO!$B$2:$B$846,"FORA DO CATÁLOGO") -> TRI003MM | C8: 1 | D8: =_xlfn.XLOOKUP(A8,CATÁLOGO!$A$2:$A$846,CATÁLOGO!$E$2:$E$846,"FORA DO CATÁLOGO") -> Fora do catálogo 2026 | F8: =SUMIFS('AVARIA PINHEIROS'!$C$2:$C$24,'AVARIA PINHEIROS'!$A$2:$A$24,A8) -> 0 | H8: % avaria – média das 4 lojas | I8: ='AVARIA ESTIMADA'!F14 -> 0.029957854
A9: VLT-TRI-003-MRR-G | B9: =_xlfn.XLOOKUP(A9,CATÁLOGO!$A$2:$A$846,CATÁLOGO!$B$2:$B$846,"FORA DO CATÁLOGO") -> TRI003MG | C9: 1 | D9: =_xlfn.XLOOKUP(A9,CATÁLOGO!$A$2:$A$846,CATÁLOGO!$E$2:$E$846,"FORA DO CATÁLOGO") -> Fora do catálogo 2026 | F9: =SUMIFS('AVARIA PINHEIROS'!$C$2:$C$24,'AVARIA PINHEIROS'!$A$2:$A$24,A9) -> 0
A10: VLT-BER-001-BRA-P | B10: =_xlfn.XLOOKUP(A10,CATÁLOGO!$A$2:$A$846,CATÁLOGO!$B$2:$B$846,"FORA DO CATÁLOGO") -> BER001B38 | C10: 6 | D10: =_xlfn.XLOOKUP(A10,CATÁLOGO!$A$2:$A$846,CATÁLOGO!$E$2:$E$846,"FORA DO CATÁLOGO") -> Ativo | F10: =SUMIFS('AVARIA PINHEIROS'!$C$2:$C$24,'AVARIA PINHEIROS'!$A$2:$A$24,A10) -> 0 | H10: SKUs com avaria (maior → menor)
A11: VLT-BER-001-BRA-M | B11: =_xlfn.XLOOKUP(A11,CATÁLOGO!$A$2:$A$846,CATÁLOGO!$B$2:$B$846,"FORA DO CATÁLOGO") -> BER001B40 | C11: 6 | D11: =_xlfn.XLOOKUP(A11,CATÁLOGO!$A$2:$A$846,CATÁLOGO!$E$2:$E$846,"FORA DO CATÁLOGO") -> Ativo | F11: =SUMIFS('AVARIA PINHEIROS'!$C$2:$C$24,'AVARIA PINHEIROS'!$A$2:$A$24,A11) -> 0 | H11: SKU | I11: PEÇAS
A12: VLT-BER-001-BRA-G | B12: =_xlfn.XLOOKUP(A12,CATÁLOGO!$A$2:$A$846,CATÁLOGO!$B$2:$B$846,"FORA DO CATÁLOGO") -> BER001B42 | C12: 6 | D12: =_xlfn.XLOOKUP(A12,CATÁLOGO!$A$2:$A$846,CATÁLOGO!$E$2:$E$846,"FORA DO CATÁLOGO") -> Ativo | F12: =SUMIFS('AVARIA PINHEIROS'!$C$2:$C$24,'AVARIA PINHEIROS'!$A$2:$A$24,A12) -> 0 | H12: {=_xlfn._xlws.SORT(_xlfn._xlws.FILTER(_xlfn.HSTACK(A2:A725,F2:F725),F2:F725>0,"sem avaria"),2,-1)} -> VLT-CAL-023-LIL-M | I12: 7
A13: VLT-BER-001-BRA-GG | B13: =_xlfn.XLOOKUP(A13,CATÁLOGO!$A$2:$A$846,CATÁLOGO!$B$2:$B$846,"FORA DO CATÁLOGO") -> BER001B44 | C13: 4 | D13: =_xlfn.XLOOKUP(A13,CATÁLOGO!$A$2:$A$846,CATÁLOGO!$E$2:$E$846,"FORA DO CATÁLOGO") -> Ativo | F13: =SUMIFS('AVARIA PINHEIROS'!$C$2:$C$24,'AVARIA PINHEIROS'!$A$2:$A$24,A13) -> 0 | H13: VLT-CAL-003-PRE-G | I13: 6
A14: VLT-CAL-003-PRE-P | B14: =_xlfn.XLOOKUP(A14,CATÁLOGO!$A$2:$A$846,CATÁLOGO!$B$2:$B$846,"FORA DO CATÁLOGO") -> CAL003P38 | C14: 6 | D14: =_xlfn.XLOOKUP(A14,CATÁLOGO!$A$2:$A$846,CATÁLOGO!$E$2:$E$846,"FORA DO CATÁLOGO") -> Ativo | F14: =SUMIFS('AVARIA PINHEIROS'!$C$2:$C$24,'AVARIA PINHEIROS'!$A$2:$A$24,A14) -> 0 | H14: VLT-TOP-006-MRR-G | I14: 5
A15: VLT-CAL-003-PRE-M | B15: =_xlfn.XLOOKUP(A15,CATÁLOGO!$A$2:$A$846,CATÁLOGO!$B$2:$B$846,"FORA DO CATÁLOGO") -> CAL003P40 | C15: 6 | D15: =_xlfn.XLOOKUP(A15,CATÁLOGO!$A$2:$A$846,CATÁLOGO!$E$2:$E$846,"FORA DO CATÁLOGO") -> Ativo | F15: =SUMIFS('AVARIA PINHEIROS'!$C$2:$C$24,'AVARIA PINHEIROS'!$A$2:$A$24,A15) -> 0 | H15: VLT-CAL-011-LIL-P | I15: 5
A16: VLT-CAL-003-PRE-G | B16: =_xlfn.XLOOKUP(A16,CATÁLOGO!$A$2:$A$846,CATÁLOGO!$B$2:$B$846,"FORA DO CATÁLOGO") -> CAL003P42 | C16: 0 | D16: =_xlfn.XLOOKUP(A16,CATÁLOGO!$A$2:$A$846,CATÁLOGO!$E$2:$E$846,"FORA DO CATÁLOGO") -> Ativo | E16: avaria? | 6 peça(s) transferida(s) p/ aba AVARIA PINHEIROS (decisão 15/10) | F16: =SUMIFS('AVARIA PINHEIROS'!$C$2:$C$24,'AVARIA PINHEIROS'!$A$2:$A$24,A16) -> 6 | H16: VLT-CAL-024-AZM-P | I16: 5
A17: VLT-CAL-003-PRE-GG | B17: =_xlfn.XLOOKUP(A17,CATÁLOGO!$A$2:$A$846,CATÁLOGO!$B$2:$B$846,"FORA DO CATÁLOGO") -> CAL003P44 | C17: 4 | D17: =_xlfn.XLOOKUP(A17,CATÁLOGO!$A$2:$A$846,CATÁLOGO!$E$2:$E$846,"FORA DO CATÁLOGO") -> Ativo | E17: provador | SKU corrigido (era VLT-CLA-003-PRE-44) | F17: =SUMIFS('AVARIA PINHEIROS'!$C$2:$C$24,'AVARIA PINHEIROS'!$A$2:$A$24,A17) -> 0 | H17: VLT-TOP-001-AMA-G | I17: 5
A18: VLT-CAL-004-CIN-XP | B18: =_xlfn.XLOOKUP(A18,CATÁLOGO!$A$2:$A$846,CATÁLOGO!$B$2:$B$846,"FORA DO CATÁLOGO") -> CAL004C36 | C18: 1 | D18: =_xlfn.XLOOKUP(A18,CATÁLOGO!$A$2:$A$846,CATÁLOGO!$E$2:$E$846,"FORA DO CATÁLOGO") -> Ativo | F18: =SUMIFS('AVARIA PINHEIROS'!$C$2:$C$24,'AVARIA PINHEIROS'!$A$2:$A$24,A18) -> 0 | H18: VLT-CAM-020-AMA-G | I18: 5
A19: VLT-CAL-004-CIN-P | B19: =_xlfn.XLOOKUP(A19,CATÁLOGO!$A$2:$A$846,CATÁLOGO!$B$2:$B$846,"FORA DO CATÁLOGO") -> CAL004C38 | C19: 2 | D19: =_xlfn.XLOOKUP(A19,CATÁLOGO!$A$2:$A$846,CATÁLOGO!$E$2:$E$846,"FORA DO CATÁLOGO") -> Ativo | F19: =SUMIFS('AVARIA PINHEIROS'!$C$2:$C$24,'AVARIA PINHEIROS'!$A$2:$A$24,A19) -> 0 | H19: VLT-VES-006-MRR-G | I19: 4
A20: VLT-CAL-004-CIN-M | B20: =_xlfn.XLOOKUP(A20,CATÁLOGO!$A$2:$A$846,CATÁLOGO!$B$2:$B$846,"FORA DO CATÁLOGO") -> CAL004C40 | C20: 2 | D20: =_xlfn.XLOOKUP(A20,CATÁLOGO!$A$2:$A$846,CATÁLOGO!$E$2:$E$846,"FORA DO CATÁLOGO") -> Ativo | F20: =SUMIFS('AVARIA PINHEIROS'!$C$2:$C$24,'AVARIA PINHEIROS'!$A$2:$A$24,A20) -> 0 | H20: VLT-CAL-016-OLI-P | I20: 4
A21: VLT-CAL-004-CIN-G | B21: =_xlfn.XLOOKUP(A21,CATÁLOGO!$A$2:$A$846,CATÁLOGO!$B$2:$B$846,"FORA DO CATÁLOGO") -> CAL004C42 | C21: 2 | D21: =_xlfn.XLOOKUP(A21,CATÁLOGO!$A$2:$A$846,CATÁLOGO!$E$2:$E$846,"FORA DO CATÁLOGO") -> Ativo | F21: =SUMIFS('AVARIA PINHEIROS'!$C$2:$C$24,'AVARIA PINHEIROS'!$A$2:$A$24,A21) -> 0 | H21: VLT-CAL-016-OLI-M | I21: 4
A22: VLT-CAL-004-CIN-GG | B22: =_xlfn.XLOOKUP(A22,CATÁLOGO!$A$2:$A$846,CATÁLOGO!$B$2:$B$846,"FORA DO CATÁLOGO") -> CAL004C44 | C22: 1 | D22: =_xlfn.XLOOKUP(A22,CATÁLOGO!$A$2:$A$846,CATÁLOGO!$E$2:$E$846,"FORA DO CATÁLOGO") -> Ativo | F22: =SUMIFS('AVARIA PINHEIROS'!$C$2:$C$24,'AVARIA PINHEIROS'!$A$2:$A$24,A22) -> 0 | H22: VLT-BER-007-AZM-G | I22: 4
A23: VLT-CAL-004-CIN-XG | B23: =_xlfn.XLOOKUP(A23,CATÁLOGO!$A$2:$A$846,CATÁLOGO!$B$2:$B$846,"FORA DO CATÁLOGO") -> CAL004C46 | C23: 1 | D23: =_xlfn.XLOOKUP(A23,CATÁLOGO!$A$2:$A$846,CATÁLOGO!$E$2:$E$846,"FORA DO CATÁLOGO") -> Ativo | F23: =SUMIFS('AVARIA PINHEIROS'!$C$2:$C$24,'AVARIA PINHEIROS'!$A$2:$A$24,A23) -> 0 | H23: VLT-CAM-017-AMA-G | I23: 4
A24: VLT-CAL-004-BEG-XP | B24: =_xlfn.XLOOKUP(A24,CATÁLOGO!$A$2:$A$846,CATÁLOGO!$B$2:$B$846,"FORA DO CATÁLOGO") -> CAL004G36 | C24: 1 | D24: =_xlfn.XLOOKUP(A24,CATÁLOGO!$A$2:$A$846,CATÁLOGO!$E$2:$E$846,"FORA DO CATÁLOGO") -> Ativo | F24: =SUMIFS('AVARIA PINHEIROS'!$C$2:$C$24,'AVARIA PINHEIROS'!$A$2:$A$24,A24) -> 0 | H24: VLT-CAM-020-AMA-P | I24: 4
A25: VLT-CAL-004-BEG-M | B25: =_xlfn.XLOOKUP(A25,CATÁLOGO!$A$2:$A$846,CATÁLOGO!$B$2:$B$846,"FORA DO CATÁLOGO") -> CAL004G40 | C25: 1 | D25: =_xlfn.XLOOKUP(A25,CATÁLOGO!$A$2:$A$846,CATÁLOGO!$E$2:$E$846,"FORA DO CATÁLOGO") -> Ativo | F25: =SUMIFS('AVARIA PINHEIROS'!$C$2:$C$24,'AVARIA PINHEIROS'!$A$2:$A$24,A25) -> 0 | H25: VLT-VES-007-OLI-GG | I25: 3
A26: VLT-CAL-004-BEG-G | B26: =_xlfn.XLOOKUP(A26,CATÁLOGO!$A$2:$A$846,CATÁLOGO!$B$2:$B$846,"FORA DO CATÁLOGO") -> CAL004G42 | C26: 1 | D26: =_xlfn.XLOOKUP(A26,CATÁLOGO!$A$2:$A$846,CATÁLOGO!$E$2:$E$846,"FORA DO CATÁLOGO") -> Ativo | F26: =SUMIFS('AVARIA PINHEIROS'!$C$2:$C$24,'AVARIA PINHEIROS'!$A$2:$A$24,A26) -> 0 | H26: VLT-VES-009-BEG-G | I26: 3
A27: VLT-CAL-004-BEG-GG | B27: =_xlfn.XLOOKUP(A27,CATÁLOGO!$A$2:$A$846,CATÁLOGO!$B$2:$B$846,"FORA DO CATÁLOGO") -> CAL004G44 | C27: 0 | D27: =_xlfn.XLOOKUP(A27,CATÁLOGO!$A$2:$A$846,CATÁLOGO!$E$2:$E$846,"FORA DO CATÁLOGO") -> Ativo | F27: =SUMIFS('AVARIA PINHEIROS'!$C$2:$C$24,'AVARIA PINHEIROS'!$A$2:$A$24,A27) -> 0 | H27: VLT-CAM-004-PRE-M | I27: 2
A28: VLT-CAL-005-PRE-XP | B28: =_xlfn.XLOOKUP(A28,CATÁLOGO!$A$2:$A$846,CATÁLOGO!$B$2:$B$846,"FORA DO CATÁLOGO") -> CAL005P36 | C28: 4 | D28: =_xlfn.XLOOKUP(A28,CATÁLOGO!$A$2:$A$846,CATÁLOGO!$E$2:$E$846,"FORA DO CATÁLOGO") -> Ativo | F28: =SUMIFS('AVARIA PINHEIROS'!$C$2:$C$24,'AVARIA PINHEIROS'!$A$2:$A$24,A28) -> 0 | H28: VLT-BER-006-LIL-G | I28: 2
A29: VLT-CAL-005-PRE-P | B29: =_xlfn.XLOOKUP(A29,CATÁLOGO!$A$2:$A$846,CATÁLOGO!$B$2:$B$846,"FORA DO CATÁLOGO") -> CAL005P38 | C29: 6 | D29: =_xlfn.XLOOKUP(A29,CATÁLOGO!$A$2:$A$846,CATÁLOGO!$E$2:$E$846,"FORA DO CATÁLOGO") -> Ativo | F29: =SUMIFS('AVARIA PINHEIROS'!$C$2:$C$24,'AVARIA PINHEIROS'!$A$2:$A$24,A29) -> 0 | H29: VLT-SAI-009-BRA-P | I29: 2
... A31: VLT-CAL-005-PRE-G | B31: =_xlfn.XLOOKUP(A31,CATÁLOGO!$A$2:$A$846,CATÁLOGO!$B$2:$B$846,"FORA DO CATÁLOGO") -> CAL005P42 | C31: 5 | D31: =_xlfn.XLOOKUP(A31,CATÁLOGO!$A$2:$A$846,CATÁLOGO!$E$2:$E$846,"FORA DO CATÁLOGO") -> Ativo | F31: =SUMIFS('AVARIA PINHEIROS'!$C$2:$C$24,'AVARIA PINHEIROS'!$A$2:$A$24,A31) -> 0 | H31: VLT-ACE-001-PRE-U | I31: 1
A32: VLT-CAL-005-PRE-GG | B32: =_xlfn.XLOOKUP(A32,CATÁLOGO!$A$2:$A$846,CATÁLOGO!$B$2:$B$846,"FORA DO CATÁLOGO") -> CAL005P44 | C32: 4 | D32: =_xlfn.XLOOKUP(A32,CATÁLOGO!$A$2:$A$846,CATÁLOGO!$E$2:$E$846,"FORA DO CATÁLOGO") -> Ativo | E32: provador | F32: =SUMIFS('AVARIA PINHEIROS'!$C$2:$C$24,'AVARIA PINHEIROS'!$A$2:$A$24,A32) -> 0 | H32: VLT-MOL-008-VIN-G | I32: 1
A33: VLT-TOP-002-AZM-P | B33: =_xlfn.XLOOKUP(A33,CATÁLOGO!$A$2:$A$846,CATÁLOGO!$B$2:$B$846,"FORA DO CATÁLOGO") -> TOP002AP | C33: 3 | D33: =_xlfn.XLOOKUP(A33,CATÁLOGO!$A$2:$A$846,CATÁLOGO!$E$2:$E$846,"FORA DO CATÁLOGO") -> Ativo | F33: =SUMIFS('AVARIA PINHEIROS'!$C$2:$C$24,'AVARIA PINHEIROS'!$A$2:$A$24,A33) -> 0 | H33: VLT-MOL-008-VIN-GG | I33: 1
A34: VLT-TOP-002-AZM-M | B34: =_xlfn.XLOOKUP(A34,CATÁLOGO!$A$2:$A$846,CATÁLOGO!$B$2:$B$846,"FORA DO CATÁLOGO") -> TOP002AM | C34: 6 | D34: =_xlfn.XLOOKUP(A34,CATÁLOGO!$A$2:$A$846,CATÁLOGO!$E$2:$E$846,"FORA DO CATÁLOGO") -> Ativo | F34: =SUMIFS('AVARIA PINHEIROS'!$C$2:$C$24,'AVARIA PINHEIROS'!$A$2:$A$24,A34) -> 0 | H34: VLT-TOP-010-AMA-M | I34: 1
A35: VLT-TOP-002-AZM-G | B35: =_xlfn.XLOOKUP(A35,CATÁLOGO!$A$2:$A$846,CATÁLOGO!$B$2:$B$846,"FORA DO CATÁLOGO") -> TOP002AG | C35: 5 | D35: =_xlfn.XLOOKUP(A35,CATÁLOGO!$A$2:$A$846,CATÁLOGO!$E$2:$E$846,"FORA DO CATÁLOGO") -> Ativo | F35: =SUMIFS('AVARIA PINHEIROS'!$C$2:$C$24,'AVARIA PINHEIROS'!$A$2:$A$24,A35) -> 0
A36: VLT-TOP-002-AZM-GG | B36: =_xlfn.XLOOKUP(A36,CATÁLOGO!$A$2:$A$846,CATÁLOGO!$B$2:$B$846,"FORA DO CATÁLOGO") -> TOP002AGG | C36: 2 | D36: =_xlfn.XLOOKUP(A36,CATÁLOGO!$A$2:$A$846,CATÁLOGO!$E$2:$E$846,"FORA DO CATÁLOGO") -> Ativo | F36: =SUMIFS('AVARIA PINHEIROS'!$C$2:$C$24,'AVARIA PINHEIROS'!$A$2:$A$24,A36) -> 0
A37: VLT-TOP-002-PRE-P | B37: =_xlfn.XLOOKUP(A37,CATÁLOGO!$A$2:$A$846,CATÁLOGO!$B$2:$B$846,"FORA DO CATÁLOGO") -> TOP002PP | C37: 2 | D37: =_xlfn.XLOOKUP(A37,CATÁLOGO!$A$2:$A$846,CATÁLOGO!$E$2:$E$846,"FORA DO CATÁLOGO") -> Descontinuado | F37: =SUMIFS('AVARIA PINHEIROS'!$C$2:$C$24,'AVARIA PINHEIROS'!$A$2:$A$24,A37) -> 0
A38: VLT-TOP-002-PRE-G | B38: =_xlfn.XLOOKUP(A38,CATÁLOGO!$A$2:$A$846,CATÁLOGO!$B$2:$B$846,"FORA DO CATÁLOGO") -> TOP002PG | C38: 1 | D38: =_xlfn.XLOOKUP(A38,CATÁLOGO!$A$2:$A$846,CATÁLOGO!$E$2:$E$846,"FORA DO CATÁLOGO") -> Descontinuado | E38: vitrine | F38: =SUMIFS('AVARIA PINHEIROS'!$C$2:$C$24,'AVARIA PINHEIROS'!$A$2:$A$24,A38) -> 0
A39: VLT-BER-002-CIN-XP | B39: =_xlfn.XLOOKUP(A39,CATÁLOGO!$A$2:$A$846,CATÁLOGO!$B$2:$B$846,"FORA DO CATÁLOGO") -> BER002C36 | C39: 1 | D39: =_xlfn.XLOOKUP(A39,CATÁLOGO!$A$2:$A$846,CATÁLOGO!$E$2:$E$846,"FORA DO CATÁLOGO") -> Ativo | F39: =SUMIFS('AVARIA PINHEIROS'!$C$2:$C$24,'AVARIA PINHEIROS'!$A$2:$A$24,A39) -> 0
A40: VLT-BER-002-CIN-P | B40: =_xlfn.XLOOKUP(A40,CATÁLOGO!$A$2:$A$846,CATÁLOGO!$B$2:$B$846,"FORA DO CATÁLOGO") -> BER002C38 | C40: 2 | D40: =_xlfn.XLOOKUP(A40,CATÁLOGO!$A$2:$A$846,CATÁLOGO!$E$2:$E$846,"FORA DO CATÁLOGO") -> Ativo | E40: vitrine | F40: =SUMIFS('AVARIA PINHEIROS'!$C$2:$C$24,'AVARIA PINHEIROS'!$A$2:$A$24,A40) -> 0
A41: VLT-BER-002-CIN-M | B41: =_xlfn.XLOOKUP(A41,CATÁLOGO!$A$2:$A$846,CATÁLOGO!$B$2:$B$846,"FORA DO CATÁLOGO") -> BER002C40 | C41: 3 | D41: =_xlfn.XLOOKUP(A41,CATÁLOGO!$A$2:$A$846,CATÁLOGO!$E$2:$E$846,"FORA DO CATÁLOGO") -> Ativo | F41: =SUMIFS('AVARIA PINHEIROS'!$C$2:$C$24,'AVARIA PINHEIROS'!$A$2:$A$24,A41) -> 0
A42: VLT-BER-002-CIN-G | B42: =_xlfn.XLOOKUP(A42,CATÁLOGO!$A$2:$A$846,CATÁLOGO!$B$2:$B$846,"FORA DO CATÁLOGO") -> BER002C42 | C42: 2 | D42: =_xlfn.XLOOKUP(A42,CATÁLOGO!$A$2:$A$846,CATÁLOGO!$E$2:$E$846,"FORA DO CATÁLOGO") -> Ativo | F42: =SUMIFS('AVARIA PINHEIROS'!$C$2:$C$24,'AVARIA PINHEIROS'!$A$2:$A$24,A42) -> 0
A43: VLT-BER-002-CIN-GG | B43: =_xlfn.XLOOKUP(A43,CATÁLOGO!$A$2:$A$846,CATÁLOGO!$B$2:$B$846,"FORA DO CATÁLOGO") -> BER002C44 | C43: 1 | D43: =_xlfn.XLOOKUP(A43,CATÁLOGO!$A$2:$A$846,CATÁLOGO!$E$2:$E$846,"FORA DO CATÁLOGO") -> Ativo | F43: =SUMIFS('AVARIA PINHEIROS'!$C$2:$C$24,'AVARIA PINHEIROS'!$A$2:$A$24,A43) -> 0
A44: VLT-BER-003-BRA-XP | B44: =_xlfn.XLOOKUP(A44,CATÁLOGO!$A$2:$A$846,CATÁLOGO!$B$2:$B$846,"FORA DO CATÁLOGO") -> BER003B36 | C44: 4 | D44: =_xlfn.XLOOKUP(A44,CATÁLOGO!$A$2:$A$846,CATÁLOGO!$E$2:$E$846,"FORA DO CATÁLOGO") -> Ativo | F44: =SUMIFS('AVARIA PINHEIROS'!$C$2:$C$24,'AVARIA PINHEIROS'!$A$2:$A$24,A44) -> 0
A45: VLT-BER-003-BRA-P | B45: =_xlfn.XLOOKUP(A45,CATÁLOGO!$A$2:$A$846,CATÁLOGO!$B$2:$B$846,"FORA DO CATÁLOGO") -> BER003B38 | C45: 6 | D45: =_xlfn.XLOOKUP(A45,CATÁLOGO!$A$2:$A$846,CATÁLOGO!$E$2:$E$846,"FORA DO CATÁLOGO") -> Ativo | F45: =SUMIFS('AVARIA PINHEIROS'!$C$2:$C$24,'AVARIA PINHEIROS'!$A$2:$A$24,A45) -> 0
A46: VLT-BER-003-BRA-M | B46: =_xlfn.XLOOKUP(A46,CATÁLOGO!$A$2:$A$846,CATÁLOGO!$B$2:$B$846,"FORA DO CATÁLOGO") -> BER003B40 | C46: 6 | D46: =_xlfn.XLOOKUP(A46,CATÁLOGO!$A$2:$A$846,CATÁLOGO!$E$2:$E$846,"FORA DO CATÁLOGO") -> Ativo | E46: estoque cima | F46: =SUMIFS('AVARIA PINHEIROS'!$C$2:$C$24,'AVARIA PINHEIROS'!$A$2:$A$24,A46) -> 0
A47: VLT-BER-003-BRA-G | B47: =_xlfn.XLOOKUP(A47,CATÁLOGO!$A$2:$A$846,CATÁLOGO!$B$2:$B$846,"FORA DO CATÁLOGO") -> BER003B42 | C47: 6 | D47: =_xlfn.XLOOKUP(A47,CATÁLOGO!$A$2:$A$846,CATÁLOGO!$E$2:$E$846,"FORA DO CATÁLOGO") -> Ativo | F47: =SUMIFS('AVARIA PINHEIROS'!$C$2:$C$24,'AVARIA PINHEIROS'!$A$2:$A$24,A47) -> 0
A48: VLT-BER-003-BRA-GG | B48: =_xlfn.XLOOKUP(A48,CATÁLOGO!$A$2:$A$846,CATÁLOGO!$B$2:$B$846,"FORA DO CATÁLOGO") -> BER003B44 | C48: 5 | D48: =_xlfn.XLOOKUP(A48,CATÁLOGO!$A$2:$A$846,CATÁLOGO!$E$2:$E$846,"FORA DO CATÁLOGO") -> Ativo | F48: =SUMIFS('AVARIA PINHEIROS'!$C$2:$C$24,'AVARIA PINHEIROS'!$A$2:$A$24,A48) -> 0
A49: VLT-BER-003-BRA-XG | B49: =_xlfn.XLOOKUP(A49,CATÁLOGO!$A$2:$A$846,CATÁLOGO!$B$2:$B$846,"FORA DO CATÁLOGO") -> BER003B46 | C49: 1 | D49: =_xlfn.XLOOKUP(A49,CATÁLOGO!$A$2:$A$846,CATÁLOGO!$E$2:$E$846,"FORA DO CATÁLOGO") -> Ativo | F49: =SUMIFS('AVARIA PINHEIROS'!$C$2:$C$24,'AVARIA PINHEIROS'!$A$2:$A$24,A49) -> 0
A50: VLT-ACE-003-BEG-U | B50: =_xlfn.XLOOKUP(A50,CATÁLOGO!$A$2:$A$846,CATÁLOGO!$B$2:$B$846,"FORA DO CATÁLOGO") -> ACE003GU | C50: 3 | D50: =_xlfn.XLOOKUP(A50,CATÁLOGO!$A$2:$A$846,CATÁLOGO!$E$2:$E$846,"FORA DO CATÁLOGO") -> Ativo | F50: =SUMIFS('AVARIA PINHEIROS'!$C$2:$C$24,'AVARIA PINHEIROS'!$A$2:$A$24,A50) -> 0
A51: VLT-CAM-001-CIN-P | B51: =_xlfn.XLOOKUP(A51,CATÁLOGO!$A$2:$A$846,CATÁLOGO!$B$2:$B$846,"FORA DO CATÁLOGO") -> CAM001CP | C51: 6 | D51: =_xlfn.XLOOKUP(A51,CATÁLOGO!$A$2:$A$846,CATÁLOGO!$E$2:$E$846,"FORA DO CATÁLOGO") -> Ativo | F51: =SUMIFS('AVARIA PINHEIROS'!$C$2:$C$24,'AVARIA PINHEIROS'!$A$2:$A$24,A51) -> 0
A52: VLT-CAM-001-CIN-M | B52: =_xlfn.XLOOKUP(A52,CATÁLOGO!$A$2:$A$846,CATÁLOGO!$B$2:$B$846,"FORA DO CATÁLOGO") -> CAM001CM | C52: 6 | D52: =_xlfn.XLOOKUP(A52,CATÁLOGO!$A$2:$A$846,CATÁLOGO!$E$2:$E$846,"FORA DO CATÁLOGO") -> Ativo | E52: provador | F52: =SUMIFS('AVARIA PINHEIROS'!$C$2:$C$24,'AVARIA PINHEIROS'!$A$2:$A$24,A52) -> 0
A53: VLT-CAM-001-CIN-G | B53: =_xlfn.XLOOKUP(A53,CATÁLOGO!$A$2:$A$846,CATÁLOGO!$B$2:$B$846,"FORA DO CATÁLOGO") -> CAM001CG | C53: 6 | D53: =_xlfn.XLOOKUP(A53,CATÁLOGO!$A$2:$A$846,CATÁLOGO!$E$2:$E$846,"FORA DO CATÁLOGO") -> Ativo | F53: =SUMIFS('AVARIA PINHEIROS'!$C$2:$C$24,'AVARIA PINHEIROS'!$A$2:$A$24,A53) -> 0
A54: VLT-ACE-004-CIN-U | B54: =_xlfn.XLOOKUP(A54,CATÁLOGO!$A$2:$A$846,CATÁLOGO!$B$2:$B$846,"FORA DO CATÁLOGO") -> ACE004CU | C54: 5 | D54: =_xlfn.XLOOKUP(A54,CATÁLOGO!$A$2:$A$846,CATÁLOGO!$E$2:$E$846,"FORA DO CATÁLOGO") -> Ativo | F54: =SUMIFS('AVARIA PINHEIROS'!$C$2:$C$24,'AVARIA PINHEIROS'!$A$2:$A$24,A54) -> 0
A55: VLT-ACE-005-OFF-U | B55: =_xlfn.XLOOKUP(A55,CATÁLOGO!$A$2:$A$846,CATÁLOGO!$B$2:$B$846,"FORA DO CATÁLOGO") -> ACE005OU | C55: 2 | D55: =_xlfn.XLOOKUP(A55,CATÁLOGO!$A$2:$A$846,CATÁLOGO!$E$2:$E$846,"FORA DO CATÁLOGO") -> Ativo | F55: =SUMIFS('AVARIA PINHEIROS'!$C$2:$C$24,'AVARIA PINHEIROS'!$A$2:$A$24,A55) -> 0
A56: VLT-MOL-003-AZM-P | B56: =_xlfn.XLOOKUP(A56,CATÁLOGO!$A$2:$A$846,CATÁLOGO!$B$2:$B$846,"FORA DO CATÁLOGO") -> MOL003AP | C56: 2 | D56: =_xlfn.XLOOKUP(A56,CATÁLOGO!$A$2:$A$846,CATÁLOGO!$E$2:$E$846,"FORA DO CATÁLOGO") -> Ativo | F56: =SUMIFS('AVARIA PINHEIROS'!$C$2:$C$24,'AVARIA PINHEIROS'!$A$2:$A$24,A56) -> 0
A57: VLT-MOL-003-AZM-M | B57: =_xlfn.XLOOKUP(A57,CATÁLOGO!$A$2:$A$846,CATÁLOGO!$B$2:$B$846,"FORA DO CATÁLOGO") -> MOL003AM | C57: 3 | D57: =_xlfn.XLOOKUP(A57,CATÁLOGO!$A$2:$A$846,CATÁLOGO!$E$2:$E$846,"FORA DO CATÁLOGO") -> Ativo | F57: =SUMIFS('AVARIA PINHEIROS'!$C$2:$C$24,'AVARIA PINHEIROS'!$A$2:$A$24,A57) -> 0
A58: VLT-MOL-003-AZM-G | B58: =_xlfn.XLOOKUP(A58,CATÁLOGO!$A$2:$A$846,CATÁLOGO!$B$2:$B$846,"FORA DO CATÁLOGO") -> MOL003AG | C58: 4 | D58: =_xlfn.XLOOKUP(A58,CATÁLOGO!$A$2:$A$846,CATÁLOGO!$E$2:$E$846,"FORA DO CATÁLOGO") -> Ativo | F58: =SUMIFS('AVARIA PINHEIROS'!$C$2:$C$24,'AVARIA PINHEIROS'!$A$2:$A$24,A58) -> 0
A59: VLT-MOL-003-AZM-GG | B59: =_xlfn.XLOOKUP(A59,CATÁLOGO!$A$2:$A$846,CATÁLOGO!$B$2:$B$846,"FORA DO CATÁLOGO") -> MOL003AGG | C59: 2 | D59: =_xlfn.XLOOKUP(A59,CATÁLOGO!$A$2:$A$846,CATÁLOGO!$E$2:$E$846,"FORA DO CATÁLOGO") -> Ativo | F59: =SUMIFS('AVARIA PINHEIROS'!$C$2:$C$24,'AVARIA PINHEIROS'!$A$2:$A$24,A59) -> 0
A60: VLT-MOL-003-BEG-M | B60: =_xlfn.XLOOKUP(A60,CATÁLOGO!$A$2:$A$846,CATÁLOGO!$B$2:$B$846,"FORA DO CATÁLOGO") -> MOL003GM | C60: 4 | D60: =_xlfn.XLOOKUP(A60,CATÁLOGO!$A$2:$A$846,CATÁLOGO!$E$2:$E$846,"FORA DO CATÁLOGO") -> Ativo | F60: =SUMIFS('AVARIA PINHEIROS'!$C$2:$C$24,'AVARIA PINHEIROS'!$A$2:$A$24,A60) -> 0
A61: VLT-MOL-003-BEG-G | B61: =_xlfn.XLOOKUP(A61,CATÁLOGO!$A$2:$A$846,CATÁLOGO!$B$2:$B$846,"FORA DO CATÁLOGO") -> MOL003GG | C61: 2 | D61: =_xlfn.XLOOKUP(A61,CATÁLOGO!$A$2:$A$846,CATÁLOGO!$E$2:$E$846,"FORA DO CATÁLOGO") -> Ativo | F61: =SUMIFS('AVARIA PINHEIROS'!$C$2:$C$24,'AVARIA PINHEIROS'!$A$2:$A$24,A61) -> 0
A62: VLT-MOL-003-BEG-GG | B62: =_xlfn.XLOOKUP(A62,CATÁLOGO!$A$2:$A$846,CATÁLOGO!$B$2:$B$846,"FORA DO CATÁLOGO") -> MOL003GGG | C62: 1 | D62: =_xlfn.XLOOKUP(A62,CATÁLOGO!$A$2:$A$846,CATÁLOGO!$E$2:$E$846,"FORA DO CATÁLOGO") -> Ativo | F62: =SUMIFS('AVARIA PINHEIROS'!$C$2:$C$24,'AVARIA PINHEIROS'!$A$2:$A$24,A62) -> 0
A63: VLT-SAI-002-BRA-P | B63: =_xlfn.XLOOKUP(A63,CATÁLOGO!$A$2:$A$846,CATÁLOGO!$B$2:$B$846,"FORA DO CATÁLOGO") -> SAI002BP | C63: 2 | D63: =_xlfn.XLOOKUP(A63,CATÁLOGO!$A$2:$A$846,CATÁLOGO!$E$2:$E$846,"FORA DO CATÁLOGO") -> Ativo | E63: provador | F63: =SUMIFS('AVARIA PINHEIROS'!$C$2:$C$24,'AVARIA PINHEIROS'!$A$2:$A$24,A63) -> 0
A64: VLT-SAI-002-BRA-M | B64: =_xlfn.XLOOKUP(A64,CATÁLOGO!$A$2:$A$846,CATÁLOGO!$B$2:$B$846,"FORA DO CATÁLOGO") -> SAI002BM | C64: 3 | D64: =_xlfn.XLOOKUP(A64,CATÁLOGO!$A$2:$A$846,CATÁLOGO!$E$2:$E$846,"FORA DO CATÁLOGO") -> Ativo | F64: =SUMIFS('AVARIA PINHEIROS'!$C$2:$C$24,'AVARIA PINHEIROS'!$A$2:$A$24,A64) -> 0
A65: VLT-SAI-002-BRA-G | B65: =_xlfn.XLOOKUP(A65,CATÁLOGO!$A$2:$A$846,CATÁLOGO!$B$2:$B$846,"FORA DO CATÁLOGO") -> SAI002BG | C65: 2 | D65: =_xlfn.XLOOKUP(A65,CATÁLOGO!$A$2:$A$846,CATÁLOGO!$E$2:$E$846,"FORA DO CATÁLOGO") -> Ativo | F65: =SUMIFS('AVARIA PINHEIROS'!$C$2:$C$24,'AVARIA PINHEIROS'!$A$2:$A$24,A65) -> 0
A66: VLT-SAI-002-BRA-GG | B66: =_xlfn.XLOOKUP(A66,CATÁLOGO!$A$2:$A$846,CATÁLOGO!$B$2:$B$846,"FORA DO CATÁLOGO") -> SAI002BGG | C66: 1 | D66: =_xlfn.XLOOKUP(A66,CATÁLOGO!$A$2:$A$846,CATÁLOGO!$E$2:$E$846,"FORA DO CATÁLOGO") -> Ativo | F66: =SUMIFS('AVARIA PINHEIROS'!$C$2:$C$24,'AVARIA PINHEIROS'!$A$2:$A$24,A66) -> 0
A67: VLT-SAI-002-OFF-P | B67: =_xlfn.XLOOKUP(A67,CATÁLOGO!$A$2:$A$846,CATÁLOGO!$B$2:$B$846,"FORA DO CATÁLOGO") -> SAI002OP | C67: 1 | D67: =_xlfn.XLOOKUP(A67,CATÁLOGO!$A$2:$A$846,CATÁLOGO!$E$2:$E$846,"FORA DO CATÁLOGO") -> Descontinuado | E67: estoque cima | F67: =SUMIFS('AVARIA PINHEIROS'!$C$2:$C$24,'AVARIA PINHEIROS'!$A$2:$A$24,A67) -> 0
A68: VLT-SAI-002-OFF-GG | B68: =_xlfn.XLOOKUP(A68,CATÁLOGO!$A$2:$A$846,CATÁLOGO!$B$2:$B$846,"FORA DO CATÁLOGO") -> SAI002OGG | C68: 1 | D68: =_xlfn.XLOOKUP(A68,CATÁLOGO!$A$2:$A$846,CATÁLOGO!$E$2:$E$846,"FORA DO CATÁLOGO") -> Descontinuado | F68: =SUMIFS('AVARIA PINHEIROS'!$C$2:$C$24,'AVARIA PINHEIROS'!$A$2:$A$24,A68) -> 0
A69: VLT-CAL-006-JCL-XP | B69: =_xlfn.XLOOKUP(A69,CATÁLOGO!$A$2:$A$846,CATÁLOGO!$B$2:$B$846,"FORA DO CATÁLOGO") -> CAL006J36 | C69: 2 | D69: =_xlfn.XLOOKUP(A69,CATÁLOGO!$A$2:$A$846,CATÁLOGO!$E$2:$E$846,"FORA DO CATÁLOGO") -> Ativo | F69: =SUMIFS('AVARIA PINHEIROS'!$C$2:$C$24,'AVARIA PINHEIROS'!$A$2:$A$24,A69) -> 0
A70: VLT-CAL-006-JCL-P | B70: =_xlfn.XLOOKUP(A70,CATÁLOGO!$A$2:$A$846,CATÁLOGO!$B$2:$B$846,"FORA DO CATÁLOGO") -> CAL006J38 | C70: 2 | D70: =_xlfn.XLOOKUP(A70,CATÁLOGO!$A$2:$A$846,CATÁLOGO!$E$2:$E$846,"FORA DO CATÁLOGO") -> Ativo | F70: =SUMIFS('AVARIA PINHEIROS'!$C$2:$C$24,'AVARIA PINHEIROS'!$A$2:$A$24,A70) -> 0
A71: VLT-CAL-006-JCL-M | B71: =_xlfn.XLOOKUP(A71,CATÁLOGO!$A$2:$A$846,CATÁLOGO!$B$2:$B$846,"FORA DO CATÁLOGO") -> CAL006J40 | C71: 1 | D71: =_xlfn.XLOOKUP(A71,CATÁLOGO!$A$2:$A$846,CATÁLOGO!$E$2:$E$846,"FORA DO CATÁLOGO") -> Ativo | F71: =SUMIFS('AVARIA PINHEIROS'!$C$2:$C$24,'AVARIA PINHEIROS'!$A$2:$A$24,A71) -> 0
A72: VLT-CAL-006-JCL-G | B72: =_xlfn.XLOOKUP(A72,CATÁLOGO!$A$2:$A$846,CATÁLOGO!$B$2:$B$846,"FORA DO CATÁLOGO") -> CAL006J42 | C72: 2 | D72: =_xlfn.XLOOKUP(A72,CATÁLOGO!$A$2:$A$846,CATÁLOGO!$E$2:$E$846,"FORA DO CATÁLOGO") -> Ativo | F72: =SUMIFS('AVARIA PINHEIROS'!$C$2:$C$24,'AVARIA PINHEIROS'!$A$2:$A$24,A72) -> 0
A73: VLT-CAL-006-JCL-GG | B73: =_xlfn.XLOOKUP(A73,CATÁLOGO!$A$2:$A$846,CATÁLOGO!$B$2:$B$846,"FORA DO CATÁLOGO") -> CAL006J44 | C73: 1 | D73: =_xlfn.XLOOKUP(A73,CATÁLOGO!$A$2:$A$846,CATÁLOGO!$E$2:$E$846,"FORA DO CATÁLOGO") -> Ativo | F73: =SUMIFS('AVARIA PINHEIROS'!$C$2:$C$24,'AVARIA PINHEIROS'!$A$2:$A$24,A73) -> 0
A74: VLT-CAL-006-BEG-G | B74: =_xlfn.XLOOKUP(A74,CATÁLOGO!$A$2:$A$846,CATÁLOGO!$B$2:$B$846,"FORA DO CATÁLOGO") -> CAL006G42 | C74: 1 | D74: =_xlfn.XLOOKUP(A74,CATÁLOGO!$A$2:$A$846,CATÁLOGO!$E$2:$E$846,"FORA DO CATÁLOGO") -> Descontinuado | F74: =SUMIFS('AVARIA PINHEIROS'!$C$2:$C$24,'AVARIA PINHEIROS'!$A$2:$A$24,A74) -> 0
A75: VLT-CAL-006-BEG-GG | B75: =_xlfn.XLOOKUP(A75,CATÁLOGO!$A$2:$A$846,CATÁLOGO!$B$2:$B$846,"FORA DO CATÁLOGO") -> CAL006G44 | C75: 1 | D75: =_xlfn.XLOOKUP(A75,CATÁLOGO!$A$2:$A$846,CATÁLOGO!$E$2:$E$846,"FORA DO CATÁLOGO") -> Descontinuado | F75: =SUMIFS('AVARIA PINHEIROS'!$C$2:$C$24,'AVARIA PINHEIROS'!$A$2:$A$24,A75) -> 0
A76: VLT-CAL-007-AZM-P | B76: =_xlfn.XLOOKUP(A76,CATÁLOGO!$A$2:$A$846,CATÁLOGO!$B$2:$B$846,"FORA DO CATÁLOGO") -> CAL007A38 | C76: 6 | D76: =_xlfn.XLOOKUP(A76,CATÁLOGO!$A$2:$A$846,CATÁLOGO!$E$2:$E$846,"FORA DO CATÁLOGO") -> Ativo | F76: =SUMIFS('AVARIA PINHEIROS'!$C$2:$C$24,'AVARIA PINHEIROS'!$A$2:$A$24,A76) -> 0
A77: VLT-CAL-007-AZM-M | B77: =_xlfn.XLOOKUP(A77,CATÁLOGO!$A$2:$A$846,CATÁLOGO!$B$2:$B$846,"FORA DO CATÁLOGO") -> CAL007A40 | C77: 7 | D77: =_xlfn.XLOOKUP(A77,CATÁLOGO!$A$2:$A$846,CATÁLOGO!$E$2:$E$846,"FORA DO CATÁLOGO") -> Ativo | F77: =SUMIFS('AVARIA PINHEIROS'!$C$2:$C$24,'AVARIA PINHEIROS'!$A$2:$A$24,A77) -> 0
A78: VLT-CAL-007-AZM-G | B78: =_xlfn.XLOOKUP(A78,CATÁLOGO!$A$2:$A$846,CATÁLOGO!$B$2:$B$846,"FORA DO CATÁLOGO") -> CAL007A42 | C78: 6 | D78: =_xlfn.XLOOKUP(A78,CATÁLOGO!$A$2:$A$846,CATÁLOGO!$E$2:$E$846,"FORA DO CATÁLOGO") -> Ativo | F78: =SUMIFS('AVARIA PINHEIROS'!$C$2:$C$24,'AVARIA PINHEIROS'!$A$2:$A$24,A78) -> 0
A79: VLT-CAL-007-AZM-GG | B79: =_xlfn.XLOOKUP(A79,CATÁLOGO!$A$2:$A$846,CATÁLOGO!$B$2:$B$846,"FORA DO CATÁLOGO") -> CAL007A44 | C79: 4 | D79: =_xlfn.XLOOKUP(A79,CATÁLOGO!$A$2:$A$846,CATÁLOGO!$E$2:$E$846,"FORA DO CATÁLOGO") -> Ativo | E79: provador | F79: =SUMIFS('AVARIA PINHEIROS'!$C$2:$C$24,'AVARIA PINHEIROS'!$A$2:$A$24,A79) -> 0
A80: VLT-TRI-004-BRA-P | B80: =_xlfn.XLOOKUP(A80,CATÁLOGO!$A$2:$A$846,CATÁLOGO!$B$2:$B$846,"FORA DO CATÁLOGO") -> TRI004BP | C80: 4 | D80: =_xlfn.XLOOKUP(A80,CATÁLOGO!$A$2:$A$846,CATÁLOGO!$E$2:$E$846,"FORA DO CATÁLOGO") -> Ativo | F80: =SUMIFS('AVARIA PINHEIROS'!$C$2:$C$24,'AVARIA PINHEIROS'!$A$2:$A$24,A80) -> 0
A81: VLT-TRI-004-BRA-M | B81: =_xlfn.XLOOKUP(A81,CATÁLOGO!$A$2:$A$846,CATÁLOGO!$B$2:$B$846,"FORA DO CATÁLOGO") -> TRI004BM | C81: 6 | D81: =_xlfn.XLOOKUP(A81,CATÁLOGO!$A$2:$A$846,CATÁLOGO!$E$2:$E$846,"FORA DO CATÁLOGO") -> Ativo | F81: =SUMIFS('AVARIA PINHEIROS'!$C$2:$C$24,'AVARIA PINHEIROS'!$A$2:$A$24,A81) -> 0
A82: VLT-TRI-004-BRA-G | B82: =_xlfn.XLOOKUP(A82,CATÁLOGO!$A$2:$A$846,CATÁLOGO!$B$2:$B$846,"FORA DO CATÁLOGO") -> TRI004BG | C82: 5 | D82: =_xlfn.XLOOKUP(A82,CATÁLOGO!$A$2:$A$846,CATÁLOGO!$E$2:$E$846,"FORA DO CATÁLOGO") -> Ativo | F82: =SUMIFS('AVARIA PINHEIROS'!$C$2:$C$24,'AVARIA PINHEIROS'!$A$2:$A$24,A82) -> 0
A83: VLT-TRI-004-BRA-GG | B83: =_xlfn.XLOOKUP(A83,CATÁLOGO!$A$2:$A$846,CATÁLOGO!$B$2:$B$846,"FORA DO CATÁLOGO") -> TRI004BGG | C83: 4 | D83: =_xlfn.XLOOKUP(A83,CATÁLOGO!$A$2:$A$846,CATÁLOGO!$E$2:$E$846,"FORA DO CATÁLOGO") -> Ativo | F83: =SUMIFS('AVARIA PINHEIROS'!$C$2:$C$24,'AVARIA PINHEIROS'!$A$2:$A$24,A83) -> 0
A84: VLT-CMS-001-BEG-P | B84: =_xlfn.XLOOKUP(A84,CATÁLOGO!$A$2:$A$846,CATÁLOGO!$B$2:$B$846,"FORA DO CATÁLOGO") -> CMS001GP | C84: 6 | D84: =_xlfn.XLOOKUP(A84,CATÁLOGO!$A$2:$A$846,CATÁLOGO!$E$2:$E$846,"FORA DO CATÁLOGO") -> Ativo | F84: =SUMIFS('AVARIA PINHEIROS'!$C$2:$C$24,'AVARIA PINHEIROS'!$A$2:$A$24,A84) -> 0
A85: VLT-CMS-001-BEG-M | B85: =_xlfn.XLOOKUP(A85,CATÁLOGO!$A$2:$A$846,CATÁLOGO!$B$2:$B$846,"FORA DO CATÁLOGO") -> CMS001GM | C85: 6 | D85: =_xlfn.XLOOKUP(A85,CATÁLOGO!$A$2:$A$846,CATÁLOGO!$E$2:$E$846,"FORA DO CATÁLOGO") -> Ativo | F85: =SUMIFS('AVARIA PINHEIROS'!$C$2:$C$24,'AVARIA PINHEIROS'!$A$2:$A$24,A85) -> 0
A86: VLT-CMS-001-BEG-G | B86: =_xlfn.XLOOKUP(A86,CATÁLOGO!$A$2:$A$846,CATÁLOGO!$B$2:$B$846,"FORA DO CATÁLOGO") -> CMS001GG | C86: 6 | D86: =_xlfn.XLOOKUP(A86,CATÁLOGO!$A$2:$A$846,CATÁLOGO!$E$2:$E$846,"FORA DO CATÁLOGO") -> Ativo | E86: estoque cima | F86: =SUMIFS('AVARIA PINHEIROS'!$C$2:$C$24,'AVARIA PINHEIROS'!$A$2:$A$24,A86) -> 0
A87: VLT-CMS-001-BEG-GG | B87: =_xlfn.XLOOKUP(A87,CATÁLOGO!$A$2:$A$846,CATÁLOGO!$B$2:$B$846,"FORA DO CATÁLOGO") -> CMS001GGG | C87: 4 | D87: =_xlfn.XLOOKUP(A87,CATÁLOGO!$A$2:$A$846,CATÁLOGO!$E$2:$E$846,"FORA DO CATÁLOGO") -> Ativo | F87: =SUMIFS('AVARIA PINHEIROS'!$C$2:$C$24,'AVARIA PINHEIROS'!$A$2:$A$24,A87) -> 0
A88: VLT-CAM-002-AZM-XP | B88: =_xlfn.XLOOKUP(A88,CATÁLOGO!$A$2:$A$846,CATÁLOGO!$B$2:$B$846,"FORA DO CATÁLOGO") -> CAM002APP | C88: 1 | D88: =_xlfn.XLOOKUP(A88,CATÁLOGO!$A$2:$A$846,CATÁLOGO!$E$2:$E$846,"FORA DO CATÁLOGO") -> Ativo | F88: =SUMIFS('AVARIA PINHEIROS'!$C$2:$C$24,'AVARIA PINHEIROS'!$A$2:$A$24,A88) -> 0
A89: VLT-CAM-002-AZM-P | B89: =_xlfn.XLOOKUP(A89,CATÁLOGO!$A$2:$A$846,CATÁLOGO!$B$2:$B$846,"FORA DO CATÁLOGO") -> CAM002AP | C89: 2 | D89: =_xlfn.XLOOKUP(A89,CATÁLOGO!$A$2:$A$846,CATÁLOGO!$E$2:$E$846,"FORA DO CATÁLOGO") -> Ativo | E89: vitrine | F89: =SUMIFS('AVARIA PINHEIROS'!$C$2:$C$24,'AVARIA PINHEIROS'!$A$2:$A$24,A89) -> 0
A90: VLT-CAM-002-AZM-M | B90: =_xlfn.XLOOKUP(A90,CATÁLOGO!$A$2:$A$846,CATÁLOGO!$B$2:$B$846,"FORA DO CATÁLOGO") -> CAM002AM | C90: 5 | D90: =_xlfn.XLOOKUP(A90,CATÁLOGO!$A$2:$A$846,CATÁLOGO!$E$2:$E$846,"FORA DO CATÁLOGO") -> Ativo | F90: =SUMIFS('AVARIA PINHEIROS'!$C$2:$C$24,'AVARIA PINHEIROS'!$A$2:$A$24,A90) -> 0
A91: VLT-CAM-002-AZM-G | B91: =_xlfn.XLOOKUP(A91,CATÁLOGO!$A$2:$A$846,CATÁLOGO!$B$2:$B$846,"FORA DO CATÁLOGO") -> CAM002AG | C91: 4 | D91: =_xlfn.XLOOKUP(A91,CATÁLOGO!$A$2:$A$846,CATÁLOGO!$E$2:$E$846,"FORA DO CATÁLOGO") -> Ativo | F91: =SUMIFS('AVARIA PINHEIROS'!$C$2:$C$24,'AVARIA PINHEIROS'!$A$2:$A$24,A91) -> 0
A92: VLT-CAM-002-AZM-GG | B92: =_xlfn.XLOOKUP(A92,CATÁLOGO!$A$2:$A$846,CATÁLOGO!$B$2:$B$846,"FORA DO CATÁLOGO") -> CAM002AGG | C92: 2 | D92: =_xlfn.XLOOKUP(A92,CATÁLOGO!$A$2:$A$846,CATÁLOGO!$E$2:$E$846,"FORA DO CATÁLOGO") -> Ativo | F92: =SUMIFS('AVARIA PINHEIROS'!$C$2:$C$24,'AVARIA PINHEIROS'!$A$2:$A$24,A92) -> 0
A93: VLT-CMS-002-BEG-P | B93: =_xlfn.XLOOKUP(A93,CATÁLOGO!$A$2:$A$846,CATÁLOGO!$B$2:$B$846,"FORA DO CATÁLOGO") -> CMS002GP | C93: 6 | D93: =_xlfn.XLOOKUP(A93,CATÁLOGO!$A$2:$A$846,CATÁLOGO!$E$2:$E$846,"FORA DO CATÁLOGO") -> Ativo | F93: =SUMIFS('AVARIA PINHEIROS'!$C$2:$C$24,'AVARIA PINHEIROS'!$A$2:$A$24,A93) -> 0
A94: VLT-CMS-002-BEG-M | B94: =_xlfn.XLOOKUP(A94,CATÁLOGO!$A$2:$A$846,CATÁLOGO!$B$2:$B$846,"FORA DO CATÁLOGO") -> CMS002GM | C94: 6 | D94: =_xlfn.XLOOKUP(A94,CATÁLOGO!$A$2:$A$846,CATÁLOGO!$E$2:$E$846,"FORA DO CATÁLOGO") -> Ativo | F94: =SUMIFS('AVARIA PINHEIROS'!$C$2:$C$24,'AVARIA PINHEIROS'!$A$2:$A$24,A94) -> 0
A95: VLT-CMS-002-BEG-G | B95: =_xlfn.XLOOKUP(A95,CATÁLOGO!$A$2:$A$846,CATÁLOGO!$B$2:$B$846,"FORA DO CATÁLOGO") -> CMS002GG | C95: 5 | D95: =_xlfn.XLOOKUP(A95,CATÁLOGO!$A$2:$A$846,CATÁLOGO!$E$2:$E$846,"FORA DO CATÁLOGO") -> Ativo | F95: =SUMIFS('AVARIA PINHEIROS'!$C$2:$C$24,'AVARIA PINHEIROS'!$A$2:$A$24,A95) -> 0
A96: VLT-CMS-002-BEG-GG | B96: =_xlfn.XLOOKUP(A96,CATÁLOGO!$A$2:$A$846,CATÁLOGO!$B$2:$B$846,"FORA DO CATÁLOGO") -> CMS002GGG | C96: 4 | D96: =_xlfn.XLOOKUP(A96,CATÁLOGO!$A$2:$A$846,CATÁLOGO!$E$2:$E$846,"FORA DO CATÁLOGO") -> Ativo | E96: vitrine | F96: =SUMIFS('AVARIA PINHEIROS'!$C$2:$C$24,'AVARIA PINHEIROS'!$A$2:$A$24,A96) -> 0
A97: VLT-CAM-003-CIN-P | B97: =_xlfn.XLOOKUP(A97,CATÁLOGO!$A$2:$A$846,CATÁLOGO!$B$2:$B$846,"FORA DO CATÁLOGO") -> CAM003CP | C97: 3 | D97: =_xlfn.XLOOKUP(A97,CATÁLOGO!$A$2:$A$846,CATÁLOGO!$E$2:$E$846,"FORA DO CATÁLOGO") -> Ativo | F97: =SUMIFS('AVARIA PINHEIROS'!$C$2:$C$24,'AVARIA PINHEIROS'!$A$2:$A$24,A97) -> 0
A98: VLT-CAM-003-CIN-M | B98: =_xlfn.XLOOKUP(A98,CATÁLOGO!$A$2:$A$846,CATÁLOGO!$B$2:$B$846,"FORA DO CATÁLOGO") -> CAM003CM | C98: 3 | D98: =_xlfn.XLOOKUP(A98,CATÁLOGO!$A$2:$A$846,CATÁLOGO!$E$2:$E$846,"FORA DO CATÁLOGO") -> Ativo | F98: =SUMIFS('AVARIA PINHEIROS'!$C$2:$C$24,'AVARIA PINHEIROS'!$A$2:$A$24,A98) -> 0
A99: VLT-CAM-003-CIN-G | B99: =_xlfn.XLOOKUP(A99,CATÁLOGO!$A$2:$A$846,CATÁLOGO!$B$2:$B$846,"FORA DO CATÁLOGO") -> CAM003CG | C99: 2 | D99: =_xlfn.XLOOKUP(A99,CATÁLOGO!$A$2:$A$846,CATÁLOGO!$E$2:$E$846,"FORA DO CATÁLOGO") -> Ativo | E99: vitrine | F99: =SUMIFS('AVARIA PINHEIROS'!$C$2:$C$24,'AVARIA PINHEIROS'!$A$2:$A$24,A99) -> 0
A100: VLT-CAM-003-CIN-GG | B100: =_xlfn.XLOOKUP(A100,CATÁLOGO!$A$2:$A$846,CATÁLOGO!$B$2:$B$846,"FORA DO CATÁLOGO") -> CAM003CGG | C100: 1 | D100: =_xlfn.XLOOKUP(A100,CATÁLOGO!$A$2:$A$846,CATÁLOGO!$E$2:$E$846,"FORA DO CATÁLOGO") -> Ativo | F100: =SUMIFS('AVARIA PINHEIROS'!$C$2:$C$24,'AVARIA PINHEIROS'!$A$2:$A$24,A100) -> 0
A101: VLT-CAM-003-AZM-P | B101: =_xlfn.XLOOKUP(A101,CATÁLOGO!$A$2:$A$846,CATÁLOGO!$B$2:$B$846,"FORA DO CATÁLOGO") -> CAM003AP | C101: 1 | D101: =_xlfn.XLOOKUP(A101,CATÁLOGO!$A$2:$A$846,CATÁLOGO!$E$2:$E$846,"FORA DO CATÁLOGO") -> Ativo | F101: =SUMIFS('AVARIA PINHEIROS'!$C$2:$C$24,'AVARIA PINHEIROS'!$A$2:$A$24,A101) -> 0
...

Sheet ELDORADO
A1: SKU | B1: CÓDIGO CD | C1: QTD | D1: STATUS CATÁLOGO | E1: OBS | F1: AVARIA EST. | H1: RESUMO AVARIA – ELDORADO
A2: VLT-MOL-002-OLI-P | B2: =_xlfn.XLOOKUP(A2,CATÁLOGO!$A$2:$A$846,CATÁLOGO!$B$2:$B$846,"FORA DO CATÁLOGO") -> MOL002VP | C2: 1 | D2: =_xlfn.XLOOKUP(A2,CATÁLOGO!$A$2:$A$846,CATÁLOGO!$E$2:$E$846,"FORA DO CATÁLOGO") -> Fora do catálogo 2026 | E2: conferente: Jéssica | SKU só na Eldorado – existe na lista 2024 (fora do catálogo 2026), mantido | F2: =SUMIFS('AVARIA ESTIMADA'!$F$18:$F$40,'AVARIA ESTIMADA'!$A$18:$A$40,A2) -> 0 | H2: Tipo de avaria | I2: Estimada (decisão 13)
A3: VLT-CAL-001-OLI-XP | B3: =_xlfn.XLOOKUP(A3,CATÁLOGO!$A$2:$A$846,CATÁLOGO!$B$2:$B$846,"FORA DO CATÁLOGO") -> CAL001V36 | C3: 1 | D3: =_xlfn.XLOOKUP(A3,CATÁLOGO!$A$2:$A$846,CATÁLOGO!$E$2:$E$846,"FORA DO CATÁLOGO") -> Fora do catálogo 2026 | E3: conferente: Lari | SKU só na Eldorado – existe na lista 2024 (fora do catálogo 2026), mantido | F3: =SUMIFS('AVARIA ESTIMADA'!$F$18:$F$40,'AVARIA ESTIMADA'!$A$18:$A$40,A3) -> 0 | H3: Estoque contado (inclui avaria) | I3: =SUM(C2:C731) -> 2323
A4: VLT-CAL-001-OLI-P | B4: =_xlfn.XLOOKUP(A4,CATÁLOGO!$A$2:$A$846,CATÁLOGO!$B$2:$B$846,"FORA DO CATÁLOGO") -> CAL001V38 | C4: 1 | D4: =_xlfn.XLOOKUP(A4,CATÁLOGO!$A$2:$A$846,CATÁLOGO!$E$2:$E$846,"FORA DO CATÁLOGO") -> Fora do catálogo 2026 | E4: conferente: Thiago | F4: =SUMIFS('AVARIA ESTIMADA'!$F$18:$F$40,'AVARIA ESTIMADA'!$A$18:$A$40,A4) -> 0 | H4: Peças com avaria | I4: =SUM(F2:F731) -> 69
A5: VLT-CAL-001-OLI-G | B5: =_xlfn.XLOOKUP(A5,CATÁLOGO!$A$2:$A$846,CATÁLOGO!$B$2:$B$846,"FORA DO CATÁLOGO") -> CAL001V42 | C5: 1 | D5: =_xlfn.XLOOKUP(A5,CATÁLOGO!$A$2:$A$846,CATÁLOGO!$E$2:$E$846,"FORA DO CATÁLOGO") -> Fora do catálogo 2026 | E5: conferente: Lari | SKU só na Eldorado – existe na lista 2024 (fora do catálogo 2026), mantido | F5: =SUMIFS('AVARIA ESTIMADA'!$F$18:$F$40,'AVARIA ESTIMADA'!$A$18:$A$40,A5) -> 0 | H5: Estoque vendável | I5: =I3-I4 -> 2254
A6: VLT-CAL-001-OLI-GG | B6: =_xlfn.XLOOKUP(A6,CATÁLOGO!$A$2:$A$846,CATÁLOGO!$B$2:$B$846,"FORA DO CATÁLOGO") -> CAL001V44 | C6: 1 | D6: =_xlfn.XLOOKUP(A6,CATÁLOGO!$A$2:$A$846,CATÁLOGO!$E$2:$E$846,"FORA DO CATÁLOGO") -> Fora do catálogo 2026 | E6: conferente: Jéssica | SKU só na Eldorado – existe na lista 2024 (fora do catálogo 2026), mantido | F6: =SUMIFS('AVARIA ESTIMADA'!$F$18:$F$40,'AVARIA ESTIMADA'!$A$18:$A$40,A6) -> 0 | H6: % avaria | I6: =I4/I3 -> 0.02970297
A7: VLT-CAL-001-VIN-XP | B7: =_xlfn.XLOOKUP(A7,CATÁLOGO!$A$2:$A$846,CATÁLOGO!$B$2:$B$846,"FORA DO CATÁLOGO") -> CAL001H36 | C7: 1 | D7: =_xlfn.XLOOKUP(A7,CATÁLOGO!$A$2:$A$846,CATÁLOGO!$E$2:$E$846,"FORA DO CATÁLOGO") -> Fora do catálogo 2026 | E7: conferente: Jéssica | F7: =SUMIFS('AVARIA ESTIMADA'!$F$18:$F$40,'AVARIA ESTIMADA'!$A$18:$A$40,A7) -> 0 | H7: SKUs afetados | I7: =COUNTIF(F2:F731,">0") -> 20
A8: VLT-CAL-001-VIN-M | B8: =_xlfn.XLOOKUP(A8,CATÁLOGO!$A$2:$A$846,CATÁLOGO!$B$2:$B$846,"FORA DO CATÁLOGO") -> CAL001H40 | C8: 1 | D8: =_xlfn.XLOOKUP(A8,CATÁLOGO!$A$2:$A$846,CATÁLOGO!$E$2:$E$846,"FORA DO CATÁLOGO") -> Fora do catálogo 2026 | E8: conferente: Jéssica | SKU só na Eldorado – existe na lista 2024 (fora do catálogo 2026), mantido | F8: =SUMIFS('AVARIA ESTIMADA'!$F$18:$F$40,'AVARIA ESTIMADA'!$A$18:$A$40,A8) -> 0 | H8: % avaria – média das 4 lojas | I8: ='AVARIA ESTIMADA'!F14 -> 0.029957854
A9: VLT-CAL-001-VIN-GG | B9: =_xlfn.XLOOKUP(A9,CATÁLOGO!$A$2:$A$846,CATÁLOGO!$B$2:$B$846,"FORA DO CATÁLOGO") -> CAL001H44 | C9: 1 | D9: =_xlfn.XLOOKUP(A9,CATÁLOGO!$A$2:$A$846,CATÁLOGO!$E$2:$E$846,"FORA DO CATÁLOGO") -> Fora do catálogo 2026 | E9: conferente: Thiago | F9: =SUMIFS('AVARIA ESTIMADA'!$F$18:$F$40,'AVARIA ESTIMADA'!$A$18:$A$40,A9) -> 0
A10: VLT-TRI-003-PRE-G | B10: =_xlfn.XLOOKUP(A10,CATÁLOGO!$A$2:$A$846,CATÁLOGO!$B$2:$B$846,"FORA DO CATÁLOGO") -> FORA DO CATÁLOGO | C10: 1 | D10: =_xlfn.XLOOKUP(A10,CATÁLOGO!$A$2:$A$846,CATÁLOGO!$E$2:$E$846,"FORA DO CATÁLOGO") -> FORA DO CATÁLOGO | E10: conferente: Lari | código contado TRI003PG não existe (TRI-003 só em BEG/MRR na lista 2024) – mantido, não identificado | F10: =SUMIFS('AVARIA ESTIMADA'!$F$18:$F$40,'AVARIA ESTIMADA'!$A$18:$A$40,A10) -> 0 | H10: SKUs com avaria (maior → menor)
A11: VLT-SAI-001-BEG-M | B11: =_xlfn.XLOOKUP(A11,CATÁLOGO!$A$2:$A$846,CATÁLOGO!$B$2:$B$846,"FORA DO CATÁLOGO") -> SAI001GM | C11: 1 | D11: =_xlfn.XLOOKUP(A11,CATÁLOGO!$A$2:$A$846,CATÁLOGO!$E$2:$E$846,"FORA DO CATÁLOGO") -> Fora do catálogo 2026 | E11: conferente: Lari | SKU só na Eldorado – existe na lista 2024 (fora do catálogo 2026), mantido | F11: =SUMIFS('AVARIA ESTIMADA'!$F$18:$F$40,'AVARIA ESTIMADA'!$A$18:$A$40,A11) -> 0 | H11: SKU | I11: PEÇAS
A12: VLT-SAI-001-JCL-P | B12: =_xlfn.XLOOKUP(A12,CATÁLOGO!$A$2:$A$846,CATÁLOGO!$B$2:$B$846,"FORA DO CATÁLOGO") -> SAI001JP | C12: 1 | D12: =_xlfn.XLOOKUP(A12,CATÁLOGO!$A$2:$A$846,CATÁLOGO!$E$2:$E$846,"FORA DO CATÁLOGO") -> Fora do catálogo 2026 | E12: conferente: Jéssica | SKU só na Eldorado – existe na lista 2024 (fora do catálogo 2026), mantido | F12: =SUMIFS('AVARIA ESTIMADA'!$F$18:$F$40,'AVARIA ESTIMADA'!$A$18:$A$40,A12) -> 0 | H12: {=_xlfn._xlws.SORT(_xlfn._xlws.FILTER(_xlfn.HSTACK(A2:A731,F2:F731),F2:F731>0,"sem avaria"),2,-1)} -> VLT-CAL-003-PRE-G | I12: 6
A13: VLT-SAI-001-JCL-M | B13: =_xlfn.XLOOKUP(A13,CATÁLOGO!$A$2:$A$846,CATÁLOGO!$B$2:$B$846,"FORA DO CATÁLOGO") -> SAI001JM | C13: 1 | D13: =_xlfn.XLOOKUP(A13,CATÁLOGO!$A$2:$A$846,CATÁLOGO!$E$2:$E$846,"FORA DO CATÁLOGO") -> Fora do catálogo 2026 | E13: conferente: Jéssica | SKU só na Eldorado – existe na lista 2024 (fora do catálogo 2026), mantido | F13: =SUMIFS('AVARIA ESTIMADA'!$F$18:$F$40,'AVARIA ESTIMADA'!$A$18:$A$40,A13) -> 0 | H13: VLT-CAL-023-LIL-M | I13: 6
A14: VLT-BER-001-BRA-P | B14: =_xlfn.XLOOKUP(A14,CATÁLOGO!$A$2:$A$846,CATÁLOGO!$B$2:$B$846,"FORA DO CATÁLOGO") -> BER001B38 | C14: 6 | D14: =_xlfn.XLOOKUP(A14,CATÁLOGO!$A$2:$A$846,CATÁLOGO!$E$2:$E$846,"FORA DO CATÁLOGO") -> Ativo | E14: conferente: Thiago | F14: =SUMIFS('AVARIA ESTIMADA'!$F$18:$F$40,'AVARIA ESTIMADA'!$A$18:$A$40,A14) -> 0 | H14: VLT-TOP-006-MRR-G | I14: 5
A15: VLT-BER-001-BRA-M | B15: =_xlfn.XLOOKUP(A15,CATÁLOGO!$A$2:$A$846,CATÁLOGO!$B$2:$B$846,"FORA DO CATÁLOGO") -> BER001B40 | C15: 9 | D15: =_xlfn.XLOOKUP(A15,CATÁLOGO!$A$2:$A$846,CATÁLOGO!$E$2:$E$846,"FORA DO CATÁLOGO") -> Ativo | E15: conferente: Jéssica | F15: =SUMIFS('AVARIA ESTIMADA'!$F$18:$F$40,'AVARIA ESTIMADA'!$A$18:$A$40,A15) -> 0 | H15: VLT-CAL-011-LIL-P | I15: 5
A16: VLT-BER-001-BRA-G | B16: =_xlfn.XLOOKUP(A16,CATÁLOGO!$A$2:$A$846,CATÁLOGO!$B$2:$B$846,"FORA DO CATÁLOGO") -> BER001B42 | C16: 6 | D16: =_xlfn.XLOOKUP(A16,CATÁLOGO!$A$2:$A$846,CATÁLOGO!$E$2:$E$846,"FORA DO CATÁLOGO") -> Ativo | E16: conferente: Jéssica | F16: =SUMIFS('AVARIA ESTIMADA'!$F$18:$F$40,'AVARIA ESTIMADA'!$A$18:$A$40,A16) -> 0 | H16: VLT-CAL-024-AZM-P | I16: 5
A17: VLT-BER-001-BRA-GG | B17: =_xlfn.XLOOKUP(A17,CATÁLOGO!$A$2:$A$846,CATÁLOGO!$B$2:$B$846,"FORA DO CATÁLOGO") -> BER001B44 | C17: 3 | D17: =_xlfn.XLOOKUP(A17,CATÁLOGO!$A$2:$A$846,CATÁLOGO!$E$2:$E$846,"FORA DO CATÁLOGO") -> Ativo | E17: conferente: Thiago | F17: =SUMIFS('AVARIA ESTIMADA'!$F$18:$F$40,'AVARIA ESTIMADA'!$A$18:$A$40,A17) -> 0 | H17: VLT-TOP-001-AMA-G | I17: 5
A18: VLT-CAL-003-PRE-P | B18: =_xlfn.XLOOKUP(A18,CATÁLOGO!$A$2:$A$846,CATÁLOGO!$B$2:$B$846,"FORA DO CATÁLOGO") -> CAL003P38 | C18: 6 | D18: =_xlfn.XLOOKUP(A18,CATÁLOGO!$A$2:$A$846,CATÁLOGO!$E$2:$E$846,"FORA DO CATÁLOGO") -> Ativo | E18: conferente: Jéssica | F18: =SUMIFS('AVARIA ESTIMADA'!$F$18:$F$40,'AVARIA ESTIMADA'!$A$18:$A$40,A18) -> 0 | H18: VLT-VES-006-MRR-G | I18: 4
A19: VLT-CAL-003-PRE-M | B19: =_xlfn.XLOOKUP(A19,CATÁLOGO!$A$2:$A$846,CATÁLOGO!$B$2:$B$846,"FORA DO CATÁLOGO") -> CAL003P40 | C19: 6 | D19: =_xlfn.XLOOKUP(A19,CATÁLOGO!$A$2:$A$846,CATÁLOGO!$E$2:$E$846,"FORA DO CATÁLOGO") -> Ativo | E19: conferente: Lari | F19: =SUMIFS('AVARIA ESTIMADA'!$F$18:$F$40,'AVARIA ESTIMADA'!$A$18:$A$40,A19) -> 0 | H19: VLT-BER-007-AZM-G | I19: 4
A20: VLT-CAL-003-PRE-G | B20: =_xlfn.XLOOKUP(A20,CATÁLOGO!$A$2:$A$846,CATÁLOGO!$B$2:$B$846,"FORA DO CATÁLOGO") -> CAL003P42 | C20: 6 | D20: =_xlfn.XLOOKUP(A20,CATÁLOGO!$A$2:$A$846,CATÁLOGO!$E$2:$E$846,"FORA DO CATÁLOGO") -> Ativo | E20: conferente: Lari | F20: =SUMIFS('AVARIA ESTIMADA'!$F$18:$F$40,'AVARIA ESTIMADA'!$A$18:$A$40,A20) -> 6 | H20: VLT-CAM-017-AMA-G | I20: 4
A21: VLT-CAL-003-PRE-GG | B21: =_xlfn.XLOOKUP(A21,CATÁLOGO!$A$2:$A$846,CATÁLOGO!$B$2:$B$846,"FORA DO CATÁLOGO") -> CAL003P44 | C21: 3 | D21: =_xlfn.XLOOKUP(A21,CATÁLOGO!$A$2:$A$846,CATÁLOGO!$E$2:$E$846,"FORA DO CATÁLOGO") -> Ativo | E21: conferente: Jéssica | F21: =SUMIFS('AVARIA ESTIMADA'!$F$18:$F$40,'AVARIA ESTIMADA'!$A$18:$A$40,A21) -> 0 | H21: VLT-CAM-020-AMA-P | I21: 4
A22: VLT-CAL-004-CIN-XP | B22: =_xlfn.XLOOKUP(A22,CATÁLOGO!$A$2:$A$846,CATÁLOGO!$B$2:$B$846,"FORA DO CATÁLOGO") -> CAL004C36 | C22: 1 | D22: =_xlfn.XLOOKUP(A22,CATÁLOGO!$A$2:$A$846,CATÁLOGO!$E$2:$E$846,"FORA DO CATÁLOGO") -> Ativo | E22: conferente: Jéssica | F22: =SUMIFS('AVARIA ESTIMADA'!$F$18:$F$40,'AVARIA ESTIMADA'!$A$18:$A$40,A22) -> 0 | H22: VLT-CAM-020-AMA-G | I22: 4
A23: VLT-CAL-004-CIN-P | B23: =_xlfn.XLOOKUP(A23,CATÁLOGO!$A$2:$A$846,CATÁLOGO!$B$2:$B$846,"FORA DO CATÁLOGO") -> CAL004C38 | C23: 1 | D23: =_xlfn.XLOOKUP(A23,CATÁLOGO!$A$2:$A$846,CATÁLOGO!$E$2:$E$846,"FORA DO CATÁLOGO") -> Ativo | E23: conferente: Lari | F23: =SUMIFS('AVARIA ESTIMADA'!$F$18:$F$40,'AVARIA ESTIMADA'!$A$18:$A$40,A23) -> 0 | H23: VLT-VES-009-BEG-G | I23: 3
A24: VLT-CAL-004-CIN-M | B24: =_xlfn.XLOOKUP(A24,CATÁLOGO!$A$2:$A$846,CATÁLOGO!$B$2:$B$846,"FORA DO CATÁLOGO") -> CAL004C40 | C24: 2 | D24: =_xlfn.XLOOKUP(A24,CATÁLOGO!$A$2:$A$846,CATÁLOGO!$E$2:$E$846,"FORA DO CATÁLOGO") -> Ativo | E24: conferente: Thiago | F24: =SUMIFS('AVARIA ESTIMADA'!$F$18:$F$40,'AVARIA ESTIMADA'!$A$18:$A$40,A24) -> 0 | H24: VLT-CAM-004-PRE-M | I24: 2
... A31: VLT-CAL-004-BEG-XG | B31: =_xlfn.XLOOKUP(A31,CATÁLOGO!$A$2:$A$846,CATÁLOGO!$B$2:$B$846,"FORA DO CATÁLOGO") -> CAL004G46 | C31: 1 | D31: =_xlfn.XLOOKUP(A31,CATÁLOGO!$A$2:$A$846,CATÁLOGO!$E$2:$E$846,"FORA DO CATÁLOGO") -> Ativo | E31: conferente: Lari | F31: =SUMIFS('AVARIA ESTIMADA'!$F$18:$F$40,'AVARIA ESTIMADA'!$A$18:$A$40,A31) -> 0 | H31: VLT-SAI-009-BRA-P | I31: 1
A32: VLT-CAL-005-PRE-XP | B32: =_xlfn.XLOOKUP(A32,CATÁLOGO!$A$2:$A$846,CATÁLOGO!$B$2:$B$846,"FORA DO CATÁLOGO") -> CAL005P36 | C32: 3 | D32: =_xlfn.XLOOKUP(A32,CATÁLOGO!$A$2:$A$846,CATÁLOGO!$E$2:$E$846,"FORA DO CATÁLOGO") -> Ativo | E32: conferente: Lari | F32: =SUMIFS('AVARIA ESTIMADA'!$F$18:$F$40,'AVARIA ESTIMADA'!$A$18:$A$40,A32) -> 0
A33: VLT-CAL-005-PRE-P | B33: =_xlfn.XLOOKUP(A33,CATÁLOGO!$A$2:$A$846,CATÁLOGO!$B$2:$B$846,"FORA DO CATÁLOGO") -> CAL005P38 | C33: 6 | D33: =_xlfn.XLOOKUP(A33,CATÁLOGO!$A$2:$A$846,CATÁLOGO!$E$2:$E$846,"FORA DO CATÁLOGO") -> Ativo | E33: conferente: Jéssica | F33: =SUMIFS('AVARIA ESTIMADA'!$F$18:$F$40,'AVARIA ESTIMADA'!$A$18:$A$40,A33) -> 0
A34: VLT-CAL-005-PRE-M | B34: =_xlfn.XLOOKUP(A34,CATÁLOGO!$A$2:$A$846,CATÁLOGO!$B$2:$B$846,"FORA DO CATÁLOGO") -> CAL005P40 | C34: 6 | D34: =_xlfn.XLOOKUP(A34,CATÁLOGO!$A$2:$A$846,CATÁLOGO!$E$2:$E$846,"FORA DO CATÁLOGO") -> Ativo | E34: conferente: Thiago | F34: =SUMIFS('AVARIA ESTIMADA'!$F$18:$F$40,'AVARIA ESTIMADA'!$A$18:$A$40,A34) -> 0
A35: VLT-CAL-005-PRE-G | B35: =_xlfn.XLOOKUP(A35,CATÁLOGO!$A$2:$A$846,CATÁLOGO!$B$2:$B$846,"FORA DO CATÁLOGO") -> CAL005P42 | C35: 6 | D35: =_xlfn.XLOOKUP(A35,CATÁLOGO!$A$2:$A$846,CATÁLOGO!$E$2:$E$846,"FORA DO CATÁLOGO") -> Ativo | E35: conferente: Thiago | F35: =SUMIFS('AVARIA ESTIMADA'!$F$18:$F$40,'AVARIA ESTIMADA'!$A$18:$A$40,A35) -> 0
A36: VLT-CAL-005-PRE-GG | B36: =_xlfn.XLOOKUP(A36,CATÁLOGO!$A$2:$A$846,CATÁLOGO!$B$2:$B$846,"FORA DO CATÁLOGO") -> CAL005P44 | C36: 3 | D36: =_xlfn.XLOOKUP(A36,CATÁLOGO!$A$2:$A$846,CATÁLOGO!$E$2:$E$846,"FORA DO CATÁLOGO") -> Ativo | E36: conferente: Thiago | F36: =SUMIFS('AVARIA ESTIMADA'!$F$18:$F$40,'AVARIA ESTIMADA'!$A$18:$A$40,A36) -> 0
A37: VLT-TOP-002-AZM-P | B37: =_xlfn.XLOOKUP(A37,CATÁLOGO!$A$2:$A$846,CATÁLOGO!$B$2:$B$846,"FORA DO CATÁLOGO") -> TOP002AP | C37: 3 | D37: =_xlfn.XLOOKUP(A37,CATÁLOGO!$A$2:$A$846,CATÁLOGO!$E$2:$E$846,"FORA DO CATÁLOGO") -> Ativo | E37: conferente: Lari | F37: =SUMIFS('AVARIA ESTIMADA'!$F$18:$F$40,'AVARIA ESTIMADA'!$A$18:$A$40,A37) -> 0
A38: VLT-TOP-002-AZM-M | B38: =_xlfn.XLOOKUP(A38,CATÁLOGO!$A$2:$A$846,CATÁLOGO!$B$2:$B$846,"FORA DO CATÁLOGO") -> TOP002AM | C38: 5 | D38: =_xlfn.XLOOKUP(A38,CATÁLOGO!$A$2:$A$846,CATÁLOGO!$E$2:$E$846,"FORA DO CATÁLOGO") -> Ativo | E38: conferente: Thiago | F38: =SUMIFS('AVARIA ESTIMADA'!$F$18:$F$40,'AVARIA ESTIMADA'!$A$18:$A$40,A38) -> 0
A39: VLT-TOP-002-AZM-G | B39: =_xlfn.XLOOKUP(A39,CATÁLOGO!$A$2:$A$846,CATÁLOGO!$B$2:$B$846,"FORA DO CATÁLOGO") -> TOP002AG | C39: 4 | D39: =_xlfn.XLOOKUP(A39,CATÁLOGO!$A$2:$A$846,CATÁLOGO!$E$2:$E$846,"FORA DO CATÁLOGO") -> Ativo | E39: conferente: Jéssica | F39: =SUMIFS('AVARIA ESTIMADA'!$F$18:$F$40,'AVARIA ESTIMADA'!$A$18:$A$40,A39) -> 0
A40: VLT-TOP-002-AZM-GG | B40: =_xlfn.XLOOKUP(A40,CATÁLOGO!$A$2:$A$846,CATÁLOGO!$B$2:$B$846,"FORA DO CATÁLOGO") -> TOP002AGG | C40: 2 | D40: =_xlfn.XLOOKUP(A40,CATÁLOGO!$A$2:$A$846,CATÁLOGO!$E$2:$E$846,"FORA DO CATÁLOGO") -> Ativo | E40: conferente: Jéssica | F40: =SUMIFS('AVARIA ESTIMADA'!$F$18:$F$40,'AVARIA ESTIMADA'!$A$18:$A$40,A40) -> 0
A41: VLT-TOP-002-PRE-M | B41: =_xlfn.XLOOKUP(A41,CATÁLOGO!$A$2:$A$846,CATÁLOGO!$B$2:$B$846,"FORA DO CATÁLOGO") -> TOP002PM | C41: 2 | D41: =_xlfn.XLOOKUP(A41,CATÁLOGO!$A$2:$A$846,CATÁLOGO!$E$2:$E$846,"FORA DO CATÁLOGO") -> Descontinuado | E41: conferente: Thiago | SKU só na Eldorado – existe no catálogo (descontinuado), mantido | F41: =SUMIFS('AVARIA ESTIMADA'!$F$18:$F$40,'AVARIA ESTIMADA'!$A$18:$A$40,A41) -> 0
A42: VLT-TOP-002-PRE-G | B42: =_xlfn.XLOOKUP(A42,CATÁLOGO!$A$2:$A$846,CATÁLOGO!$B$2:$B$846,"FORA DO CATÁLOGO") -> TOP002PG | C42: 1 | D42: =_xlfn.XLOOKUP(A42,CATÁLOGO!$A$2:$A$846,CATÁLOGO!$E$2:$E$846,"FORA DO CATÁLOGO") -> Descontinuado | E42: conferente: Jéssica | F42: =SUMIFS('AVARIA ESTIMADA'!$F$18:$F$40,'AVARIA ESTIMADA'!$A$18:$A$40,A42) -> 0
A43: VLT-TOP-002-PRE-GG | B43: =_xlfn.XLOOKUP(A43,CATÁLOGO!$A$2:$A$846,CATÁLOGO!$B$2:$B$846,"FORA DO CATÁLOGO") -> TOP002PGG | C43: 1 | D43: =_xlfn.XLOOKUP(A43,CATÁLOGO!$A$2:$A$846,CATÁLOGO!$E$2:$E$846,"FORA DO CATÁLOGO") -> Descontinuado | E43: conferente: Jéssica | F43: =SUMIFS('AVARIA ESTIMADA'!$F$18:$F$40,'AVARIA ESTIMADA'!$A$18:$A$40,A43) -> 0
... A731: VLT-JAQ-011-OLI-GG | B731: =_xlfn.XLOOKUP(A731,CATÁLOGO!$A$2:$A$846,CATÁLOGO!$B$2:$B$846,"FORA DO CATÁLOGO") -> JAQ011VGG | C731: 3 | D731: =_xlfn.XLOOKUP(A731,CATÁLOGO!$A$2:$A$846,CATÁLOGO!$E$2:$E$846,"FORA DO CATÁLOGO") -> Ativo | E731: conferente: Lari | F731: =SUMIFS('AVARIA ESTIMADA'!$F$18:$F$40,'AVARIA ESTIMADA'!$A$18:$A$40,A731) -> 0

Sheet SAVASSI
A1: SKU | B1: CÓDIGO CD | C1: QTD | D1: STATUS CATÁLOGO | E1: OBS | F1: AVARIA EST. | H1: RESUMO AVARIA – SAVASSI
A2: VLT-CAL-001-VIN-G | B2: =_xlfn.XLOOKUP(A2,CATÁLOGO!$A$2:$A$846,CATÁLOGO!$B$2:$B$846,"FORA DO CATÁLOGO") -> CAL001H42 | C2: 1 | D2: =_xlfn.XLOOKUP(A2,CATÁLOGO!$A$2:$A$846,CATÁLOGO!$E$2:$E$846,"FORA DO CATÁLOGO") -> Fora do catálogo 2026 | E2: ESTOQUE SIMULADO | F2: =SUMIFS('AVARIA ESTIMADA'!$H$18:$H$40,'AVARIA ESTIMADA'!$A$18:$A$40,A2) -> 0 | H2: Tipo de avaria | I2: Estimada (decisão 13)
A3: VLT-BER-001-BRA-P | B3: =_xlfn.XLOOKUP(A3,CATÁLOGO!$A$2:$A$846,CATÁLOGO!$B$2:$B$846,"FORA DO CATÁLOGO") -> BER001B38 | C3: 6 | D3: =_xlfn.XLOOKUP(A3,CATÁLOGO!$A$2:$A$846,CATÁLOGO!$E$2:$E$846,"FORA DO CATÁLOGO") -> Ativo | E3: ESTOQUE SIMULADO | F3: =SUMIFS('AVARIA ESTIMADA'!$H$18:$H$40,'AVARIA ESTIMADA'!$A$18:$A$40,A3) -> 0 | H3: Estoque contado (inclui avaria) | I3: =SUM(C2:C720) -> 2114
A4: VLT-BER-001-BRA-M | B4: =_xlfn.XLOOKUP(A4,CATÁLOGO!$A$2:$A$846,CATÁLOGO!$B$2:$B$846,"FORA DO CATÁLOGO") -> BER001B40 | C4: 5 | D4: =_xlfn.XLOOKUP(A4,CATÁLOGO!$A$2:$A$846,CATÁLOGO!$E$2:$E$846,"FORA DO CATÁLOGO") -> Ativo | E4: ESTOQUE SIMULADO | F4: =SUMIFS('AVARIA ESTIMADA'!$H$18:$H$40,'AVARIA ESTIMADA'!$A$18:$A$40,A4) -> 0 | H4: Peças com avaria | I4: =SUM(F2:F720) -> 65
A5: VLT-BER-001-BRA-G | B5: =_xlfn.XLOOKUP(A5,CATÁLOGO!$A$2:$A$846,CATÁLOGO!$B$2:$B$846,"FORA DO CATÁLOGO") -> BER001B42 | C5: 5 | D5: =_xlfn.XLOOKUP(A5,CATÁLOGO!$A$2:$A$846,CATÁLOGO!$E$2:$E$846,"FORA DO CATÁLOGO") -> Ativo | E5: ESTOQUE SIMULADO | F5: =SUMIFS('AVARIA ESTIMADA'!$H$18:$H$40,'AVARIA ESTIMADA'!$A$18:$A$40,A5) -> 0 | H5: Estoque vendável | I5: =I3-I4 -> 2049
A6: VLT-BER-001-BRA-GG | B6: =_xlfn.XLOOKUP(A6,CATÁLOGO!$A$2:$A$846,CATÁLOGO!$B$2:$B$846,"FORA DO CATÁLOGO") -> BER001B44 | C6: 4 | D6: =_xlfn.XLOOKUP(A6,CATÁLOGO!$A$2:$A$846,CATÁLOGO!$E$2:$E$846,"FORA DO CATÁLOGO") -> Ativo | E6: ESTOQUE SIMULADO | F6: =SUMIFS('AVARIA ESTIMADA'!$H$18:$H$40,'AVARIA ESTIMADA'!$A$18:$A$40,A6) -> 0 | H6: % avaria | I6: =I4/I3 -> 0.030747398
A7: VLT-CAL-003-PRE-P | B7: =_xlfn.XLOOKUP(A7,CATÁLOGO!$A$2:$A$846,CATÁLOGO!$B$2:$B$846,"FORA DO CATÁLOGO") -> CAL003P38 | C7: 5 | D7: =_xlfn.XLOOKUP(A7,CATÁLOGO!$A$2:$A$846,CATÁLOGO!$E$2:$E$846,"FORA DO CATÁLOGO") -> Ativo | E7: ESTOQUE SIMULADO | F7: =SUMIFS('AVARIA ESTIMADA'!$H$18:$H$40,'AVARIA ESTIMADA'!$A$18:$A$40,A7) -> 0 | H7: SKUs afetados | I7: =COUNTIF(F2:F720,">0") -> 22
A8: VLT-CAL-003-PRE-M | B8: =_xlfn.XLOOKUP(A8,CATÁLOGO!$A$2:$A$846,CATÁLOGO!$B$2:$B$846,"FORA DO CATÁLOGO") -> CAL003P40 | C8: 5 | D8: =_xlfn.XLOOKUP(A8,CATÁLOGO!$A$2:$A$846,CATÁLOGO!$E$2:$E$846,"FORA DO CATÁLOGO") -> Ativo | E8: ESTOQUE SIMULADO | F8: =SUMIFS('AVARIA ESTIMADA'!$H$18:$H$40,'AVARIA ESTIMADA'!$A$18:$A$40,A8) -> 0 | H8: % avaria – média das 4 lojas | I8: ='AVARIA ESTIMADA'!F14 -> 0.029957854
A9: VLT-CAL-003-PRE-G | B9: =_xlfn.XLOOKUP(A9,CATÁLOGO!$A$2:$A$846,CATÁLOGO!$B$2:$B$846,"FORA DO CATÁLOGO") -> CAL003P42 | C9: 5 | D9: =_xlfn.XLOOKUP(A9,CATÁLOGO!$A$2:$A$846,CATÁLOGO!$E$2:$E$846,"FORA DO CATÁLOGO") -> Ativo | E9: ESTOQUE SIMULADO | F9: =SUMIFS('AVARIA ESTIMADA'!$H$18:$H$40,'AVARIA ESTIMADA'!$A$18:$A$40,A9) -> 5
A10: VLT-CAL-003-PRE-GG | B10: =_xlfn.XLOOKUP(A10,CATÁLOGO!$A$2:$A$846,CATÁLOGO!$B$2:$B$846,"FORA DO CATÁLOGO") -> CAL003P44 | C10: 3 | D10: =_xlfn.XLOOKUP(A10,CATÁLOGO!$A$2:$A$846,CATÁLOGO!$E$2:$E$846,"FORA DO CATÁLOGO") -> Ativo | E10: ESTOQUE SIMULADO | F10: =SUMIFS('AVARIA ESTIMADA'!$H$18:$H$40,'AVARIA ESTIMADA'!$A$18:$A$40,A10) -> 0 | H10: SKUs com avaria (maior → menor)
A11: VLT-CAL-004-CIN-XP | B11: =_xlfn.XLOOKUP(A11,CATÁLOGO!$A$2:$A$846,CATÁLOGO!$B$2:$B$846,"FORA DO CATÁLOGO") -> CAL004C36 | C11: 1 | D11: =_xlfn.XLOOKUP(A11,CATÁLOGO!$A$2:$A$846,CATÁLOGO!$E$2:$E$846,"FORA DO CATÁLOGO") -> Ativo | E11: ESTOQUE SIMULADO | F11: =SUMIFS('AVARIA ESTIMADA'!$H$18:$H$40,'AVARIA ESTIMADA'!$A$18:$A$40,A11) -> 0 | H11: SKU | I11: PEÇAS
A12: VLT-CAL-004-CIN-P | B12: =_xlfn.XLOOKUP(A12,CATÁLOGO!$A$2:$A$846,CATÁLOGO!$B$2:$B$846,"FORA DO CATÁLOGO") -> CAL004C38 | C12: 3 | D12: =_xlfn.XLOOKUP(A12,CATÁLOGO!$A$2:$A$846,CATÁLOGO!$E$2:$E$846,"FORA DO CATÁLOGO") -> Ativo | E12: ESTOQUE SIMULADO | F12: =SUMIFS('AVARIA ESTIMADA'!$H$18:$H$40,'AVARIA ESTIMADA'!$A$18:$A$40,A12) -> 0 | H12: {=_xlfn._xlws.SORT(_xlfn._xlws.FILTER(_xlfn.HSTACK(A2:A720,F2:F720),F2:F720>0,"sem avaria"),2,-1)} -> VLT-CAL-023-LIL-M | I12: 6
A13: VLT-CAL-004-CIN-M | B13: =_xlfn.XLOOKUP(A13,CATÁLOGO!$A$2:$A$846,CATÁLOGO!$B$2:$B$846,"FORA DO CATÁLOGO") -> CAL004C40 | C13: 3 | D13: =_xlfn.XLOOKUP(A13,CATÁLOGO!$A$2:$A$846,CATÁLOGO!$E$2:$E$846,"FORA DO CATÁLOGO") -> Ativo | E13: ESTOQUE SIMULADO | F13: =SUMIFS('AVARIA ESTIMADA'!$H$18:$H$40,'AVARIA ESTIMADA'!$A$18:$A$40,A13) -> 0 | H13: VLT-CAL-003-PRE-G | I13: 5
A14: VLT-CAL-004-CIN-G | B14: =_xlfn.XLOOKUP(A14,CATÁLOGO!$A$2:$A$846,CATÁLOGO!$B$2:$B$846,"FORA DO CATÁLOGO") -> CAL004C42 | C14: 2 | D14: =_xlfn.XLOOKUP(A14,CATÁLOGO!$A$2:$A$846,CATÁLOGO!$E$2:$E$846,"FORA DO CATÁLOGO") -> Ativo | E14: ESTOQUE SIMULADO | F14: =SUMIFS('AVARIA ESTIMADA'!$H$18:$H$40,'AVARIA ESTIMADA'!$A$18:$A$40,A14) -> 0 | H14: VLT-TOP-006-MRR-G | I14: 4
A15: VLT-CAL-004-CIN-GG | B15: =_xlfn.XLOOKUP(A15,CATÁLOGO!$A$2:$A$846,CATÁLOGO!$B$2:$B$846,"FORA DO CATÁLOGO") -> CAL004C44 | C15: 1 | D15: =_xlfn.XLOOKUP(A15,CATÁLOGO!$A$2:$A$846,CATÁLOGO!$E$2:$E$846,"FORA DO CATÁLOGO") -> Ativo | E15: ESTOQUE SIMULADO | F15: =SUMIFS('AVARIA ESTIMADA'!$H$18:$H$40,'AVARIA ESTIMADA'!$A$18:$A$40,A15) -> 0 | H15: VLT-CAL-011-LIL-P | I15: 4
A16: VLT-CAL-004-CIN-XG | B16: =_xlfn.XLOOKUP(A16,CATÁLOGO!$A$2:$A$846,CATÁLOGO!$B$2:$B$846,"FORA DO CATÁLOGO") -> CAL004C46 | C16: 1 | D16: =_xlfn.XLOOKUP(A16,CATÁLOGO!$A$2:$A$846,CATÁLOGO!$E$2:$E$846,"FORA DO CATÁLOGO") -> Ativo | E16: ESTOQUE SIMULADO | F16: =SUMIFS('AVARIA ESTIMADA'!$H$18:$H$40,'AVARIA ESTIMADA'!$A$18:$A$40,A16) -> 0 | H16: VLT-CAL-024-AZM-P | I16: 4
A17: VLT-CAL-004-BEG-XP | B17: =_xlfn.XLOOKUP(A17,CATÁLOGO!$A$2:$A$846,CATÁLOGO!$B$2:$B$846,"FORA DO CATÁLOGO") -> CAL004G36 | C17: 1 | D17: =_xlfn.XLOOKUP(A17,CATÁLOGO!$A$2:$A$846,CATÁLOGO!$E$2:$E$846,"FORA DO CATÁLOGO") -> Ativo | E17: ESTOQUE SIMULADO | F17: =SUMIFS('AVARIA ESTIMADA'!$H$18:$H$40,'AVARIA ESTIMADA'!$A$18:$A$40,A17) -> 0 | H17: VLT-TOP-001-AMA-G | I17: 4
A18: VLT-CAL-004-BEG-M | B18: =_xlfn.XLOOKUP(A18,CATÁLOGO!$A$2:$A$846,CATÁLOGO!$B$2:$B$846,"FORA DO CATÁLOGO") -> CAL004G40 | C18: 1 | D18: =_xlfn.XLOOKUP(A18,CATÁLOGO!$A$2:$A$846,CATÁLOGO!$E$2:$E$846,"FORA DO CATÁLOGO") -> Ativo | E18: ESTOQUE SIMULADO | F18: =SUMIFS('AVARIA ESTIMADA'!$H$18:$H$40,'AVARIA ESTIMADA'!$A$18:$A$40,A18) -> 0 | H18: VLT-CAM-020-AMA-G | I18: 4
A19: VLT-CAL-004-BEG-G | B19: =_xlfn.XLOOKUP(A19,CATÁLOGO!$A$2:$A$846,CATÁLOGO!$B$2:$B$846,"FORA DO CATÁLOGO") -> CAL004G42 | C19: 1 | D19: =_xlfn.XLOOKUP(A19,CATÁLOGO!$A$2:$A$846,CATÁLOGO!$E$2:$E$846,"FORA DO CATÁLOGO") -> Ativo | E19: ESTOQUE SIMULADO | F19: =SUMIFS('AVARIA ESTIMADA'!$H$18:$H$40,'AVARIA ESTIMADA'!$A$18:$A$40,A19) -> 0 | H19: VLT-VES-006-MRR-G | I19: 3
A20: VLT-CAL-004-BEG-GG | B20: =_xlfn.XLOOKUP(A20,CATÁLOGO!$A$2:$A$846,CATÁLOGO!$B$2:$B$846,"FORA DO CATÁLOGO") -> CAL004G44 | C20: 0 | D20: =_xlfn.XLOOKUP(A20,CATÁLOGO!$A$2:$A$846,CATÁLOGO!$E$2:$E$846,"FORA DO CATÁLOGO") -> Ativo | E20: ESTOQUE SIMULADO | F20: =SUMIFS('AVARIA ESTIMADA'!$H$18:$H$40,'AVARIA ESTIMADA'!$A$18:$A$40,A20) -> 0 | H20: VLT-CAL-016-OLI-P | I20: 3
A21: VLT-CAL-005-PRE-XP | B21: =_xlfn.XLOOKUP(A21,CATÁLOGO!$A$2:$A$846,CATÁLOGO!$B$2:$B$846,"FORA DO CATÁLOGO") -> CAL005P36 | C21: 4 | D21: =_xlfn.XLOOKUP(A21,CATÁLOGO!$A$2:$A$846,CATÁLOGO!$E$2:$E$846,"FORA DO CATÁLOGO") -> Ativo | E21: ESTOQUE SIMULADO | F21: =SUMIFS('AVARIA ESTIMADA'!$H$18:$H$40,'AVARIA ESTIMADA'!$A$18:$A$40,A21) -> 0 | H21: VLT-CAL-016-OLI-M | I21: 3
A22: VLT-CAL-005-PRE-P | B22: =_xlfn.XLOOKUP(A22,CATÁLOGO!$A$2:$A$846,CATÁLOGO!$B$2:$B$846,"FORA DO CATÁLOGO") -> CAL005P38 | C22: 5 | D22: =_xlfn.XLOOKUP(A22,CATÁLOGO!$A$2:$A$846,CATÁLOGO!$E$2:$E$846,"FORA DO CATÁLOGO") -> Ativo | E22: ESTOQUE SIMULADO | F22: =SUMIFS('AVARIA ESTIMADA'!$H$18:$H$40,'AVARIA ESTIMADA'!$A$18:$A$40,A22) -> 0 | H22: VLT-BER-007-AZM-G | I22: 3
A23: VLT-CAL-005-PRE-M | B23: =_xlfn.XLOOKUP(A23,CATÁLOGO!$A$2:$A$846,CATÁLOGO!$B$2:$B$846,"FORA DO CATÁLOGO") -> CAL005P40 | C23: 5 | D23: =_xlfn.XLOOKUP(A23,CATÁLOGO!$A$2:$A$846,CATÁLOGO!$E$2:$E$846,"FORA DO CATÁLOGO") -> Ativo | E23: ESTOQUE SIMULADO | F23: =SUMIFS('AVARIA ESTIMADA'!$H$18:$H$40,'AVARIA ESTIMADA'!$A$18:$A$40,A23) -> 0 | H23: VLT-CAM-017-AMA-G | I23: 3
A24: VLT-CAL-005-PRE-G | B24: =_xlfn.XLOOKUP(A24,CATÁLOGO!$A$2:$A$846,CATÁLOGO!$B$2:$B$846,"FORA DO CATÁLOGO") -> CAL005P42 | C24: 4 | D24: =_xlfn.XLOOKUP(A24,CATÁLOGO!$A$2:$A$846,CATÁLOGO!$E$2:$E$846,"FORA DO CATÁLOGO") -> Ativo | E24: ESTOQUE SIMULADO | F24: =SUMIFS('AVARIA ESTIMADA'!$H$18:$H$40,'AVARIA ESTIMADA'!$A$18:$A$40,A24) -> 0 | H24: VLT-VES-009-BEG-G | I24: 3
... A33: VLT-BER-002-CIN-P | B33: =_xlfn.XLOOKUP(A33,CATÁLOGO!$A$2:$A$846,CATÁLOGO!$B$2:$B$846,"FORA DO CATÁLOGO") -> BER002C38 | C33: 2 | D33: =_xlfn.XLOOKUP(A33,CATÁLOGO!$A$2:$A$846,CATÁLOGO!$E$2:$E$846,"FORA DO CATÁLOGO") -> Ativo | E33: ESTOQUE SIMULADO | F33: =SUMIFS('AVARIA ESTIMADA'!$H$18:$H$40,'AVARIA ESTIMADA'!$A$18:$A$40,A33) -> 0 | H33: VLT-TOP-010-AMA-M | I33: 1
A34: VLT-BER-002-CIN-M | B34: =_xlfn.XLOOKUP(A34,CATÁLOGO!$A$2:$A$846,CATÁLOGO!$B$2:$B$846,"FORA DO CATÁLOGO") -> BER002C40 | C34: 2 | D34: =_xlfn.XLOOKUP(A34,CATÁLOGO!$A$2:$A$846,CATÁLOGO!$E$2:$E$846,"FORA DO CATÁLOGO") -> Ativo | E34: ESTOQUE SIMULADO | F34: =SUMIFS('AVARIA ESTIMADA'!$H$18:$H$40,'AVARIA ESTIMADA'!$A$18:$A$40,A34) -> 0
A35: VLT-BER-002-CIN-G | B35: =_xlfn.XLOOKUP(A35,CATÁLOGO!$A$2:$A$846,CATÁLOGO!$B$2:$B$846,"FORA DO CATÁLOGO") -> BER002C42 | C35: 1 | D35: =_xlfn.XLOOKUP(A35,CATÁLOGO!$A$2:$A$846,CATÁLOGO!$E$2:$E$846,"FORA DO CATÁLOGO") -> Ativo | E35: ESTOQUE SIMULADO | F35: =SUMIFS('AVARIA ESTIMADA'!$H$18:$H$40,'AVARIA ESTIMADA'!$A$18:$A$40,A35) -> 0
A36: VLT-BER-002-CIN-GG | B36: =_xlfn.XLOOKUP(A36,CATÁLOGO!$A$2:$A$846,CATÁLOGO!$B$2:$B$846,"FORA DO CATÁLOGO") -> BER002C44 | C36: 1 | D36: =_xlfn.XLOOKUP(A36,CATÁLOGO!$A$2:$A$846,CATÁLOGO!$E$2:$E$846,"FORA DO CATÁLOGO") -> Ativo | E36: ESTOQUE SIMULADO | F36: =SUMIFS('AVARIA ESTIMADA'!$H$18:$H$40,'AVARIA ESTIMADA'!$A$18:$A$40,A36) -> 0
A37: VLT-BER-003-BRA-XP | B37: =_xlfn.XLOOKUP(A37,CATÁLOGO!$A$2:$A$846,CATÁLOGO!$B$2:$B$846,"FORA DO CATÁLOGO") -> BER003B36 | C37: 3 | D37: =_xlfn.XLOOKUP(A37,CATÁLOGO!$A$2:$A$846,CATÁLOGO!$E$2:$E$846,"FORA DO CATÁLOGO") -> Ativo | E37: ESTOQUE SIMULADO | F37: =SUMIFS('AVARIA ESTIMADA'!$H$18:$H$40,'AVARIA ESTIMADA'!$A$18:$A$40,A37) -> 0
A38: VLT-BER-003-BRA-P | B38: =_xlfn.XLOOKUP(A38,CATÁLOGO!$A$2:$A$846,CATÁLOGO!$B$2:$B$846,"FORA DO CATÁLOGO") -> BER003B38 | C38: 5 | D38: =_xlfn.XLOOKUP(A38,CATÁLOGO!$A$2:$A$846,CATÁLOGO!$E$2:$E$846,"FORA DO CATÁLOGO") -> Ativo | E38: ESTOQUE SIMULADO | F38: =SUMIFS('AVARIA ESTIMADA'!$H$18:$H$40,'AVARIA ESTIMADA'!$A$18:$A$40,A38) -> 0
A39: VLT-BER-003-BRA-M | B39: =_xlfn.XLOOKUP(A39,CATÁLOGO!$A$2:$A$846,CATÁLOGO!$B$2:$B$846,"FORA DO CATÁLOGO") -> BER003B40 | C39: 4 | D39: =_xlfn.XLOOKUP(A39,CATÁLOGO!$A$2:$A$846,CATÁLOGO!$E$2:$E$846,"FORA DO CATÁLOGO") -> Ativo | E39: ESTOQUE SIMULADO | F39: =SUMIFS('AVARIA ESTIMADA'!$H$18:$H$40,'AVARIA ESTIMADA'!$A$18:$A$40,A39) -> 0
A40: VLT-BER-003-BRA-G | B40: =_xlfn.XLOOKUP(A40,CATÁLOGO!$A$2:$A$846,CATÁLOGO!$B$2:$B$846,"FORA DO CATÁLOGO") -> BER003B42 | C40: 4 | D40: =_xlfn.XLOOKUP(A40,CATÁLOGO!$A$2:$A$846,CATÁLOGO!$E$2:$E$846,"FORA DO CATÁLOGO") -> Ativo | E40: ESTOQUE SIMULADO | F40: =SUMIFS('AVARIA ESTIMADA'!$H$18:$H$40,'AVARIA ESTIMADA'!$A$18:$A$40,A40) -> 0
A41: VLT-BER-003-BRA-GG | B41: =_xlfn.XLOOKUP(A41,CATÁLOGO!$A$2:$A$846,CATÁLOGO!$B$2:$B$846,"FORA DO CATÁLOGO") -> BER003B44 | C41: 4 | D41: =_xlfn.XLOOKUP(A41,CATÁLOGO!$A$2:$A$846,CATÁLOGO!$E$2:$E$846,"FORA DO CATÁLOGO") -> Ativo | E41: ESTOQUE SIMULADO | F41: =SUMIFS('AVARIA ESTIMADA'!$H$18:$H$40,'AVARIA ESTIMADA'!$A$18:$A$40,A41) -> 0
A42: VLT-BER-003-BRA-XG | B42: =_xlfn.XLOOKUP(A42,CATÁLOGO!$A$2:$A$846,CATÁLOGO!$B$2:$B$846,"FORA DO CATÁLOGO") -> BER003B46 | C42: 1 | D42: =_xlfn.XLOOKUP(A42,CATÁLOGO!$A$2:$A$846,CATÁLOGO!$E$2:$E$846,"FORA DO CATÁLOGO") -> Ativo | E42: ESTOQUE SIMULADO | F42: =SUMIFS('AVARIA ESTIMADA'!$H$18:$H$40,'AVARIA ESTIMADA'!$A$18:$A$40,A42) -> 0
A43: VLT-ACE-003-BEG-U | B43: =_xlfn.XLOOKUP(A43,CATÁLOGO!$A$2:$A$846,CATÁLOGO!$B$2:$B$846,"FORA DO CATÁLOGO") -> ACE003GU | C43: 6 | D43: =_xlfn.XLOOKUP(A43,CATÁLOGO!$A$2:$A$846,CATÁLOGO!$E$2:$E$846,"FORA DO CATÁLOGO") -> Ativo | E43: ESTOQUE SIMULADO | F43: =SUMIFS('AVARIA ESTIMADA'!$H$18:$H$40,'AVARIA ESTIMADA'!$A$18:$A$40,A43) -> 0
A44: VLT-CAM-001-CIN-P | B44: =_xlfn.XLOOKUP(A44,CATÁLOGO!$A$2:$A$846,CATÁLOGO!$B$2:$B$846,"FORA DO CATÁLOGO") -> CAM001CP | C44: 6 | D44: =_xlfn.XLOOKUP(A44,CATÁLOGO!$A$2:$A$846,CATÁLOGO!$E$2:$E$846,"FORA DO CATÁLOGO") -> Ativo | E44: ESTOQUE SIMULADO | F44: =SUMIFS('AVARIA ESTIMADA'!$H$18:$H$40,'AVARIA ESTIMADA'!$A$18:$A$40,A44) -> 0
A45: VLT-CAM-001-CIN-M | B45: =_xlfn.XLOOKUP(A45,CATÁLOGO!$A$2:$A$846,CATÁLOGO!$B$2:$B$846,"FORA DO CATÁLOGO") -> CAM001CM | C45: 6 | D45: =_xlfn.XLOOKUP(A45,CATÁLOGO!$A$2:$A$846,CATÁLOGO!$E$2:$E$846,"FORA DO CATÁLOGO") -> Ativo | E45: ESTOQUE SIMULADO | F45: =SUMIFS('AVARIA ESTIMADA'!$H$18:$H$40,'AVARIA ESTIMADA'!$A$18:$A$40,A45) -> 0
... A720: VLT-ACE-007-BEG-U | B720: =_xlfn.XLOOKUP(A720,CATÁLOGO!$A$2:$A$846,CATÁLOGO!$B$2:$B$846,"FORA DO CATÁLOGO") -> ACE007GU | C720: 5 | D720: =_xlfn.XLOOKUP(A720,CATÁLOGO!$A$2:$A$846,CATÁLOGO!$E$2:$E$846,"FORA DO CATÁLOGO") -> Descontinuado | E720: ESTOQUE SIMULADO | F720: =SUMIFS('AVARIA ESTIMADA'!$H$18:$H$40,'AVARIA ESTIMADA'!$A$18:$A$40,A720) -> 0

Sheet BATEL
A1: SKU | B1: CÓDIGO CD | C1: QTD | D1: STATUS CATÁLOGO | E1: OBS | F1: AVARIA EST. | H1: RESUMO AVARIA – BATEL
A2: VLT-CAL-001-OLI-P | B2: =_xlfn.XLOOKUP(A2,CATÁLOGO!$A$2:$A$846,CATÁLOGO!$B$2:$B$846,"FORA DO CATÁLOGO") -> CAL001V38 | C2: 1 | D2: =_xlfn.XLOOKUP(A2,CATÁLOGO!$A$2:$A$846,CATÁLOGO!$E$2:$E$846,"FORA DO CATÁLOGO") -> Fora do catálogo 2026 | E2: faltou contar provador | provador considerado 0 (decisão 15/10) | F2: =SUMIFS('AVARIA ESTIMADA'!$J$18:$J$40,'AVARIA ESTIMADA'!$A$18:$A$40,A2) -> 0 | H2: Tipo de avaria | I2: Estimada (decisão 13)
A3: VLT-CAL-001-VIN-XP | B3: =_xlfn.XLOOKUP(A3,CATÁLOGO!$A$2:$A$846,CATÁLOGO!$B$2:$B$846,"FORA DO CATÁLOGO") -> CAL001H36 | C3: 2 | D3: =_xlfn.XLOOKUP(A3,CATÁLOGO!$A$2:$A$846,CATÁLOGO!$E$2:$E$846,"FORA DO CATÁLOGO") -> Fora do catálogo 2026 | F3: =SUMIFS('AVARIA ESTIMADA'!$J$18:$J$40,'AVARIA ESTIMADA'!$A$18:$A$40,A3) -> 0 | H3: Estoque contado (inclui avaria) | I3: =SUM(C2:C721) -> 1904
A4: VLT-CAL-001-VIN-P | B4: =_xlfn.XLOOKUP(A4,CATÁLOGO!$A$2:$A$846,CATÁLOGO!$B$2:$B$846,"FORA DO CATÁLOGO") -> CAL001H38 | C4: 1 | D4: =_xlfn.XLOOKUP(A4,CATÁLOGO!$A$2:$A$846,CATÁLOGO!$E$2:$E$846,"FORA DO CATÁLOGO") -> Fora do catálogo 2026 | F4: =SUMIFS('AVARIA ESTIMADA'!$J$18:$J$40,'AVARIA ESTIMADA'!$A$18:$A$40,A4) -> 0 | H4: Peças com avaria | I4: =SUM(F2:F721) -> 49
A5: VLT-CAL-001-VIN-GG | B5: =_xlfn.XLOOKUP(A5,CATÁLOGO!$A$2:$A$846,CATÁLOGO!$B$2:$B$846,"FORA DO CATÁLOGO") -> CAL001H44 | C5: 1 | D5: =_xlfn.XLOOKUP(A5,CATÁLOGO!$A$2:$A$846,CATÁLOGO!$E$2:$E$846,"FORA DO CATÁLOGO") -> Fora do catálogo 2026 | F5: =SUMIFS('AVARIA ESTIMADA'!$J$18:$J$40,'AVARIA ESTIMADA'!$A$18:$A$40,A5) -> 0 | H5: Estoque vendável | I5: =I3-I4 -> 1855
A6: VLT-TRI-003-BEG-G | B6: =_xlfn.XLOOKUP(A6,CATÁLOGO!$A$2:$A$846,CATÁLOGO!$B$2:$B$846,"FORA DO CATÁLOGO") -> TRI003GG | C6: 1 | D6: =_xlfn.XLOOKUP(A6,CATÁLOGO!$A$2:$A$846,CATÁLOGO!$E$2:$E$846,"FORA DO CATÁLOGO") -> Fora do catálogo 2026 | F6: =SUMIFS('AVARIA ESTIMADA'!$J$18:$J$40,'AVARIA ESTIMADA'!$A$18:$A$40,A6) -> 0 | H6: % avaria | I6: =I4/I3 -> 0.025735294
A7: VLT-TRI-003-MRR-G | B7: =_xlfn.XLOOKUP(A7,CATÁLOGO!$A$2:$A$846,CATÁLOGO!$B$2:$B$846,"FORA DO CATÁLOGO") -> TRI003MG | C7: 1 | D7: =_xlfn.XLOOKUP(A7,CATÁLOGO!$A$2:$A$846,CATÁLOGO!$E$2:$E$846,"FORA DO CATÁLOGO") -> Fora do catálogo 2026 | F7: =SUMIFS('AVARIA ESTIMADA'!$J$18:$J$40,'AVARIA ESTIMADA'!$A$18:$A$40,A7) -> 0 | H7: SKUs afetados | I7: =COUNTIF(F2:F721,">0") -> 20
A8: VLT-SAI-001-PRE-GG | B8: =_xlfn.XLOOKUP(A8,CATÁLOGO!$A$2:$A$846,CATÁLOGO!$B$2:$B$846,"FORA DO CATÁLOGO") -> SAI001PGG | C8: 1 | D8: =_xlfn.XLOOKUP(A8,CATÁLOGO!$A$2:$A$846,CATÁLOGO!$E$2:$E$846,"FORA DO CATÁLOGO") -> Fora do catálogo 2026 | F8: =SUMIFS('AVARIA ESTIMADA'!$J$18:$J$40,'AVARIA ESTIMADA'!$A$18:$A$40,A8) -> 0 | H8: % avaria – média das 4 lojas | I8: ='AVARIA ESTIMADA'!F14 -> 0.029957854
A9: VLT-SAI-001-BEG-GG | B9: =_xlfn.XLOOKUP(A9,CATÁLOGO!$A$2:$A$846,CATÁLOGO!$B$2:$B$846,"FORA DO CATÁLOGO") -> SAI001GGG | C9: 1 | D9: =_xlfn.XLOOKUP(A9,CATÁLOGO!$A$2:$A$846,CATÁLOGO!$E$2:$E$846,"FORA DO CATÁLOGO") -> Fora do catálogo 2026 | F9: =SUMIFS('AVARIA ESTIMADA'!$J$18:$J$40,'AVARIA ESTIMADA'!$A$18:$A$40,A9) -> 0
A10: VLT-BER-001-BRA-M | B10: =_xlfn.XLOOKUP(A10,CATÁLOGO!$A$2:$A$846,CATÁLOGO!$B$2:$B$846,"FORA DO CATÁLOGO") -> BER001B40 | C10: 6 | D10: =_xlfn.XLOOKUP(A10,CATÁLOGO!$A$2:$A$846,CATÁLOGO!$E$2:$E$846,"FORA DO CATÁLOGO") -> Ativo | E10: faltou contar provador | provador considerado 0 (decisão 15/10) | F10: =SUMIFS('AVARIA ESTIMADA'!$J$18:$J$40,'AVARIA ESTIMADA'!$A$18:$A$40,A10) -> 0 | H10: SKUs com avaria (maior → menor)
A11: VLT-BER-001-BRA-G | B11: =_xlfn.XLOOKUP(A11,CATÁLOGO!$A$2:$A$846,CATÁLOGO!$B$2:$B$846,"FORA DO CATÁLOGO") -> BER001B42 | C11: 4 | D11: =_xlfn.XLOOKUP(A11,CATÁLOGO!$A$2:$A$846,CATÁLOGO!$E$2:$E$846,"FORA DO CATÁLOGO") -> Ativo | F11: =SUMIFS('AVARIA ESTIMADA'!$J$18:$J$40,'AVARIA ESTIMADA'!$A$18:$A$40,A11) -> 0 | H11: SKU | I11: PEÇAS
A12: VLT-BER-001-BRA-GG | B12: =_xlfn.XLOOKUP(A12,CATÁLOGO!$A$2:$A$846,CATÁLOGO!$B$2:$B$846,"FORA DO CATÁLOGO") -> BER001B44 | C12: 3 | D12: =_xlfn.XLOOKUP(A12,CATÁLOGO!$A$2:$A$846,CATÁLOGO!$E$2:$E$846,"FORA DO CATÁLOGO") -> Ativo | F12: =SUMIFS('AVARIA ESTIMADA'!$J$18:$J$40,'AVARIA ESTIMADA'!$A$18:$A$40,A12) -> 0 | H12: {=_xlfn._xlws.SORT(_xlfn._xlws.FILTER(_xlfn.HSTACK(A2:A721,F2:F721),F2:F721>0,"sem avaria"),2,-1)} -> VLT-CAL-023-LIL-M | I12: 5
A13: VLT-CAL-003-PRE-P | B13: =_xlfn.XLOOKUP(A13,CATÁLOGO!$A$2:$A$846,CATÁLOGO!$B$2:$B$846,"FORA DO CATÁLOGO") -> CAL003P38 | C13: 6 | D13: =_xlfn.XLOOKUP(A13,CATÁLOGO!$A$2:$A$846,CATÁLOGO!$E$2:$E$846,"FORA DO CATÁLOGO") -> Ativo | E13: recontar | QTD imputada pela mediana Pinheiros/Eldorado (contado: 5; decisão 15/10) | F13: =SUMIFS('AVARIA ESTIMADA'!$J$18:$J$40,'AVARIA ESTIMADA'!$A$18:$A$40,A13) -> 0 | H13: VLT-CAL-003-PRE-G | I13: 4
A14: VLT-CAL-003-PRE-M | B14: =_xlfn.XLOOKUP(A14,CATÁLOGO!$A$2:$A$846,CATÁLOGO!$B$2:$B$846,"FORA DO CATÁLOGO") -> CAL003P40 | C14: 5 | D14: =_xlfn.XLOOKUP(A14,CATÁLOGO!$A$2:$A$846,CATÁLOGO!$E$2:$E$846,"FORA DO CATÁLOGO") -> Ativo | F14: =SUMIFS('AVARIA ESTIMADA'!$J$18:$J$40,'AVARIA ESTIMADA'!$A$18:$A$40,A14) -> 0 | H14: VLT-CAL-011-LIL-P | I14: 4
A15: VLT-CAL-003-PRE-G | B15: =_xlfn.XLOOKUP(A15,CATÁLOGO!$A$2:$A$846,CATÁLOGO!$B$2:$B$846,"FORA DO CATÁLOGO") -> CAL003P42 | C15: 4 | D15: =_xlfn.XLOOKUP(A15,CATÁLOGO!$A$2:$A$846,CATÁLOGO!$E$2:$E$846,"FORA DO CATÁLOGO") -> Ativo | F15: =SUMIFS('AVARIA ESTIMADA'!$J$18:$J$40,'AVARIA ESTIMADA'!$A$18:$A$40,A15) -> 4 | H15: VLT-CAL-024-AZM-P | I15: 4
A16: VLT-CAL-003-PRE-GG | B16: =_xlfn.XLOOKUP(A16,CATÁLOGO!$A$2:$A$846,CATÁLOGO!$B$2:$B$846,"FORA DO CATÁLOGO") -> CAL003P44 | C16: 2 | D16: =_xlfn.XLOOKUP(A16,CATÁLOGO!$A$2:$A$846,CATÁLOGO!$E$2:$E$846,"FORA DO CATÁLOGO") -> Ativo | F16: =SUMIFS('AVARIA ESTIMADA'!$J$18:$J$40,'AVARIA ESTIMADA'!$A$18:$A$40,A16) -> 0 | H16: VLT-TOP-001-AMA-G | I16: 4
A17: VLT-CAL-004-CIN-XP | B17: =_xlfn.XLOOKUP(A17,CATÁLOGO!$A$2:$A$846,CATÁLOGO!$B$2:$B$846,"FORA DO CATÁLOGO") -> CAL004C36 | C17: 1 | D17: =_xlfn.XLOOKUP(A17,CATÁLOGO!$A$2:$A$846,CATÁLOGO!$E$2:$E$846,"FORA DO CATÁLOGO") -> Ativo | F17: =SUMIFS('AVARIA ESTIMADA'!$J$18:$J$40,'AVARIA ESTIMADA'!$A$18:$A$40,A17) -> 0 | H17: VLT-TOP-006-MRR-G | I17: 3
A18: VLT-CAL-004-CIN-P | B18: =_xlfn.XLOOKUP(A18,CATÁLOGO!$A$2:$A$846,CATÁLOGO!$B$2:$B$846,"FORA DO CATÁLOGO") -> CAL004C38 | C18: 1 | D18: =_xlfn.XLOOKUP(A18,CATÁLOGO!$A$2:$A$846,CATÁLOGO!$E$2:$E$846,"FORA DO CATÁLOGO") -> Ativo | F18: =SUMIFS('AVARIA ESTIMADA'!$J$18:$J$40,'AVARIA ESTIMADA'!$A$18:$A$40,A18) -> 0 | H18: VLT-VES-006-MRR-G | I18: 3
A19: VLT-CAL-004-CIN-M | B19: =_xlfn.XLOOKUP(A19,CATÁLOGO!$A$2:$A$846,CATÁLOGO!$B$2:$B$846,"FORA DO CATÁLOGO") -> CAL004C40 | C19: 3 | D19: =_xlfn.XLOOKUP(A19,CATÁLOGO!$A$2:$A$846,CATÁLOGO!$E$2:$E$846,"FORA DO CATÁLOGO") -> Ativo | F19: =SUMIFS('AVARIA ESTIMADA'!$J$18:$J$40,'AVARIA ESTIMADA'!$A$18:$A$40,A19) -> 0 | H19: VLT-CAM-017-AMA-G | I19: 3
A20: VLT-CAL-004-CIN-G | B20: =_xlfn.XLOOKUP(A20,CATÁLOGO!$A$2:$A$846,CATÁLOGO!$B$2:$B$846,"FORA DO CATÁLOGO") -> CAL004C42 | C20: 1 | D20: =_xlfn.XLOOKUP(A20,CATÁLOGO!$A$2:$A$846,CATÁLOGO!$E$2:$E$846,"FORA DO CATÁLOGO") -> Ativo | E20: faltou contar provador | provador considerado 0 (decisão 15/10) | F20: =SUMIFS('AVARIA ESTIMADA'!$J$18:$J$40,'AVARIA ESTIMADA'!$A$18:$A$40,A20) -> 0 | H20: VLT-CAM-020-AMA-G | I20: 3
A21: VLT-CAL-004-CIN-GG | B21: =_xlfn.XLOOKUP(A21,CATÁLOGO!$A$2:$A$846,CATÁLOGO!$B$2:$B$846,"FORA DO CATÁLOGO") -> CAL004C44 | C21: 1 | D21: =_xlfn.XLOOKUP(A21,CATÁLOGO!$A$2:$A$846,CATÁLOGO!$E$2:$E$846,"FORA DO CATÁLOGO") -> Ativo | F21: =SUMIFS('AVARIA ESTIMADA'!$J$18:$J$40,'AVARIA ESTIMADA'!$A$18:$A$40,A21) -> 0 | H21: VLT-CAM-004-PRE-M | I21: 2
A22: VLT-CAL-004-CIN-XG | B22: =_xlfn.XLOOKUP(A22,CATÁLOGO!$A$2:$A$846,CATÁLOGO!$B$2:$B$846,"FORA DO CATÁLOGO") -> CAL004C46 | C22: 1 | D22: =_xlfn.XLOOKUP(A22,CATÁLOGO!$A$2:$A$846,CATÁLOGO!$E$2:$E$846,"FORA DO CATÁLOGO") -> Ativo | E22: faltou contar provador | provador considerado 0 (decisão 15/10) | F22: =SUMIFS('AVARIA ESTIMADA'!$J$18:$J$40,'AVARIA ESTIMADA'!$A$18:$A$40,A22) -> 0 | H22: VLT-VES-007-OLI-GG | I22: 2
A23: VLT-CAL-004-BEG-XP | B23: =_xlfn.XLOOKUP(A23,CATÁLOGO!$A$2:$A$846,CATÁLOGO!$B$2:$B$846,"FORA DO CATÁLOGO") -> CAL004G36 | C23: 1 | D23: =_xlfn.XLOOKUP(A23,CATÁLOGO!$A$2:$A$846,CATÁLOGO!$E$2:$E$846,"FORA DO CATÁLOGO") -> Ativo | F23: =SUMIFS('AVARIA ESTIMADA'!$J$18:$J$40,'AVARIA ESTIMADA'!$A$18:$A$40,A23) -> 0 | H23: VLT-CAL-016-OLI-P | I23: 2
A24: VLT-CAL-004-BEG-P | B24: =_xlfn.XLOOKUP(A24,CATÁLOGO!$A$2:$A$846,CATÁLOGO!$B$2:$B$846,"FORA DO CATÁLOGO") -> CAL004G38 | C24: 1 | D24: =_xlfn.XLOOKUP(A24,CATÁLOGO!$A$2:$A$846,CATÁLOGO!$E$2:$E$846,"FORA DO CATÁLOGO") -> Ativo | F24: =SUMIFS('AVARIA ESTIMADA'!$J$18:$J$40,'AVARIA ESTIMADA'!$A$18:$A$40,A24) -> 0 | H24: VLT-BER-007-AZM-G | I24: 2
A25: VLT-CAL-004-BEG-G | B25: =_xlfn.XLOOKUP(A25,CATÁLOGO!$A$2:$A$846,CATÁLOGO!$B$2:$B$846,"FORA DO CATÁLOGO") -> CAL004G42 | C25: 1 | D25: =_xlfn.XLOOKUP(A25,CATÁLOGO!$A$2:$A$846,CATÁLOGO!$E$2:$E$846,"FORA DO CATÁLOGO") -> Ativo | E25: recontar | QTD imputada pela mediana Pinheiros/Eldorado (contado: 1; decisão 15/10) | F25: =SUMIFS('AVARIA ESTIMADA'!$J$18:$J$40,'AVARIA ESTIMADA'!$A$18:$A$40,A25) -> 0 | H25: VLT-VES-009-BEG-G | I25: 2
A26: VLT-CAL-004-BEG-GG | B26: =_xlfn.XLOOKUP(A26,CATÁLOGO!$A$2:$A$846,CATÁLOGO!$B$2:$B$846,"FORA DO CATÁLOGO") -> CAL004G44 | C26: 1 | D26: =_xlfn.XLOOKUP(A26,CATÁLOGO!$A$2:$A$846,CATÁLOGO!$E$2:$E$846,"FORA DO CATÁLOGO") -> Ativo | F26: =SUMIFS('AVARIA ESTIMADA'!$J$18:$J$40,'AVARIA ESTIMADA'!$A$18:$A$40,A26) -> 0 | H26: VLT-MOL-008-VIN-GG | I26: 1
A27: VLT-CAL-004-BEG-XG | B27: =_xlfn.XLOOKUP(A27,CATÁLOGO!$A$2:$A$846,CATÁLOGO!$B$2:$B$846,"FORA DO CATÁLOGO") -> CAL004G46 | C27: 1 | D27: =_xlfn.XLOOKUP(A27,CATÁLOGO!$A$2:$A$846,CATÁLOGO!$E$2:$E$846,"FORA DO CATÁLOGO") -> Ativo | F27: =SUMIFS('AVARIA ESTIMADA'!$J$18:$J$40,'AVARIA ESTIMADA'!$A$18:$A$40,A27) -> 0 | H27: VLT-TOP-010-AMA-M | I27: 1
A28: VLT-CAL-005-PRE-XP | B28: =_xlfn.XLOOKUP(A28,CATÁLOGO!$A$2:$A$846,CATÁLOGO!$B$2:$B$846,"FORA DO CATÁLOGO") -> CAL005P36 | C28: 3 | D28: =_xlfn.XLOOKUP(A28,CATÁLOGO!$A$2:$A$846,CATÁLOGO!$E$2:$E$846,"FORA DO CATÁLOGO") -> Ativo | F28: =SUMIFS('AVARIA ESTIMADA'!$J$18:$J$40,'AVARIA ESTIMADA'!$A$18:$A$40,A28) -> 0 | H28: VLT-BER-006-LIL-G | I28: 1
A29: VLT-CAL-005-PRE-P | B29: =_xlfn.XLOOKUP(A29,CATÁLOGO!$A$2:$A$846,CATÁLOGO!$B$2:$B$846,"FORA DO CATÁLOGO") -> CAL005P38 | C29: 5 | D29: =_xlfn.XLOOKUP(A29,CATÁLOGO!$A$2:$A$846,CATÁLOGO!$E$2:$E$846,"FORA DO CATÁLOGO") -> Ativo | F29: =SUMIFS('AVARIA ESTIMADA'!$J$18:$J$40,'AVARIA ESTIMADA'!$A$18:$A$40,A29) -> 0 | H29: VLT-CAL-016-OLI-M | I29: 1
A30: VLT-CAL-005-PRE-M | B30: =_xlfn.XLOOKUP(A30,CATÁLOGO!$A$2:$A$846,CATÁLOGO!$B$2:$B$846,"FORA DO CATÁLOGO") -> CAL005P40 | C30: 6 | D30: =_xlfn.XLOOKUP(A30,CATÁLOGO!$A$2:$A$846,CATÁLOGO!$E$2:$E$846,"FORA DO CATÁLOGO") -> Ativo | F30: =SUMIFS('AVARIA ESTIMADA'!$J$18:$J$40,'AVARIA ESTIMADA'!$A$18:$A$40,A30) -> 0 | H30: VLT-SAI-009-BRA-P | I30: 1
A31: VLT-CAL-005-PRE-G | B31: =_xlfn.XLOOKUP(A31,CATÁLOGO!$A$2:$A$846,CATÁLOGO!$B$2:$B$846,"FORA DO CATÁLOGO") -> CAL005P42 | C31: 4 | D31: =_xlfn.XLOOKUP(A31,CATÁLOGO!$A$2:$A$846,CATÁLOGO!$E$2:$E$846,"FORA DO CATÁLOGO") -> Ativo | F31: =SUMIFS('AVARIA ESTIMADA'!$J$18:$J$40,'AVARIA ESTIMADA'!$A$18:$A$40,A31) -> 0 | H31: VLT-MOL-019-OLI-GG | I31: 1
A32: VLT-CAL-005-PRE-GG | B32: =_xlfn.XLOOKUP(A32,CATÁLOGO!$A$2:$A$846,CATÁLOGO!$B$2:$B$846,"FORA DO CATÁLOGO") -> CAL005P44 | C32: 3 | D32: =_xlfn.XLOOKUP(A32,CATÁLOGO!$A$2:$A$846,CATÁLOGO!$E$2:$E$846,"FORA DO CATÁLOGO") -> Ativo | F32: =SUMIFS('AVARIA ESTIMADA'!$J$18:$J$40,'AVARIA ESTIMADA'!$A$18:$A$40,A32) -> 0
A33: VLT-TOP-002-AZM-P | B33: =_xlfn.XLOOKUP(A33,CATÁLOGO!$A$2:$A$846,CATÁLOGO!$B$2:$B$846,"FORA DO CATÁLOGO") -> TOP002AP | C33: 3 | D33: =_xlfn.XLOOKUP(A33,CATÁLOGO!$A$2:$A$846,CATÁLOGO!$E$2:$E$846,"FORA DO CATÁLOGO") -> Ativo | F33: =SUMIFS('AVARIA ESTIMADA'!$J$18:$J$40,'AVARIA ESTIMADA'!$A$18:$A$40,A33) -> 0
A34: VLT-TOP-002-AZM-M | B34: =_xlfn.XLOOKUP(A34,CATÁLOGO!$A$2:$A$846,CATÁLOGO!$B$2:$B$846,"FORA DO CATÁLOGO") -> TOP002AM | C34: 2 | D34: =_xlfn.XLOOKUP(A34,CATÁLOGO!$A$2:$A$846,CATÁLOGO!$E$2:$E$846,"FORA DO CATÁLOGO") -> Ativo | F34: =SUMIFS('AVARIA ESTIMADA'!$J$18:$J$40,'AVARIA ESTIMADA'!$A$18:$A$40,A34) -> 0
A35: VLT-TOP-002-AZM-G | B35: =_xlfn.XLOOKUP(A35,CATÁLOGO!$A$2:$A$846,CATÁLOGO!$B$2:$B$846,"FORA DO CATÁLOGO") -> TOP002AG | C35: 4 | D35: =_xlfn.XLOOKUP(A35,CATÁLOGO!$A$2:$A$846,CATÁLOGO!$E$2:$E$846,"FORA DO CATÁLOGO") -> Ativo | F35: =SUMIFS('AVARIA ESTIMADA'!$J$18:$J$40,'AVARIA ESTIMADA'!$A$18:$A$40,A35) -> 0
A36: VLT-TOP-002-AZM-GG | B36: =_xlfn.XLOOKUP(A36,CATÁLOGO!$A$2:$A$846,CATÁLOGO!$B$2:$B$846,"FORA DO CATÁLOGO") -> TOP002AGG | C36: 2 | D36: =_xlfn.XLOOKUP(A36,CATÁLOGO!$A$2:$A$846,CATÁLOGO!$E$2:$E$846,"FORA DO CATÁLOGO") -> Ativo | F36: =SUMIFS('AVARIA ESTIMADA'!$J$18:$J$40,'AVARIA ESTIMADA'!$A$18:$A$40,A36) -> 0
A37: VLT-BER-002-CIN-XP | B37: =_xlfn.XLOOKUP(A37,CATÁLOGO!$A$2:$A$846,CATÁLOGO!$B$2:$B$846,"FORA DO CATÁLOGO") -> BER002C36 | C37: 1 | D37: =_xlfn.XLOOKUP(A37,CATÁLOGO!$A$2:$A$846,CATÁLOGO!$E$2:$E$846,"FORA DO CATÁLOGO") -> Ativo | F37: =SUMIFS('AVARIA ESTIMADA'!$J$18:$J$40,'AVARIA ESTIMADA'!$A$18:$A$40,A37) -> 0
A38: VLT-BER-002-CIN-P | B38: =_xlfn.XLOOKUP(A38,CATÁLOGO!$A$2:$A$846,CATÁLOGO!$B$2:$B$846,"FORA DO CATÁLOGO") -> BER002C38 | C38: 2 | D38: =_xlfn.XLOOKUP(A38,CATÁLOGO!$A$2:$A$846,CATÁLOGO!$E$2:$E$846,"FORA DO CATÁLOGO") -> Ativo | F38: =SUMIFS('AVARIA ESTIMADA'!$J$18:$J$40,'AVARIA ESTIMADA'!$A$18:$A$40,A38) -> 0
A39: VLT-BER-002-CIN-M | B39: =_xlfn.XLOOKUP(A39,CATÁLOGO!$A$2:$A$846,CATÁLOGO!$B$2:$B$846,"FORA DO CATÁLOGO") -> BER002C40 | C39: 2 | D39: =_xlfn.XLOOKUP(A39,CATÁLOGO!$A$2:$A$846,CATÁLOGO!$E$2:$E$846,"FORA DO CATÁLOGO") -> Ativo | F39: =SUMIFS('AVARIA ESTIMADA'!$J$18:$J$40,'AVARIA ESTIMADA'!$A$18:$A$40,A39) -> 0
A40: VLT-BER-002-CIN-G | B40: =_xlfn.XLOOKUP(A40,CATÁLOGO!$A$2:$A$846,CATÁLOGO!$B$2:$B$846,"FORA DO CATÁLOGO") -> BER002C42 | C40: 1 | D40: =_xlfn.XLOOKUP(A40,CATÁLOGO!$A$2:$A$846,CATÁLOGO!$E$2:$E$846,"FORA DO CATÁLOGO") -> Ativo | F40: =SUMIFS('AVARIA ESTIMADA'!$J$18:$J$40,'AVARIA ESTIMADA'!$A$18:$A$40,A40) -> 0
A41: VLT-BER-002-CIN-GG | B41: =_xlfn.XLOOKUP(A41,CATÁLOGO!$A$2:$A$846,CATÁLOGO!$B$2:$B$846,"FORA DO CATÁLOGO") -> BER002C44 | C41: 1 | D41: =_xlfn.XLOOKUP(A41,CATÁLOGO!$A$2:$A$846,CATÁLOGO!$E$2:$E$846,"FORA DO CATÁLOGO") -> Ativo | F41: =SUMIFS('AVARIA ESTIMADA'!$J$18:$J$40,'AVARIA ESTIMADA'!$A$18:$A$40,A41) -> 0
A42: VLT-BER-003-BRA-XP | B42: =_xlfn.XLOOKUP(A42,CATÁLOGO!$A$2:$A$846,CATÁLOGO!$B$2:$B$846,"FORA DO CATÁLOGO") -> BER003B36 | C42: 2 | D42: =_xlfn.XLOOKUP(A42,CATÁLOGO!$A$2:$A$846,CATÁLOGO!$E$2:$E$846,"FORA DO CATÁLOGO") -> Ativo | F42: =SUMIFS('AVARIA ESTIMADA'!$J$18:$J$40,'AVARIA ESTIMADA'!$A$18:$A$40,A42) -> 0
A43: VLT-BER-003-BRA-P | B43: =_xlfn.XLOOKUP(A43,CATÁLOGO!$A$2:$A$846,CATÁLOGO!$B$2:$B$846,"FORA DO CATÁLOGO") -> BER003B38 | C43: 5 | D43: =_xlfn.XLOOKUP(A43,CATÁLOGO!$A$2:$A$846,CATÁLOGO!$E$2:$E$846,"FORA DO CATÁLOGO") -> Ativo | F43: =SUMIFS('AVARIA ESTIMADA'!$J$18:$J$40,'AVARIA ESTIMADA'!$A$18:$A$40,A43) -> 0
... A46: VLT-BER-003-BRA-GG | B46: =_xlfn.XLOOKUP(A46,CATÁLOGO!$A$2:$A$846,CATÁLOGO!$B$2:$B$846,"FORA DO CATÁLOGO") -> BER003B44 | C46: 2 | D46: =_xlfn.XLOOKUP(A46,CATÁLOGO!$A$2:$A$846,CATÁLOGO!$E$2:$E$846,"FORA DO CATÁLOGO") -> Ativo | F46: =SUMIFS('AVARIA ESTIMADA'!$J$18:$J$40,'AVARIA ESTIMADA'!$A$18:$A$40,A46) -> 0
A47: VLT-BER-003-BRA-XG | B47: =_xlfn.XLOOKUP(A47,CATÁLOGO!$A$2:$A$846,CATÁLOGO!$B$2:$B$846,"FORA DO CATÁLOGO") -> BER003B46 | C47: 1 | D47: =_xlfn.XLOOKUP(A47,CATÁLOGO!$A$2:$A$846,CATÁLOGO!$E$2:$E$846,"FORA DO CATÁLOGO") -> Ativo | E47: recontar | QTD imputada pela mediana Pinheiros/Eldorado (contado: 1; decisão 15/10) | F47: =SUMIFS('AVARIA ESTIMADA'!$J$18:$J$40,'AVARIA ESTIMADA'!$A$18:$A$40,A47) -> 0
A48: VLT-ACE-003-BEG-U | B48: =_xlfn.XLOOKUP(A48,CATÁLOGO!$A$2:$A$846,CATÁLOGO!$B$2:$B$846,"FORA DO CATÁLOGO") -> ACE003GU | C48: 5 | D48: =_xlfn.XLOOKUP(A48,CATÁLOGO!$A$2:$A$846,CATÁLOGO!$E$2:$E$846,"FORA DO CATÁLOGO") -> Ativo | F48: =SUMIFS('AVARIA ESTIMADA'!$J$18:$J$40,'AVARIA ESTIMADA'!$A$18:$A$40,A48) -> 0
A49: VLT-ACE-003-OFF-U | B49: =_xlfn.XLOOKUP(A49,CATÁLOGO!$A$2:$A$846,CATÁLOGO!$B$2:$B$846,"FORA DO CATÁLOGO") -> ACE003OU | C49: 4 | D49: =_xlfn.XLOOKUP(A49,CATÁLOGO!$A$2:$A$846,CATÁLOGO!$E$2:$E$846,"FORA DO CATÁLOGO") -> Descontinuado | F49: =SUMIFS('AVARIA ESTIMADA'!$J$18:$J$40,'AVARIA ESTIMADA'!$A$18:$A$40,A49) -> 0
A50: VLT-CAM-001-CIN-P | B50: =_xlfn.XLOOKUP(A50,CATÁLOGO!$A$2:$A$846,CATÁLOGO!$B$2:$B$846,"FORA DO CATÁLOGO") -> CAM001CP | C50: 4 | D50: =_xlfn.XLOOKUP(A50,CATÁLOGO!$A$2:$A$846,CATÁLOGO!$E$2:$E$846,"FORA DO CATÁLOGO") -> Ativo | F50: =SUMIFS('AVARIA ESTIMADA'!$J$18:$J$40,'AVARIA ESTIMADA'!$A$18:$A$40,A50) -> 0
A51: VLT-CAM-001-CIN-G | B51: =_xlfn.XLOOKUP(A51,CATÁLOGO!$A$2:$A$846,CATÁLOGO!$B$2:$B$846,"FORA DO CATÁLOGO") -> CAM001CG | C51: 5 | D51: =_xlfn.XLOOKUP(A51,CATÁLOGO!$A$2:$A$846,CATÁLOGO!$E$2:$E$846,"FORA DO CATÁLOGO") -> Ativo | F51: =SUMIFS('AVARIA ESTIMADA'!$J$18:$J$40,'AVARIA ESTIMADA'!$A$18:$A$40,A51) -> 0
A52: VLT-CAM-001-CIN-GG | B52: =_xlfn.XLOOKUP(A52,CATÁLOGO!$A$2:$A$846,CATÁLOGO!$B$2:$B$846,"FORA DO CATÁLOGO") -> CAM001CGG | C52: 2 | D52: =_xlfn.XLOOKUP(A52,CATÁLOGO!$A$2:$A$846,CATÁLOGO!$E$2:$E$846,"FORA DO CATÁLOGO") -> Ativo | F52: =SUMIFS('AVARIA ESTIMADA'!$J$18:$J$40,'AVARIA ESTIMADA'!$A$18:$A$40,A52) -> 0
A53: VLT-ACE-004-CIN-U | B53: =_xlfn.XLOOKUP(A53,CATÁLOGO!$A$2:$A$846,CATÁLOGO!$B$2:$B$846,"FORA DO CATÁLOGO") -> ACE004CU | C53: 5 | D53: =_xlfn.XLOOKUP(A53,CATÁLOGO!$A$2:$A$846,CATÁLOGO!$E$2:$E$846,"FORA DO CATÁLOGO") -> Ativo | F53: =SUMIFS('AVARIA ESTIMADA'!$J$18:$J$40,'AVARIA ESTIMADA'!$A$18:$A$40,A53) -> 0
A54: VLT-MOL-003-AZM-M | B54: =_xlfn.XLOOKUP(A54,CATÁLOGO!$A$2:$A$846,CATÁLOGO!$B$2:$B$846,"FORA DO CATÁLOGO") -> MOL003AM | C54: 3 | D54: =_xlfn.XLOOKUP(A54,CATÁLOGO!$A$2:$A$846,CATÁLOGO!$E$2:$E$846,"FORA DO CATÁLOGO") -> Ativo | F54: =SUMIFS('AVARIA ESTIMADA'!$J$18:$J$40,'AVARIA ESTIMADA'!$A$18:$A$40,A54) -> 0
A55: VLT-MOL-003-AZM-G | B55: =_xlfn.XLOOKUP(A55,CATÁLOGO!$A$2:$A$846,CATÁLOGO!$B$2:$B$846,"FORA DO CATÁLOGO") -> MOL003AG | C55: 2 | D55: =_xlfn.XLOOKUP(A55,CATÁLOGO!$A$2:$A$846,CATÁLOGO!$E$2:$E$846,"FORA DO CATÁLOGO") -> Ativo | F55: =SUMIFS('AVARIA ESTIMADA'!$J$18:$J$40,'AVARIA ESTIMADA'!$A$18:$A$40,A55) -> 0
A56: VLT-MOL-003-AZM-GG | B56: =_xlfn.XLOOKUP(A56,CATÁLOGO!$A$2:$A$846,CATÁLOGO!$B$2:$B$846,"FORA DO CATÁLOGO") -> MOL003AGG | C56: 1 | D56: =_xlfn.XLOOKUP(A56,CATÁLOGO!$A$2:$A$846,CATÁLOGO!$E$2:$E$846,"FORA DO CATÁLOGO") -> Ativo | F56: =SUMIFS('AVARIA ESTIMADA'!$J$18:$J$40,'AVARIA ESTIMADA'!$A$18:$A$40,A56) -> 0
A57: VLT-MOL-003-BEG-M | B57: =_xlfn.XLOOKUP(A57,CATÁLOGO!$A$2:$A$846,CATÁLOGO!$B$2:$B$846,"FORA DO CATÁLOGO") -> MOL003GM | C57: 1 | D57: =_xlfn.XLOOKUP(A57,CATÁLOGO!$A$2:$A$846,CATÁLOGO!$E$2:$E$846,"FORA DO CATÁLOGO") -> Ativo | F57: =SUMIFS('AVARIA ESTIMADA'!$J$18:$J$40,'AVARIA ESTIMADA'!$A$18:$A$40,A57) -> 0
A58: VLT-MOL-003-BEG-GG | B58: =_xlfn.XLOOKUP(A58,CATÁLOGO!$A$2:$A$846,CATÁLOGO!$B$2:$B$846,"FORA DO CATÁLOGO") -> MOL003GGG | C58: 2 | D58: =_xlfn.XLOOKUP(A58,CATÁLOGO!$A$2:$A$846,CATÁLOGO!$E$2:$E$846,"FORA DO CATÁLOGO") -> Ativo | F58: =SUMIFS('AVARIA ESTIMADA'!$J$18:$J$40,'AVARIA ESTIMADA'!$A$18:$A$40,A58) -> 0
A59: VLT-SAI-002-BRA-P | B59: =_xlfn.XLOOKUP(A59,CATÁLOGO!$A$2:$A$846,CATÁLOGO!$B$2:$B$846,"FORA DO CATÁLOGO") -> SAI002BP | C59: 1 | D59: =_xlfn.XLOOKUP(A59,CATÁLOGO!$A$2:$A$846,CATÁLOGO!$E$2:$E$846,"FORA DO CATÁLOGO") -> Ativo | F59: =SUMIFS('AVARIA ESTIMADA'!$J$18:$J$40,'AVARIA ESTIMADA'!$A$18:$A$40,A59) -> 0
... A70: VLT-CAL-007-AZM-P | B70: =_xlfn.XLOOKUP(A70,CATÁLOGO!$A$2:$A$846,CATÁLOGO!$B$2:$B$846,"FORA DO CATÁLOGO") -> CAL007A38 | C70: 6 | D70: =_xlfn.XLOOKUP(A70,CATÁLOGO!$A$2:$A$846,CATÁLOGO!$E$2:$E$846,"FORA DO CATÁLOGO") -> Ativo | F70: =SUMIFS('AVARIA ESTIMADA'!$J$18:$J$40,'AVARIA ESTIMADA'!$A$18:$A$40,A70) -> 0
A71: VLT-CAL-007-AZM-M | B71: =_xlfn.XLOOKUP(A71,CATÁLOGO!$A$2:$A$846,CATÁLOGO!$B$2:$B$846,"FORA DO CATÁLOGO") -> CAL007A40 | C71: 6 | D71: =_xlfn.XLOOKUP(A71,CATÁLOGO!$A$2:$A$846,CATÁLOGO!$E$2:$E$846,"FORA DO CATÁLOGO") -> Ativo | E71: faltou contar provador | provador considerado 0 (decisão 15/10) | F71: =SUMIFS('AVARIA ESTIMADA'!$J$18:$J$40,'AVARIA ESTIMADA'!$A$18:$A$40,A71) -> 0
A72: VLT-CAL-007-AZM-G | B72: =_xlfn.XLOOKUP(A72,CATÁLOGO!$A$2:$A$846,CATÁLOGO!$B$2:$B$846,"FORA DO CATÁLOGO") -> CAL007A42 | C72: 4 | D72: =_xlfn.XLOOKUP(A72,CATÁLOGO!$A$2:$A$846,CATÁLOGO!$E$2:$E$846,"FORA DO CATÁLOGO") -> Ativo | F72: =SUMIFS('AVARIA ESTIMADA'!$J$18:$J$40,'AVARIA ESTIMADA'!$A$18:$A$40,A72) -> 0
A73: VLT-CAL-007-AZM-GG | B73: =_xlfn.XLOOKUP(A73,CATÁLOGO!$A$2:$A$846,CATÁLOGO!$B$2:$B$846,"FORA DO CATÁLOGO") -> CAL007A44 | C73: 3 | D73: =_xlfn.XLOOKUP(A73,CATÁLOGO!$A$2:$A$846,CATÁLOGO!$E$2:$E$846,"FORA DO CATÁLOGO") -> Ativo | F73: =SUMIFS('AVARIA ESTIMADA'!$J$18:$J$40,'AVARIA ESTIMADA'!$A$18:$A$40,A73) -> 0
A74: VLT-TRI-004-BRA-P | B74: =_xlfn.XLOOKUP(A74,CATÁLOGO!$A$2:$A$846,CATÁLOGO!$B$2:$B$846,"FORA DO CATÁLOGO") -> TRI004BP | C74: 6 | D74: =_xlfn.XLOOKUP(A74,CATÁLOGO!$A$2:$A$846,CATÁLOGO!$E$2:$E$846,"FORA DO CATÁLOGO") -> Ativo | F74: =SUMIFS('AVARIA ESTIMADA'!$J$18:$J$40,'AVARIA ESTIMADA'!$A$18:$A$40,A74) -> 0
A75: VLT-TRI-004-BRA-M | B75: =_xlfn.XLOOKUP(A75,CATÁLOGO!$A$2:$A$846,CATÁLOGO!$B$2:$B$846,"FORA DO CATÁLOGO") -> TRI004BM | C75: 5 | D75: =_xlfn.XLOOKUP(A75,CATÁLOGO!$A$2:$A$846,CATÁLOGO!$E$2:$E$846,"FORA DO CATÁLOGO") -> Ativo | F75: =SUMIFS('AVARIA ESTIMADA'!$J$18:$J$40,'AVARIA ESTIMADA'!$A$18:$A$40,A75) -> 0
A76: VLT-TRI-004-BRA-G | B76: =_xlfn.XLOOKUP(A76,CATÁLOGO!$A$2:$A$846,CATÁLOGO!$B$2:$B$846,"FORA DO CATÁLOGO") -> TRI004BG | C76: 4 | D76: =_xlfn.XLOOKUP(A76,CATÁLOGO!$A$2:$A$846,CATÁLOGO!$E$2:$E$846,"FORA DO CATÁLOGO") -> Ativo | F76: =SUMIFS('AVARIA ESTIMADA'!$J$18:$J$40,'AVARIA ESTIMADA'!$A$18:$A$40,A76) -> 0
A77: VLT-TRI-004-BRA-GG | B77: =_xlfn.XLOOKUP(A77,CATÁLOGO!$A$2:$A$846,CATÁLOGO!$B$2:$B$846,"FORA DO CATÁLOGO") -> TRI004BGG | C77: 2 | D77: =_xlfn.XLOOKUP(A77,CATÁLOGO!$A$2:$A$846,CATÁLOGO!$E$2:$E$846,"FORA DO CATÁLOGO") -> Ativo | F77: =SUMIFS('AVARIA ESTIMADA'!$J$18:$J$40,'AVARIA ESTIMADA'!$A$18:$A$40,A77) -> 0
A78: VLT-CMS-001-BEG-P | B78: =_xlfn.XLOOKUP(A78,CATÁLOGO!$A$2:$A$846,CATÁLOGO!$B$2:$B$846,"FORA DO CATÁLOGO") -> CMS001GP | C78: 5 | D78: =_xlfn.XLOOKUP(A78,CATÁLOGO!$A$2:$A$846,CATÁLOGO!$E$2:$E$846,"FORA DO CATÁLOGO") -> Ativo | F78: =SUMIFS('AVARIA ESTIMADA'!$J$18:$J$40,'AVARIA ESTIMADA'!$A$18:$A$40,A78) -> 0
A79: VLT-CMS-001-BEG-M | B79: =_xlfn.XLOOKUP(A79,CATÁLOGO!$A$2:$A$846,CATÁLOGO!$B$2:$B$846,"FORA DO CATÁLOGO") -> CMS001GM | C79: 6 | D79: =_xlfn.XLOOKUP(A79,CATÁLOGO!$A$2:$A$846,CATÁLOGO!$E$2:$E$846,"FORA DO CATÁLOGO") -> Ativo | F79: =SUMIFS('AVARIA ESTIMADA'!$J$18:$J$40,'AVARIA ESTIMADA'!$A$18:$A$40,A79) -> 0
A80: VLT-CMS-001-BEG-G | B80: =_xlfn.XLOOKUP(A80,CATÁLOGO!$A$2:$A$846,CATÁLOGO!$B$2:$B$846,"FORA DO CATÁLOGO") -> CMS001GG | C80: 5 | D80: =_xlfn.XLOOKUP(A80,CATÁLOGO!$A$2:$A$846,CATÁLOGO!$E$2:$E$846,"FORA DO CATÁLOGO") -> Ativo | F80: =SUMIFS('AVARIA ESTIMADA'!$J$18:$J$40,'AVARIA ESTIMADA'!$A$18:$A$40,A80) -> 0
A81: VLT-CMS-001-BEG-GG | B81: =_xlfn.XLOOKUP(A81,CATÁLOGO!$A$2:$A$846,CATÁLOGO!$B$2:$B$846,"FORA DO CATÁLOGO") -> CMS001GGG | C81: 1 | D81: =_xlfn.XLOOKUP(A81,CATÁLOGO!$A$2:$A$846,CATÁLOGO!$E$2:$E$846,"FORA DO CATÁLOGO") -> Ativo | F81: =SUMIFS('AVARIA ESTIMADA'!$J$18:$J$40,'AVARIA ESTIMADA'!$A$18:$A$40,A81) -> 0
A82: VLT-CAM-002-AZM-XP | B82: =_xlfn.XLOOKUP(A82,CATÁLOGO!$A$2:$A$846,CATÁLOGO!$B$2:$B$846,"FORA DO CATÁLOGO") -> CAM002APP | C82: 1 | D82: =_xlfn.XLOOKUP(A82,CATÁLOGO!$A$2:$A$846,CATÁLOGO!$E$2:$E$846,"FORA DO CATÁLOGO") -> Ativo | F82: =SUMIFS('AVARIA ESTIMADA'!$J$18:$J$40,'AVARIA ESTIMADA'!$A$18:$A$40,A82) -> 0
A83: VLT-CAM-002-AZM-P | B83: =_xlfn.XLOOKUP(A83,CATÁLOGO!$A$2:$A$846,CATÁLOGO!$B$2:$B$846,"FORA DO CATÁLOGO") -> CAM002AP | C83: 2 | D83: =_xlfn.XLOOKUP(A83,CATÁLOGO!$A$2:$A$846,CATÁLOGO!$E$2:$E$846,"FORA DO CATÁLOGO") -> Ativo | F83: =SUMIFS('AVARIA ESTIMADA'!$J$18:$J$40,'AVARIA ESTIMADA'!$A$18:$A$40,A83) -> 0
... A93: VLT-CAM-003-CIN-GG | B93: =_xlfn.XLOOKUP(A93,CATÁLOGO!$A$2:$A$846,CATÁLOGO!$B$2:$B$846,"FORA DO CATÁLOGO") -> CAM003CGG | C93: 1 | D93: =_xlfn.XLOOKUP(A93,CATÁLOGO!$A$2:$A$846,CATÁLOGO!$E$2:$E$846,"FORA DO CATÁLOGO") -> Ativo | F93: =SUMIFS('AVARIA ESTIMADA'!$J$18:$J$40,'AVARIA ESTIMADA'!$A$18:$A$40,A93) -> 0
A94: VLT-CAM-003-AZM-P | B94: =_xlfn.XLOOKUP(A94,CATÁLOGO!$A$2:$A$846,CATÁLOGO!$B$2:$B$846,"FORA DO CATÁLOGO") -> CAM003AP | C94: 1 | D94: =_xlfn.XLOOKUP(A94,CATÁLOGO!$A$2:$A$846,CATÁLOGO!$E$2:$E$846,"FORA DO CATÁLOGO") -> Ativo | E94: recontar | QTD imputada pela mediana Pinheiros/Eldorado (contado: 1; decisão 15/10) | F94: =SUMIFS('AVARIA ESTIMADA'!$J$18:$J$40,'AVARIA ESTIMADA'!$A$18:$A$40,A94) -> 0
A95: VLT-CAM-003-AZM-M | B95: =_xlfn.XLOOKUP(A95,CATÁLOGO!$A$2:$A$846,CATÁLOGO!$B$2:$B$846,"FORA DO CATÁLOGO") -> CAM003AM | C95: 1 | D95: =_xlfn.XLOOKUP(A95,CATÁLOGO!$A$2:$A$846,CATÁLOGO!$E$2:$E$846,"FORA DO CATÁLOGO") -> Ativo | F95: =SUMIFS('AVARIA ESTIMADA'!$J$18:$J$40,'AVARIA ESTIMADA'!$A$18:$A$40,A95) -> 0
A96: VLT-CAM-003-AZM-G | B96: =_xlfn.XLOOKUP(A96,CATÁLOGO!$A$2:$A$846,CATÁLOGO!$B$2:$B$846,"FORA DO CATÁLOGO") -> CAM003AG | C96: 0 | D96: =_xlfn.XLOOKUP(A96,CATÁLOGO!$A$2:$A$846,CATÁLOGO!$E$2:$E$846,"FORA DO CATÁLOGO") -> Ativo | F96: =SUMIFS('AVARIA ESTIMADA'!$J$18:$J$40,'AVARIA ESTIMADA'!$A$18:$A$40,A96) -> 0
A97: VLT-CAM-003-AZM-GG | B97: =_xlfn.XLOOKUP(A97,CATÁLOGO!$A$2:$A$846,CATÁLOGO!$B$2:$B$846,"FORA DO CATÁLOGO") -> CAM003AGG | C97: 1 | D97: =_xlfn.XLOOKUP(A97,CATÁLOGO!$A$2:$A$846,CATÁLOGO!$E$2:$E$846,"FORA DO CATÁLOGO") -> Ativo | E97: recontar | QTD imputada pela mediana Pinheiros/Eldorado (contado: 1; decisão 15/10) | F97: =SUMIFS('AVARIA ESTIMADA'!$J$18:$J$40,'AVARIA ESTIMADA'!$A$18:$A$40,A97) -> 0
A98: VLT-MOL-004-BRA-P | B98: =_xlfn.XLOOKUP(A98,CATÁLOGO!$A$2:$A$846,CATÁLOGO!$B$2:$B$846,"FORA DO CATÁLOGO") -> MOL004BP | C98: 5 | D98: =_xlfn.XLOOKUP(A98,CATÁLOGO!$A$2:$A$846,CATÁLOGO!$E$2:$E$846,"FORA DO CATÁLOGO") -> Ativo | F98: =SUMIFS('AVARIA ESTIMADA'!$J$18:$J$40,'AVARIA ESTIMADA'!$A$18:$A$40,A98) -> 0
A99: VLT-MOL-004-BRA-M | B99: =_xlfn.XLOOKUP(A99,CATÁLOGO!$A$2:$A$846,CATÁLOGO!$B$2:$B$846,"FORA DO CATÁLOGO") -> MOL004BM | C99: 4 | D99: =_xlfn.XLOOKUP(A99,CATÁLOGO!$A$2:$A$846,CATÁLOGO!$E$2:$E$846,"FORA DO CATÁLOGO") -> Ativo | F99: =SUMIFS('AVARIA ESTIMADA'!$J$18:$J$40,'AVARIA ESTIMADA'!$A$18:$A$40,A99) -> 0
A100: VLT-MOL-004-BRA-G | B100: =_xlfn.XLOOKUP(A100,CATÁLOGO!$A$2:$A$846,CATÁLOGO!$B$2:$B$846,"FORA DO CATÁLOGO") -> MOL004BG | C100: 2 | D100: =_xlfn.XLOOKUP(A100,CATÁLOGO!$A$2:$A$846,CATÁLOGO!$E$2:$E$846,"FORA DO CATÁLOGO") -> Ativo | F100: =SUMIFS('AVARIA ESTIMADA'!$J$18:$J$40,'AVARIA ESTIMADA'!$A$18:$A$40,A100) -> 0
A101: VLT-MOL-004-BRA-GG | B101: =_xlfn.XLOOKUP(A101,CATÁLOGO!$A$2:$A$846,CATÁLOGO!$B$2:$B$846,"FORA DO CATÁLOGO") -> MOL004BGG | C101: 2 | D101: =_xlfn.XLOOKUP(A101,CATÁLOGO!$A$2:$A$846,CATÁLOGO!$E$2:$E$846,"FORA DO CATÁLOGO") -> Ativo | F101: =SUMIFS('AVARIA ESTIMADA'!$J$18:$J$40,'AVARIA ESTIMADA'!$A$18:$A$40,A101) -> 0
A102: VLT-CAM-004-BRA-P | B102: =_xlfn.XLOOKUP(A102,CATÁLOGO!$A$2:$A$846,CATÁLOGO!$B$2:$B$846,"FORA DO CATÁLOGO") -> CAM004BP | C102: 2 | D102: =_xlfn.XLOOKUP(A102,CATÁLOGO!$A$2:$A$846,CATÁLOGO!$E$2:$E$846,"FORA DO CATÁLOGO") -> Ativo | F102: =SUMIFS('AVARIA ESTIMADA'!$J$18:$J$40,'AVARIA ESTIMADA'!$A$18:$A$40,A102) -> 0
A103: VLT-CAM-004-BRA-M | B103: =_xlfn.XLOOKUP(A103,CATÁLOGO!$A$2:$A$846,CATÁLOGO!$B$2:$B$846,"FORA DO CATÁLOGO") -> CAM004BM | C103: 3 | D103: =_xlfn.XLOOKUP(A103,CATÁLOGO!$A$2:$A$846,CATÁLOGO!$E$2:$E$846,"FORA DO CATÁLOGO") -> Ativo | F103: =SUMIFS('AVARIA ESTIMADA'!$J$18:$J$40,'AVARIA ESTIMADA'!$A$18:$A$40,A103) -> 0
A104: VLT-CAM-004-BRA-G | B104: =_xlfn.XLOOKUP(A104,CATÁLOGO!$A$2:$A$846,CATÁLOGO!$B$2:$B$846,"FORA DO CATÁLOGO") -> CAM004BG | C104: 2 | D104: =_xlfn.XLOOKUP(A104,CATÁLOGO!$A$2:$A$846,CATÁLOGO!$E$2:$E$846,"FORA DO CATÁLOGO") -> Ativo | F104: =SUMIFS('AVARIA ESTIMADA'!$J$18:$J$40,'AVARIA ESTIMADA'!$A$18:$A$40,A104) -> 0
A105: VLT-CAM-004-BRA-GG | B105: =_xlfn.XLOOKUP(A105,CATÁLOGO!$A$2:$A$846,CATÁLOGO!$B$2:$B$846,"FORA DO CATÁLOGO") -> CAM004BGG | C105: 1 | D105: =_xlfn.XLOOKUP(A105,CATÁLOGO!$A$2:$A$846,CATÁLOGO!$E$2:$E$846,"FORA DO CATÁLOGO") -> Ativo | F105: =SUMIFS('AVARIA ESTIMADA'!$J$18:$J$40,'AVARIA ESTIMADA'!$A$18:$A$40,A105) -> 0
A106: VLT-CAM-004-CIN-P | B106: =_xlfn.XLOOKUP(A106,CATÁLOGO!$A$2:$A$846,CATÁLOGO!$B$2:$B$846,"FORA DO CATÁLOGO") -> CAM004CP | C106: 1 | D106: =_xlfn.XLOOKUP(A106,CATÁLOGO!$A$2:$A$846,CATÁLOGO!$E$2:$E$846,"FORA DO CATÁLOGO") -> Ativo | F106: =SUMIFS('AVARIA ESTIMADA'!$J$18:$J$40,'AVARIA ESTIMADA'!$A$18:$A$40,A106) -> 0
A107: VLT-CAM-004-CIN-M | B107: =_xlfn.XLOOKUP(A107,CATÁLOGO!$A$2:$A$846,CATÁLOGO!$B$2:$B$846,"FORA DO CATÁLOGO") -> CAM004CM | C107: 3 | D107: =_xlfn.XLOOKUP(A107,CATÁLOGO!$A$2:$A$846,CATÁLOGO!$E$2:$E$846,"FORA DO CATÁLOGO") -> Ativo | E107: recontar | QTD imputada pela mediana Pinheiros/Eldorado (contado: 2; decisão 15/10) | F107: =SUMIFS('AVARIA ESTIMADA'!$J$18:$J$40,'AVARIA ESTIMADA'!$A$18:$A$40,A107) -> 0
A108: VLT-CAM-004-CIN-GG | B108: =_xlfn.XLOOKUP(A108,CATÁLOGO!$A$2:$A$846,CATÁLOGO!$B$2:$B$846,"FORA DO CATÁLOGO") -> CAM004CGG | C108: 1 | D108: =_xlfn.XLOOKUP(A108,CATÁLOGO!$A$2:$A$846,CATÁLOGO!$E$2:$E$846,"FORA DO CATÁLOGO") -> Ativo | F108: =SUMIFS('AVARIA ESTIMADA'!$J$18:$J$40,'AVARIA ESTIMADA'!$A$18:$A$40,A108) -> 0
A109: VLT-CAM-004-PRE-P | B109: =_xlfn.XLOOKUP(A109,CATÁLOGO!$A$2:$A$846,CATÁLOGO!$B$2:$B$846,"FORA DO CATÁLOGO") -> CAM004PP | C109: 2 | D109: =_xlfn.XLOOKUP(A109,CATÁLOGO!$A$2:$A$846,CATÁLOGO!$E$2:$E$846,"FORA DO CATÁLOGO") -> Ativo | F109: =SUMIFS('AVARIA ESTIMADA'!$J$18:$J$40,'AVARIA ESTIMADA'!$A$18:$A$40,A109) -> 0
A110: VLT-CAM-004-PRE-M | B110: =_xlfn.XLOOKUP(A110,CATÁLOGO!$A$2:$A$846,CATÁLOGO!$B$2:$B$846,"FORA DO CATÁLOGO") -> CAM004PM | C110: 3 | D110: =_xlfn.XLOOKUP(A110,CATÁLOGO!$A$2:$A$846,CATÁLOGO!$E$2:$E$846,"FORA DO CATÁLOGO") -> Ativo | F110: =SUMIFS('AVARIA ESTIMADA'!$J$18:$J$40,'AVARIA ESTIMADA'!$A$18:$A$40,A110) -> 2
A111: VLT-CAM-004-PRE-G | B111: =_xlfn.XLOOKUP(A111,CATÁLOGO!$A$2:$A$846,CATÁLOGO!$B$2:$B$846,"FORA DO CATÁLOGO") -> CAM004PG | C111: 2 | D111: =_xlfn.XLOOKUP(A111,CATÁLOGO!$A$2:$A$846,CATÁLOGO!$E$2:$E$846,"FORA DO CATÁLOGO") -> Ativo | F111: =SUMIFS('AVARIA ESTIMADA'!$J$18:$J$40,'AVARIA ESTIMADA'!$A$18:$A$40,A111) -> 0
A112: VLT-CAM-004-PRE-GG | B112: =_xlfn.XLOOKUP(A112,CATÁLOGO!$A$2:$A$846,CATÁLOGO!$B$2:$B$846,"FORA DO CATÁLOGO") -> CAM004PGG | C112: 2 | D112: =_xlfn.XLOOKUP(A112,CATÁLOGO!$A$2:$A$846,CATÁLOGO!$E$2:$E$846,"FORA DO CATÁLOGO") -> Ativo | F112: =SUMIFS('AVARIA ESTIMADA'!$J$18:$J$40,'AVARIA ESTIMADA'!$A$18:$A$40,A112) -> 0
A113: VLT-TOP-003-BRA-P | B113: =_xlfn.XLOOKUP(A113,CATÁLOGO!$A$2:$A$846,CATÁLOGO!$B$2:$B$846,"FORA DO CATÁLOGO") -> TOP003BP | C113: 5 | D113: =_xlfn.XLOOKUP(A113,CATÁLOGO!$A$2:$A$846,CATÁLOGO!$E$2:$E$846,"FORA DO CATÁLOGO") -> Ativo | F113: =SUMIFS('AVARIA ESTIMADA'!$J$18:$J$40,'AVARIA ESTIMADA'!$A$18:$A$40,A113) -> 0
A114: VLT-TOP-003-BRA-M | B114: =_xlfn.XLOOKUP(A114,CATÁLOGO!$A$2:$A$846,CATÁLOGO!$B$2:$B$846,"FORA DO CATÁLOGO") -> TOP003BM | C114: 7 | D114: =_xlfn.XLOOKUP(A114,CATÁLOGO!$A$2:$A$846,CATÁLOGO!$E$2:$E$846,"FORA DO CATÁLOGO") -> Ativo | F114: =SUMIFS('AVARIA ESTIMADA'!$J$18:$J$40,'AVARIA ESTIMADA'!$A$18:$A$40,A114) -> 0
A115: VLT-TOP-003-BRA-G | B115: =_xlfn.XLOOKUP(A115,CATÁLOGO!$A$2:$A$846,CATÁLOGO!$B$2:$B$846,"FORA DO CATÁLOGO") -> TOP003BG | C115: 4 | D115: =_xlfn.XLOOKUP(A115,CATÁLOGO!$A$2:$A$846,CATÁLOGO!$E$2:$E$846,"FORA DO CATÁLOGO") -> Ativo | F115: =SUMIFS('AVARIA ESTIMADA'!$J$18:$J$40,'AVARIA ESTIMADA'!$A$18:$A$40,A115) -> 0
A116: VLT-TOP-003-BRA-GG | B116: =_xlfn.XLOOKUP(A116,CATÁLOGO!$A$2:$A$846,CATÁLOGO!$B$2:$B$846,"FORA DO CATÁLOGO") -> TOP003BGG | C116: 2 | D116: =_xlfn.XLOOKUP(A116,CATÁLOGO!$A$2:$A$846,CATÁLOGO!$E$2:$E$846,"FORA DO CATÁLOGO") -> Ativo | F116: =SUMIFS('AVARIA ESTIMADA'!$J$18:$J$40,'AVARIA ESTIMADA'!$A$18:$A$40,A116) -> 0
A117: VLT-CMS-003-BRA-XP | B117: =_xlfn.XLOOKUP(A117,CATÁLOGO!$A$2:$A$846,CATÁLOGO!$B$2:$B$846,"FORA DO CATÁLOGO") -> CMS003BPP | C117: 2 | D117: =_xlfn.XLOOKUP(A117,CATÁLOGO!$A$2:$A$846,CATÁLOGO!$E$2:$E$846,"FORA DO CATÁLOGO") -> Ativo | F117: =SUMIFS('AVARIA ESTIMADA'!$J$18:$J$40,'AVARIA ESTIMADA'!$A$18:$A$40,A117) -> 0
A118: VLT-CMS-003-BRA-P | B118: =_xlfn.XLOOKUP(A118,CATÁLOGO!$A$2:$A$846,CATÁLOGO!$B$2:$B$846,"FORA DO CATÁLOGO") -> CMS003BP | C118: 3 | D118: =_xlfn.XLOOKUP(A118,CATÁLOGO!$A$2:$A$846,CATÁLOGO!$E$2:$E$846,"FORA DO CATÁLOGO") -> Ativo | F118: =SUMIFS('AVARIA ESTIMADA'!$J$18:$J$40,'AVARIA ESTIMADA'!$A$18:$A$40,A118) -> 0
A119: VLT-CMS-003-BRA-M | B119: =_xlfn.XLOOKUP(A119,CATÁLOGO!$A$2:$A$846,CATÁLOGO!$B$2:$B$846,"FORA DO CATÁLOGO") -> CMS003BM | C119: 5 | D119: =_xlfn.XLOOKUP(A119,CATÁLOGO!$A$2:$A$846,CATÁLOGO!$E$2:$E$846,"FORA DO CATÁLOGO") -> Ativo | F119: =SUMIFS('AVARIA ESTIMADA'!$J$18:$J$40,'AVARIA ESTIMADA'!$A$18:$A$40,A119) -> 0
... A129: VLT-CAM-005-OFF-G | B129: =_xlfn.XLOOKUP(A129,CATÁLOGO!$A$2:$A$846,CATÁLOGO!$B$2:$B$846,"FORA DO CATÁLOGO") -> CAM005OG | C129: 5 | D129: =_xlfn.XLOOKUP(A129,CATÁLOGO!$A$2:$A$846,CATÁLOGO!$E$2:$E$846,"FORA DO CATÁLOGO") -> Ativo | F129: =SUMIFS('AVARIA ESTIMADA'!$J$18:$J$40,'AVARIA ESTIMADA'!$A$18:$A$40,A129) -> 0
A130: VLT-CAM-005-OFF-GG | B130: =_xlfn.XLOOKUP(A130,CATÁLOGO!$A$2:$A$846,CATÁLOGO!$B$2:$B$846,"FORA DO CATÁLOGO") -> CAM005OGG | C130: 2 | D130: =_xlfn.XLOOKUP(A130,CATÁLOGO!$A$2:$A$846,CATÁLOGO!$E$2:$E$846,"FORA DO CATÁLOGO") -> Ativo | E130: (1 no estoque + 1 vitrine) | F130: =SUMIFS('AVARIA ESTIMADA'!$J$18:$J$40,'AVARIA ESTIMADA'!$A$18:$A$40,A130) -> 0
...

Sheet CD
A1: SKU | B1: CÓDIGO CD | C1: QTD | D1: QTD RESERVADA | E1: QTD DISPONÍVEL | F1: STATUS CATÁLOGO | G1: OBS
A2: VLT-BER-001-BRA-P | B2: =_xlfn.XLOOKUP(A2,CATÁLOGO!$A$2:$A$846,CATÁLOGO!$B$2:$B$846,"FORA DO CATÁLOGO") -> BER001B38 | C2: 6 | D2: 2 | E2: 4 | F2: =_xlfn.XLOOKUP(A2,CATÁLOGO!$A$2:$A$846,CATÁLOGO!$E$2:$E$846,"FORA DO CATÁLOGO") -> Ativo
A3: VLT-BER-001-BRA-M | B3: =_xlfn.XLOOKUP(A3,CATÁLOGO!$A$2:$A$846,CATÁLOGO!$B$2:$B$846,"FORA DO CATÁLOGO") -> BER001B40 | C3: 4 | D3: 0 | E3: 4 | F3: =_xlfn.XLOOKUP(A3,CATÁLOGO!$A$2:$A$846,CATÁLOGO!$E$2:$E$846,"FORA DO CATÁLOGO") -> Ativo
A4: VLT-BER-001-BRA-G | B4: =_xlfn.XLOOKUP(A4,CATÁLOGO!$A$2:$A$846,CATÁLOGO!$B$2:$B$846,"FORA DO CATÁLOGO") -> BER001B42 | C4: 2 | D4: 2 | E4: 0 | F4: =_xlfn.XLOOKUP(A4,CATÁLOGO!$A$2:$A$846,CATÁLOGO!$E$2:$E$846,"FORA DO CATÁLOGO") -> Ativo
A5: VLT-BER-001-BRA-GG | B5: =_xlfn.XLOOKUP(A5,CATÁLOGO!$A$2:$A$846,CATÁLOGO!$B$2:$B$846,"FORA DO CATÁLOGO") -> BER001B44 | C5: 4 | D5: 0 | E5: 4 | F5: =_xlfn.XLOOKUP(A5,CATÁLOGO!$A$2:$A$846,CATÁLOGO!$E$2:$E$846,"FORA DO CATÁLOGO") -> Ativo
A6: VLT-CAL-003-PRE-P | B6: =_xlfn.XLOOKUP(A6,CATÁLOGO!$A$2:$A$846,CATÁLOGO!$B$2:$B$846,"FORA DO CATÁLOGO") -> CAL003P38 | C6: 2 | D6: 0 | E6: 2 | F6: =_xlfn.XLOOKUP(A6,CATÁLOGO!$A$2:$A$846,CATÁLOGO!$E$2:$E$846,"FORA DO CATÁLOGO") -> Ativo
A7: VLT-CAL-003-PRE-M | B7: =_xlfn.XLOOKUP(A7,CATÁLOGO!$A$2:$A$846,CATÁLOGO!$B$2:$B$846,"FORA DO CATÁLOGO") -> CAL003P40 | C7: 10 | D7: 0 | E7: 10 | F7: =_xlfn.XLOOKUP(A7,CATÁLOGO!$A$2:$A$846,CATÁLOGO!$E$2:$E$846,"FORA DO CATÁLOGO") -> Ativo
A8: VLT-CAL-003-PRE-G | B8: =_xlfn.XLOOKUP(A8,CATÁLOGO!$A$2:$A$846,CATÁLOGO!$B$2:$B$846,"FORA DO CATÁLOGO") -> CAL003P42 | C8: 9 | D8: 0 | E8: 9 | F8: =_xlfn.XLOOKUP(A8,CATÁLOGO!$A$2:$A$846,CATÁLOGO!$E$2:$E$846,"FORA DO CATÁLOGO") -> Ativo
A9: VLT-CAL-003-PRE-GG | B9: =_xlfn.XLOOKUP(A9,CATÁLOGO!$A$2:$A$846,CATÁLOGO!$B$2:$B$846,"FORA DO CATÁLOGO") -> CAL003P44 | C9: 9 | D9: 0 | E9: 9 | F9: =_xlfn.XLOOKUP(A9,CATÁLOGO!$A$2:$A$846,CATÁLOGO!$E$2:$E$846,"FORA DO CATÁLOGO") -> Ativo
A10: VLT-CAL-004-CIN-XP | B10: =_xlfn.XLOOKUP(A10,CATÁLOGO!$A$2:$A$846,CATÁLOGO!$B$2:$B$846,"FORA DO CATÁLOGO") -> CAL004C36 | C10: 6 | D10: 0 | E10: 6 | F10: =_xlfn.XLOOKUP(A10,CATÁLOGO!$A$2:$A$846,CATÁLOGO!$E$2:$E$846,"FORA DO CATÁLOGO") -> Ativo
A11: VLT-CAL-004-CIN-P | B11: =_xlfn.XLOOKUP(A11,CATÁLOGO!$A$2:$A$846,CATÁLOGO!$B$2:$B$846,"FORA DO CATÁLOGO") -> CAL004C38 | C11: 3 | D11: 0 | E11: 3 | F11: =_xlfn.XLOOKUP(A11,CATÁLOGO!$A$2:$A$846,CATÁLOGO!$E$2:$E$846,"FORA DO CATÁLOGO") -> Ativo
A12: VLT-CAL-004-CIN-M | B12: =_xlfn.XLOOKUP(A12,CATÁLOGO!$A$2:$A$846,CATÁLOGO!$B$2:$B$846,"FORA DO CATÁLOGO") -> CAL004C40 | C12: 12 | D12: 2 | E12: 10 | F12: =_xlfn.XLOOKUP(A12,CATÁLOGO!$A$2:$A$846,CATÁLOGO!$E$2:$E$846,"FORA DO CATÁLOGO") -> Ativo
A13: VLT-CAL-004-CIN-G | B13: =_xlfn.XLOOKUP(A13,CATÁLOGO!$A$2:$A$846,CATÁLOGO!$B$2:$B$846,"FORA DO CATÁLOGO") -> CAL004C42 | C13: 6 | D13: 0 | E13: 6 | F13: =_xlfn.XLOOKUP(A13,CATÁLOGO!$A$2:$A$846,CATÁLOGO!$E$2:$E$846,"FORA DO CATÁLOGO") -> Ativo
... A604: VLT-JAQ-011-OLI-GG | B604: =_xlfn.XLOOKUP(A604,CATÁLOGO!$A$2:$A$846,CATÁLOGO!$B$2:$B$846,"FORA DO CATÁLOGO") -> JAQ011VGG | C604: 4 | D604: 0 | E604: 4 | F604: =_xlfn.XLOOKUP(A604,CATÁLOGO!$A$2:$A$846,CATÁLOGO!$E$2:$E$846,"FORA DO CATÁLOGO") -> Ativo

Sheet AVARIA PINHEIROS
A1: SKU | B1: CÓDIGO CD | C1: QTD | D1: STATUS CATÁLOGO | E1: OBS
A2: VLT-ACE-001-PRE-U | B2: =_xlfn.XLOOKUP(A2,CATÁLOGO!$A$2:$A$846,CATÁLOGO!$B$2:$B$846,"FORA DO CATÁLOGO") -> ACE001PU | C2: 1 | D2: =_xlfn.XLOOKUP(A2,CATÁLOGO!$A$2:$A$846,CATÁLOGO!$E$2:$E$846,"FORA DO CATÁLOGO") -> Fora do catálogo 2026 | E2: avaria? | transferido da aba PINHEIROS linha 6 (decisão 15/10)
A3: VLT-CAL-003-PRE-G | B3: =_xlfn.XLOOKUP(A3,CATÁLOGO!$A$2:$A$846,CATÁLOGO!$B$2:$B$846,"FORA DO CATÁLOGO") -> CAL003P42 | C3: 6 | D3: =_xlfn.XLOOKUP(A3,CATÁLOGO!$A$2:$A$846,CATÁLOGO!$E$2:$E$846,"FORA DO CATÁLOGO") -> Ativo | E3: avaria? | transferido da aba PINHEIROS linha 18 (decisão 15/10)
A4: VLT-CAM-004-PRE-M | B4: =_xlfn.XLOOKUP(A4,CATÁLOGO!$A$2:$A$846,CATÁLOGO!$B$2:$B$846,"FORA DO CATÁLOGO") -> CAM004PM | C4: 2 | D4: =_xlfn.XLOOKUP(A4,CATÁLOGO!$A$2:$A$846,CATÁLOGO!$E$2:$E$846,"FORA DO CATÁLOGO") -> Ativo | E4: avaria? | transferido da aba PINHEIROS linha 119 (decisão 15/10)
A5: VLT-MOL-008-VIN-G | B5: =_xlfn.XLOOKUP(A5,CATÁLOGO!$A$2:$A$846,CATÁLOGO!$B$2:$B$846,"FORA DO CATÁLOGO") -> MOL008HG | C5: 1 | D5: =_xlfn.XLOOKUP(A5,CATÁLOGO!$A$2:$A$846,CATÁLOGO!$E$2:$E$846,"FORA DO CATÁLOGO") -> Descontinuado | E5: avaria? | transferido da aba PINHEIROS linha 200 (decisão 15/10)
A6: VLT-MOL-008-VIN-GG | B6: =_xlfn.XLOOKUP(A6,CATÁLOGO!$A$2:$A$846,CATÁLOGO!$B$2:$B$846,"FORA DO CATÁLOGO") -> MOL008HGG | C6: 1 | D6: =_xlfn.XLOOKUP(A6,CATÁLOGO!$A$2:$A$846,CATÁLOGO!$E$2:$E$846,"FORA DO CATÁLOGO") -> Descontinuado | E6: avaria? | transferido da aba PINHEIROS linha 201 (decisão 15/10)
A7: VLT-TOP-006-MRR-G | B7: =_xlfn.XLOOKUP(A7,CATÁLOGO!$A$2:$A$846,CATÁLOGO!$B$2:$B$846,"FORA DO CATÁLOGO") -> TOP006MG | C7: 5 | D7: =_xlfn.XLOOKUP(A7,CATÁLOGO!$A$2:$A$846,CATÁLOGO!$E$2:$E$846,"FORA DO CATÁLOGO") -> Ativo | E7: avaria? | transferido da aba PINHEIROS linha 227 (decisão 15/10)
A8: VLT-TOP-010-AMA-M | B8: =_xlfn.XLOOKUP(A8,CATÁLOGO!$A$2:$A$846,CATÁLOGO!$B$2:$B$846,"FORA DO CATÁLOGO") -> TOP010YM | C8: 1 | D8: =_xlfn.XLOOKUP(A8,CATÁLOGO!$A$2:$A$846,CATÁLOGO!$E$2:$E$846,"FORA DO CATÁLOGO") -> Descontinuado | E8: avaria? | transferido da aba PINHEIROS linha 247 (decisão 15/10)
A9: VLT-CAL-011-LIL-P | B9: =_xlfn.XLOOKUP(A9,CATÁLOGO!$A$2:$A$846,CATÁLOGO!$B$2:$B$846,"FORA DO CATÁLOGO") -> CAL011L38 | C9: 5 | D9: =_xlfn.XLOOKUP(A9,CATÁLOGO!$A$2:$A$846,CATÁLOGO!$E$2:$E$846,"FORA DO CATÁLOGO") -> Ativo | E9: avaria? | transferido da aba PINHEIROS linha 279 (decisão 15/10)
A10: VLT-VES-006-MRR-G | B10: =_xlfn.XLOOKUP(A10,CATÁLOGO!$A$2:$A$846,CATÁLOGO!$B$2:$B$846,"FORA DO CATÁLOGO") -> VES006MG | C10: 4 | D10: =_xlfn.XLOOKUP(A10,CATÁLOGO!$A$2:$A$846,CATÁLOGO!$E$2:$E$846,"FORA DO CATÁLOGO") -> Ativo | E10: avaria? | transferido da aba PINHEIROS linha 286 (decisão 15/10)
A11: VLT-BER-006-LIL-G | B11: =_xlfn.XLOOKUP(A11,CATÁLOGO!$A$2:$A$846,CATÁLOGO!$B$2:$B$846,"FORA DO CATÁLOGO") -> BER006L42 | C11: 2 | D11: =_xlfn.XLOOKUP(A11,CATÁLOGO!$A$2:$A$846,CATÁLOGO!$E$2:$E$846,"FORA DO CATÁLOGO") -> Ativo | E11: avaria? | transferido da aba PINHEIROS linha 327 (decisão 15/10)
A12: VLT-VES-007-OLI-GG | B12: =_xlfn.XLOOKUP(A12,CATÁLOGO!$A$2:$A$846,CATÁLOGO!$B$2:$B$846,"FORA DO CATÁLOGO") -> VES007VGG | C12: 3 | D12: =_xlfn.XLOOKUP(A12,CATÁLOGO!$A$2:$A$846,CATÁLOGO!$E$2:$E$846,"FORA DO CATÁLOGO") -> Ativo | E12: avaria? | transferido da aba PINHEIROS linha 336 (decisão 15/10)
A13: VLT-CAL-016-OLI-P | B13: =_xlfn.XLOOKUP(A13,CATÁLOGO!$A$2:$A$846,CATÁLOGO!$B$2:$B$846,"FORA DO CATÁLOGO") -> CAL016V38 | C13: 4 | D13: =_xlfn.XLOOKUP(A13,CATÁLOGO!$A$2:$A$846,CATÁLOGO!$E$2:$E$846,"FORA DO CATÁLOGO") -> Descontinuado | E13: avaria? | transferido da aba PINHEIROS linha 364 (decisão 15/10)
... A24: VLT-MOL-019-OLI-GG | B24: =_xlfn.XLOOKUP(A24,CATÁLOGO!$A$2:$A$846,CATÁLOGO!$B$2:$B$846,"FORA DO CATÁLOGO") -> MOL019VGG | C24: 2 | D24: =_xlfn.XLOOKUP(A24,CATÁLOGO!$A$2:$A$846,CATÁLOGO!$E$2:$E$846,"FORA DO CATÁLOGO") -> Ativo | E24: avaria? | transferido da aba PINHEIROS linha 679 (decisão 15/10)

Sheet AVARIA ESTIMADA
A1: Avaria estimada – Eldorado, Savassi e Batel (rateio da avaria real da Pinheiros)
A2: Estimativa, não contagem: todas as lojas recebem do mesmo CD, então aplica-se a taxa de avaria medida na Pinheiros, com a mesma distribuição por SKU (decisão 13).
A4: PREMISSA | B4: VALOR
A5: Avaria contada na Pinheiros (peças) | B5: =SUM('AVARIA PINHEIROS'!C2:C24) -> 80
A6: Estoque bom da Pinheiros (peças) | B6: =SUM(PINHEIROS!C2:C725) -> 2358
A7: Taxa de avaria = avaria ÷ (estoque bom + avaria) | B7: =B5/(B5+B6) -> 0.032813782
A9: LOJA | B9: ESTOQUE CONTADO | C9: AVARIA TEÓRICA (contado × taxa) | D9: AVARIA ESTIMADA (soma por SKU) | E9: ESTOQUE VENDÁVEL ESTIMADO | F9: % AVARIA
A10: PINHEIROS (real) | B10: =B5+B6 -> 2438 | C10: =B5 -> 80 | D10: =B5 -> 80 | E10: =B10-D10 -> 2358 | F10: =D10/B10 -> 0.032813782
A11: ELDORADO | B11: =SUM(ELDORADO!C2:C731) -> 2323 | C11: =B11*$B$7 -> 76.226415 | D11: =F41 -> 69 | E11: =B11-D11 -> 2254 | F11: =D11/B11 -> 0.02970297
A12: SAVASSI | B12: =SUM(SAVASSI!C2:C720) -> 2114 | C12: =B12*$B$7 -> 69.368335 | D12: =H41 -> 65 | E12: =B12-D12 -> 2049 | F12: =D12/B12 -> 0.030747398
A13: BATEL | B13: =SUM(BATEL!C2:C721) -> 1904 | C13: =B13*$B$7 -> 62.477441 | D13: =J41 -> 49 | E13: =B13-D13 -> 1855 | F13: =D13/B13 -> 0.025735294
A14: TOTAL 4 LOJAS | B14: =SUM(B10:B13) -> 8779 | C14: =SUM(C10:C13) -> 288.07219 | D14: =SUM(D10:D13) -> 263 | E14: =SUM(E10:E13) -> 8516 | F14: =D14/B14 -> 0.029957854
A16: Distribuição por SKU: avaria est. = MENOR(estoque do SKU na loja ; ARRED(peso × avaria teórica da loja))
A17: SKU | B17: CÓDIGO CD | C17: AVARIA PINHEIROS | D17: PESO NA AVARIA | E17: ELDORADO – estoque do SKU | F17: ELDORADO – avaria est. | G17: SAVASSI – estoque do SKU | H17: SAVASSI – avaria est. | I17: BATEL – estoque do SKU | J17: BATEL – avaria est.
A18: ='AVARIA PINHEIROS'!A2 -> VLT-ACE-001-PRE-U | B18: ='AVARIA PINHEIROS'!B2 -> ACE001PU | C18: ='AVARIA PINHEIROS'!C2 -> 1 | D18: =C18/$C$41 -> 0.0125 | E18: =SUMIFS(ELDORADO!$C$2:$C$731,ELDORADO!$A$2:$A$731,$A18) -> 0 | F18: =MIN(E18,ROUND($D18*$C$11,0)) -> 0 | G18: =SUMIFS(SAVASSI!$C$2:$C$720,SAVASSI!$A$2:$A$720,$A18) -> 0 | H18: =MIN(G18,ROUND($D18*$C$12,0)) -> 0 | I18: =SUMIFS(BATEL!$C$2:$C$721,BATEL!$A$2:$A$721,$A18) -> 0 | J18: =MIN(I18,ROUND($D18*$C$13,0)) -> 0
A19: ='AVARIA PINHEIROS'!A3 -> VLT-CAL-003-PRE-G | B19: ='AVARIA PINHEIROS'!B3 -> CAL003P42 | C19: ='AVARIA PINHEIROS'!C3 -> 6 | D19: =C19/$C$41 -> 0.075 | E19: =SUMIFS(ELDORADO!$C$2:$C$731,ELDORADO!$A$2:$A$731,$A19) -> 6 | F19: =MIN(E19,ROUND($D19*$C$11,0)) -> 6 | G19: =SUMIFS(SAVASSI!$C$2:$C$720,SAVASSI!$A$2:$A$720,$A19) -> 5 | H19: =MIN(G19,ROUND($D19*$C$12,0)) -> 5 | I19: =SUMIFS(BATEL!$C$2:$C$721,BATEL!$A$2:$A$721,$A19) -> 4 | J19: =MIN(I19,ROUND($D19*$C$13,0)) -> 4
A20: ='AVARIA PINHEIROS'!A4 -> VLT-CAM-004-PRE-M | B20: ='AVARIA PINHEIROS'!B4 -> CAM004PM | C20: ='AVARIA PINHEIROS'!C4 -> 2 | D20: =C20/$C$41 -> 0.025 | E20: =SUMIFS(ELDORADO!$C$2:$C$731,ELDORADO!$A$2:$A$731,$A20) -> 3 | F20: =MIN(E20,ROUND($D20*$C$11,0)) -> 2 | G20: =SUMIFS(SAVASSI!$C$2:$C$720,SAVASSI!$A$2:$A$720,$A20) -> 2 | H20: =MIN(G20,ROUND($D20*$C$12,0)) -> 2 | I20: =SUMIFS(BATEL!$C$2:$C$721,BATEL!$A$2:$A$721,$A20) -> 3 | J20: =MIN(I20,ROUND($D20*$C$13,0)) -> 2
A21: ='AVARIA PINHEIROS'!A5 -> VLT-MOL-008-VIN-G | B21: ='AVARIA PINHEIROS'!B5 -> MOL008HG | C21: ='AVARIA PINHEIROS'!C5 -> 1 | D21: =C21/$C$41 -> 0.0125 | E21: =SUMIFS(ELDORADO!$C$2:$C$731,ELDORADO!$A$2:$A$731,$A21) -> 0 | F21: =MIN(E21,ROUND($D21*$C$11,0)) -> 0 | G21: =SUMIFS(SAVASSI!$C$2:$C$720,SAVASSI!$A$2:$A$720,$A21) -> 1 | H21: =MIN(G21,ROUND($D21*$C$12,0)) -> 1 | I21: =SUMIFS(BATEL!$C$2:$C$721,BATEL!$A$2:$A$721,$A21) -> 0 | J21: =MIN(I21,ROUND($D21*$C$13,0)) -> 0
A22: ='AVARIA PINHEIROS'!A6 -> VLT-MOL-008-VIN-GG | B22: ='AVARIA PINHEIROS'!B6 -> MOL008HGG | C22: ='AVARIA PINHEIROS'!C6 -> 1 | D22: =C22/$C$41 -> 0.0125 | E22: =SUMIFS(ELDORADO!$C$2:$C$731,ELDORADO!$A$2:$A$731,$A22) -> 1 | F22: =MIN(E22,ROUND($D22*$C$11,0)) -> 1 | G22: =SUMIFS(SAVASSI!$C$2:$C$720,SAVASSI!$A$2:$A$720,$A22) -> 1 | H22: =MIN(G22,ROUND($D22*$C$12,0)) -> 1 | I22: =SUMIFS(BATEL!$C$2:$C$721,BATEL!$A$2:$A$721,$A22) -> 1 | J22: =MIN(I22,ROUND($D22*$C$13,0)) -> 1
A23: ='AVARIA PINHEIROS'!A7 -> VLT-TOP-006-MRR-G | B23: ='AVARIA PINHEIROS'!B7 -> TOP006MG | C23: ='AVARIA PINHEIROS'!C7 -> 5 | D23: =C23/$C$41 -> 0.0625 | E23: =SUMIFS(ELDORADO!$C$2:$C$731,ELDORADO!$A$2:$A$731,$A23) -> 6 | F23: =MIN(E23,ROUND($D23*$C$11,0)) -> 5 | G23: =SUMIFS(SAVASSI!$C$2:$C$720,SAVASSI!$A$2:$A$720,$A23) -> 4 | H23: =MIN(G23,ROUND($D23*$C$12,0)) -> 4 | I23: =SUMIFS(BATEL!$C$2:$C$721,BATEL!$A$2:$A$721,$A23) -> 3 | J23: =MIN(I23,ROUND($D23*$C$13,0)) -> 3
A24: ='AVARIA PINHEIROS'!A8 -> VLT-TOP-010-AMA-M | B24: ='AVARIA PINHEIROS'!B8 -> TOP010YM | C24: ='AVARIA PINHEIROS'!C8 -> 1 | D24: =C24/$C$41 -> 0.0125 | E24: =SUMIFS(ELDORADO!$C$2:$C$731,ELDORADO!$A$2:$A$731,$A24) -> 0 | F24: =MIN(E24,ROUND($D24*$C$11,0)) -> 0 | G24: =SUMIFS(SAVASSI!$C$2:$C$720,SAVASSI!$A$2:$A$720,$A24) -> 1 | H24: =MIN(G24,ROUND($D24*$C$12,0)) -> 1 | I24: =SUMIFS(BATEL!$C$2:$C$721,BATEL!$A$2:$A$721,$A24) -> 1 | J24: =MIN(I24,ROUND($D24*$C$13,0)) -> 1
A25: ='AVARIA PINHEIROS'!A9 -> VLT-CAL-011-LIL-P | B25: ='AVARIA PINHEIROS'!B9 -> CAL011L38 | C25: ='AVARIA PINHEIROS'!C9 -> 5 | D25: =C25/$C$41 -> 0.0625 | E25: =SUMIFS(ELDORADO!$C$2:$C$731,ELDORADO!$A$2:$A$731,$A25) -> 6 | F25: =MIN(E25,ROUND($D25*$C$11,0)) -> 5 | G25: =SUMIFS(SAVASSI!$C$2:$C$720,SAVASSI!$A$2:$A$720,$A25) -> 4 | H25: =MIN(G25,ROUND($D25*$C$12,0)) -> 4 | I25: =SUMIFS(BATEL!$C$2:$C$721,BATEL!$A$2:$A$721,$A25) -> 4 | J25: =MIN(I25,ROUND($D25*$C$13,0)) -> 4
A26: ='AVARIA PINHEIROS'!A10 -> VLT-VES-006-MRR-G | B26: ='AVARIA PINHEIROS'!B10 -> VES006MG | C26: ='AVARIA PINHEIROS'!C10 -> 4 | D26: =C26/$C$41 -> 0.05 | E26: =SUMIFS(ELDORADO!$C$2:$C$731,ELDORADO!$A$2:$A$731,$A26) -> 4 | F26: =MIN(E26,ROUND($D26*$C$11,0)) -> 4 | G26: =SUMIFS(SAVASSI!$C$2:$C$720,SAVASSI!$A$2:$A$720,$A26) -> 3 | H26: =MIN(G26,ROUND($D26*$C$12,0)) -> 3 | I26: =SUMIFS(BATEL!$C$2:$C$721,BATEL!$A$2:$A$721,$A26) -> 3 | J26: =MIN(I26,ROUND($D26*$C$13,0)) -> 3
A27: ='AVARIA PINHEIROS'!A11 -> VLT-BER-006-LIL-G | B27: ='AVARIA PINHEIROS'!B11 -> BER006L42 | C27: ='AVARIA PINHEIROS'!C11 -> 2 | D27: =C27/$C$41 -> 0.025 | E27: =SUMIFS(ELDORADO!$C$2:$C$731,ELDORADO!$A$2:$A$731,$A27) -> 2 | F27: =MIN(E27,ROUND($D27*$C$11,0)) -> 2 | G27: =SUMIFS(SAVASSI!$C$2:$C$720,SAVASSI!$A$2:$A$720,$A27) -> 2 | H27: =MIN(G27,ROUND($D27*$C$12,0)) -> 2 | I27: =SUMIFS(BATEL!$C$2:$C$721,BATEL!$A$2:$A$721,$A27) -> 1 | J27: =MIN(I27,ROUND($D27*$C$13,0)) -> 1
A28: ='AVARIA PINHEIROS'!A12 -> VLT-VES-007-OLI-GG | B28: ='AVARIA PINHEIROS'!B12 -> VES007VGG | C28: ='AVARIA PINHEIROS'!C12 -> 3 | D28: =C28/$C$41 -> 0.0375 | E28: =SUMIFS(ELDORADO!$C$2:$C$731,ELDORADO!$A$2:$A$731,$A28) -> 2 | F28: =MIN(E28,ROUND($D28*$C$11,0)) -> 2 | G28: =SUMIFS(SAVASSI!$C$2:$C$720,SAVASSI!$A$2:$A$720,$A28) -> 2 | H28: =MIN(G28,ROUND($D28*$C$12,0)) -> 2 | I28: =SUMIFS(BATEL!$C$2:$C$721,BATEL!$A$2:$A$721,$A28) -> 2 | J28: =MIN(I28,ROUND($D28*$C$13,0)) -> 2
A29: ='AVARIA PINHEIROS'!A13 -> VLT-CAL-016-OLI-P | B29: ='AVARIA PINHEIROS'!B13 -> CAL016V38 | C29: ='AVARIA PINHEIROS'!C13 -> 4 | D29: =C29/$C$41 -> 0.05 | E29: =SUMIFS(ELDORADO!$C$2:$C$731,ELDORADO!$A$2:$A$731,$A29) -> 2 | F29: =MIN(E29,ROUND($D29*$C$11,0)) -> 2 | G29: =SUMIFS(SAVASSI!$C$2:$C$720,SAVASSI!$A$2:$A$720,$A29) -> 3 | H29: =MIN(G29,ROUND($D29*$C$12,0)) -> 3 | I29: =SUMIFS(BATEL!$C$2:$C$721,BATEL!$A$2:$A$721,$A29) -> 2 | J29: =MIN(I29,ROUND($D29*$C$13,0)) -> 2
... A40: ='AVARIA PINHEIROS'!A24 -> VLT-MOL-019-OLI-GG | B40: ='AVARIA PINHEIROS'!B24 -> MOL019VGG | C40: ='AVARIA PINHEIROS'!C24 -> 2 | D40: =C40/$C$41 -> 0.025 | E40: =SUMIFS(ELDORADO!$C$2:$C$731,ELDORADO!$A$2:$A$731,$A40) -> 2 | F40: =MIN(E40,ROUND($D40*$C$11,0)) -> 2 | G40: =SUMIFS(SAVASSI!$C$2:$C$720,SAVASSI!$A$2:$A$720,$A40) -> 4 | H40: =MIN(G40,ROUND($D40*$C$12,0)) -> 2 | I40: =SUMIFS(BATEL!$C$2:$C$721,BATEL!$A$2:$A$721,$A40) -> 1 | J40: =MIN(I40,ROUND($D40*$C$13,0)) -> 1
A41: TOTAL | C41: =SUM(C18:C40) -> 80 | D41: =SUM(D18:D40) -> 1 | E41: =SUM(E18:E40) -> 76 | F41: =SUM(F18:F40) -> 69 | G41: =SUM(G18:G40) -> 72 | H41: =SUM(H18:H40) -> 65 | I41: =SUM(I18:I40) -> 55 | J41: =SUM(J18:J40) -> 49

Sheet DECISÕES
A1: Registro de decisões – Inventário
A3: # | B3: Data | C3: Tema | D3: Decisão | E3: Impacto para os próximos passos
A4: 1 | B4: 15/10/2026 | C4: Pinheiros – avaria | D4: Peças com avaria saem do estoque bom e ficam na aba AVARIA PINHEIROS (23 SKUs, 80 peças) | E4: Avaria não entra como estoque vendável
A5: 2 | B5: 15/10/2026 | C5: Batel – provador | D5: 46 SKUs com 'faltou contar provador' considerados com provador = 0 | E5: Estoque da Batel pode estar subestimado
A6: 3 | B6: 15/10/2026 | C6: Batel – recontar | D6: Recontagem solicitada à loja NÃO foi recebida. 36 SKUs imputados pela mediana do mesmo SKU na Pinheiros e Eldorado (arredondada; sem referência = mantém contado), tratados como MAR. Valor contado original fica na OBS de cada linha da aba BATEL | E6: Valores estimados, não contados: 113 peças imputadas vs 90 contadas (+23). Se a loja enviar a recontagem, substituir na aba BATEL
A7: 4 | B7: 15/10/2026 | C7: Savassi – por SKU | D7: Total por modelo rateado pela proporção de cor/tamanho da Pinheiros (Eldorado+Batel para CMS-006 e ACE-007) – estoque simulado | E7: Quantidades por SKU da Savassi são simuladas (OBS = ESTOQUE SIMULADO). A contagem original por modelo foi removida com os backups; total por modelo = soma da aba SAVASSI
A8: 5 | B8: 15/10/2026 | C8: CD – reservado | D8: Reservado no CD = reposições de lojas já pedidas. Mantido no CD (não somado às lojas, não descartado) | E8: Usar SALDO vs DISPONÍVEL conforme a análise; ao somar lojas + CD, não contar o reservado em duplicidade quando a reposição chegar na loja
A9: 6 | B9: 15/10/2026 | C9: Data de corte | D9: Todas as contagens consideradas como posição de 28/09/2026 (Pinheiros foi contada em 20/09; Eldorado, Savassi e Batel sem data informada; CD = WMS 28/09) | E9: ATENÇÃO: entre 20/09 e 28/09 houve vendas/reposições não refletidas na Pinheiros. Se tivermos acesso às vendas, ajustar cada loja para 28/09 (contagem – vendas + entradas no período) | 16/10: relatório de vendas da Pinheiros 21–28/09 não disponível (arquivo recebido era de vendas manuais da Batel de março/26, não utilizado). Decisão mantida: contagem de 20/09 tratada como 28/09
A10: 7 | B10: 16/10/2026 | C10: Avaria – outras lojas | D10: Eldorado, Savassi, Batel e CD não têm nenhum registro de avaria (conferido também nas contagens originais). Avaria considerada inexistente nessas lojas | E10: Se surgir avaria fora da Pinheiros, não está refletida; todo o estoque dessas lojas é tratado como vendável | 19/10: SUBSTITUÍDA pela decisão 13 (avaria estimada por rateio da Pinheiros)
A11: 8 | B11: 16/10/2026 | C11: Padronização final | D11: Abas renomeadas (PINHEIROS, ELDORADO, SAVASSI, BATEL, CD, AVARIA PINHEIROS, DECISÕES); cabeçalho único SKU | QTD | OBS (CD: SKU | QTD | QTD RESERVADA | QTD DISPONÍVEL | OBS; QTD do CD = antigo SALDO); título da Pinheiros removido (cabeçalho na linha 1); fórmulas da Batel fixadas em valor; aba RECONTAGEM BATEL excluída; abas BKP excluídas | E11: Sem backups: originais não estão mais no arquivo. Datas das contagens só ficam registradas nesta aba (decisão 6)
A12: 9 | B12: 15/10/2026 | C12: Catálogo Vulto 2026 / código CD | D12: Catálogo (novo-catalogo_vulto_2026_REVISADO_final) importado na aba CATÁLOGO como cadastro mestre: vale a coleção mais nova; Atemporais só se o produto não estiver em coleção. Código CD do catálogo segue 100% a regra CAT+NNN+letra da cor+tamanho (numérico 36–46 em CAL/BER). 172 SKUs descontinuados sem código e 35 SKUs da lista 2024 receberam código pela mesma regra. Todas as abas de estoque ganharam CÓDIGO CD (col. B) e STATUS CATÁLOGO (fórmulas na aba CATÁLOGO) | E12: Estoque de descontinuados continua contado (Pinheiros 314, Eldorado 357, Savassi 342, Batel 293, CD 871 peças) – decidir liquidação/PMI. Fora do catálogo: só 5 SKUs da Eldorado (12 peças)
A13: 10 | B13: 15/10/2026 | C13: Padrão de tamanho no SKU | D13: SKU das abas de estoque convertido para o padrão do catálogo: 36=XP, 38=P, 40=M, 42=G, 44=GG, 46=XG e PP=XP (código CD mantém o numérico em CAL/BER). Modelos fora do catálogo 2026 mas presentes na lista 2024 (CAL-001, MOL-002-OLI, TRI-003, SAI-001, ACE-001) ficam com status 'Fora do catálogo 2026' | E13: SKUs como VLT-CAL-001-OLI-38 passam a VLT-CAL-001-OLI-P. Nenhuma duplicidade gerada; totais por aba inalterados
A14: 11 | B14: 15/10/2026 | C14: Descontinuados e fora do catálogo 2026 no PMI | D14: Peças com status Descontinuado ou Fora do catálogo 2026 ENTRAM no PMI como estoque normal. ⚠ ÊNFASE: são candidatas a desconto/liquidação (aplicado no PDV/site – regra 5 do catálogo, não altera preço). Destacadas em laranja/amarelo na coluna STATUS CATÁLOGO | E14: Descontinuados: Pinheiros 314, Eldorado 357, Savassi 342, Batel 293, CD 871 peças. Fora do catálogo 2026: Pinheiros 6, Eldorado 11, Savassi 1, Batel 9, Avaria 1
A15: 12 | B15: 15/10/2026 | C15: Eldorado contada por código CD – revalidação | D15: A Eldorado foi contada por código CD (ex.: CAL001V36). Com o catálogo, 4 códigos inexistentes eram dígitos invertidos e foram corrigidos: TOP030BP→TOP-003-BRA-P (5), TOP021PGG→TOP-012-PRE-GG (2), MOL071LP→MOL-017-LIL-P (2), CAM002YGG→CAM-020-AMA-GG (2). TRI003PG (1 peça) não identificado – mantido como FORA DO CATÁLOGO. As 8 correções de letra feitas antes e os demais 'só na Eldorado' existem no catálogo ou na lista 2024 | E15: Estimativas reconferidas: Batel (36 imputados) = mediana Pinheiros/Eldorado atual em 100% dos casos; nenhum SKU corrigido afeta a imputação. Savassi: rateio bate com a proporção da Pinheiros+avaria (desvio máx. 0,88 peça, só arredondamento)
A16: 13 | B16: 19/10/2026 | C16: Avaria – estimativa nas outras lojas | D16: SUBSTITUI a decisão 7. Todas as lojas recebem do mesmo CD, então é improvável que só a Pinheiros tenha avaria; considerar as demais sem avaria superestimaria o estoque vendável. Aplicada às lojas Eldorado, Savassi e Batel a taxa real da Pinheiros: 80 peças ÷ 2.438 peças contadas (80 + 2.358 boas) = 3,3% (taxa de 16% avaliada e descartada: não é sustentada pelos dados). A distribuição segue os mesmos 23 SKUs e o mesmo peso de cada SKU na avaria da Pinheiros, limitada ao estoque que a loja tem do SKU. CD fora do cálculo (é a origem; a avaria acontece no transporte/manuseio até a loja). Cálculo na aba AVARIA ESTIMADA (fórmulas) | E16: Avaria estimada (não contada): Eldorado 69, Savassi 65, Batel 49 peças (teórica 76/69/62; a diferença existe porque as lojas não têm estoque suficiente de alguns SKUs). Total das 4 lojas ≈ 263 peças (3,0%). As abas de estoque NÃO foram alteradas: para o vendável, usar ESTOQUE VENDÁVEL ESTIMADO da aba AVARIA ESTIMADA. Se as lojas fizerem a triagem física de avaria, substituir a estimativa pelo contado
D17: Referência CD (peças)
D18: QTD total (antigo SALDO) | E18: =SUM(CD!C2:C604) -> 6601
D19: QTD RESERVADA (reposições pedidas) | E19: =SUM(CD!D2:D604) -> 189
D20: QTD DISPONÍVEL | E20: =SUM(CD!E2:E604) -> 6412

Sheet CATÁLOGO
A1: SKU | B1: CÓDIGO CD | C1: PRODUTO | D1: COLEÇÃO VIGENTE | E1: STATUS CATÁLOGO | F1: ORIGEM CÓDIGO CD
A2: VLT-ACE-003-BEG-U | B2: ACE003GU | C2: Meia Cano Alto (par) Couro Eco | D2: Atemporais | E2: Ativo | F2: Catálogo
A3: VLT-ACE-003-OFF-U | B3: ACE003OU | C3: Meia Cano Alto (par) Couro Eco | D3: Atemporais | E3: Descontinuado | F3: Gerado pela regra (sem código no catálogo)
A4: VLT-ACE-004-CIN-U | B4: ACE004CU | C4: Cinto Nylon | D4: Atemporais | E4: Ativo | F4: Catálogo
A5: VLT-ACE-005-BEG-U | B5: ACE005GU | C5: Cinto Básico | D5: Verão 26 | E5: Ativo | F5: Catálogo
A6: VLT-ACE-005-OFF-U | B6: ACE005OU | C6: Cinto Básico | D6: Verão 26 | E6: Ativo | F6: Catálogo
A7: VLT-ACE-006-PRE-U | B7: ACE006PU | C7: Bolsa Tiracolo Logo | D7: Verão 25 | E7: Descontinuado | F7: Gerado pela regra (sem código no catálogo)
A8: VLT-ACE-007-BEG-U | B8: ACE007GU | C8: Ecobag Couro Eco | D8: Verão 25 | E8: Descontinuado | F8: Gerado pela regra (sem código no catálogo)
A9: VLT-ACE-008-OLI-U | B9: ACE008VU | C9: Meia Cano Alto (par) Bordado | D9: Inverno 26 | E9: Ativo | F9: Catálogo
A10: VLT-ACE-009-BRA-U | B10: ACE009BU | C10: Ecobag Básico | D10: Inverno 25 | E10: Descontinuado | F10: Gerado pela regra (sem código no catálogo)
A11: VLT-ACE-009-OLI-U | B11: ACE009VU | C11: Ecobag Básico | D11: Inverno 25 | E11: Descontinuado | F11: Gerado pela regra (sem código no catálogo)
A12: VLT-ACE-010-AMA-U | B12: ACE010YU | C12: Bolsa Tiracolo Couro Eco | D12: Verão 26 | E12: Ativo | F12: Catálogo
... A846: VLT-SAI-001-PRE-GG | B846: SAI001PGG | C846: Saia Jeans Cetim | D846: Lista 2024 (PLANILHA ANTIGA) | E846: Fora do catálogo 2026 | F846: Gerado pela regra (sem código no catálogo)
